Workbook

Sheet Table of Contents
A1: ='DETAIL.XLS'!$A$1
A2: Financial Model: Table of Contents
B4: 1) | C4: PRELIMINARY STATEMENTS
C5: - | D5: Instructions | I5: 1
C6: - | D6: Assumptions | I6: =I5+1
B8: 2) | C8: SUMMARY STATEMENTS
C9: - | D9: Income Statement | I9: =I6+2
C10: - | D10: Balance Sheet | I10: =I9+1
C11: - | D11: Statement of Sources & Uses | I11: =I10+1
C12: - | D12: Revenue, Gross Margin, & Profit Graph | I12: =I11+1
C13: - | D13: Breakeven Chart | I13: =I12+1
B15: 3) | C15: DETAILED FINANCIAL STATEMENTS
C16: - | D16: Receipts & Disbursements | I16: =I13+1
C17: - | D17: Statement of Sources & Uses | I17: =I16+3
C18: - | D18: Income Statement | I18: =I17+3
C19: - | D19: Balance Sheet | I19: =I18+6
B21: 4) | C21: SALES PROJECTIONS AND MARGIN ANALYSES
C22: - | D22: =Assumptions!I10 | I22: =I19+3
C23: - | D23: =Assumptions!I11 | I23: =I22+3
C24: - | D24: =Assumptions!I12 | I24: =I23+3
C25: - | D25: =Assumptions!I13 | I25: =I24+3
B27: 5) | C27: STAFFING PLAN | I27: =I25+3
B29: 6) | C29: EQUIPMENT PURCHASES | I29: =I27+6
B31: 7) | C31: MANUFACTURING & INVENTORY | I31: =I29+6
B33: 8) | C33: RENT & TAXES | I33: =I31+3
B35: 9) | C35: FINANCING ACTIVITIES | I35: =I33+3
B41: Created by:
B42: Source Address:
B43: Used with permission: www.exinfm.com/free_spreadsheets.html

Sheet Instructions
B1: ='DETAIL.XLS'!$A$1
B2: Financial Model: Instructions
B4: 1) | C4: ENTERING INFORMATION INTO THE MODEL: The DETAIL Worksheet.
C6: - | D6: Enter all inputs & assumptions in either the Assumptions page or the DETAIL worksheet.
C7: - | D7: Inputs are shaded yellow and appear blue when entered.
C8: - | D8: All other cells are protected and their formulas cannot be altered or seen without unprotecting the sheet.
C9: - | D9: At the top of the worksheet are three check lines. Values in each of these cells should always equal zero.
C10: - | D10: For information on the principles of financial projections, please contact a Coopers & Lybrand Emerging Company Services Consultant.
B12: 2) | C12: VIEWING THE RESULTS: The Assumptions Page, Summary Statements, and Revenue Growth and Breakeven Charts.
C14: - | D14: Click on the Assumptions tab to view all inputs and underlying assumptions for the financial model.
C15: - | D15: Click on the Summary Statements tab to view the annual Income Statement, Balance Sheet, and Statement of Sources & Uses for each of the five years projected.
C16: - | D16: At the top of the Summary Statements sheet are three check lines similar to those in the DETAIL worksheet. These should equal zero at all times as well.
C17: - | D17: Click on the Revenue Growth Chart tab to view the growth in revenues over the five-year projection period.
C18: - | D18: Click on the Breakeven Chart tab to view the cash flow breakeven point.
C19: - | D19: Data for the Assumptions page and Financial Charts are drawn automatically from the DETAIL worksheet. You do not need to add anything more to these sheets.
B21: 3) | C21: CUSTOMIZING THE FINANCIAL MODEL
C23: - | D23: To view the formula cells, choose Protection from the TOOLS menu and select Unprotect Worksheet. To protect the sheet again, choose Protection and select Protect Worksheet.
C24: - | D24: The variable inputs in the DETAIL worksheet are designed to accomodate most business models; however, the financial model can be tailored to suit specific business needs or operating procedures.
C25: - | D25: Structural changes to the model, such as additional product lines, extra departments, or embedded sales forecasts, require modifications of the underlying formulas. To make such changes, please contact an ECS Consultant.
B27: 4) | C27: PRINTING THE FINANCIAL STATEMENTS
C29: - | D29: To print the entire model, choose Print from the FILE menu and select "Entire Workbook". Click OK.
C30: - | D30: To print an individual worksheet (such as the Assumptions sheet only) click on the tab of the sheet you would like to print, choose Print from the FILE menu, and select "Selected Sheet". Click OK.

Sheet Assumptions
A1: =I8
A2: Financial Model: Assumptions
D5: LABELS
D8: Company name to be used on all statements................................................................................................................................................................................................................. | I8: Company name
D9: Date projections first begin............................................................................................................................................................................................................................... | I9: 38353
D10: Name of 1st product line..................................................................................................................................................................................................................................... | I10: Product One
D11: Name of 2nd product line..................................................................................................................................................................................................................................... | I11: Product Two
D12: Name of 3rd product line..................................................................................................................................................................................................................................... | I12: Product Three
D13: Name of 4th product line..................................................................................................................................................................................................................................... | I13: Services
D14: Name of department to be included in COGS..................................................................................................................................................................................................................... | I14: Content
D15: Name of 1st department to be included in operating expenses............................................................................................................................................................................................. | I15: Engineering
D16: Name of 2nd department to be included in operating expenses............................................................................................................................................................................................. | I16: Sales & Marketing
D17: Name of 3rd department to be included in operating expenses............................................................................................................................................................................................. | I17: Administration
D22: SALES
D25: UNITS SALES | E25: ='DETAIL.XLS'!R1 | F25: ='DETAIL.XLS'!AE1 | G25: ='DETAIL.XLS'!AF1 | H25: ='DETAIL.XLS'!AG1 | I25: ='DETAIL.XLS'!AH1
D26: =$I$10 | E26: ='DETAIL.XLS'!R246 | F26: ='DETAIL.XLS'!AE246 | G26: ='DETAIL.XLS'!AF246 | H26: ='DETAIL.XLS'!AG246 | I26: ='DETAIL.XLS'!AH246
D27: =$I$11 | E27: ='DETAIL.XLS'!R285 | F27: ='DETAIL.XLS'!AE285 | G27: ='DETAIL.XLS'!AF285 | H27: ='DETAIL.XLS'!AG285 | I27: ='DETAIL.XLS'!AH285
D28: =$I$12 | E28: ='DETAIL.XLS'!R324 | F28: ='DETAIL.XLS'!AE324 | G28: ='DETAIL.XLS'!AF324 | H28: ='DETAIL.XLS'!AG324 | I28: ='DETAIL.XLS'!AH324
D29: =$I$13 | E29: ='DETAIL.XLS'!R363 | F29: ='DETAIL.XLS'!AE363 | G29: ='DETAIL.XLS'!AF363 | H29: ='DETAIL.XLS'!AG363 | I29: ='DETAIL.XLS'!AH363
D32: AVERAGE UNIT PRICE | E32: =$E$25 | F32: =$F$25 | G32: =$G$25 | H32: =$H$25 | I32: =$I$25
D33: =$I$10 | E33: =IF(E26>0,'DETAIL.XLS'!R255/E26,0) | F33: =IF(F26>0,'DETAIL.XLS'!AE255/F26,0) | G33: =IF(G26>0,'DETAIL.XLS'!AF255/G26,0) | H33: =IF(H26>0,'DETAIL.XLS'!AG255/H26,0) | I33: =IF(I26>0,'DETAIL.XLS'!AH255/I26,0)
D34: =$I$11 | E34: =IF(E27>0,'DETAIL.XLS'!R294/E27,0) | F34: =IF(F27>0,'DETAIL.XLS'!AE294/F27,0) | G34: =IF(G27>0,'DETAIL.XLS'!AF294/G27,0) | H34: =IF(H27>0,'DETAIL.XLS'!AG294/H27,0) | I34: =IF(I27>0,'DETAIL.XLS'!AH294/I27,0)
D35: =$I$12 | E35: =IF(E28>0,'DETAIL.XLS'!R333/E28,0) | F35: =IF(F28>0,'DETAIL.XLS'!AE333/F28,0) | G35: =IF(G28>0,'DETAIL.XLS'!AF333/G28,0) | H35: =IF(H28>0,'DETAIL.XLS'!AG333/H28,0) | I35: =IF(I28>0,'DETAIL.XLS'!AH333/I28,0)
D36: =$I$13 | E36: =IF(E29>0,'DETAIL.XLS'!R372/E29,0) | F36: =IF(F29>0,'DETAIL.XLS'!AE372/F29,0) | G36: =IF(G29>0,'DETAIL.XLS'!AF372/G29,0) | H36: =IF(H29>0,'DETAIL.XLS'!AG372/H29,0) | I36: =IF(I29>0,'DETAIL.XLS'!AH372/I29,0)
D39: COST OF GOODS
D42: AVERAGE UNIT COST | E42: =E$25 | F42: =F$25 | G42: =G$25 | H42: =H$25 | I42: =I$25
D43: =$I$10 | E43: =IF(E26>0,'DETAIL.XLS'!R267/E26,0) | F43: =IF(F26>0,'DETAIL.XLS'!AE267/F26,0) | G43: =IF(G26>0,'DETAIL.XLS'!AF267/G26,0) | H43: =IF(H26>0,'DETAIL.XLS'!AG267/H26,0) | I43: =IF(I26>0,'DETAIL.XLS'!AH267/I26,0)
D44: =$I$11 | E44: =IF(E27>0,'DETAIL.XLS'!R306/E27,0) | F44: =IF(F27>0,'DETAIL.XLS'!AE306/F27,0) | G44: =IF(G27>0,'DETAIL.XLS'!AF306/G27,0) | H44: =IF(H27>0,'DETAIL.XLS'!AG306/H27,0) | I44: =IF(I27>0,'DETAIL.XLS'!AH306/I27,0)
D45: =$I$12 | E45: =IF(E28>0,'DETAIL.XLS'!R345/E28,0) | F45: =IF(F28>0,'DETAIL.XLS'!AE345/F28,0) | G45: =IF(G28>0,'DETAIL.XLS'!AF345/G28,0) | H45: =IF(H28>0,'DETAIL.XLS'!AG345/H28,0) | I45: =IF(I28>0,'DETAIL.XLS'!AH345/I28,0)
D46: =$I$13 | E46: =IF(E29>0,'DETAIL.XLS'!R384/E29,0) | F46: =IF(F29>0,'DETAIL.XLS'!AE384/F29,0) | G46: =IF(G29>0,'DETAIL.XLS'!AF384/G29,0) | H46: =IF(H29>0,'DETAIL.XLS'!AG384/H29,0) | I46: =IF(I29>0,'DETAIL.XLS'!AH384/I29,0)
D49: Returns.................................................................................................................................................................................................." | E49: ="(as a percentage of "&$D$26&" revenue)...................................................................................................................................................................................." | I49: 0
D50: Returns.................................................................................................................................................................................................." | E50: ="(as a percentage of "&$D$27&" revenue)...................................................................................................................................................................................." | I50: 0
D51: Returns.................................................................................................................................................................................................." | E51: ="(as a percentage of "&$D$28&" revenue)...................................................................................................................................................................................." | I51: 0
D52: Returns.................................................................................................................................................................................................." | E52: ="(as a percentage of "&$D$29&" revenue)...................................................................................................................................................................................." | I52: 0
D55: BALANCE SHEET
D58: Accounts Receivable (adjustable up to 360 days)................................................................................................................................................................................................................ | F58: (in days)................................................................................................................................................................................................................ | I58: 60
D59: Accounts Payable (fixed at 30 days)..................................................................................................................................................................................................................... | F59: (in days)..................................................................................................................................................................................................................... | I59: 30
D60: Salaries Payable (fixed at 15 days)............................................................................................................................................................................................................................ | F60: (in days)............................................................................................................................................................................................................................ | I60: 15
D61: Taxes Payable (fixed at 90 days)............................................................................................................................................................................................................................. | F61: (in days)............................................................................................................................................................................................................................. | I61: 90
D62: Inventory (adjustable up to 360 days).......................................................................................................................................................................................................................... | F62: (in days).......................................................................................................................................................................................................................... | I62: 0
D63: Available Credit Line......................................................................................................................................................................................................................................... | F63: (as a percentage of net accounts receivable)................................................................................................................................................................................................ | I63: 0
D64: Maximum Credit Line Used..................................................................................................................................................................................................................................... | F64: (amount borrowed not to exceed)................................................................................................................................................................................................... | I64: 0
D65: Capital Equipment Lease Term (1 year minimum).............................................................................................................................................................................................................. | F65: (in years).............................................................................................................................................................................................................. | I65: 3
D66: Long Term Borrowings Term (1 year minimum).............................................................................................................................................................................................................. | F66: (in years).............................................................................................................................................................................................................. | I66: 5
D69: DEPRECIATION | E69: Hardware | F69: Software | G69: Furn & Fixtures
D70: =$I$14 | E70: 3 | F70: 3 | G70: 3
D71: =$I$15 | E71: 3 | F71: 3 | G71: 3
D72: =$I$16 | E72: 3 | F72: 3 | G72: 3
D73: =$I$17 | E73: 3 | F73: 3 | G73: 3
D79: EXPENSES
D82: HEADCOUNT | E82: =E$25 | F82: =F$25 | G82: =G$25 | H82: =H$25 | I82: =I$25
D83: =$I$14 | E83: ='DETAIL.XLS'!R407 | F83: ='DETAIL.XLS'!AE407 | G83: ='DETAIL.XLS'!AF407 | H83: ='DETAIL.XLS'!AG407 | I83: ='DETAIL.XLS'!AH407
D84: =$I$15 | E84: ='DETAIL.XLS'!R415 | F84: ='DETAIL.XLS'!AE415 | G84: ='DETAIL.XLS'!AF415 | H84: ='DETAIL.XLS'!AG415 | I84: ='DETAIL.XLS'!AH415
D85: =$I$16 | E85: ='DETAIL.XLS'!R426 | F85: ='DETAIL.XLS'!AE426 | G85: ='DETAIL.XLS'!AF426 | H85: ='DETAIL.XLS'!AG426 | I85: ='DETAIL.XLS'!AH426
D86: =$I$17 | E86: ='DETAIL.XLS'!R435 | F86: ='DETAIL.XLS'!AE435 | G86: ='DETAIL.XLS'!AF435 | H86: ='DETAIL.XLS'!AG435 | I86: ='DETAIL.XLS'!AH435
D87: TOTAL | E87: =SUM(E83:E86) | F87: =SUM(F83:F86) | G87: =SUM(G83:G86) | H87: =SUM(H83:H86) | I87: =SUM(I83:I86)
D90: PER PERSON EXPENSES | E90: Supplies | F90: Travel & Meals | G90: Phone/Postage
D91: =$I$14 | E91: 100 | F91: 500 | G91: 100
D92: =$I$15 | E92: 100 | F92: 500 | G92: 100
D93: =$I$16 | E93: 100 | F93: 2500 | G93: 300
D94: =$I$17 | E94: 100 | F94: 1000 | G94: 250
D97: EQUIPMENT PURCHASES | E97: Hardware | F97: Software | G97: Furn & Fixtures
D98: =$I$14 | E98: 3000 | F98: 1500 | G98: 1000
D99: =$I$15 | E99: 3500 | F99: 1500 | G99: 1000
D100: =$I$16 | E100: 2500 | F100: 1000 | G100: 1000
D101: =$I$17 | E101: 1500 | F101: 1000 | G101: 1000
D104: Benefits & Taxes....................................................................................................................................................................................... | F104: (as a percentage of salaries)....................................................................................................................................................................................... | I104: 0.25
D105: Salary Increases.................................................................................................................................................................................................. | F105: (as an annual percentage).................................................................................................................................................................................................. | I105: 0.05
D106: Sales Commissions..................................................................................................................................................................................................... | F106: (as a percentage of sales)..................................................................................................................................................................................................... | I106: 1
D107: Total Sales Through Commissions................................................................................................................................................... | F107: (as a percentage of total revenue)................................................................................................................................................... | I107: 0.1
D108: Business Insurance.................................................................................................................................................................................................. | F108: (as a percentage of total revenue)................................................................................................................................................................................................... | I108: 0.01
D109: Anticipated Bad Debt................................................................................................................................................................................................... | F109: (as a percentage of collections)........................................................................................................................................................................................................ | I109: 0.01
D110: Interest Revenue........................................................................................................................................................................................................................... | F110: (as a percentage of cash balance)....................................................................................................................................................................................................... | I110: 0.04
D111: Interest Expense On Credit Line.................................................................................................................................................................................................... | F111: (as a percentage of outstanding balance)...................................................................................................................................................................................................... | I111: 0.1
D112: Interest Expense On Capital Equipment Lease.................................................................................................................................................................................................... | F112: (as a percentage of outstanding balance)...................................................................................................................................................................................................... | I112: 0.1
D113: Interest Expense On Long Term Borrowings.................................................................................................................................................................................................... | F113: (as a percentage of outstanding balance)...................................................................................................................................................................................................... | I113: 0.1
D114: Combined Federal & State Tax Rate................................................................................................................................................................................. | F114: (as a percentage of positive cumulative income)................................................................................................................................................... | I114: 0.4
D115: Office Rent................................................................................................................................................................................................................ | F115: (per square foot)....................................................................................................................................................................................................... | I115: 1.5
... D119: Maintanence Expense................................................................................................................................................................................................ | F119: (per square foot)....................................................................................................................................................................................................... | I119: 0.1

Sheet DETAIL.XLS
A1: =Assumptions!I8 | C1: Assumptions in | E1: Enter existing | F1: =Assumptions!$I$9 | G1: =F1+31 | H1: =G1+31 | I1: =H1+31 | J1: =I1+31 | K1: =J1+31 | L1: =K1+31 | M1: =L1+31 | N1: =M1+31 | ... Q1: =P1+31 | R1: =IF(MONTH(Q1)=12,Q1,IF(MONTH(Q1)>3,"FY "&YEAR(Q1),"FY "&YEAR(F1))) | S1: =Q1+31 | T1: =S1+31 | U1: =T1+31 | V1: =U1+31 | W1: =V1+31 | X1: =W1+31 | Y1: =X1+31 | Z1: =Y1+31 | AA1: =Z1+31 | ... AD1: =AC1+31 | AE1: =IF(MONTH(AD1)=12,AD1,IF(MONTH(AD1)>3,"FY "&YEAR(AD1),"FY "&YEAR(S1))) | AF1: =IF(MONTH(AD1)=12,AD1+365,IF(MONTH(AD1)>3,"FY "&YEAR(AD1+365),"FY "&YEAR(S1+365))) | AG1: =IF(MONTH(AD1)=12,AD1+730,IF(MONTH(AD1)>3,"FY "&YEAR(AD1+730),"FY "&YEAR(S1+730))) | AH1: =IF(MONTH(AD1)=12,AD1+1095,IF(MONTH(AD1)>3,"FY "&YEAR(AD1+1095),"FY "&YEAR(S1+1095)))
B2: Sources & Uses Check | C2: gray cells are entered | E2: or year-to-date | F2: =F82-F189 | G2: =G82-G189 | H2: =H82-H189 | I2: =I82-I189 | J2: =J82-J189 | K2: =K82-K189 | L2: =L82-L189 | M2: =M82-M189 | ... AH2: =AH82-AH189
B3: Rec. & Disb. Check | C3: into and refer to the | E3: entries in this | F3: =F46-F189 | G3: =G46-G189 | H3: =H46-H189 | I3: =I46-I189 | J3: =J46-J189 | K3: =K46-K189 | L3: =L46-L189 | M3: =M46-M189 | ... AH3: =AH46-AH189
B4: Balance Sheet Check | C4: "Assumptions" page. | E4: column. | F4: =F236-F210 | G4: =G236-G210 | H4: =H236-H210 | I4: =I236-I210 | J4: =J236-J210 | K4: =K236-K210 | L4: =L236-L210 | M4: =M236-M210 | ... AH4: =AH236-AH210
A5: RECEIPTS & DISBURSEMENTS
A6: =$A$1
B7: =NOW() | F7: Month 1 | G7: Month 2 | H7: Month 3 | I7: Month 4 | J7: Month 5 | K7: Month 6 | L7: Month 7 | M7: Month 8 | N7: Month 9 | O7: Month 10 | P7: Month 11 | Q7: Month 12 | R7: Total | S7: Month 13 | T7: Month 14 | U7: Month 15 | V7: Month 16 | W7: Month 17 | X7: Month 18 | Y7: Month 19 | Z7: Month 20 | AA7: Month 21 | AB7: Month 22 | AC7: Month 23 | AD7: Month 24 | AE7: Total | AF7: Total | AG7: Total | AH7: Total
B8: =NOW() | F8: =F$1 | G8: =G$1 | H8: =H$1 | I8: =I$1 | J8: =J$1 | K8: =K$1 | L8: =L$1 | M8: =M$1 | ... AH8: =AH$1
A10: BEGINNING CASH | F10: =E189 | G10: =F46 | H10: =G46 | I10: =H46 | J10: =I46 | K10: =J46 | L10: =K46 | M10: =L46 | N10: =M46 | ... Q10: =P46 | R10: =F10 | S10: =Q46 | T10: =S46 | U10: =T46 | V10: =U46 | W10: =V46 | X10: =W46 | Y10: =X46 | Z10: =Y46 | AA10: =Z46 | ... AD10: =AC46 | AE10: =S10 | AF10: =AE46 | AG10: =AF46 | AH10: =AG46
A12: Receipts
B13: Collections | F13: =F93-(F192-E192)-F154 | G13: =G93-(G192-F192)-G154 | H13: =H93-(H192-G192)-H154 | I13: =I93-(I192-H192)-I154 | J13: =J93-(J192-I192)-J154 | K13: =K93-(K192-J192)-K154 | L13: =L93-(L192-K192)-L154 | M13: =M93-(M192-L192)-M154 | ... Q13: =Q93-(Q192-P192)-Q154 | R13: =SUM(F13:Q13) | S13: =S93-(S192-Q192)-S154 | T13: =T93-(T192-S192)-T154 | U13: =U93-(U192-T192)-U154 | V13: =V93-(V192-U192)-V154 | W13: =W93-(W192-V192)-W154 | X13: =X93-(X192-W192)-X154 | Y13: =Y93-(Y192-X192)-Y154 | Z13: =Z93-(Z192-Y192)-Z154 | AA13: =AA93-(AA192-Z192)-AA154 | ... AD13: =AD93-(AD192-AC192)-AD154 | AE13: =SUM(S13:AD13) | AF13: =AF93-(AF192-AE192)-AF154 | AG13: =AG93-(AG192-AF192)-AG154 | AH13: =AH93-(AH192-AG192)-AH154
B14: Financings | F14: =SUM(F231:F232)-SUM(E231:E232) | G14: =SUM(G231:G232)-SUM(F231:F232) | H14: =SUM(H231:H232)-SUM(G231:G232) | I14: =SUM(I231:I232)-SUM(H231:H232) | J14: =SUM(J231:J232)-SUM(I231:I232) | K14: =SUM(K231:K232)-SUM(J231:J232) | L14: =SUM(L231:L232)-SUM(K231:K232) | M14: =SUM(M231:M232)-SUM(L231:L232) | ... Q14: =SUM(Q231:Q232)-SUM(P231:P232) | R14: =SUM(F14:Q14) | S14: =SUM(S231:S232)-SUM(R231:R232) | T14: =SUM(T231:T232)-SUM(S231:S232) | U14: =SUM(U231:U232)-SUM(T231:T232) | V14: =SUM(V231:V232)-SUM(U231:U232) | W14: =SUM(W231:W232)-SUM(V231:V232) | X14: =SUM(X231:X232)-SUM(W231:W232) | Y14: =SUM(Y231:Y232)-SUM(X231:X232) | Z14: =SUM(Z231:Z232)-SUM(Y231:Y232) | ... AD14: =SUM(AD231:AD232)-SUM(AC231:AC232) | AE14: =SUM(S14:AD14) | AF14: =SUM(AF231:AF232)-SUM(AE231:AE232) | AG14: =SUM(AG231:AG232)-SUM(AF231:AF232) | AH14: =SUM(AH231:AH232)-SUM(AG231:AG232)
B15: Borrowings | F15: =SUM(F63:F65) | G15: =SUM(G63:G65) | H15: =SUM(H63:H65) | I15: =SUM(I63:I65) | J15: =SUM(J63:J65) | K15: =SUM(K63:K65) | L15: =SUM(L63:L65) | M15: =SUM(M63:M65) | ... Q15: =SUM(Q63:Q65) | R15: =SUM(F15:Q15) | S15: =SUM(S63:S65) | T15: =SUM(T63:T65) | U15: =SUM(U63:U65) | V15: =SUM(V63:V65) | W15: =SUM(W63:W65) | X15: =SUM(X63:X65) | Y15: =SUM(Y63:Y65) | Z15: =SUM(Z63:Z65) | ... AD15: =SUM(AD63:AD65) | AE15: =SUM(S15:AD15) | AF15: =SUM(AF63:AF65) | AG15: =SUM(AG63:AG65) | AH15: =SUM(AH63:AH65)
B16: Interest Revenue | F16: =F169 | G16: =G169 | H16: =H169 | I16: =I169 | J16: =J169 | K16: =K169 | L16: =L169 | M16: =M169 | ... Q16: =Q169 | R16: =SUM(F16:Q16) | S16: =S169 | T16: =T169 | U16: =U169 | V16: =V169 | W16: =W169 | X16: =X169 | Y16: =Y169 | Z16: =Z169 | ... AD16: =AD169 | AE16: =SUM(S16:AD16) | AF16: =AF169 | AG16: =AG169 | AH16: =AH169
A17: Total receipts | F17: =SUM(F13:F16) | G17: =SUM(G13:G16) | H17: =SUM(H13:H16) | I17: =SUM(I13:I16) | J17: =SUM(J13:J16) | K17: =SUM(K13:K16) | L17: =SUM(L13:L16) | M17: =SUM(M13:M16) | ... Q17: =SUM(Q13:Q16) | R17: =SUM(F17:Q17) | S17: =SUM(S13:S16) | T17: =SUM(T13:T16) | U17: =SUM(U13:U16) | V17: =SUM(V13:V16) | W17: =SUM(W13:W16) | X17: =SUM(X13:X16) | Y17: =SUM(Y13:Y16) | Z17: =SUM(Z13:Z16) | ... AD17: =SUM(AD13:AD16) | AE17: =SUM(S17:AD17) | AF17: =SUM(AF13:AF16) | AG17: =SUM(AG13:AG16) | AH17: =SUM(AH13:AH16)
A19: Disbursements
B20: Salaries | F20: =F480-F216+E216 | G20: =G480-G216+F216 | H20: =H480-H216+G216 | I20: =I480-I216+H216 | J20: =J480-J216+I216 | K20: =K480-K216+J216 | L20: =L480-L216+K216 | M20: =M480-M216+L216 | ... Q20: =Q480-Q216+P216 | R20: =SUM(F20:Q20) | S20: =S480-S216+Q216 | T20: =T480-T216+S216 | U20: =U480-U216+T216 | V20: =V480-V216+U216 | W20: =W480-W216+V216 | X20: =X480-X216+W216 | Y20: =Y480-Y216+X216 | Z20: =Z480-Z216+Y216 | AA20: =AA480-AA216+Z216 | ... AD20: =AD480-AD216+AC216 | AE20: =SUM(S20:AD20) | AF20: =AF480-AF216+AE216 | AG20: =AG480-AG216+AF216 | AH20: =AH480-AH216+AG216
B21: Benefits & Empl Taxes | F21: =F111+F125+F148+F561 | G21: =G111+G125+G148+G561 | H21: =H111+H125+H148+H561 | I21: =I111+I125+I148+I561 | J21: =J111+J125+J148+J561 | K21: =K111+K125+K148+K561 | L21: =L111+L125+L148+L561 | M21: =M111+M125+M148+M561 | ... Q21: =Q111+Q125+Q148+Q561 | R21: =SUM(F21:Q21) | S21: =S111+S125+S148+S561 | T21: =T111+T125+T148+T561 | U21: =U111+U125+U148+U561 | V21: =V111+V125+V148+V561 | W21: =W111+W125+W148+W561 | X21: =X111+X125+X148+X561 | Y21: =Y111+Y125+Y148+Y561 | Z21: =Z111+Z125+Z148+Z561 | ... AD21: =AD111+AD125+AD148+AD561 | AE21: =SUM(S21:AD21) | AF21: =AF111+AF125+AF148+AF561 | AG21: =AG111+AG125+AG148+AG561 | AH21: =AH111+AH125+AH148+AH561
B22: Incentives/commissions | F22: =F110+F124+F147+F560 | G22: =G110+G124+G147 | H22: =H110+H124+H147 | I22: =I110+I124+I147 | J22: =J110+J124+J147 | K22: =K110+K124+K147 | L22: =L110+L124+L147 | M22: =M110+M124+M147 | N22: =N110+N124+N147 | ... Q22: =Q110+Q124+Q147 | R22: =SUM(F22:Q22) | S22: =S110+S124+S147 | T22: =T110+T124+T147 | U22: =U110+U124+U147 | V22: =V110+V124+V147 | W22: =W110+W124+W147 | X22: =X110+X124+X147 | Y22: =Y110+Y124+Y147 | Z22: =Z110+Z124+Z147 | ... AD22: =AD110+AD124+AD147 | AE22: =SUM(S22:AD22) | AF22: =AF110+AF124+AF147 | AG22: =AG110+AG124+AG147 | AH22: =AH110+AH124+AH147
B23: Direct Material | F23: =E588 | G23: =F588 | H23: =G588 | I23: =H588 | J23: =I588 | K23: =J588 | L23: =K588 | M23: =L588 | ... Q23: =P588 | R23: =SUM(F23:Q23) | S23: =Q588 | T23: =S588 | U23: =T588 | V23: =U588 | W23: =V588 | X23: =W588 | Y23: =X588 | Z23: =Y588 | AA23: =Z588 | ... AD23: =AC588 | AE23: =SUM(S23:AD23) | AF23: =AD588+AF588*11/12 | AG23: =AF588/12+AG588*11/12 | AH23: =AG588/12+AH588*11/12
B24: Returns | F24: =F100 | G24: =G100 | H24: =H100 | I24: =I100 | J24: =J100 | K24: =K100 | L24: =L100 | M24: =M100 | ... Q24: =Q100 | R24: =SUM(F24:Q24) | S24: =S100 | T24: =T100 | U24: =U100 | V24: =V100 | W24: =W100 | X24: =X100 | Y24: =Y100 | Z24: =Z100 | ... AD24: =AD100 | AE24: =SUM(S24:AD24) | AF24: =AF100 | AG24: =AG100 | AH24: =AH100
B25: Advertising | F25: =E138 | G25: =F138 | H25: =G138 | I25: =H138 | J25: =I138 | K25: =J138 | L25: =K138 | M25: =L138 | ... Q25: =P138 | R25: =SUM(F25:Q25) | S25: =Q138 | T25: =S138 | U25: =T138 | V25: =U138 | W25: =V138 | X25: =W138 | Y25: =X138 | Z25: =Y138 | AA25: =Z138 | ... AD25: =AC138 | AE25: =SUM(S25:AD25) | AF25: =AD138+AF138*11/12 | AG25: =AF138/12+AG138*11/12 | AH25: =AG138/12+AH138*11/12
B26: Promotional Material | F26: =E140 | G26: =F140 | H26: =G140 | I26: =H140 | J26: =I140 | K26: =J140 | L26: =K140 | M26: =L140 | ... Q26: =P140 | R26: =SUM(F26:Q26) | S26: =Q140 | T26: =S140 | U26: =T140 | V26: =U140 | W26: =V140 | X26: =W140 | Y26: =X140 | Z26: =Y140 | AA26: =Z140 | ... AD26: =AC140 | AE26: =SUM(S26:AD26) | AF26: =AD140+AF140*11/12 | AG26: =AF140/12+AG140*11/12 | AH26: =AG140/12+AH140*11/12
B27: Trade Shows | F27: =F139 | G27: =G139 | H27: =H139 | I27: =I139 | J27: =J139 | K27: =K139 | L27: =L139 | M27: =M139 | ... Q27: =Q139 | R27: =SUM(F27:Q27) | S27: =S139 | T27: =T139 | U27: =U139 | V27: =V139 | W27: =W139 | X27: =X139 | Y27: =Y139 | Z27: =Z139 | ... AD27: =AD139 | AE27: =SUM(S27:AD27) | AF27: =AF139 | AG27: =AG139 | AH27: =AH139
B28: Supplies/Materials | F28: =E113+E126+E149+E565 | G28: =F113+F126+F149+F565 | H28: =G113+G126+G149+G565 | I28: =H113+H126+H149+H565 | J28: =I113+I126+I149+I565 | K28: =J113+J126+J149+J565 | L28: =K113+K126+K149+K565 | M28: =L113+L126+L149+L565 | ... Q28: =P113+P126+P149+P565 | R28: =SUM(F28:Q28) | S28: =Q113+Q126+Q149+Q565 | T28: =S113+S126+S149+S565 | U28: =T113+T126+T149+T565 | V28: =U113+U126+U149+U565 | W28: =V113+V126+V149+V565 | X28: =W113+W126+W149+W565 | Y28: =X113+X126+X149+X565 | Z28: =Y113+Y126+Y149+Y565 | AA28: =Z113+Z126+Z149+Z565 | ... AD28: =AC113+AC126+AC149+AC565 | AE28: =SUM(S28:AD28) | AF28: =(AD113+AD126+AD149+AD565)+(AF113+AF126+AF149+AF565)*11/12 | AG28: =(AF113+AF126+AF149+AF565)/12+(AG113+AG126+AG149+AG565)*11/12 | AH28: =(AG113+AG126+AG149+AG565)/12+(AH113+AH126+AH149+AH565)*11/12
B29: Travel & Meals | F29: =E114+E127+E150+E566 | G29: =F114+F127+F150+F566 | H29: =G114+G127+G150+G566 | I29: =H114+H127+H150+H566 | J29: =I114+I127+I150+I566 | K29: =J114+J127+J150+J566 | L29: =K114+K127+K150+K566 | M29: =L114+L127+L150+L566 | ... Q29: =P114+P127+P150+P566 | R29: =SUM(F29:Q29) | S29: =Q114+Q127+Q150+Q566 | T29: =S114+S127+S150+S566 | U29: =T114+T127+T150+T566 | V29: =U114+U127+U150+U566 | W29: =V114+V127+V150+V566 | X29: =W114+W127+W150+W566 | Y29: =X114+X127+X150+X566 | Z29: =Y114+Y127+Y150+Y566 | AA29: =Z114+Z127+Z150+Z566 | ... AD29: =AC114+AC127+AC150+AC566 | AE29: =SUM(S29:AD29) | AF29: =(AD114+AD127+AD150+AD566)+(AF114+AF127+AF150+AF566)*11/12 | AG29: =(AF114+AF127+AF150+AF566)/12+(AG114+AG127+AG150+AG566)*11/12 | AH29: =(AG114+AG127+AG150+AG566)/12+(AH114+AH127+AH150+AH566)*11/12
B30: Telephone/Postage | F30: =E115+E128+E151+E567 | G30: =F115+F128+F151+F567 | H30: =G115+G128+G151+G567 | I30: =H115+H128+H151+H567 | J30: =I115+I128+I151+I567 | K30: =J115+J128+J151+J567 | L30: =K115+K128+K151+K567 | M30: =L115+L128+L151+L567 | ... Q30: =P115+P128+P151+P567 | R30: =SUM(F30:Q30) | S30: =Q115+Q128+Q151+Q567 | T30: =S115+S128+S151+S567 | U30: =T115+T128+T151+T567 | V30: =U115+U128+U151+U567 | W30: =V115+V128+V151+V567 | X30: =W115+W128+W151+W567 | Y30: =X115+X128+X151+X567 | Z30: =Y115+Y128+Y151+Y567 | AA30: =Z115+Z128+Z151+Z567 | ... AD30: =AC115+AC128+AC151+AC567 | AE30: =SUM(S30:AD30) | AF30: =(AD115+AD128+AD151+AD567)+(AF115+AF128+AF151+AF567)*11/12 | AG30: =(AF115+AF128+AF151+AF567)/12+(AG115+AG128+AG151+AG567)*11/12 | AH30: =(AG115+AG128+AG151+AG567)/12+(AH115+AH128+AH151+AH567)*11/12
B31: Maintenance & Repair | F31: =E157 | G31: =F157 | H31: =G157 | I31: =H157 | J31: =I157 | K31: =J157 | L31: =K157 | M31: =L157 | ... Q31: =P157 | R31: =SUM(F31:Q31) | S31: =Q157 | T31: =S157 | U31: =T157 | V31: =U157 | W31: =V157 | X31: =W157 | Y31: =X157 | Z31: =Y157 | AA31: =Z157 | ... AD31: =AC157 | AE31: =SUM(S31:AD31) | AF31: =AD157+AF157*11/12 | AG31: =AF157/12+AG157*11/12 | AH31: =AG157/12+AH157*11/12
B32: Rent | F32: =F613 | G32: =G613 | H32: =H613 | I32: =I613 | J32: =J613 | K32: =K613 | L32: =L613 | M32: =M613 | ... Q32: =Q613 | R32: =SUM(F32:Q32) | S32: =S613 | T32: =T613 | U32: =U613 | V32: =V613 | W32: =W613 | X32: =X613 | Y32: =Y613 | Z32: =Z613 | ... AD32: =AD613 | AE32: =SUM(S32:AD32) | AF32: =AF613 | AG32: =AG613 | AH32: =AH613
B33: Utilities | F33: =E156 | G33: =F156 | H33: =G156 | I33: =H156 | J33: =I156 | K33: =J156 | L33: =K156 | M33: =L156 | ... Q33: =P156 | R33: =SUM(F33:Q33) | S33: =Q156 | T33: =S156 | U33: =T156 | V33: =U156 | W33: =V156 | X33: =W156 | Y33: =X156 | Z33: =Y156 | AA33: =Z156 | ... AD33: =AC156 | AE33: =SUM(S33:AD33) | AF33: =AD156+AF156*11/12 | AG33: =AF156/12+AG156*11/12 | AH33: =AG156/12+AH156*11/12
B34: Insurance | F34: =F152 | G34: =G152 | H34: =H152 | I34: =I152 | J34: =J152 | K34: =K152 | L34: =L152 | M34: =M152 | ... Q34: =Q152 | R34: =SUM(F34:Q34) | S34: =S152 | T34: =T152 | U34: =U152 | V34: =V152 | W34: =W152 | X34: =X152 | Y34: =Y152 | Z34: =Z152 | ... AD34: =AD152 | AE34: =SUM(S34:AD34) | AF34: =AF152 | AG34: =AG152 | AH34: =AH152
B35: Consultants | F35: =E112 | G35: =F112 | H35: =G112 | I35: =H112 | J35: =I112 | K35: =J112 | L35: =K112 | M35: =L112 | ... Q35: =P112 | R35: =SUM(F35:Q35) | S35: =Q112 | T35: =S112 | U35: =T112 | V35: =U112 | W35: =V112 | X35: =W112 | Y35: =X112 | Z35: =Y112 | AA35: =Z112 | ... AD35: =AC112 | AE35: =SUM(S35:AD35) | AF35: =AD112+AF112*11/12 | AG35: =AF112/12+AG112*11/12 | AH35: =AG112/12+AH112*11/12
B36: Professional Services | F36: =E153 | G36: =F153 | H36: =G153 | I36: =H153 | J36: =I153 | K36: =J153 | L36: =K153 | M36: =L153 | ... Q36: =P153 | R36: =SUM(F36:Q36) | S36: =Q153 | T36: =S153 | U36: =T153 | V36: =U153 | W36: =V153 | X36: =W153 | Y36: =X153 | Z36: =Y153 | AA36: =Z153 | ... AD36: =AC153 | AE36: =SUM(S36:AD36) | AF36: =AD153+AF153*11/12 | AG36: =AF153/12+AG153*11/12 | AH36: =AG153/12+AH153*11/12
B37: Taxes | F37: =-F217+E217+F176 | G37: =-G217+F217+G176 | H37: =-H217+G217+H176 | I37: =-I217+H217+I176 | J37: =-J217+I217+J176 | K37: =-K217+J217+K176 | L37: =-L217+K217+L176 | M37: =-M217+L217+M176 | ... Q37: =-Q217+P217+Q176 | R37: =SUM(F37:Q37) | S37: =-S217+R217+S176 | T37: =-T217+S217+T176 | U37: =-U217+T217+U176 | V37: =-V217+U217+V176 | W37: =-W217+V217+W176 | X37: =-X217+W217+X176 | Y37: =-Y217+X217+Y176 | Z37: =-Z217+Y217+Z176 | ... AD37: =-AD217+AC217+AD176 | AE37: =SUM(S37:AD37) | AF37: =-AF217+AE217+AF176 | AG37: =-AG217+AF217+AG176 | AH37: =-AH217+AG217+AH176
B38: Equipment Purchases | F38: =F200-E200 | G38: =G200-F200 | H38: =H200-G200 | I38: =I200-H200 | J38: =J200-I200 | K38: =K200-J200 | L38: =L200-K200 | M38: =M200-L200 | ... Q38: =Q200-P200 | R38: =SUM(F38:Q38) | S38: =S200-Q200 | T38: =T200-S200 | U38: =U200-T200 | V38: =V200-U200 | W38: =W200-V200 | X38: =X200-W200 | Y38: =Y200-X200 | Z38: =Z200-Y200 | AA38: =AA200-Z200 | ... AD38: =AD200-AC200 | AE38: =SUM(S38:AD38) | AF38: =AF200-AE200 | AG38: =AG200-AF200 | AH38: =AH200-AG200
B39: Debt Repayments | F39: =SUM(F75:F77) | G39: =SUM(G75:G77) | H39: =SUM(H75:H77) | I39: =SUM(I75:I77) | J39: =SUM(J75:J77) | K39: =SUM(K75:K77) | L39: =SUM(L75:L77) | M39: =SUM(M75:M77) | ... Q39: =SUM(Q75:Q77) | R39: =SUM(F39:Q39) | S39: =SUM(S75:S77) | T39: =SUM(T75:T77) | U39: =SUM(U75:U77) | V39: =SUM(V75:V77) | W39: =SUM(W75:W77) | X39: =SUM(X75:X77) | Y39: =SUM(Y75:Y77) | Z39: =SUM(Z75:Z77) | ... AD39: =SUM(AD75:AD77) | AE39: =SUM(S39:AD39) | AF39: =SUM(AF75:AF77) | AG39: =SUM(AG75:AG77) | AH39: =SUM(AH75:AH77)
B40: Interest Expense | F40: =SUM(F170:F172) | G40: =SUM(G170:G172) | H40: =SUM(H170:H172) | I40: =SUM(I170:I172) | J40: =SUM(J170:J172) | K40: =SUM(K170:K172) | L40: =SUM(L170:L172) | M40: =SUM(M170:M172) | ... Q40: =SUM(Q170:Q172) | R40: =SUM(F40:Q40) | S40: =SUM(S170:S172) | T40: =SUM(T170:T172) | U40: =SUM(U170:U172) | V40: =SUM(V170:V172) | W40: =SUM(W170:W172) | X40: =SUM(X170:X172) | Y40: =SUM(Y170:Y172) | Z40: =SUM(Z170:Z172) | ... AD40: =SUM(AD170:AD172) | AE40: =SUM(S40:AD40) | AF40: =SUM(AF170:AF172) | AG40: =SUM(AG170:AG172) | AH40: =SUM(AH170:AH172)
B41: Prior Accounts Payable | F41: =E215 | G41: 0 | H41: 0 | I41: 0 | J41: 0 | K41: 0 | L41: 0 | M41: 0 | N41: 0 | O41: 0 | P41: 0 | Q41: 0 | R41: =SUM(F41:Q41) | S41: 0 | T41: 0 | U41: 0 | V41: 0 | W41: 0 | X41: 0 | Y41: 0 | Z41: 0 | AA41: 0 | AB41: 0 | AC41: 0 | AD41: 0 | AE41: =SUM(S41:AD41) | AF41: 0 | AG41: 0 | AH41: 0
A42: Total Disbursements | F42: =SUM(F20:F41) | G42: =SUM(G20:G41) | H42: =SUM(H20:H41) | I42: =SUM(I20:I41) | J42: =SUM(J20:J41) | K42: =SUM(K20:K41) | L42: =SUM(L20:L41) | M42: =SUM(M20:M41) | ... Q42: =SUM(Q20:Q41) | R42: =SUM(F42:Q42) | S42: =SUM(S20:S41) | T42: =SUM(T20:T41) | U42: =SUM(U20:U41) | V42: =SUM(V20:V41) | W42: =SUM(W20:W41) | X42: =SUM(X20:X41) | Y42: =SUM(Y20:Y41) | Z42: =SUM(Z20:Z41) | ... AD42: =SUM(AD20:AD41) | AE42: =SUM(S42:AD42) | AF42: =SUM(AF20:AF41) | AG42: =SUM(AG20:AG41) | AH42: =SUM(AH20:AH41)
A44: Changes in Cash | F44: =F17-F42 | G44: =G17-G42 | H44: =H17-H42 | I44: =I17-I42 | J44: =J17-J42 | K44: =K17-K42 | L44: =L17-L42 | M44: =M17-M42 | ... AH44: =AH17-AH42
A46: ENDING CASH | F46: =F10+F44 | G46: =G10+G44 | H46: =H10+H44 | I46: =I10+I44 | J46: =J10+J44 | K46: =K10+K44 | L46: =L10+L44 | M46: =M10+M44 | ... Q46: =Q10+Q44 | R46: =Q46 | S46: =S10+S44 | T46: =T10+T44 | U46: =U10+U44 | V46: =V10+V44 | W46: =W10+W44 | X46: =X10+X44 | Y46: =Y10+Y44 | Z46: =Z10+Z44 | ... AD46: =AD10+AD44 | AE46: =AD46 | AF46: =AF10+AF44 | AG46: =AG10+AG44 | AH46: =AH10+AH44
A47: STATEMENT OF SOURCES AND USES
A48: =$A$1
B49: =NOW() | F49: =F$7 | G49: =G$7 | H49: =H$7 | I49: =I$7 | J49: =J$7 | K49: =K$7 | L49: =L$7 | M49: =M$7 | ... Q49: =Q$7 | R49: Total | S49: =S$7 | T49: =T$7 | U49: =U$7 | V49: =V$7 | W49: =W$7 | X49: =X$7 | Y49: =Y$7 | Z49: =Z$7 | ... AD49: =AD$7 | AE49: Total | AF49: =AF$7 | AG49: =AG$7 | AH49: =AH$7
B50: =NOW() | F50: =F$1 | G50: =G$1 | H50: =H$1 | I50: =I$1 | J50: =J$1 | K50: =K$1 | L50: =L$1 | M50: =M$1 | ... AH50: =AH$1
A52: BEGINNING CASH | F52: =E189 | G52: =F82 | H52: =G82 | I52: =H82 | J52: =I82 | K52: =J82 | L52: =K82 | M52: =L82 | N52: =M82 | ... Q52: =P82 | R52: =F52 | S52: =Q82 | T52: =S82 | U52: =T82 | V52: =U82 | W52: =V82 | X52: =W82 | Y52: =X82 | Z52: =Y82 | AA52: =Z82 | ... AD52: =AC82 | AE52: =S52 | AF52: =AE82 | AG52: =AF82 | AH52: =AG82
A54: Sources of Cash
B55: Net Income | F55: =F178 | G55: =G178 | H55: =H178 | I55: =I178 | J55: =J178 | K55: =K178 | L55: =L178 | M55: =M178 | ... Q55: =Q178 | R55: =SUM(F55:Q55) | S55: =S178 | T55: =T178 | U55: =U178 | V55: =V178 | W55: =W178 | X55: =X178 | Y55: =Y178 | Z55: =Z178 | ... AD55: =AD178 | AE55: =SUM(S55:AD55) | AF55: =AF178 | AG55: =AG178 | AH55: =AH178
B56: Add Depr/Amort | F56: =F206-E206 | G56: =G206-F206 | H56: =H206-G206 | I56: =I206-H206 | J56: =J206-I206 | K56: =K206-J206 | L56: =L206-K206 | M56: =M206-L206 | ... Q56: =Q206-P206 | R56: =SUM(F56:Q56) | S56: =S206-R206 | T56: =T206-S206 | U56: =U206-T206 | V56: =V206-U206 | W56: =W206-V206 | X56: =X206-W206 | Y56: =Y206-X206 | Z56: =Z206-Y206 | ... AD56: =AD206-AC206 | AE56: =SUM(S56:AD56) | AF56: =AF206-AE206 | AG56: =AG206-AF206 | AH56: =AH206-AG206
B57: ="Issuance of "&B231 | F57: =IF(F231-E231>0,F231-E231,0) | G57: =IF(G231-F231>0,G231-F231,0) | H57: =IF(H231-G231>0,H231-G231,0) | I57: =IF(I231-H231>0,I231-H231,0) | J57: =IF(J231-I231>0,J231-I231,0) | K57: =IF(K231-J231>0,K231-J231,0) | L57: =IF(L231-K231>0,L231-K231,0) | M57: =IF(M231-L231>0,M231-L231,0) | ... Q57: =IF(Q231-P231>0,Q231-P231,0) | R57: =SUM(F57:Q57) | S57: =IF(S231-R231>0,S231-R231,0) | T57: =IF(T231-S231>0,T231-S231,0) | U57: =IF(U231-T231>0,U231-T231,0) | V57: =IF(V231-U231>0,V231-U231,0) | W57: =IF(W231-V231>0,W231-V231,0) | X57: =IF(X231-W231>0,X231-W231,0) | Y57: =IF(Y231-X231>0,Y231-X231,0) | Z57: =IF(Z231-Y231>0,Z231-Y231,0) | ... AD57: =IF(AD231-AC231>0,AD231-AC231,0) | AE57: =SUM(S57:AD57) | AF57: =IF(AF231-AE231>0,AF231-AE231,0) | AG57: =IF(AG231-AF231>0,AG231-AF231,0) | AH57: =IF(AH231-AG231>0,AH231-AG231,0)
B58: ="Issuance of "&B232 | F58: =IF(F232-E232>0,F232-E232,0) | G58: =IF(G232-F232>0,G232-F232,0) | H58: =IF(H232-G232>0,H232-G232,0) | I58: =IF(I232-H232>0,I232-H232,0) | J58: =IF(J232-I232>0,J232-I232,0) | K58: =IF(K232-J232>0,K232-J232,0) | L58: =IF(L232-K232>0,L232-K232,0) | M58: =IF(M232-L232>0,M232-L232,0) | ... Q58: =IF(Q232-P232>0,Q232-P232,0) | R58: =SUM(F58:Q58) | S58: =IF(S232-R232>0,S232-R232,0) | T58: =IF(T232-S232>0,T232-S232,0) | U58: =IF(U232-T232>0,U232-T232,0) | V58: =IF(V232-U232>0,V232-U232,0) | W58: =IF(W232-V232>0,W232-V232,0) | X58: =IF(X232-W232>0,X232-W232,0) | Y58: =IF(Y232-X232>0,Y232-X232,0) | Z58: =IF(Z232-Y232>0,Z232-Y232,0) | ... AD58: =IF(AD232-AC232>0,AD232-AC232,0) | AE58: =SUM(S58:AD58) | AF58: =IF(AF232-AE232>0,AF232-AE232,0) | AG58: =IF(AG232-AF232>0,AG232-AF232,0) | AH58: =IF(AH232-AG232>0,AH232-AG232,0)
A59: Plus Changes In:
B60: =B215 | F60: =F215-E215 | G60: =G215-F215 | H60: =H215-G215 | I60: =I215-H215 | J60: =J215-I215 | K60: =K215-J215 | L60: =L215-K215 | M60: =M215-L215 | ... Q60: =Q215-P215 | R60: =SUM(F60:Q60) | S60: =S215-Q215 | T60: =T215-S215 | U60: =U215-T215 | V60: =V215-U215 | W60: =W215-V215 | X60: =X215-W215 | Y60: =Y215-X215 | Z60: =Z215-Y215 | AA60: =AA215-Z215 | ... AD60: =AD215-AC215 | AE60: =SUM(S60:AD60) | AF60: =AF215-AE215 | AG60: =AG215-AF215 | AH60: =AH215-AG215
B61: =B216 | F61: =F216-E216 | G61: =G216-F216 | H61: =H216-G216 | I61: =I216-H216 | J61: =J216-I216 | K61: =K216-J216 | L61: =L216-K216 | M61: =M216-L216 | ... Q61: =Q216-P216 | R61: =SUM(F61:Q61) | S61: =S216-Q216 | T61: =T216-S216 | U61: =U216-T216 | V61: =V216-U216 | W61: =W216-V216 | X61: =X216-W216 | Y61: =Y216-X216 | Z61: =Z216-Y216 | AA61: =AA216-Z216 | ... AD61: =AD216-AC216 | AE61: =SUM(S61:AD61) | AF61: =AF216-AE216 | AG61: =AG216-AF216 | AH61: =AH216-AG216
B62: =B217 | F62: =F217-E217 | G62: =G217-F217 | H62: =H217-G217 | I62: =I217-H217 | J62: =J217-I217 | K62: =K217-J217 | L62: =L217-K217 | M62: =M217-L217 | ... Q62: =Q217-P217 | R62: =SUM(F62:Q62) | S62: =S217-Q217 | T62: =T217-S217 | U62: =U217-T217 | V62: =V217-U217 | W62: =W217-V217 | X62: =X217-W217 | Y62: =Y217-X217 | Z62: =Z217-Y217 | AA62: =AA217-Z217 | ... AD62: =AD217-AC217 | AE62: =SUM(S62:AD62) | AF62: =AF217-AE217 | AG62: =AG217-AF217 | AH62: =AH217-AG217
B63: ="Additions to "&B218 | F63: =IF(F218-E218>0,F218-E218,0) | G63: =IF(G218-F218>0,G218-F218,0) | H63: =IF(H218-G218>0,H218-G218,0) | I63: =IF(I218-H218>0,I218-H218,0) | J63: =IF(J218-I218>0,J218-I218,0) | K63: =IF(K218-J218>0,K218-J218,0) | L63: =IF(L218-K218>0,L218-K218,0) | M63: =IF(M218-L218>0,M218-L218,0) | ... Q63: =IF(Q218-P218>0,Q218-P218,0) | R63: =SUM(F63:Q63) | S63: =IF(S218-R218>0,S218-R218,0) | T63: =IF(T218-S218>0,T218-S218,0) | U63: =IF(U218-T218>0,U218-T218,0) | V63: =IF(V218-U218>0,V218-U218,0) | W63: =IF(W218-V218>0,W218-V218,0) | X63: =IF(X218-W218>0,X218-W218,0) | Y63: =IF(Y218-X218>0,Y218-X218,0) | Z63: =IF(Z218-Y218>0,Z218-Y218,0) | ... AD63: =IF(AD218-AC218>0,AD218-AC218,0) | AE63: =SUM(S63:AD63) | AF63: =IF(AF218-AE218>0,AF218-AE218,0) | AG63: =IF(AG218-AF218>0,AG218-AF218,0) | AH63: =IF(AH218-AG218>0,AH218-AG218,0)
B64: ="Additions to "&B224 | F64: =IF(F219+F224-E219-E224>0,F219+F224-E219-E224,0) | G64: =IF(G219+G224-F219-F224>0,G219+G224-F219-F224,0) | H64: =IF(H219+H224-G219-G224>0,H219+H224-G219-G224,0) | I64: =IF(I219+I224-H219-H224>0,I219+I224-H219-H224,0) | J64: =IF(J219+J224-I219-I224>0,J219+J224-I219-I224,0) | K64: =IF(K219+K224-J219-J224>0,K219+K224-J219-J224,0) | L64: =IF(L219+L224-K219-K224>0,L219+L224-K219-K224,0) | M64: =IF(M219+M224-L219-L224>0,M219+M224-L219-L224,0) | ... Q64: =IF(Q219+Q224-P219-P224>0,Q219+Q224-P219-P224,0) | R64: =SUM(F64:Q64) | S64: =IF(S219+S224-R219-R224>0,S219+S224-R219-R224,0) | T64: =IF(T219+T224-S219-S224>0,T219+T224-S219-S224,0) | U64: =IF(U219+U224-T219-T224>0,U219+U224-T219-T224,0) | V64: =IF(V219+V224-U219-U224>0,V219+V224-U219-U224,0) | W64: =IF(W219+W224-V219-V224>0,W219+W224-V219-V224,0) | X64: =IF(X219+X224-W219-W224>0,X219+X224-W219-W224,0) | Y64: =IF(Y219+Y224-X219-X224>0,Y219+Y224-X219-X224,0) | Z64: =IF(Z219+Z224-Y219-Y224>0,Z219+Z224-Y219-Y224,0) | ... AD64: =IF(AD219+AD224-AC219-AC224>0,AD219+AD224-AC219-AC224,0) | AE64: =SUM(S64:AD64) | AF64: =IF(AF219+AF224-AE219-AE224>0,AF219+AF224-AE219-AE224,0) | AG64: =IF(AG219+AG224-AF219-AF224>0,AG219+AG224-AF219-AF224,0) | AH64: =IF(AH219+AH224-AG219-AG224>0,AH219+AH224-AG219-AG224,0)
B65: ="Additions to "&B225 | F65: =IF(F220+F225-E220-E225>0,F220+F225-E220-E225,0) | G65: =IF(G220+G225-F220-F225>0,G220+G225-F220-F225,0) | H65: =IF(H220+H225-G220-G225>0,H220+H225-G220-G225,0) | I65: =IF(I220+I225-H220-H225>0,I220+I225-H220-H225,0) | J65: =IF(J220+J225-I220-I225>0,J220+J225-I220-I225,0) | K65: =IF(K220+K225-J220-J225>0,K220+K225-J220-J225,0) | L65: =IF(L220+L225-K220-K225>0,L220+L225-K220-K225,0) | M65: =IF(M220+M225-L220-L225>0,M220+M225-L220-L225,0) | ... Q65: =IF(Q220+Q225-P220-P225>0,Q220+Q225-P220-P225,0) | R65: =SUM(F65:Q65) | S65: =IF(S220+S225-R220-R225>0,S220+S225-R220-R225,0) | T65: =IF(T220+T225-S220-S225>0,T220+T225-S220-S225,0) | U65: =IF(U220+U225-T220-T225>0,U220+U225-T220-T225,0) | V65: =IF(V220+V225-U220-U225>0,V220+V225-U220-U225,0) | W65: =IF(W220+W225-V220-V225>0,W220+W225-V220-V225,0) | X65: =IF(X220+X225-W220-W225>0,X220+X225-W220-W225,0) | Y65: =IF(Y220+Y225-X220-X225>0,Y220+Y225-X220-X225,0) | Z65: =IF(Z220+Z225-Y220-Y225>0,Z220+Z225-Y220-Y225,0) | ... AD65: =IF(AD220+AD225-AC220-AC225>0,AD220+AD225-AC220-AC225,0) | AE65: =SUM(S65:AD65) | AF65: =IF(AF220+AF225-AE220-AE225>0,AF220+AF225-AE220-AE225,0) | AG65: =IF(AG220+AG225-AF220-AF225>0,AG220+AG225-AF220-AF225,0) | AH65: =IF(AH220+AH225-AG220-AG225>0,AH220+AH225-AG220-AG225,0)
A66: Total Sources of Cash | F66: =SUM(F55:F65) | G66: =SUM(G55:G65) | H66: =SUM(H55:H65) | I66: =SUM(I55:I65) | J66: =SUM(J55:J65) | K66: =SUM(K55:K65) | L66: =SUM(L55:L65) | M66: =SUM(M55:M65) | ... Q66: =SUM(Q55:Q65) | R66: =SUM(F66:Q66) | S66: =SUM(S55:S65) | T66: =SUM(T55:T65) | U66: =SUM(U55:U65) | V66: =SUM(V55:V65) | W66: =SUM(W55:W65) | X66: =SUM(X55:X65) | Y66: =SUM(Y55:Y65) | Z66: =SUM(Z55:Z65) | ... AD66: =SUM(AD55:AD65) | AE66: =SUM(S66:AD66) | AF66: =SUM(AF55:AF65) | AG66: =SUM(AG55:AG65) | AH66: =SUM(AH55:AH65)
A68: Uses of Cash
B69: Buyback of Preferred Stock | F69: =IF(F231-E231<0,-(F231-E231),0) | G69: =IF(G231-F231<0,-(G231-F231),0) | H69: =IF(H231-G231<0,-(H231-G231),0) | I69: =IF(I231-H231<0,-(I231-H231),0) | J69: =IF(J231-I231<0,-(J231-I231),0) | K69: =IF(K231-J231<0,-(K231-J231),0) | L69: =IF(L231-K231<0,-(L231-K231),0) | M69: =IF(M231-L231<0,-(M231-L231),0) | ... Q69: =IF(Q231-P231<0,-(Q231-P231),0) | R69: =SUM(F69:Q69) | S69: =IF(S231-R231<0,-(S231-R231),0) | T69: =IF(T231-S231<0,-(T231-S231),0) | U69: =IF(U231-T231<0,-(U231-T231),0) | V69: =IF(V231-U231<0,-(V231-U231),0) | W69: =IF(W231-V231<0,-(W231-V231),0) | X69: =IF(X231-W231<0,-(X231-W231),0) | Y69: =IF(Y231-X231<0,-(Y231-X231),0) | Z69: =IF(Z231-Y231<0,-(Z231-Y231),0) | ... AD69: =IF(AD231-AC231<0,-(AD231-AC231),0) | AE69: =SUM(S69:AD69) | AF69: =IF(AF231-AE231<0,-(AF231-AE231),0) | AG69: =IF(AG231-AF231<0,-(AG231-AF231),0) | AH69: =IF(AH231-AG231<0,-(AH231-AG231),0)
B70: Buyback of Common Stock | F70: =IF(F232-E232<0,-(F232-E232),0) | G70: =IF(G232-F232<0,-(G232-F232),0) | H70: =IF(H232-G232<0,-(H232-G232),0) | I70: =IF(I232-H232<0,-(I232-H232),0) | J70: =IF(J232-I232<0,-(J232-I232),0) | K70: =IF(K232-J232<0,-(K232-J232),0) | L70: =IF(L232-K232<0,-(L232-K232),0) | M70: =IF(M232-L232<0,-(M232-L232),0) | ... Q70: =IF(Q232-P232<0,-(Q232-P232),0) | R70: =SUM(F70:Q70) | S70: =IF(S232-R232<0,-(S232-R232),0) | T70: =IF(T232-S232<0,-(T232-S232),0) | U70: =IF(U232-T232<0,-(U232-T232),0) | V70: =IF(V232-U232<0,-(V232-U232),0) | W70: =IF(W232-V232<0,-(W232-V232),0) | X70: =IF(X232-W232<0,-(X232-W232),0) | Y70: =IF(Y232-X232<0,-(Y232-X232),0) | Z70: =IF(Z232-Y232<0,-(Z232-Y232),0) | ... AD70: =IF(AD232-AC232<0,-(AD232-AC232),0) | AE70: =SUM(S70:AD70) | AF70: =IF(AF232-AE232<0,-(AF232-AE232),0) | AG70: =IF(AG232-AF232<0,-(AG232-AF232),0) | AH70: =IF(AH232-AG232<0,-(AH232-AG232),0)
A71: Less Changes In:
B72: =B192 | F72: =F192-E192 | G72: =G192-F192 | H72: =H192-G192 | I72: =I192-H192 | J72: =J192-I192 | K72: =K192-J192 | L72: =L192-K192 | M72: =M192-L192 | ... Q72: =Q192-P192 | R72: =SUM(F72:Q72) | S72: =S192-Q192 | T72: =T192-S192 | U72: =U192-T192 | V72: =V192-U192 | W72: =W192-V192 | X72: =X192-W192 | Y72: =Y192-X192 | Z72: =Z192-Y192 | AA72: =AA192-Z192 | ... AD72: =AD192-AC192 | AE72: =SUM(S72:AD72) | AF72: =AF192-AE192 | AG72: =AG192-AF192 | AH72: =AH192-AG192
B73: =B193 | F73: =F193-E193 | G73: =G193-F193 | H73: =H193-G193 | I73: =I193-H193 | J73: =J193-I193 | K73: =K193-J193 | L73: =L193-K193 | M73: =M193-L193 | ... Q73: =Q193-P193 | R73: =SUM(F73:Q73) | S73: =S193-Q193 | T73: =T193-S193 | U73: =U193-T193 | V73: =V193-U193 | W73: =W193-V193 | X73: =X193-W193 | Y73: =Y193-X193 | Z73: =Z193-Y193 | AA73: =AA193-Z193 | ... AD73: =AD193-AC193 | AE73: =SUM(S73:AD73) | AF73: =AF193-AE193 | AG73: =AG193-AF193 | AH73: =AH193-AG193
B74: Gross Fixed Assets | F74: =F200-E200 | G74: =G200-F200 | H74: =H200-G200 | I74: =I200-H200 | J74: =J200-I200 | K74: =K200-J200 | L74: =L200-K200 | M74: =M200-L200 | ... Q74: =Q200-P200 | R74: =SUM(F74:Q74) | S74: =S200-Q200 | T74: =T200-S200 | U74: =U200-T200 | V74: =V200-U200 | W74: =W200-V200 | X74: =X200-W200 | Y74: =Y200-X200 | Z74: =Z200-Y200 | AA74: =AA200-Z200 | ... AD74: =AD200-AC200 | AE74: =SUM(S74:AD74) | AF74: =AF200-AE200 | AG74: =AG200-AF200 | AH74: =AH200-AG200
B75: Reductions To Credit Line | F75: =IF(F218-E218<0,-(F218-E218),0) | G75: =IF(G218-F218<0,-(G218-F218),0) | H75: =IF(H218-G218<0,-(H218-G218),0) | I75: =IF(I218-H218<0,-(I218-H218),0) | J75: =IF(J218-I218<0,-(J218-I218),0) | K75: =IF(K218-J218<0,-(K218-J218),0) | L75: =IF(L218-K218<0,-(L218-K218),0) | M75: =IF(M218-L218<0,-(M218-L218),0) | ... Q75: =IF(Q218-P218<0,-(Q218-P218),0) | R75: =SUM(F75:Q75) | S75: =IF(S218-R218<0,-(S218-R218),0) | T75: =IF(T218-S218<0,-(T218-S218),0) | U75: =IF(U218-T218<0,-(U218-T218),0) | V75: =IF(V218-U218<0,-(V218-U218),0) | W75: =IF(W218-V218<0,-(W218-V218),0) | X75: =IF(X218-W218<0,-(X218-W218),0) | Y75: =IF(Y218-X218<0,-(Y218-X218),0) | Z75: =IF(Z218-Y218<0,-(Z218-Y218),0) | ... AD75: =IF(AD218-AC218<0,-(AD218-AC218),0) | AE75: =SUM(S75:AD75) | AF75: =IF(AF218-AE218<0,-(AF218-AE218),0) | AG75: =IF(AG218-AF218<0,-(AG218-AF218),0) | AH75: =IF(AH218-AG218<0,-(AH218-AG218),0)
B76: Reductions To Capital Equipment Lease | F76: =IF(F219+F224-E219-E224<0,-(F219+F224-E219-E224),0) | G76: =IF(G219+G224-F219-F224<0,-(G219+G224-F219-F224),0) | H76: =IF(H219+H224-G219-G224<0,-(H219+H224-G219-G224),0) | I76: =IF(I219+I224-H219-H224<0,-(I219+I224-H219-H224),0) | J76: =IF(J219+J224-I219-I224<0,-(J219+J224-I219-I224),0) | K76: =IF(K219+K224-J219-J224<0,-(K219+K224-J219-J224),0) | L76: =IF(L219+L224-K219-K224<0,-(L219+L224-K219-K224),0) | M76: =IF(M219+M224-L219-L224<0,-(M219+M224-L219-L224),0) | ... Q76: =IF(Q219+Q224-P219-P224<0,-(Q219+Q224-P219-P224),0) | R76: =SUM(F76:Q76) | S76: =IF(S219+S224-R219-R224<0,-(S219+S224-R219-R224),0) | T76: =IF(T219+T224-S219-S224<0,-(T219+T224-S219-S224),0) | U76: =IF(U219+U224-T219-T224<0,-(U219+U224-T219-T224),0) | V76: =IF(V219+V224-U219-U224<0,-(V219+V224-U219-U224),0) | W76: =IF(W219+W224-V219-V224<0,-(W219+W224-V219-V224),0) | X76: =IF(X219+X224-W219-W224<0,-(X219+X224-W219-W224),0) | Y76: =IF(Y219+Y224-X219-X224<0,-(Y219+Y224-X219-X224),0) | Z76: =IF(Z219+Z224-Y219-Y224<0,-(Z219+Z224-Y219-Y224),0) | ... AD76: =IF(AD219+AD224-AC219-AC224<0,-(AD219+AD224-AC219-AC224),0) | AE76: =SUM(S76:AD76) | AF76: =IF(AF219+AF224-AE219-AE224<0,-(AF219+AF224-AE219-AE224),0) | AG76: =IF(AG219+AG224-AF219-AF224<0,-(AG219+AG224-AF219-AF224),0) | AH76: =IF(AH219+AH224-AG219-AG224<0,-(AH219+AH224-AG219-AG224),0)
B77: Reductions To Long Term Debt | F77: =IF(F220+F225-E220-E225<0,-(F220+F225-E220-E225),0) | G77: =IF(G220+G225-F220-F225<0,-(G220+G225-F220-F225),0) | H77: =IF(H220+H225-G220-G225<0,-(H220+H225-G220-G225),0) | I77: =IF(I220+I225-H220-H225<0,-(I220+I225-H220-H225),0) | J77: =IF(J220+J225-I220-I225<0,-(J220+J225-I220-I225),0) | K77: =IF(K220+K225-J220-J225<0,-(K220+K225-J220-J225),0) | L77: =IF(L220+L225-K220-K225<0,-(L220+L225-K220-K225),0) | M77: =IF(M220+M225-L220-L225<0,-(M220+M225-L220-L225),0) | ... Q77: =IF(Q220+Q225-P220-P225<0,-(Q220+Q225-P220-P225),0) | R77: =SUM(F77:Q77) | S77: =IF(S220+S225-R220-R225<0,-(S220+S225-R220-R225),0) | T77: =IF(T220+T225-S220-S225<0,-(T220+T225-S220-S225),0) | U77: =IF(U220+U225-T220-T225<0,-(U220+U225-T220-T225),0) | V77: =IF(V220+V225-U220-U225<0,-(V220+V225-U220-U225),0) | W77: =IF(W220+W225-V220-V225<0,-(W220+W225-V220-V225),0) | X77: =IF(X220+X225-W220-W225<0,-(X220+X225-W220-W225),0) | Y77: =IF(Y220+Y225-X220-X225<0,-(Y220+Y225-X220-X225),0) | Z77: =IF(Z220+Z225-Y220-Y225<0,-(Z220+Z225-Y220-Y225),0) | ... AD77: =IF(AD220+AD225-AC220-AC225<0,-(AD220+AD225-AC220-AC225),0) | AE77: =SUM(S77:AD77) | AF77: =IF(AF220+AF225-AE220-AE225<0,-(AF220+AF225-AE220-AE225),0) | AG77: =IF(AG220+AG225-AF220-AF225<0,-(AG220+AG225-AF220-AF225),0) | AH77: =IF(AH220+AH225-AG220-AG225<0,-(AH220+AH225-AG220-AG225),0)
A78: Total Uses | F78: =SUM(F72:F77) | G78: =SUM(G72:G77) | H78: =SUM(H72:H77) | I78: =SUM(I72:I77) | J78: =SUM(J72:J77) | K78: =SUM(K72:K77) | L78: =SUM(L72:L77) | M78: =SUM(M72:M77) | ... Q78: =SUM(Q72:Q77) | R78: =SUM(F78:Q78) | S78: =SUM(S72:S77) | T78: =SUM(T72:T77) | U78: =SUM(U72:U77) | V78: =SUM(V72:V77) | W78: =SUM(W72:W77) | X78: =SUM(X72:X77) | Y78: =SUM(Y72:Y77) | Z78: =SUM(Z72:Z77) | ... AD78: =SUM(AD72:AD77) | AE78: =SUM(S78:AD78) | AF78: =SUM(AF72:AF77) | AG78: =SUM(AG72:AG77) | AH78: =SUM(AH72:AH77)
A80: CHANGES IN CASH | F80: =F66-F78 | G80: =G66-G78 | H80: =H66-H78 | I80: =I66-I78 | J80: =J66-J78 | K80: =K66-K78 | L80: =L66-L78 | M80: =M66-M78 | ... Q80: =Q66-Q78 | R80: =SUM(F80:Q80) | S80: =S66-S78 | T80: =T66-T78 | U80: =U66-U78 | V80: =V66-V78 | W80: =W66-W78 | X80: =X66-X78 | Y80: =Y66-Y78 | Z80: =Z66-Z78 | ... AD80: =AD66-AD78 | AE80: =SUM(S80:AD80) | AF80: =AF66-AF78 | AG80: =AG66-AG78 | AH80: =AH66-AH78
A82: ENDING CASH | F82: =F52+F80 | G82: =G52+G80 | H82: =H52+H80 | I82: =I52+I80 | J82: =J52+J80 | K82: =K52+K80 | L82: =L52+L80 | M82: =M52+M80 | ... Q82: =Q52+Q80 | R82: =Q82 | S82: =S52+S80 | T82: =T52+T80 | U82: =U52+U80 | V82: =V52+V80 | W82: =W52+W80 | X82: =X52+X80 | Y82: =Y52+Y80 | Z82: =Z52+Z80 | ... AD82: =AD52+AD80 | AE82: =AD82 | AF82: =AF52+AF80 | AG82: =AG52+AG80 | AH82: =AH52+AH80
A83: INCOME STATEMENT
A84: =$A$1
B85: =NOW() | F85: =F$7 | G85: =G$7 | H85: =H$7 | I85: =I$7 | J85: =J$7 | K85: =K$7 | L85: =L$7 | M85: =M$7 | ... Q85: =Q$7 | R85: Total | S85: =S$7 | T85: =T$7 | U85: =U$7 | V85: =V$7 | W85: =W$7 | X85: =X$7 | Y85: =Y$7 | Z85: =Z$7 | ... AD85: =AD$7 | AE85: Total | AF85: =AF$7 | AG85: =AG$7 | AH85: =AH$7
B86: =NOW() | F86: =F$1 | G86: =G$1 | H86: =H$1 | I86: =I$1 | J86: =J$1 | K86: =K$1 | L86: =L$1 | M86: =M$1 | ... AH86: =AH$1
A88: Revenue
B89: =Assumptions!I10 | F89: =F255 | G89: =G255 | H89: =H255 | I89: =I255 | J89: =J255 | K89: =K255 | L89: =L255 | M89: =M255 | ... Q89: =Q255 | R89: =SUM(F89:Q89) | S89: =S255 | T89: =T255 | U89: =U255 | V89: =V255 | W89: =W255 | X89: =X255 | Y89: =Y255 | Z89: =Z255 | ... AD89: =AD255 | AE89: =SUM(S89:AD89) | AF89: =AF255 | AG89: =AG255 | AH89: =AH255
B90: =Assumptions!I11 | F90: =F294 | G90: =G294 | H90: =H294 | I90: =I294 | J90: =J294 | K90: =K294 | L90: =L294 | M90: =M294 | ... Q90: =Q294 | R90: =SUM(F90:Q90) | S90: =S294 | T90: =T294 | U90: =U294 | V90: =V294 | W90: =W294 | X90: =X294 | Y90: =Y294 | Z90: =Z294 | ... AD90: =AD294 | AE90: =SUM(S90:AD90) | AF90: =AF294 | AG90: =AG294 | AH90: =AH294
B91: =Assumptions!I12 | F91: =F333 | G91: =G333 | H91: =H333 | I91: =I333 | J91: =J333 | K91: =K333 | L91: =L333 | M91: =M333 | ... Q91: =Q333 | R91: =SUM(F91:Q91) | S91: =S333 | T91: =T333 | U91: =U333 | V91: =V333 | W91: =W333 | X91: =X333 | Y91: =Y333 | Z91: =Z333 | ... AD91: =AD333 | AE91: =SUM(S91:AD91) | AF91: =AF333 | AG91: =AG333 | AH91: =AH333
B92: =Assumptions!I13 | F92: =F372 | G92: =G372 | H92: =H372 | I92: =I372 | J92: =J372 | K92: =K372 | L92: =L372 | M92: =M372 | ... Q92: =Q372 | R92: =SUM(F92:Q92) | S92: =S372 | T92: =T372 | U92: =U372 | V92: =V372 | W92: =W372 | X92: =X372 | Y92: =Y372 | Z92: =Z372 | ... AD92: =AD372 | AE92: =SUM(S92:AD92) | AF92: =AF372 | AG92: =AG372 | AH92: =AH372
A93: Total Revenue | F93: =SUM(F89:F92) | G93: =SUM(G89:G92) | H93: =SUM(H89:H92) | I93: =SUM(I89:I92) | J93: =SUM(J89:J92) | K93: =SUM(K89:K92) | L93: =SUM(L89:L92) | M93: =SUM(M89:M92) | ... Q93: =SUM(Q89:Q92) | R93: =SUM(F93:Q93) | S93: =SUM(S89:S92) | T93: =SUM(T89:T92) | U93: =SUM(U89:U92) | V93: =SUM(V89:V92) | W93: =SUM(W89:W92) | X93: =SUM(X89:X92) | Y93: =SUM(Y89:Y92) | Z93: =SUM(Z89:Z92) | ... AD93: =SUM(AD89:AD92) | AE93: =SUM(S93:AD93) | AF93: =SUM(AF89:AF92) | AG93: =SUM(AG89:AG92) | AH93: =SUM(AH89:AH92)
A95: Expenses
A96: Cost of Goods Sold
B97: Direct Labor | F97: =IF(F$93=0,0,F386) | G97: =IF(G$93=0,0,G386) | H97: =IF(H$93=0,0,H386) | I97: =IF(I$93=0,0,I386) | J97: =IF(J$93=0,0,J386) | K97: =IF(K$93=0,0,K386) | L97: =IF(L$93=0,0,L386) | M97: =IF(M$93=0,0,M386) | ... Q97: =IF(Q$93=0,0,Q386) | R97: =SUM(F97:Q97) | S97: =IF(S$93=0,0,S386) | T97: =IF(T$93=0,0,T386) | U97: =IF(U$93=0,0,U386) | V97: =IF(V$93=0,0,V386) | W97: =IF(W$93=0,0,W386) | X97: =IF(X$93=0,0,X386) | Y97: =IF(Y$93=0,0,Y386) | Z97: =IF(Z$93=0,0,Z386) | ... AD97: =IF(AD$93=0,0,AD386) | AE97: =SUM(S97:AD97) | AF97: =IF(AF$93=0,0,AF386) | AG97: =IF(AG$93=0,0,AG386) | AH97: =IF(AH$93=0,0,AH386)
B98: Other Direct Costs | F98: =IF(F$93=0,0,F388) | G98: =IF(G$93=0,0,G388) | H98: =IF(H$93=0,0,H388) | I98: =IF(I$93=0,0,I388) | J98: =IF(J$93=0,0,J388) | K98: =IF(K$93=0,0,K388) | L98: =IF(L$93=0,0,L388) | M98: =IF(M$93=0,0,M388) | ... Q98: =IF(Q$93=0,0,Q388) | R98: =SUM(F98:Q98) | S98: =IF(S$93=0,0,S388) | T98: =IF(T$93=0,0,T388) | U98: =IF(U$93=0,0,U388) | V98: =IF(V$93=0,0,V388) | W98: =IF(W$93=0,0,W388) | X98: =IF(X$93=0,0,X388) | Y98: =IF(Y$93=0,0,Y388) | Z98: =IF(Z$93=0,0,Z388) | ... AD98: =IF(AD$93=0,0,AD388) | AE98: =SUM(S98:AD98) | AF98: =IF(AF$93=0,0,AF388) | AG98: =IF(AG$93=0,0,AG388) | AH98: =IF(AH$93=0,0,AH388)
B99: Direct Materials | F99: =F267+F306+F345+F384 | G99: =G267+G306+G345+G384 | H99: =H267+H306+H345+H384 | I99: =I267+I306+I345+I384 | J99: =J267+J306+J345+J384 | K99: =K267+K306+K345+K384 | L99: =L267+L306+L345+L384 | M99: =M267+M306+M345+M384 | ... Q99: =Q267+Q306+Q345+Q384 | R99: =SUM(F99:Q99) | S99: =S267+S306+S345+S384 | T99: =T267+T306+T345+T384 | U99: =U267+U306+U345+U384 | V99: =V267+V306+V345+V384 | W99: =W267+W306+W345+W384 | X99: =X267+X306+X345+X384 | Y99: =Y267+Y306+Y345+Y384 | Z99: =Z267+Z306+Z345+Z384 | ... AD99: =AD267+AD306+AD345+AD384 | AE99: =SUM(S99:AD99) | AF99: =AF267+AF306+AF345+AF384 | AG99: =AG267+AG306+AG345+AG384 | AH99: =AH267+AH306+AH345+AH384
B100: Returns | F100: =F269+F308+F347+F390 | G100: =G269+G308+G347+G390 | H100: =H269+H308+H347+H390 | I100: =I269+I308+I347+I390 | J100: =J269+J308+J347+J390 | K100: =K269+K308+K347+K390 | L100: =L269+L308+L347+L390 | M100: =M269+M308+M347+M390 | ... Q100: =Q269+Q308+Q347+Q390 | R100: =SUM(F100:Q100) | S100: =S269+S308+S347+S390 | T100: =T269+T308+T347+T390 | U100: =U269+U308+U347+U390 | V100: =V269+V308+V347+V390 | W100: =W269+W308+W347+W390 | X100: =X269+X308+X347+X390 | Y100: =Y269+Y308+Y347+Y390 | Z100: =Z269+Z308+Z347+Z390 | ... AD100: =AD269+AD308+AD347+AD390 | AE100: =SUM(S100:AD100) | AF100: =AF269+AF308+AF347+AF390 | AG100: =AG269+AG308+AG347+AG390 | AH100: =AH269+AH308+AH347+AH390
A101: Total COGS | F101: =SUM(F97:F100) | G101: =SUM(G97:G100) | H101: =SUM(H97:H100) | I101: =SUM(I97:I100) | J101: =SUM(J97:J100) | K101: =SUM(K97:K100) | L101: =SUM(L97:L100) | M101: =SUM(M97:M100) | ... Q101: =SUM(Q97:Q100) | R101: =SUM(F101:Q101) | S101: =SUM(S97:S100) | T101: =SUM(T97:T100) | U101: =SUM(U97:U100) | V101: =SUM(V97:V100) | W101: =SUM(W97:W100) | X101: =SUM(X97:X100) | Y101: =SUM(Y97:Y100) | Z101: =SUM(Z97:Z100) | ... AD101: =SUM(AD97:AD100) | AE101: =SUM(S101:AD101) | AF101: =SUM(AF97:AF100) | AG101: =SUM(AG97:AG100) | AH101: =SUM(AH97:AH100)
A103: Gross Margin | F103: =F93-F101 | G103: =G93-G101 | H103: =H93-H101 | I103: =I93-I101 | J103: =J93-J101 | K103: =K93-K101 | L103: =L93-L101 | M103: =M93-M101 | ... Q103: =Q93-Q101 | R103: =SUM(F103:Q103) | S103: =S93-S101 | T103: =T93-T101 | U103: =U93-U101 | V103: =V93-V101 | W103: =W93-W101 | X103: =X93-X101 | Y103: =Y93-Y101 | Z103: =Z93-Z101 | ... AD103: =AD93-AD101 | AE103: =SUM(S103:AD103) | AF103: =AF93-AF101 | AG103: =AG93-AG101 | AH103: =AH93-AH101
B104: % of Sales | F104: =IF(F$93>0,F103/F$93,0) | G104: =IF(G$93>0,G103/G$93,0) | H104: =IF(H$93>0,H103/H$93,0) | I104: =IF(I$93>0,I103/I$93,0) | J104: =IF(J$93>0,J103/J$93,0) | K104: =IF(K$93>0,K103/K$93,0) | L104: =IF(L$93>0,L103/L$93,0) | M104: =IF(M$93>0,M103/M$93,0) | ... AH104: =IF(AH$93>0,AH103/AH$93,0)
A106: Operating Expenses
A107: =UPPER($A$409)
B108: Headcount | F108: =F415 | G108: =G415 | H108: =H415 | I108: =I415 | J108: =J415 | K108: =K415 | L108: =L415 | M108: =M415 | ... Q108: =Q415 | R108: =Q108 | S108: =S415 | T108: =T415 | U108: =U415 | V108: =V415 | W108: =W415 | X108: =X415 | Y108: =Y415 | Z108: =Z415 | ... AD108: =AD415 | AE108: =AD108 | AF108: =AF415 | AG108: =AG415 | AH108: =AH415
B109: Salary | F109: =F458 | G109: =G458 | H109: =H458 | I109: =I458 | J109: =J458 | K109: =K458 | L109: =L458 | M109: =M458 | ... Q109: =Q458 | R109: =SUM(F109:Q109) | S109: =S458 | T109: =T458 | U109: =U458 | V109: =V458 | W109: =W458 | X109: =X458 | Y109: =Y458 | Z109: =Z458 | ... AD109: =AD458 | AE109: =SUM(S109:AD109) | AF109: =AF458 | AG109: =AG458 | AH109: =AH458
B110: Incentives | F110: 0 | G110: 0 | H110: 0 | I110: 0 | J110: 0 | K110: 0 | L110: 0 | M110: 0 | N110: 0 | O110: 0 | P110: 0 | Q110: 0 | R110: =SUM(F110:Q110) | S110: 0 | T110: 0 | U110: 0 | V110: 0 | W110: 0 | X110: 0 | Y110: 0 | Z110: 0 | AA110: 0 | AB110: 0 | AC110: 0 | AD110: 0 | AE110: =SUM(S110:AD110) | AF110: 0 | AG110: 0 | AH110: 0
B111: Benefits & Taxes | F111: =SUM(F109:F110)*F$482 | G111: =SUM(G109:G110)*G$482 | H111: =SUM(H109:H110)*H$482 | I111: =SUM(I109:I110)*I$482 | J111: =SUM(J109:J110)*J$482 | K111: =SUM(K109:K110)*K$482 | L111: =SUM(L109:L110)*L$482 | M111: =SUM(M109:M110)*M$482 | ... Q111: =SUM(Q109:Q110)*Q$482 | R111: =SUM(F111:Q111) | S111: =SUM(S109:S110)*S$482 | T111: =SUM(T109:T110)*T$482 | U111: =SUM(U109:U110)*U$482 | V111: =SUM(V109:V110)*V$482 | W111: =SUM(W109:W110)*W$482 | X111: =SUM(X109:X110)*X$482 | Y111: =SUM(Y109:Y110)*Y$482 | Z111: =SUM(Z109:Z110)*Z$482 | ... AD111: =SUM(AD109:AD110)*AD$482 | AE111: =SUM(S111:AD111) | AF111: =SUM(AF109:AF110)*AF$482 | AG111: =SUM(AG109:AG110)*AG$482 | AH111: =SUM(AH109:AH110)*AH$482
B112: Consultants | F112: 0 | G112: 0 | H112: 0 | I112: 0 | J112: 0 | K112: 0 | L112: 0 | M112: 0 | N112: 0 | O112: 0 | P112: 0 | Q112: 0 | R112: =SUM(F112:Q112) | S112: 0 | T112: 0 | U112: 0 | V112: 0 | W112: 0 | X112: 0 | Y112: 0 | Z112: 0 | AA112: 0 | AB112: 0 | AC112: 0 | AD112: 0 | AE112: =SUM(S112:AD112) | AF112: 0 | AG112: 0 | AH112: 0
B113: Supplies/ Materials | C113: =Assumptions!E92 | F113: =$C113*F$108 | G113: =$C113*G$108 | H113: =$C113*H$108 | I113: =$C113*I$108 | J113: =$C113*J$108 | K113: =$C113*K$108 | L113: =$C113*L$108 | M113: =$C113*M$108 | ... Q113: =$C113*Q$108 | R113: =SUM(F113:Q113) | S113: =$C113*S$108 | T113: =$C113*T$108 | U113: =$C113*U$108 | V113: =$C113*V$108 | W113: =$C113*W$108 | X113: =$C113*X$108 | Y113: =$C113*Y$108 | Z113: =$C113*Z$108 | ... AD113: =$C113*AD$108 | AE113: =SUM(S113:AD113) | AF113: =$C113*AF$108*12 | AG113: =$C113*AG$108*12 | AH113: =$C113*AH$108*12
B114: Travel & Meals | C114: =Assumptions!F92 | F114: =$C114*F$108 | G114: =$C114*G$108 | H114: =$C114*H$108 | I114: =$C114*I$108 | J114: =$C114*J$108 | K114: =$C114*K$108 | L114: =$C114*L$108 | M114: =$C114*M$108 | ... Q114: =$C114*Q$108 | R114: =SUM(F114:Q114) | S114: =$C114*S$108 | T114: =$C114*T$108 | U114: =$C114*U$108 | V114: =$C114*V$108 | W114: =$C114*W$108 | X114: =$C114*X$108 | Y114: =$C114*Y$108 | Z114: =$C114*Z$108 | ... AD114: =$C114*AD$108 | AE114: =SUM(S114:AD114) | AF114: =$C114*AF$108*12 | AG114: =$C114*AG$108*12 | AH114: =$C114*AH$108*12
...

Sheet Summary Statements
A1: CHECKS | C1: ='DETAIL.XLS'!R1 | D1: ='DETAIL.XLS'!AE1 | E1: ='DETAIL.XLS'!AF1 | F1: ='DETAIL.XLS'!AG1 | G1: ='DETAIL.XLS'!AH1
B2: Balance Sheet Check | C2: =+C59-C84 | D2: =+D59-D84 | E2: =+E59-E84 | F2: =+F59-F84 | G2: =+G59-G84
B3: S & U to Income Stmt | C3: =+C41-C93 | D3: =+D41-D93 | E3: =+E41-E93 | F3: =+F41-F93 | G3: =+G41-G93
B4: S & U to Balance Sheet | C4: =+C118-C50 | D4: =+D118-D50 | E4: =+E118-E50 | F4: =+F118-F50 | G4: =+G118-G50
A5: ='DETAIL.XLS'!$A$1
A6: Income Statement ($)
C8: =C$1 | D8: =D$1 | E8: =E$1 | F8: =F$1 | G8: =G$1
A10: Revenue
B11: =+'DETAIL.XLS'!B89 | C11: =+'DETAIL.XLS'!R89 | D11: =+'DETAIL.XLS'!AE89 | E11: =+'DETAIL.XLS'!AF89 | F11: =+'DETAIL.XLS'!AG89 | G11: =+'DETAIL.XLS'!AH89
B12: =+'DETAIL.XLS'!B90 | C12: =+'DETAIL.XLS'!R90 | D12: =+'DETAIL.XLS'!AE90 | E12: =+'DETAIL.XLS'!AF90 | F12: =+'DETAIL.XLS'!AG90 | G12: =+'DETAIL.XLS'!AH90
B13: =+'DETAIL.XLS'!B91 | C13: =+'DETAIL.XLS'!R91 | D13: =+'DETAIL.XLS'!AE91 | E13: =+'DETAIL.XLS'!AF91 | F13: =+'DETAIL.XLS'!AG91 | G13: =+'DETAIL.XLS'!AH91
B14: =+'DETAIL.XLS'!B92 | C14: =+'DETAIL.XLS'!R92 | D14: =+'DETAIL.XLS'!AE92 | E14: =+'DETAIL.XLS'!AF92 | F14: =+'DETAIL.XLS'!AG92 | G14: =+'DETAIL.XLS'!AH92
A15: Total Revenue | C15: =SUM(C11:C14) | D15: =SUM(D11:D14) | E15: =SUM(E11:E14) | F15: =SUM(F11:F14) | G15: =SUM(G11:G14)
A17: Cost of Goods Sold | C17: =+'DETAIL.XLS'!R101 | D17: =+'DETAIL.XLS'!AE101 | E17: =+'DETAIL.XLS'!AF101 | F17: =+'DETAIL.XLS'!AG101 | G17: =+'DETAIL.XLS'!AH101
A19: Gross Margin | C19: =+C15-C17 | D19: =+D15-D17 | E19: =+E15-E17 | F19: =+F15-F17 | G19: =+G15-G17
B20: % of Revenue | C20: =IF(C$15=0,0,C19/C$15) | D20: =IF(D$15=0,0,D19/D$15) | E20: =IF(E$15=0,0,E19/E$15) | F20: =IF(F$15=0,0,F19/F$15) | G20: =IF(G$15=0,0,G19/G$15)
A22: Operating Expenses
B23: Engineering | C23: =+'DETAIL.XLS'!R118 | D23: =+'DETAIL.XLS'!AE118 | E23: =+'DETAIL.XLS'!AF118 | F23: =+'DETAIL.XLS'!AG118 | G23: =+'DETAIL.XLS'!AH118
B24: % of Revenue | C24: =IF(C$15=0,0,C23/C$15) | D24: =IF(D$15=0,0,D23/D$15) | E24: =IF(E$15=0,0,E23/E$15) | F24: =IF(F$15=0,0,F23/F$15) | G24: =IF(G$15=0,0,G23/G$15)
B25: Marketing/Sales | C25: =+'DETAIL.XLS'!R130+'DETAIL.XLS'!R141 | D25: =+'DETAIL.XLS'!AE130+'DETAIL.XLS'!AE141 | E25: =+'DETAIL.XLS'!AF130+'DETAIL.XLS'!AF141 | F25: =+'DETAIL.XLS'!AG130+'DETAIL.XLS'!AG141 | G25: =+'DETAIL.XLS'!AH130+'DETAIL.XLS'!AH141
B26: % of Revenue | C26: =IF(C$15=0,0,C25/C$15) | D26: =IF(D$15=0,0,D25/D$15) | E26: =IF(E$15=0,0,E25/E$15) | F26: =IF(F$15=0,0,F25/F$15) | G26: =IF(G$15=0,0,G25/G$15)
B27: Administration | C27: =+'DETAIL.XLS'!R159 | D27: =+'DETAIL.XLS'!AE159 | E27: =+'DETAIL.XLS'!AF159 | F27: =+'DETAIL.XLS'!AG159 | G27: =+'DETAIL.XLS'!AH159
B28: % of Revenue | C28: =IF(C$15=0,0,C27/C$15) | D28: =IF(D$15=0,0,D27/D$15) | E28: =IF(E$15=0,0,E27/E$15) | F28: =IF(F$15=0,0,F27/F$15) | G28: =IF(G$15=0,0,G27/G$15)
A29: Total Operating Expenses | C29: =+C23+C25+C27 | D29: =+D23+D25+D27 | E29: =+E23+E25+E27 | F29: =+F23+F25+F27 | G29: =+G23+G25+G27
B30: % of Revenue | C30: =IF(C$15=0,0,C29/C$15) | D30: =IF(D$15=0,0,D29/D$15) | E30: =IF(E$15=0,0,E29/E$15) | F30: =IF(F$15=0,0,F29/F$15) | G30: =IF(G$15=0,0,G29/G$15)
A32: Income Before Int & Taxes | C32: =+C19-C29 | D32: =+D19-D29 | E32: =+E19-E29 | F32: =+F19-F29 | G32: =+G19-G29
B33: % of Revenue | C33: =IF(C$15=0,0,C32/C$15) | D33: =IF(D$15=0,0,D32/D$15) | E33: =IF(E$15=0,0,E32/E$15) | F33: =IF(F$15=0,0,F32/F$15) | G33: =IF(G$15=0,0,G32/G$15)
B35: Interest Expense | C35: =SUM('DETAIL.XLS'!R170:R172) | D35: =SUM('DETAIL.XLS'!AE170:AE172) | E35: =SUM('DETAIL.XLS'!AF170:AF172) | F35: =SUM('DETAIL.XLS'!AG170:AG172) | G35: =SUM('DETAIL.XLS'!AH170:AH172)
B36: Interest Revenue | C36: ='DETAIL.XLS'!R169 | D36: ='DETAIL.XLS'!AE169 | E36: ='DETAIL.XLS'!AF169 | F36: ='DETAIL.XLS'!AG169 | G36: ='DETAIL.XLS'!AH169
A38: Income Before Taxes | C38: =+C32-C35+C36 | D38: =+D32-D35+D36 | E38: =+E32-E35+E36 | F38: =+F32-F35+F36 | G38: =+G32-G35+G36
B39: =+'DETAIL.XLS'!B176 | C39: =+'DETAIL.XLS'!R176 | D39: =+'DETAIL.XLS'!AE176 | E39: =+'DETAIL.XLS'!AF176 | F39: =+'DETAIL.XLS'!AG176 | G39: =+'DETAIL.XLS'!AH176
A41: Net Income | C41: =+C38-C39 | D41: =+D38-D39 | E41: =+E38-E39 | F41: =+F38-F39 | G41: =+G38-G39
B42: % of Revenue | C42: =IF(C$15=0,0,C41/C$15) | D42: =IF(D$15=0,0,D41/D$15) | E42: =IF(E$15=0,0,E41/E$15) | F42: =IF(F$15=0,0,F41/F$15) | G42: =IF(G$15=0,0,G41/G$15)
A44: =+$A$5
A45: Balance Sheet ($)
C47: =C$1 | D47: =D$1 | E47: =E$1 | F47: =F$1 | G47: =G$1
A48: ASSETS
A49: Current Assets
B50: =+'DETAIL.XLS'!B189 | C50: =+'DETAIL.XLS'!R189 | D50: =+'DETAIL.XLS'!AE189 | E50: =+'DETAIL.XLS'!AF189 | F50: =+'DETAIL.XLS'!AG189 | G50: =+'DETAIL.XLS'!AH189
B51: =+'DETAIL.XLS'!B192 | C51: =+'DETAIL.XLS'!R192 | D51: =+'DETAIL.XLS'!AE192 | E51: =+'DETAIL.XLS'!AF192 | F51: =+'DETAIL.XLS'!AG192 | G51: =+'DETAIL.XLS'!AH192
B52: =+'DETAIL.XLS'!B193 | C52: =+'DETAIL.XLS'!R193 | D52: =+'DETAIL.XLS'!AE193 | E52: =+'DETAIL.XLS'!AF193 | F52: =+'DETAIL.XLS'!AG193 | G52: =+'DETAIL.XLS'!AH193
A53: Total Current Assets | C53: =SUM(C50:C52) | D53: =SUM(D50:D52) | E53: =SUM(E50:E52) | F53: =SUM(F50:F52) | G53: =SUM(G50:G52)
A55: Gross Fixed Assets | C55: =+'DETAIL.XLS'!R200 | D55: =+'DETAIL.XLS'!AE200 | E55: =+'DETAIL.XLS'!AF200 | F55: =+'DETAIL.XLS'!AG200 | G55: =+'DETAIL.XLS'!AH200
B56: Less Accum Depreciation | C56: =+'DETAIL.XLS'!R206 | D56: =+'DETAIL.XLS'!AE206 | E56: =+'DETAIL.XLS'!AF206 | F56: =+'DETAIL.XLS'!AG206 | G56: =+'DETAIL.XLS'!AH206
A57: Net Fixed Assets | C57: =+C55-C56 | D57: =+D55-D56 | E57: =+E55-E56 | F57: =+F55-F56 | G57: =+G55-G56
A59: TOTAL ASSETS | C59: =+C53+C57 | D59: =+D53+D57 | E59: =+E53+E57 | F59: =+F53+F57 | G59: =+G53+G57
A61: LIABILITIES
A62: Short Term Liabilities
B63: =+'DETAIL.XLS'!B215 | C63: =+'DETAIL.XLS'!R215 | D63: =+'DETAIL.XLS'!AE215 | E63: =+'DETAIL.XLS'!AF215 | F63: =+'DETAIL.XLS'!AG215 | G63: =+'DETAIL.XLS'!AH215
B64: =+'DETAIL.XLS'!B216 | C64: =+'DETAIL.XLS'!R216 | D64: =+'DETAIL.XLS'!AE216 | E64: =+'DETAIL.XLS'!AF216 | F64: =+'DETAIL.XLS'!AG216 | G64: =+'DETAIL.XLS'!AH216
B65: =+'DETAIL.XLS'!B217 | C65: =+'DETAIL.XLS'!R217 | D65: =+'DETAIL.XLS'!AE217 | E65: =+'DETAIL.XLS'!AF217 | F65: =+'DETAIL.XLS'!AG217 | G65: =+'DETAIL.XLS'!AH217
B66: =+'DETAIL.XLS'!B218 | C66: =+'DETAIL.XLS'!R218 | D66: =+'DETAIL.XLS'!AE218 | E66: =+'DETAIL.XLS'!AF218 | F66: =+'DETAIL.XLS'!AG218 | G66: =+'DETAIL.XLS'!AH218
B67: =+'DETAIL.XLS'!B219 | C67: =+'DETAIL.XLS'!R219 | D67: =+'DETAIL.XLS'!AE219 | E67: =+'DETAIL.XLS'!AF219 | F67: =+'DETAIL.XLS'!AG219 | G67: =+'DETAIL.XLS'!AH219
B68: =+'DETAIL.XLS'!B220 | C68: =+'DETAIL.XLS'!R220 | D68: =+'DETAIL.XLS'!AE220 | E68: =+'DETAIL.XLS'!AF220 | F68: =+'DETAIL.XLS'!AG220 | G68: =+'DETAIL.XLS'!AH220
A69: Total Short Term Liabilities | C69: =SUM(C63:C68) | D69: =SUM(D63:D68) | E69: =SUM(E63:E68) | F69: =SUM(F63:F68) | G69: =SUM(G63:G68)
A71: Long Term Liabilities
B72: =+'DETAIL.XLS'!B224 | C72: =+'DETAIL.XLS'!R224 | D72: =+'DETAIL.XLS'!AE224 | E72: =+'DETAIL.XLS'!AF224 | F72: =+'DETAIL.XLS'!AG224 | G72: =+'DETAIL.XLS'!AH224
B73: =+'DETAIL.XLS'!B225 | C73: =+'DETAIL.XLS'!R225 | D73: =+'DETAIL.XLS'!AE225 | E73: =+'DETAIL.XLS'!AF225 | F73: =+'DETAIL.XLS'!AG225 | G73: =+'DETAIL.XLS'!AH225
A74: Total Long Term Liabilities | C74: =SUM(C72:C73) | D74: =SUM(D72:D73) | E74: =SUM(E72:E73) | F74: =SUM(F72:F73) | G74: =SUM(G72:G73)
A76: TOTAL LIABILITIES | C76: =+C69+C74 | D76: =+D69+D74 | E76: =+E69+E74 | F76: =+F69+F74 | G76: =+G69+G74
A78: Equity
B79: =+'DETAIL.XLS'!B231 | C79: =+'DETAIL.XLS'!R231 | D79: =+'DETAIL.XLS'!AE231 | E79: =+'DETAIL.XLS'!AF231 | F79: =+'DETAIL.XLS'!AG231 | G79: =+'DETAIL.XLS'!AH231
B80: =+'DETAIL.XLS'!B232 | C80: =+'DETAIL.XLS'!R232 | D80: =+'DETAIL.XLS'!AE232 | E80: =+'DETAIL.XLS'!AF232 | F80: =+'DETAIL.XLS'!AG232 | G80: =+'DETAIL.XLS'!AH232
B81: =+'DETAIL.XLS'!B233 | C81: =+'DETAIL.XLS'!R233 | D81: =+'DETAIL.XLS'!AE233 | E81: =+'DETAIL.XLS'!AF233 | F81: =+'DETAIL.XLS'!AG233 | G81: =+'DETAIL.XLS'!AH233
A82: Total Equity | C82: =SUM(C79:C81) | D82: =SUM(D79:D81) | E82: =SUM(E79:E81) | F82: =SUM(F79:F81) | G82: =SUM(G79:G81)
A84: LIABILITIES & EQUITY | C84: =+C76+C82 | D84: =+D76+D82 | E84: =+E76+E82 | F84: =+F76+F82 | G84: =+G76+G82
A85: =+$A$5
A86: Statement of Sources & Uses ($)
C88: =C$1 | D88: =D$1 | E88: =E$1 | F88: =F$1 | G88: =G$1
A90: BEGINNING CASH | C90: =+'DETAIL.XLS'!R52 | D90: =+'DETAIL.XLS'!AE52 | E90: =+'DETAIL.XLS'!AF52 | F90: =+'DETAIL.XLS'!AG52 | G90: =+'DETAIL.XLS'!AH52
A92: Sources of Cash
B93: =+'DETAIL.XLS'!B55 | C93: =+'DETAIL.XLS'!R55 | D93: =+'DETAIL.XLS'!AE55 | E93: =+'DETAIL.XLS'!AF55 | F93: =+'DETAIL.XLS'!AG55 | G93: =+'DETAIL.XLS'!AH55
B94: =+'DETAIL.XLS'!B56 | C94: =+'DETAIL.XLS'!R56 | D94: =+'DETAIL.XLS'!AE56 | E94: =+'DETAIL.XLS'!AF56 | F94: =+'DETAIL.XLS'!AG56 | G94: =+'DETAIL.XLS'!AH56
B95: =+'DETAIL.XLS'!B57 | C95: =+'DETAIL.XLS'!R57 | D95: =+'DETAIL.XLS'!AE57 | E95: =+'DETAIL.XLS'!AF57 | F95: =+'DETAIL.XLS'!AG57 | G95: =+'DETAIL.XLS'!AH57
B96: =+'DETAIL.XLS'!B58 | C96: =+'DETAIL.XLS'!R58 | D96: =+'DETAIL.XLS'!AE58 | E96: =+'DETAIL.XLS'!AF58 | F96: =+'DETAIL.XLS'!AG58 | G96: =+'DETAIL.XLS'!AH58
A97: Plus Changes In:
B98: =+'DETAIL.XLS'!B60 | C98: =+'DETAIL.XLS'!R60 | D98: =+'DETAIL.XLS'!AE60 | E98: =+'DETAIL.XLS'!AF60 | F98: =+'DETAIL.XLS'!AG60 | G98: =+'DETAIL.XLS'!AH60
B99: =+'DETAIL.XLS'!B61 | C99: =+'DETAIL.XLS'!R61 | D99: =+'DETAIL.XLS'!AE61 | E99: =+'DETAIL.XLS'!AF61 | F99: =+'DETAIL.XLS'!AG61 | G99: =+'DETAIL.XLS'!AH61
B100: =+'DETAIL.XLS'!B62 | C100: =+'DETAIL.XLS'!R62 | D100: =+'DETAIL.XLS'!AE62 | E100: =+'DETAIL.XLS'!AF62 | F100: =+'DETAIL.XLS'!AG62 | G100: =+'DETAIL.XLS'!AH62
B101: =+'DETAIL.XLS'!B63 | C101: =+'DETAIL.XLS'!R63 | D101: =+'DETAIL.XLS'!AE63 | E101: =+'DETAIL.XLS'!AF63 | F101: =+'DETAIL.XLS'!AG63 | G101: =+'DETAIL.XLS'!AH63
B102: =+'DETAIL.XLS'!B64 | C102: =+'DETAIL.XLS'!R64 | D102: =+'DETAIL.XLS'!AE64 | E102: =+'DETAIL.XLS'!AF64 | F102: =+'DETAIL.XLS'!AG64 | G102: =+'DETAIL.XLS'!AH64
B103: =+'DETAIL.XLS'!B65 | C103: =+'DETAIL.XLS'!R65 | D103: =+'DETAIL.XLS'!AE65 | E103: =+'DETAIL.XLS'!AF65 | F103: =+'DETAIL.XLS'!AG65 | G103: =+'DETAIL.XLS'!AH65
A104: Total Sources of Cash | C104: =SUM(C93:C103) | D104: =SUM(D93:D103) | E104: =SUM(E93:E103) | F104: =SUM(F93:F103) | G104: =SUM(G93:G103)
A106: Uses of Cash
A107: Less Changes In:
B108: =+'DETAIL.XLS'!B72 | C108: =+'DETAIL.XLS'!R72 | D108: =+'DETAIL.XLS'!AE72 | E108: =+'DETAIL.XLS'!AF72 | F108: =+'DETAIL.XLS'!AG72 | G108: =+'DETAIL.XLS'!AH72
B109: =+'DETAIL.XLS'!B73 | C109: =+'DETAIL.XLS'!R73 | D109: =+'DETAIL.XLS'!AE73 | E109: =+'DETAIL.XLS'!AF73 | F109: =+'DETAIL.XLS'!AG73 | G109: =+'DETAIL.XLS'!AH73
B110: =+'DETAIL.XLS'!B74 | C110: =+'DETAIL.XLS'!R74 | D110: =+'DETAIL.XLS'!AE74 | E110: =+'DETAIL.XLS'!AF74 | F110: =+'DETAIL.XLS'!AG74 | G110: =+'DETAIL.XLS'!AH74
B111: =+'DETAIL.XLS'!B75 | C111: =+'DETAIL.XLS'!R75 | D111: =+'DETAIL.XLS'!AE75 | E111: =+'DETAIL.XLS'!AF75 | F111: =+'DETAIL.XLS'!AG75 | G111: =+'DETAIL.XLS'!AH75
B112: =+'DETAIL.XLS'!B76 | C112: =+'DETAIL.XLS'!R76 | D112: =+'DETAIL.XLS'!AE76 | E112: =+'DETAIL.XLS'!AF76 | F112: =+'DETAIL.XLS'!AG76 | G112: =+'DETAIL.XLS'!AH76
B113: =+'DETAIL.XLS'!B77 | C113: =+'DETAIL.XLS'!R77 | D113: =+'DETAIL.XLS'!AE77 | E113: =+'DETAIL.XLS'!AF77 | F113: =+'DETAIL.XLS'!AG77 | G113: =+'DETAIL.XLS'!AH77
A114: Total Uses | C114: =SUM(C108:C113) | D114: =SUM(D108:D113) | E114: =SUM(E108:E113) | F114: =SUM(F108:F113) | G114: =SUM(G108:G113)
A116: CHANGES IN CASH | C116: =+C104-C114 | D116: =+D104-D114 | E116: =+E104-E114 | F116: =+F104-F114 | G116: =+G104-G114
A118: ENDING CASH | C118: =+C90+C116 | D118: =+D90+D116 | E118: =+E90+E116 | F118: =+F90+F116 | G118: =+G90+G116

Sheet Revenue Growth Chart

Sheet Breakeven Chart

Sheet Graph Input
A1: Revenue Growth
C2: =+'Summary Statements'!C8 | D2: =+'Summary Statements'!D8 | E2: =+'Summary Statements'!E8 | F2: =+'Summary Statements'!F8 | G2: =+'Summary Statements'!G8
B3: Revenue | C3: =+'Summary Statements'!C15 | D3: =+'Summary Statements'!D15 | E3: =+'Summary Statements'!E15 | F3: =+'Summary Statements'!F15 | G3: =+'Summary Statements'!G15
B4: Gross Margin | C4: =+'Summary Statements'!C19 | D4: =+'Summary Statements'!D19 | E4: =+'Summary Statements'!E19 | F4: =+'Summary Statements'!F19 | G4: =+'Summary Statements'!G19
B5: Net Income | C5: =+'Summary Statements'!C41 | D5: =+'Summary Statements'!D41 | E5: =+'Summary Statements'!E41 | F5: =+'Summary Statements'!F41 | G5: =+'Summary Statements'!G41
A8: Cash Flow Breakeven
C9: =+'DETAIL.XLS'!$F$1 | D9: =+C9+31 | E9: =+D9+31 | F9: =+E9+31 | G9: =+F9+31 | H9: =+G9+31 | I9: =+H9+31 | J9: =+I9+31 | K9: =+J9+31 | ... Z9: =+Y9+31
B10: Receipts | C10: ='DETAIL.XLS'!F17 | D10: ='DETAIL.XLS'!G17 | E10: ='DETAIL.XLS'!H17 | F10: ='DETAIL.XLS'!I17 | G10: ='DETAIL.XLS'!J17 | H10: ='DETAIL.XLS'!K17 | I10: ='DETAIL.XLS'!L17 | J10: ='DETAIL.XLS'!M17 | ... N10: ='DETAIL.XLS'!Q17 | O10: ='DETAIL.XLS'!S17 | P10: ='DETAIL.XLS'!T17 | Q10: ='DETAIL.XLS'!U17 | R10: ='DETAIL.XLS'!V17 | S10: ='DETAIL.XLS'!W17 | T10: ='DETAIL.XLS'!X17 | U10: ='DETAIL.XLS'!Y17 | V10: ='DETAIL.XLS'!Z17 | ... Z10: ='DETAIL.XLS'!AD17
B11: Disbursements | C11: ='DETAIL.XLS'!F42 | D11: ='DETAIL.XLS'!G42 | E11: ='DETAIL.XLS'!H42 | F11: ='DETAIL.XLS'!I42 | G11: ='DETAIL.XLS'!J42 | H11: ='DETAIL.XLS'!K42 | I11: ='DETAIL.XLS'!L42 | J11: ='DETAIL.XLS'!M42 | ... N11: ='DETAIL.XLS'!Q42 | O11: ='DETAIL.XLS'!S42 | P11: ='DETAIL.XLS'!T42 | Q11: ='DETAIL.XLS'!U42 | R11: ='DETAIL.XLS'!V42 | S11: ='DETAIL.XLS'!W42 | T11: ='DETAIL.XLS'!X42 | U11: ='DETAIL.XLS'!Y42 | V11: ='DETAIL.XLS'!Z42 | ... Z11: ='DETAIL.XLS'!AD42
