Workbook

Sheet Cover
E3: Reference Model
E5: Aurobindo Pharma
E6: Prepared By: Gopal Sathis Kumar, Distance learning, Chennai
E14: http://proschoolonline.com
E15: Email ID : mumbai@proschoolonline.com
E17: Mumbai
E19: IMS Proschool Pvt Ltd,
E20: Maharashtra High School Complex,
E21: Principal N.M Kale Marg, Off Gokhale Rd,
E22: Dadar (W), Mumbai 400028
E23: Tel. No. : 022-65285393/94
E24: +91 9372895050

Sheet Directions
A1: Directions
A3: Aurobindo pharma is one of the leading pharmaceutical company of the country. A financial model of such a company is in great demand in the investment market. This gave us the opportunity to guide our student to come out with a financial model on the company. These exercises help the student at IMS Proschool to hone their financial modeling skills. This model is being developed by a financial modeling student at IMS Proschool. This is provided as reference model and is for information purpose only. Keeping in view the objective of the reference model, the formulas and linkages of the model are kept intact. IMS Proschool provides certificate programs in Financial Modeling. The program grooms the candidates for entry level jobs in the finance sector which require financial analysis and modeling skills. The program aims to impart the necessary skills required to perform the role of a Financial Research Analyst. The program equips students with the practical skill sets required to perform financial analysis, modeling and valuation through Excel. For more details, please contact the address furnished below. You can also email us at the below mentioned email-id.
I20: IMS Proschool Pvt Ltd,
I21: Maharashtra High School Complex,
I22: Principal N.M Kale Marg, Off Gokhale Rd,
I23: Dadar (W), Mumbai 400028
I24: Tel. No. : 022-65285393/94
I25: +91 9372895050
I26: Email ID : mumbai@proschoolonline.com

Sheet Company Overview
A1: Aurobindo Pharma
A2: Company Overview
A3: (In Rs Millions, except per share data)
A5: Company Information | F5: Company Description
A6: Industry | B6: Pharmceuticals | F6: Aurobindo Pharma, incorporated in 1986 is a Hyderabad based pharma company, which initially forayed into the pharmaceutical sector as an API supplier focusing on antibiotics like Semi Synthetic Penicillins (SSPs) and Cephalosporins, emerging a market leader in these segments. Over the years, the company has diversified into the cardiovascular (CVS), central nervous system (CNS), gastrointestinal (GI), anti-infective segments, etc. After a strong presence in its core business of bulk actives, the company is now focusing on generic formulations. It has 14 state-of-the-art manufacturing facilities spread across India, China, USA and Brazil. The company’s operations are vertically integrated and its formulations profile is supported by in-house APIs. Aurobindo has a presence across US, Europe, India and other emerging countries like Brazil, China, South Africa, etc. A higher proportion of the company’s revenue is from APIs and formulations are likely to replace this, going forward.
A7: Sector | B7: Pharma
A8: Country | B8: India
A9: Current Market Price Rs | B9: ='DCF Valuation'!E7 -> 753
A10: Ticker | B10: AUROPHARMA
A11: Market Capitalization (Rs in Mn) | B11: =B9*'Profit & Loss Consolidated'!S55 -> 48655.609
A12: Relative Index | B12: S&P CNX Nifty
A13: Year end | B13: 39903
A14: Reporting currency | B14: INR
F17: Products
F18: Aurobindo is a leading player in APIs and has a strong presence in SSPs, CCPs, and ARVs. Aurobindo ranks the highest in terms of DMF filings by any Indian company and is the second largest globally. Aurobindo has set up seven state–of-the-art manufacturing facilities and all have the necessary regulatory approvals. Six of these facilities are situated in India near Hyderabad and one is in China. The key products segments are:- CVS,CNS, Anti-allergic, Cephalosporins,(synthetic & non-synthetic) SSP’s, Gastro intestinals, and ARV’s.
A25: Per Share Data & Key Ratios
A26: For the Fiscal Period Ending | B26: 3 months Jun-30- 2008 | C26: 3 months Sep-30-2008 | D26: 3 months Dec-31-2008 | E26: 3 months Mar-31-2009 | F26: FY2009 A | G26: 3 months Jun-30-2009 | H26: 3 months Sep-30-2009 | I26: 3 months Dec-31- 2009 | J26: 3 months Mar-31-2010 | K26: FY2010 E | L26: 3 months Jun-30- 2010 | M26: 3 months Sep-30-2010 | N26: 3 months Dec-31-2010 | O26: 3 months Mar-31-2011 | P26: FY2011 E
A27: EPS diluted (reported) | B27: ='Profit & Loss Consolidated'!M52 -> 2.43 | C27: ='Profit & Loss Consolidated'!N52 -> -7.15 | D27: ='Profit & Loss Consolidated'!O52 -> 6.19 | E27: ='Profit & Loss Consolidated'!P52 -> 12.37 | F27: ='Profit & Loss Consolidated'!Q52 -> 15.43 | G27: ='Profit & Loss Consolidated'!R52 -> 25.76 | H27: ='Profit & Loss Consolidated'!S52 -> 14.037987 | I27: ='Profit & Loss Consolidated'!T52 -> 15.390835 | ... P27: ='Profit & Loss Consolidated'!AA52 -> 78.966962
A28: Operating Margin (%) | B28: ='Presentation sheet'!H45 -> 0.12372841 | C28: ='Presentation sheet'!I45 -> 0.13271628 | D28: ='Presentation sheet'!J45 -> 0.16741986 | E28: ='Presentation sheet'!K45 -> 0.16205702 | F28: ='Presentation sheet'!L45 -> 0.14757132 | G28: ='Presentation sheet'!M45 -> 0.1964897 | H28: ='Presentation sheet'!N45 -> 0.14080637 | I28: ='Presentation sheet'!O45 -> 0.14899431 | ... P28: ='Presentation sheet'!V45 -> 0.15484751
A29: EBITDA/sales (%) | B29: ='Presentation sheet'!H51 -> 0.16410815 | C29: ='Presentation sheet'!I51 -> 0.17773177 | D29: ='Presentation sheet'!J51 -> 0.21551838 | E29: ='Presentation sheet'!K51 -> 0.20867143 | F29: ='Presentation sheet'!L51 -> 0.19273269 | G29: ='Presentation sheet'!M51 -> 0.2394189 | H29: ='Presentation sheet'!N51 -> 0.17264109 | I29: ='Presentation sheet'!O51 -> 0.18233393 | ... P29: ='Presentation sheet'!V51 -> 0.18605065
A30: EBIT/sales (%) | B30: ='Presentation sheet'!H48 -> 0.12585068 | C30: ='Presentation sheet'!I48 -> 0.13790984 | D30: ='Presentation sheet'!J48 -> 0.17444964 | E30: ='Presentation sheet'!K48 -> 0.16819171 | F30: ='Presentation sheet'!L48 -> 0.15277684 | G30: ='Presentation sheet'!M48 -> 0.19918714 | H30: ='Presentation sheet'!N48 -> 0.14443357 | I30: ='Presentation sheet'!O48 -> 0.15412642 | ... P30: ='Presentation sheet'!V48 -> 0.15825643
A31: Net income/sales (%) | B31: ='Presentation sheet'!H62 -> 0.023231794 | C31: ='Presentation sheet'!I62 -> -0.053064134 | D31: ='Presentation sheet'!J62 -> 0.055286873 | E31: ='Presentation sheet'!K62 -> 0.0921354 | F31: ='Presentation sheet'!L62 -> 0.032683511 | G31: ='Presentation sheet'!M62 -> 0.20134025 | H31: ='Presentation sheet'!N62 -> 0.087503722 | I31: ='Presentation sheet'!O62 -> 0.095936499 | ... P31: ='Presentation sheet'!V62 -> 0.1045313
A32: Interest Cover | B32: ='Presentation sheet'!H86 -> 8.7539623 | C32: ='Presentation sheet'!I86 -> 8.2324376 | D32: ='Presentation sheet'!J86 -> 6.4036121 | E32: ='Presentation sheet'!K86 -> 6.7801047 | F32: ='Presentation sheet'!L86 -> 7.2643113 | G32: ='Presentation sheet'!M86 -> 8.7270723 | H32: ='Presentation sheet'!N86 -> 3.2895413 | I32: ='Presentation sheet'!O86 -> 3.4742309 | ... P32: ='Presentation sheet'!V86 -> 4.2606088
A33: ROE | B33: Quarterly data not available | F33: ='Presentation sheet'!L87 -> 0.081617729 | G33: Quarterly data not available | K33: ='Presentation sheet'!Q87 -> 0.27706017 | L33: Quarterly data not available | P33: ='Presentation sheet'!V87 -> 0.20947993
A34: EV/Sales | H34: ='Presentation sheet'!N88 -> 1.5507274 | I34: ='Presentation sheet'!O88 -> 1.5507274 | J34: ='Presentation sheet'!P88 -> 1.5507274 | K34: ='Presentation sheet'!Q88 -> 1.6334143 | L34: ='Presentation sheet'!R88 -> 1.4240602 | M34: ='Presentation sheet'!S88 -> 1.3902289 | N34: ='Presentation sheet'!T88 -> 1.3299758 | O34: ='Presentation sheet'!U88 -> 1.1585241 | P34: ='Presentation sheet'!V88 -> 1.3172696
A35: EV/EBITDA | H35: ='Presentation sheet'!N89 -> 8.9823775 | I35: ='Presentation sheet'!O89 -> 8.5048756 | J35: ='Presentation sheet'!P89 -> 7.8818402 | K35: ='Presentation sheet'!Q89 -> 8.3522736 | L35: ='Presentation sheet'!R89 -> 6.3363601 | M35: ='Presentation sheet'!S89 -> 8.1100267 | N35: ='Presentation sheet'!T89 -> 7.8437573 | O35: ='Presentation sheet'!U89 -> 6.3961085 | P35: ='Presentation sheet'!V89 -> 7.0801666
A36: P/E | H36: ='Presentation sheet'!N90 -> 13.410042 | I36: ='Presentation sheet'!O90 -> 12.231305 | J36: ='Presentation sheet'!P90 -> 10.817427 | K36: ='Presentation sheet'!Q90 -> 10.373144 | L36: ='Presentation sheet'!R90 -> 8.3979009 | M36: ='Presentation sheet'!S90 -> 12.5954 | N36: ='Presentation sheet'!T90 -> 11.875556 | O36: ='Presentation sheet'!U90 -> 8.5191663 | P36: ='Presentation sheet'!V90 -> 9.5356334
A37: P/Sales | H37: ='DCF Valuation'!$E$7/(('Profit & Loss Consolidated'!S13*4)/'Profit & Loss Consolidated'!S55) -> 1.2017666 | I37: ='DCF Valuation'!$E$7/(('Profit & Loss Consolidated'!T13*4)/'Profit & Loss Consolidated'!T55) -> 1.1112248 | J37: ='DCF Valuation'!$E$7/(('Profit & Loss Consolidated'!U13*4)/'Profit & Loss Consolidated'!U55) -> 1.133756 | K37: ='DCF Valuation'!$E$7/('Profit & Loss Consolidated'!V13/'Profit & Loss Consolidated'!V55) -> 1.2066038 | L37: ='DCF Valuation'!$E$7/(('Profit & Loss Consolidated'!W13*4)/'Profit & Loss Consolidated'!W55) -> 1.0589993 | M37: ='DCF Valuation'!$E$7/(('Profit & Loss Consolidated'!X13*4)/'Profit & Loss Consolidated'!X55) -> 1.078318 | N37: ='DCF Valuation'!$E$7/(('Profit & Loss Consolidated'!Y13*4)/'Profit & Loss Consolidated'!Y55) -> 0.96403409 | O37: ='DCF Valuation'!$E$7/(('Profit & Loss Consolidated'!Z13*4)/'Profit & Loss Consolidated'!Z55) -> 0.85889222 | P37: ='DCF Valuation'!$E$7/('Profit & Loss Consolidated'!AA13/'Profit & Loss Consolidated'!AA55) -> 0.98201535
A38: P/BV | G38: Quarterly data not available | K38: ='DCF Valuation'!$E$7/('Balance Sheet'!F15/'Profit & Loss Consolidated'!V55) -> 2.8739852 | L38: Quarterly data not available | P38: ='DCF Valuation'!$E$7/('Balance Sheet'!G15/'Profit & Loss Consolidated'!AA55) -> 1.9975238
A41: Geographic Revenue breakup for 2009 | I41: Product Revenue Breakup for 2009
A43: India | B43: 24443.844 | I43: Formulations | S43: Active Ingredients | AC43: Formulations | AD43: 14098
A44: China | B44: 366.56211 | I44: USA | J44: 5584 | S44: SSPs | T44: 7379 | AC44: Active Ingredients | AD44: 16466
A45: Rest of the World | B45: 6432.0236 | I45: Europe | J45: 1923 | S45: Cephs | T45: 6344
A46: Consolidated | B46: 31242.43 | I46: ARV's | J46: 4640 | S46: ARVs & Others | T46: 2743
I47: Rest of the World | J47: 1951 | S47: Total | T47: 16466
I48: Total | J48: 14098
A55: Revenue Forecast | L55: Enterprise Value Added
A78: Revenue Data
B79: FY2007 A | C79: FY2008 A | D79: FY2009 A | E79: FY2010 E | F79: FY2011 E | G79: FY2012 E | H79: FY2013 E | I79: FY2014 E | L79: Explicit Forecast FCF (First Stage) | M79: =SUM('DCF Valuation'!D34:H34) -> 7583.456
A80: Formulations | B80: ='Segment Revenue Model'!B23 -> 7196.2 | C80: ='Segment Revenue Model'!G23 -> 10048 | D80: ='Segment Revenue Model'!L23 -> 14098 | E80: ='Segment Revenue Model'!Q23 -> 21408.619 | F80: ='Segment Revenue Model'!V23 -> 28084.807 | G80: ='Segment Revenue Model'!AA23 -> 34825.161 | H80: ='Segment Revenue Model'!AF23 -> 42486.697 | I80: ='Segment Revenue Model'!AK23 -> 50984.036 | L80: Second Stage | M80: =M79 -> 7583.456 | N80: =SUM('DCF Valuation'!I34:M34) -> 13507.846
A81: Active Ingredients | B81: ='Segment Revenue Model'!B24 -> 15306 | C81: ='Segment Revenue Model'!G24 -> 15476 | D81: ='Segment Revenue Model'!L24 -> 16466 | E81: ='Segment Revenue Model'!Q24 -> 17956.842 | F81: ='Segment Revenue Model'!V24 -> 20728.365 | G81: ='Segment Revenue Model'!AA24 -> 25703.173 | H81: ='Segment Revenue Model'!AF24 -> 31357.871 | I81: ='Segment Revenue Model'!AK24 -> 37629.445 | L81: Terminal Year Forecast FCF | M81: =M80 -> 7583.456 | N81: =N80 -> 13507.846 | O81: ='DCF Valuation'!B55 -> 41293.419
A82: % Y-o-Y Growth | C82: =SUM(C80:C81)/SUM(B80:B81)-1 -> 0.13428909 | D82: =SUM(D80:D81)/SUM(C80:C81)-1 -> 0.19746121 | E82: =SUM(E80:E81)/SUM(D80:D81)-1 -> 0.28796826 | F82: =SUM(F80:F81)/SUM(E80:E81)-1 -> 0.24 | G82: =SUM(G80:G81)/SUM(F80:F81)-1 -> 0.24 | H82: =SUM(H80:H81)/SUM(G80:G81)-1 -> 0.22 | I82: =SUM(I80:I81)/SUM(H80:H81)-1 -> 0.2 | L82: Total Enterprise Value | O82: =SUM(M81:O81) -> 62384.72

Sheet Presentation sheet
A1: Aurobindo Pharma
A2: Presentation
A3: (In Rs Millions, Except per share items)
A5: For the Fiscal Period Ending | B5: FY2007 A | C5: 3 months Jun-30-2007 | D5: 3 months Sep-30-2007 | E5: 3 months Dec-31-2007 | F5: 3 months Mar-31-2008 | G5: FY2008 A | H5: 3 months Jun-30-2008 | I5: 3 months Sep-30-2008 | J5: 3 months Dec-31-2008 | K5: 3 months Mar-31-2009 | L5: FY2009 A | M5: 3 months Jun-30-2009 | N5: 3 months Sep-30-2009 | O5: 3 months Dec-31-2009 | P5: 3 months Mar-31-2010 | Q5: FY2010 E | R5: 3 months Jun-30-2010 | S5: 3 months Sep-30-2010 | T5: 3 months Dec-31-2010 | U5: 3 months Mar-31-2011 | V5: FY2011 E | W5: 3 months Jun-30-2011 | X5: 3 months Sep-30-2011 | Y5: 3 months Dec-31-2011 | Z5: 3 months Mar-31-2012 | AA5: FY2012 E | AB5: 3 months Jun-30-2012 | AC5: 3 months Sep-30-2012 | AD5: 3 months Dec-31-2012 | AE5: 3 months Mar-31-2013 | AF5: FY2013 E | AG5: 3 months Jun-30-2013 | AH5: 3 months Sep-30-2013 | AI5: 3 months Dec-31-2013 | AJ5: 3 months Mar-31-2014 | AK5: FY2014 E
A7: Geographic Revenue
A8: India | B8: ='Geographic Revenue Model'!D8 -> 16023.4 | C8: Quarterly data not available | G8: ='Geographic Revenue Model'!E8 -> 19058.3 | H8: Quarterly data not available | L8: ='Geographic Revenue Model'!F8 -> 24443.844 | M8: Quarterly data not available | Q8: ='Geographic Revenue Model'!G8 -> 31492.369 | R8: Quarterly data not available | V8: ='Geographic Revenue Model'!H8 -> 39538.67 | W8: Quarterly data not available | AA8: ='Geographic Revenue Model'!I8 -> 47817.384 | AB8: Quarterly data not available | AF8: ='Geographic Revenue Model'!J8 -> 57598.763 | AG8: Quarterly data not available | AK8: ='Geographic Revenue Model'!K8 -> 70890.785
A9: China | B9: ='Geographic Revenue Model'!D9 -> 976 | G9: ='Geographic Revenue Model'!E9 -> 285.8 | L9: ='Geographic Revenue Model'!F9 -> 366.56211 | Q9: ='Geographic Revenue Model'!G9 -> 461.86826 | V9: ='Geographic Revenue Model'!H9 -> 572.71664 | AA9: ='Geographic Revenue Model'!I9 -> 710.16864 | AF9: ='Geographic Revenue Model'!J9 -> 866.40574 | AK9: ='Geographic Revenue Model'!K9 -> 1039.6869
A10: Rest of the World | B10: ='Geographic Revenue Model'!D10 -> 4229.8 | G10: ='Geographic Revenue Model'!E10 -> 5014.9 | L10: ='Geographic Revenue Model'!F10 -> 6432.0236 | Q10: ='Geographic Revenue Model'!G10 -> 7479.4377 | V10: ='Geographic Revenue Model'!H10 -> 8786.3711 | AA10: ='Geographic Revenue Model'!I10 -> 12105.667 | AF10: ='Geographic Revenue Model'!J10 -> 15507.359 | AK10: ='Geographic Revenue Model'!K10 -> 16836.561
A11: Consolidated | B11: ='Geographic Revenue Model'!D11 -> 21229.2 | G11: ='Geographic Revenue Model'!E11 -> 24359 | L11: ='Geographic Revenue Model'!F11 -> 31242.43 | Q11: ='Geographic Revenue Model'!G11 -> 39365.462 | V11: ='Geographic Revenue Model'!H11 -> 48813.173 | AA11: ='Geographic Revenue Model'!I11 -> 60528.334 | AF11: ='Geographic Revenue Model'!J11 -> 73844.568 | AK11: ='Geographic Revenue Model'!K11 -> 88613.481
A14: Segment Revenues
A16: Formulations
A17: USA | B17: ='Segment Revenue Model'!B10 -> 1563 | C17: ='Segment Revenue Model'!C10 -> 546 | D17: ='Segment Revenue Model'!D10 -> 518 | E17: ='Segment Revenue Model'!E10 -> 497 | F17: ='Segment Revenue Model'!F10 -> 798 | G17: ='Segment Revenue Model'!G10 -> 2359 | H17: ='Segment Revenue Model'!H10 -> 817 | I17: ='Segment Revenue Model'!I10 -> 1051 | ... AK17: ='Segment Revenue Model'!AK10 -> 22366.021
A18: Europe | B18: ='Segment Revenue Model'!B11 -> 1280 | C18: ='Segment Revenue Model'!C11 -> 362 | D18: ='Segment Revenue Model'!D11 -> 562 | E18: ='Segment Revenue Model'!E11 -> 641 | F18: ='Segment Revenue Model'!F11 -> 446 | G18: ='Segment Revenue Model'!G11 -> 2011 | H18: ='Segment Revenue Model'!H11 -> 447 | I18: ='Segment Revenue Model'!I11 -> 557 | ... AK18: ='Segment Revenue Model'!AK11 -> 6377.644
A19: ARV's | B19: ='Segment Revenue Model'!B12 -> 2875 | C19: ='Segment Revenue Model'!C12 -> 642 | D19: ='Segment Revenue Model'!D12 -> 1072 | E19: ='Segment Revenue Model'!E12 -> 939 | F19: ='Segment Revenue Model'!F12 -> 1391 | G19: ='Segment Revenue Model'!G12 -> 4044 | H19: ='Segment Revenue Model'!H12 -> 1249 | I19: ='Segment Revenue Model'!I12 -> 858 | ... AK19: ='Segment Revenue Model'!AK12 -> 15311.109
A20: Rest of the World | B20: ='Segment Revenue Model'!B13 -> 1478.2 | C20: ='Segment Revenue Model'!C13 -> 246 | D20: ='Segment Revenue Model'!D13 -> 245 | E20: ='Segment Revenue Model'!E13 -> 389 | F20: ='Segment Revenue Model'!F13 -> 754 | G20: ='Segment Revenue Model'!G13 -> 1634 | H20: ='Segment Revenue Model'!H13 -> 384 | I20: ='Segment Revenue Model'!I13 -> 727 | ... AK20: ='Segment Revenue Model'!AK13 -> 6929.2617
A21: Total | B21: ='Segment Revenue Model'!B14 -> 7196.2 | C21: ='Segment Revenue Model'!C14 -> 1796 | D21: ='Segment Revenue Model'!D14 -> 2397 | E21: ='Segment Revenue Model'!E14 -> 2466 | F21: ='Segment Revenue Model'!F14 -> 3389 | G21: ='Segment Revenue Model'!G14 -> 10048 | H21: ='Segment Revenue Model'!H14 -> 2897 | I21: ='Segment Revenue Model'!I14 -> 3193 | ... AK21: ='Segment Revenue Model'!AK14 -> 50984.036
A23: Active Ingredients
A24: SSPs | B24: ='Segment Revenue Model'!B17 -> 5913 | C24: ='Segment Revenue Model'!C17 -> 2123 | D24: ='Segment Revenue Model'!D17 -> 2278 | E24: ='Segment Revenue Model'!E17 -> 1748 | F24: ='Segment Revenue Model'!F17 -> 1892 | G24: ='Segment Revenue Model'!G17 -> 8041 | H24: ='Segment Revenue Model'!H17 -> 2140 | I24: ='Segment Revenue Model'!I17 -> 1856 | ... AK24: ='Segment Revenue Model'!AK17 -> 15986.447
A25: Cephs | B25: ='Segment Revenue Model'!B18 -> 6429 | C25: ='Segment Revenue Model'!C18 -> 1309 | D25: ='Segment Revenue Model'!D18 -> 1577 | E25: ='Segment Revenue Model'!E18 -> 1620 | F25: ='Segment Revenue Model'!F18 -> 1412 | G25: ='Segment Revenue Model'!G18 -> 5918 | H25: ='Segment Revenue Model'!H18 -> 1564 | I25: ='Segment Revenue Model'!I18 -> 1560 | ... AK25: ='Segment Revenue Model'!AK18 -> 14632.993
A26: ARVs & Others | B26: ='Segment Revenue Model'!B19 -> 2964 | C26: ='Segment Revenue Model'!C19 -> 436 | D26: ='Segment Revenue Model'!D19 -> 418 | E26: ='Segment Revenue Model'!E19 -> 268 | F26: ='Segment Revenue Model'!F19 -> 395 | G26: ='Segment Revenue Model'!G19 -> 1517 | H26: ='Segment Revenue Model'!H19 -> 467 | I26: ='Segment Revenue Model'!I19 -> 631 | ... AK26: ='Segment Revenue Model'!AK19 -> 7010.0052
A27: Total | B27: ='Segment Revenue Model'!B20 -> 15306 | C27: ='Segment Revenue Model'!C20 -> 3868 | D27: ='Segment Revenue Model'!D20 -> 4273 | E27: ='Segment Revenue Model'!E20 -> 3636 | F27: ='Segment Revenue Model'!F20 -> 3699 | G27: ='Segment Revenue Model'!G20 -> 15476 | H27: ='Segment Revenue Model'!H20 -> 4171 | I27: ='Segment Revenue Model'!I20 -> 4047 | ... AK27: ='Segment Revenue Model'!AK20 -> 37629.445
A29: Formulations | B29: ='Segment Revenue Model'!B23 -> 7196.2 | C29: ='Segment Revenue Model'!C23 -> 1796 | D29: ='Segment Revenue Model'!D23 -> 2397 | E29: ='Segment Revenue Model'!E23 -> 2466 | F29: ='Segment Revenue Model'!F23 -> 3389 | G29: ='Segment Revenue Model'!G23 -> 10048 | H29: ='Segment Revenue Model'!H23 -> 2897 | I29: ='Segment Revenue Model'!I23 -> 3193 | ... AK29: ='Segment Revenue Model'!AK23 -> 50984.036
A30: Active Ingredients | B30: ='Segment Revenue Model'!B24 -> 15306 | C30: ='Segment Revenue Model'!C24 -> 3868 | D30: ='Segment Revenue Model'!D24 -> 4273 | E30: ='Segment Revenue Model'!E24 -> 3636 | F30: ='Segment Revenue Model'!F24 -> 3699 | G30: ='Segment Revenue Model'!G24 -> 15476 | H30: ='Segment Revenue Model'!H24 -> 4171 | I30: ='Segment Revenue Model'!I24 -> 4047 | ... AK30: ='Segment Revenue Model'!AK24 -> 37629.445
A31: Total | B31: ='Segment Revenue Model'!B25 -> 22502.2 | C31: ='Segment Revenue Model'!C25 -> 5664 | D31: ='Segment Revenue Model'!D25 -> 6670 | E31: ='Segment Revenue Model'!E25 -> 6102 | F31: ='Segment Revenue Model'!F25 -> 7088 | G31: ='Segment Revenue Model'!G25 -> 25524 | H31: ='Segment Revenue Model'!H25 -> 7068 | I31: ='Segment Revenue Model'!I25 -> 7240 | ... AK31: ='Segment Revenue Model'!AK25 -> 88613.481
A34: Income Statement
A36: Total Income | B36: ='Profit & Loss Consolidated'!G13 -> 21229.2 | C36: ='Profit & Loss Consolidated'!H13 -> 5323.4 | D36: ='Profit & Loss Consolidated'!I13 -> 6302 | E36: ='Profit & Loss Consolidated'!J13 -> 5695.6 | F36: ='Profit & Loss Consolidated'!K13 -> 7056.2 | G36: ='Profit & Loss Consolidated'!L13 -> 24359 | H36: ='Profit & Loss Consolidated'!M13 -> 6832.4 | I36: ='Profit & Loss Consolidated'!N13 -> 7094.53 | ... AK36: ='Profit & Loss Consolidated'!AP13 -> 88331.072
A38: Material Consumed | B38: ='Profit & Loss Consolidated'!G17 -> 11755.7 | C38: ='Profit & Loss Consolidated'!H17 -> 3036.9 | D38: ='Profit & Loss Consolidated'!I17 -> 3309.3 | E38: ='Profit & Loss Consolidated'!J17 -> 2974.7 | F38: ='Profit & Loss Consolidated'!K17 -> 3290.8 | G38: ='Profit & Loss Consolidated'!L17 -> 12611.7 | H38: ='Profit & Loss Consolidated'!M17 -> 3572.4 | I38: ='Profit & Loss Consolidated'!N17 -> 3995 | ... AK38: ='Profit & Loss Consolidated'!AP17 -> 44526.38
A39: Staff Cost | B39: ='Profit & Loss Consolidated'!G19 -> 1504.2 | C39: ='Profit & Loss Consolidated'!H19 -> 442.3 | D39: ='Profit & Loss Consolidated'!I19 -> 492.9 | E39: ='Profit & Loss Consolidated'!J19 -> 497.9 | F39: ='Profit & Loss Consolidated'!K19 -> 496.9 | G39: ='Profit & Loss Consolidated'!L19 -> 1930 | H39: ='Profit & Loss Consolidated'!M19 -> 573.7 | I39: ='Profit & Loss Consolidated'!N19 -> 589.6 | ... AK39: ='Profit & Loss Consolidated'!AP19 -> 7107.4308
A40: Other Expenditure | B40: ='Profit & Loss Consolidated'!G21 -> 4486.8 | C40: ='Profit & Loss Consolidated'!H21 -> 1258.7 | D40: ='Profit & Loss Consolidated'!I21 -> 1422.6 | E40: ='Profit & Loss Consolidated'!J21 -> 1380.6 | F40: ='Profit & Loss Consolidated'!K21 -> 1441.7 | G40: ='Profit & Loss Consolidated'!L21 -> 5503.6 | H40: ='Profit & Loss Consolidated'!M21 -> 1424.7 | I40: ='Profit & Loss Consolidated'!N21 -> 1641.1 | ... AK40: ='Profit & Loss Consolidated'!AP21 -> 19693.563
A41: Depreciation & Amortization | B41: ='Profit & Loss Consolidated'!G20 -> 997.2 | C41: ='Profit & Loss Consolidated'!H20 -> 233.5 | D41: ='Profit & Loss Consolidated'!I20 -> 249.5 | E41: ='Profit & Loss Consolidated'!J20 -> 256 | F41: ='Profit & Loss Consolidated'!K20 -> 264.8 | G41: ='Profit & Loss Consolidated'!L20 -> 1003.8 | H41: ='Profit & Loss Consolidated'!M20 -> 270.4 | I41: ='Profit & Loss Consolidated'!N20 -> 288.3 | ... AK41: ='Profit & Loss Consolidated'!AP20 -> 1969.2694
A42: Total Expenditure | B42: ='Profit & Loss Consolidated'!G22 -> 19204.5 | C42: ='Profit & Loss Consolidated'!H22 -> 4862 | D42: ='Profit & Loss Consolidated'!I22 -> 5599.5 | E42: ='Profit & Loss Consolidated'!J22 -> 5163.7 | F42: ='Profit & Loss Consolidated'!K22 -> 6326.2 | G42: ='Profit & Loss Consolidated'!L22 -> 21951.4 | H42: ='Profit & Loss Consolidated'!M22 -> 5957.9 | I42: ='Profit & Loss Consolidated'!N22 -> 6133.7 | ... AK42: ='Profit & Loss Consolidated'!AP22 -> 75729.827
A44: Operating Income | B44: ='Profit & Loss Consolidated'!G23 -> 2024.7 | C44: ='Profit & Loss Consolidated'!H23 -> 461.4 | D44: ='Profit & Loss Consolidated'!I23 -> 702.5 | E44: ='Profit & Loss Consolidated'!J23 -> 531.9 | F44: ='Profit & Loss Consolidated'!K23 -> 711.8 | G44: ='Profit & Loss Consolidated'!L23 -> 2407.6 | H44: ='Profit & Loss Consolidated'!M23 -> 874.5 | I44: ='Profit & Loss Consolidated'!N23 -> 960.83 | ... AK44: ='Profit & Loss Consolidated'!AP23 -> 12601.246
A45: Operating Income Margin(%) | B45: ='Profit & Loss Consolidated'!G23/'Profit & Loss Consolidated'!G9 -> 0.089977869 | C45: ='Profit & Loss Consolidated'!H23/'Profit & Loss Consolidated'!H9 -> 0.081456112 | D45: ='Profit & Loss Consolidated'!I23/'Profit & Loss Consolidated'!I9 -> 0.10532866 | E45: ='Profit & Loss Consolidated'!J23/'Profit & Loss Consolidated'!J9 -> 0.08716957 | F45: ='Profit & Loss Consolidated'!K23/'Profit & Loss Consolidated'!K9 -> 0.10043742 | G45: ='Profit & Loss Consolidated'!L23/'Profit & Loss Consolidated'!L9 -> 0.094330973 | H45: ='Profit & Loss Consolidated'!M23/'Profit & Loss Consolidated'!M9 -> 0.12372841 | I45: ='Profit & Loss Consolidated'!N23/'Profit & Loss Consolidated'!N9 -> 0.13271628 | ... AK45: ='Profit & Loss Consolidated'!AP23/'Profit & Loss Consolidated'!AP9 -> 0.14220461
A47: Profit Before Interest and Tax (PBIT) | B47: ='Profit & Loss Consolidated'!G25 -> 2517.8 | C47: ='Profit & Loss Consolidated'!H25 -> 796.7 | D47: ='Profit & Loss Consolidated'!I25 -> 728.6 | E47: ='Profit & Loss Consolidated'!J25 -> 707.1 | F47: ='Profit & Loss Consolidated'!K25 -> 1117.6 | G47: ='Profit & Loss Consolidated'!L25 -> 3350 | H47: ='Profit & Loss Consolidated'!M25 -> 889.5 | I47: ='Profit & Loss Consolidated'!N25 -> 998.43 | ... AK47: ='Profit & Loss Consolidated'!AP25 -> 12767.646
A48: PBIT Margin (%) | B48: ='Profit & Loss Consolidated'!G27 -> 0.11189128 | C48: ='Profit & Loss Consolidated'!H27 -> 0.14065038 | D48: ='Profit & Loss Consolidated'!I27 -> 0.10924193 | E48: ='Profit & Loss Consolidated'!J27 -> 0.11588194 | F48: ='Profit & Loss Consolidated'!K27 -> 0.15769719 | G48: ='Profit & Loss Consolidated'!L27 -> 0.13125468 | H48: ='Profit & Loss Consolidated'!M27 -> 0.12585068 | I48: ='Profit & Loss Consolidated'!N27 -> 0.13790984 | ... AK48: ='Profit & Loss Consolidated'!AP27 -> 0.14408243
A50: EBITDA | B50: ='Profit & Loss Consolidated'!G25+'Profit & Loss Consolidated'!G20 -> 3515 | C50: ='Profit & Loss Consolidated'!H25+'Profit & Loss Consolidated'!H20 -> 1030.2 | D50: ='Profit & Loss Consolidated'!I25+'Profit & Loss Consolidated'!I20 -> 978.1 | E50: ='Profit & Loss Consolidated'!J25+'Profit & Loss Consolidated'!J20 -> 963.1 | F50: ='Profit & Loss Consolidated'!K25+'Profit & Loss Consolidated'!K20 -> 1382.4 | G50: ='Profit & Loss Consolidated'!L25+'Profit & Loss Consolidated'!L20 -> 4353.8 | H50: ='Profit & Loss Consolidated'!M25+'Profit & Loss Consolidated'!M20 -> 1159.9 | I50: ='Profit & Loss Consolidated'!N25+'Profit & Loss Consolidated'!N20 -> 1286.73 | ... AK50: ='Profit & Loss Consolidated'!AP25+'Profit & Loss Consolidated'!AP20 -> 14736.915
A51: EBITDA Margin (%) | B51: =B50/'Profit & Loss Consolidated'!G9 -> 0.15620695 | C51: =C50/'Profit & Loss Consolidated'!H9 -> 0.18187275 | D51: =D50/'Profit & Loss Consolidated'!I9 -> 0.14665047 | E51: =E50/'Profit & Loss Consolidated'!J9 -> 0.15783608 | F51: =F50/'Profit & Loss Consolidated'!K9 -> 0.19506138 | G51: =G50/'Profit & Loss Consolidated'!L9 -> 0.17058406 | H51: =H50/'Profit & Loss Consolidated'!M9 -> 0.16410815 | I51: =I50/'Profit & Loss Consolidated'!N9 -> 0.17773177 | ... AK51: =AK50/'Profit & Loss Consolidated'!AP9 -> 0.16630556
A53: Interest (net) | B53: ='Profit & Loss Consolidated'!G29 -> 453.6 | C53: ='Profit & Loss Consolidated'!H29 -> 106.3 | D53: ='Profit & Loss Consolidated'!I29 -> 116.1 | E53: ='Profit & Loss Consolidated'!J29 -> 101 | F53: ='Profit & Loss Consolidated'!K29 -> 109 | G53: ='Profit & Loss Consolidated'!L29 -> 432.4 | H53: ='Profit & Loss Consolidated'!M29 -> 132.5 | I53: ='Profit & Loss Consolidated'!N29 -> 156.3 | ... AK53: ='Profit & Loss Consolidated'!AP29 -> 1695.8558
A55: Profit from Ordinary Activities before Tax (PBT) | B55: ='Profit & Loss Consolidated'!G32 -> 2064.2 | C55: ='Profit & Loss Consolidated'!H32 -> 690.4 | D55: ='Profit & Loss Consolidated'!I32 -> 838.2 | E55: ='Profit & Loss Consolidated'!J32 -> 606.1 | F55: ='Profit & Loss Consolidated'!K32 -> 782.9 | G55: ='Profit & Loss Consolidated'!L32 -> 2917.6 | H55: ='Profit & Loss Consolidated'!M32 -> 219.9 | I55: ='Profit & Loss Consolidated'!N32 -> -208.87 | ... AK55: ='Profit & Loss Consolidated'!AP32 -> 11071.79
A56: PBT Margin (%) | B56: ='Profit & Loss Consolidated'!G34 -> 0.091733253 | C56: ='Profit & Loss Consolidated'!H34 -> 0.12188405 | D56: ='Profit & Loss Consolidated'!I34 -> 0.1256747 | E56: ='Profit & Loss Consolidated'!J34 -> 0.099329717 | F56: ='Profit & Loss Consolidated'!K34 -> 0.11046987 | G56: ='Profit & Loss Consolidated'!L34 -> 0.11431303 | H56: ='Profit & Loss Consolidated'!M34 -> 0.031112495 | I56: ='Profit & Loss Consolidated'!N34 -> -0.028850523 | ... AK56: ='Profit & Loss Consolidated'!AP34 -> 0.12494476
A58: Total Tax | B58: ='Profit & Loss Consolidated'!G42 -> 43.7 | C58: ='Profit & Loss Consolidated'!H42 -> 70.1 | D58: ='Profit & Loss Consolidated'!I42 -> 215 | E58: ='Profit & Loss Consolidated'!J42 -> 161.7 | F58: ='Profit & Loss Consolidated'!K42 -> 89.2 | G58: ='Profit & Loss Consolidated'!L42 -> 536 | H58: ='Profit & Loss Consolidated'!M42 -> 55.3 | I58: ='Profit & Loss Consolidated'!N42 -> 173.3 | ... AK58: ='Profit & Loss Consolidated'!AP42 -> 1439.3327
A59: Tax Rate | B59: ='Cost Model'!G20 -> 0.021170429 | C59: ='Cost Model'!H20 -> 0.10153534 | D59: ='Cost Model'!I20 -> 0.25650203 | E59: ='Cost Model'!J20 -> 0.26678766 | F59: ='Cost Model'!K20 -> 0.11393537 | G59: ='Cost Model'!L20 -> 0.18371264 | H59: ='Cost Model'!M20 -> 0.25147794 | I59: ='Cost Model'!N20 -> -0.82970269 | ... AK59: ='Cost Model'!AP20 -> 0.13
A61: Net Profit (PAT) | B61: ='Profit & Loss Consolidated'!G45 -> 2009.5 | C61: ='Profit & Loss Consolidated'!H45 -> 617.4 | D61: ='Profit & Loss Consolidated'!I45 -> 620.6 | E61: ='Profit & Loss Consolidated'!J45 -> 445.7 | F61: ='Profit & Loss Consolidated'!K45 -> 701.3 | G61: ='Profit & Loss Consolidated'!L45 -> 2385 | H61: ='Profit & Loss Consolidated'!M45 -> 164.2 | I61: ='Profit & Loss Consolidated'!N45 -> -384.17 | ... AK61: ='Profit & Loss Consolidated'!AP45 -> 9632.4571
A62: Net Profit Margin (%) | B62: ='Profit & Loss Consolidated'!G46 -> 0.089302379 | C62: ='Profit & Loss Consolidated'!H46 -> 0.10899654 | D62: ='Profit & Loss Consolidated'!I46 -> 0.093049058 | E62: ='Profit & Loss Consolidated'!J46 -> 0.073042823 | F62: ='Profit & Loss Consolidated'!K46 -> 0.098955835 | G62: ='Profit & Loss Consolidated'!L46 -> 0.093445494 | H62: ='Profit & Loss Consolidated'!M46 -> 0.023231794 | I62: ='Profit & Loss Consolidated'!N46 -> -0.053064134 | ... AK62: ='Profit & Loss Consolidated'!AP46 -> 0.10870194
A63: Diluted EPS | B63: ='Profit & Loss Consolidated'!G52 -> 30.27 | C63: ='Profit & Loss Consolidated'!H52 -> 9.13 | D63: ='Profit & Loss Consolidated'!I52 -> 9.19 | E63: ='Profit & Loss Consolidated'!J52 -> 6.59 | F63: ='Profit & Loss Consolidated'!K52 -> 10.37 | G63: ='Profit & Loss Consolidated'!L52 -> 35.33 | H63: ='Profit & Loss Consolidated'!M52 -> 2.43 | I63: ='Profit & Loss Consolidated'!N52 -> -7.15 | ... AK63: ='Profit & Loss Consolidated'!AP52 -> 165.55323
A66: Other Selected Items and Ratios
A68: Cash and Bank Balances | B68: ='Balance Sheet'!C42 -> 5824.6 | C68: Quarterly data not available | G68: ='Balance Sheet'!D42 -> 2825.7 | H68: Quarterly data not available | L68: ='Balance Sheet'!E42 -> 1594.6348 | M68: Quarterly data not available | Q68: ='Balance Sheet'!F42 -> 869.29382 | R68: Quarterly data not available | V68: ='Balance Sheet'!G42 -> 2450.1652 | W68: Quarterly data not available | AA68: ='Balance Sheet'!H42 -> 747.33248 | AB68: Quarterly data not available | AF68: ='Balance Sheet'!I42 -> 1555.521 | AG68: Quarterly data not available | AK68: ='Balance Sheet'!J42 -> 2886.5104
A69: Capex | B69: ='Fixed Asset'!E17 -> 1809.5 | G69: ='Fixed Asset'!F17 -> 2456.9 | L69: ='Fixed Asset'!G17 -> 2292.2798 | Q69: ='Fixed Asset'!H17 -> 2755.5823 | V69: ='Fixed Asset'!I17 -> 3416.9221 | AA69: ='Fixed Asset'!J17 -> 3631.7 | AF69: ='Fixed Asset'!K17 -> 4430.6741 | AK69: ='Fixed Asset'!L17 -> 5316.8089
A70: Total Debt | B70: ='Balance Sheet'!C62 -> 20781.4 | G70: ='Balance Sheet'!D62 -> 18470.2 | L70: ='Balance Sheet'!E62 -> 18470.2 | Q70: ='Balance Sheet'!F62 -> 17534.93 | V70: ='Balance Sheet'!G62 -> 16972.93 | AA70: ='Balance Sheet'!H62 -> 15569.73 | AF70: ='Balance Sheet'!I62 -> 15569.73 | AK70: ='Balance Sheet'!J62 -> 15569.73
A71: Total Shareholder's Equity | B71: ='Balance Sheet'!C15 -> 8860.1 | G71: ='Balance Sheet'!D15 -> 11240.2 | L71: ='Balance Sheet'!E15 -> 12239.13 | Q71: ='Balance Sheet'!F15 -> 16929.666 | V71: ='Balance Sheet'!G15 -> 24357.962 | AA71: ='Balance Sheet'!H15 -> 30093.203 | AF71: ='Balance Sheet'!I15 -> 38076.177 | AK71: ='Balance Sheet'!J15 -> 47708.634
A72: Cash Ratio | B72: ='Balance Sheet'!C42/'Balance Sheet'!C46 -> 1.3111381 | G72: ='Balance Sheet'!D42/'Balance Sheet'!D46 -> 0.50950234 | L72: ='Balance Sheet'!E42/'Balance Sheet'!E46 -> 0.2480504 | Q72: ='Balance Sheet'!F42/'Balance Sheet'!F46 -> 0.10490617 | V72: ='Balance Sheet'!G42/'Balance Sheet'!G46 -> 0.24008383 | AA72: ='Balance Sheet'!H42/'Balance Sheet'!H46 -> 0.059055413 | AF72: ='Balance Sheet'!I42/'Balance Sheet'!I46 -> 0.10075391 | AK72: ='Balance Sheet'!J42/'Balance Sheet'!J46 -> 0.15580375
A73: Days Sales Outstanding (DSO) | B73: ='Balance Sheet'!C59 -> 101.55903 | G73: ='Balance Sheet'!D59 -> 95.1023 | L73: ='Balance Sheet'!E59 -> 95.1023 | Q73: ='Balance Sheet'!F59 -> 95.1023 | V73: ='Balance Sheet'!G59 -> 95.1023 | AA73: ='Balance Sheet'!H59 -> 95.1023 | AF73: ='Balance Sheet'!I59 -> 95.1023 | AK73: ='Balance Sheet'!J59 -> 95.1023
A74: Inventory Days | B74: ='Balance Sheet'!C60 -> 91.339213 | G74: ='Balance Sheet'!D60 -> 103.64064 | L74: ='Balance Sheet'!E60 -> 103.64064 | Q74: ='Balance Sheet'!F60 -> 103.64064 | V74: ='Balance Sheet'!G60 -> 103.64064 | AA74: ='Balance Sheet'!H60 -> 103.64064 | AF74: ='Balance Sheet'!I60 -> 103.64064 | AK74: ='Balance Sheet'!J60 -> 103.64064
A75: Payable Days | B75: ='Balance Sheet'!C61 -> 123.71258 | G75: ='Balance Sheet'!D61 -> 142.29109 | L75: ='Balance Sheet'!E61 -> 142.29109 | Q75: ='Balance Sheet'!F61 -> 142.29109 | V75: ='Balance Sheet'!G61 -> 142.29109 | AA75: ='Balance Sheet'!H61 -> 142.29109 | AF75: ='Balance Sheet'!I61 -> 142.29109 | AK75: ='Balance Sheet'!J61 -> 142.29109
A76: Book Value Per Share | B76: ='Balance Sheet'!C64 -> 133.46366 | G76: ='Balance Sheet'!D64 -> 166.50577 | L76: ='Balance Sheet'!E64 -> 189.05206 | Q76: ='Balance Sheet'!F64 -> 262.00553 | V76: ='Balance Sheet'!G64 -> 376.96672 | AA76: ='Balance Sheet'!H64 -> 517.21248 | AF76: ='Balance Sheet'!I64 -> 654.416 | AK76: ='Balance Sheet'!J64 -> 819.96923
A77: Net Cash Per Share | B77: ='Balance Sheet'!C42/'Profit & Loss Consolidated'!G55 -> 87.738563 | G77: ='Balance Sheet'!D42/'Profit & Loss Consolidated'!L55 -> 41.858273 | L77: ='Balance Sheet'!E42/'Profit & Loss Consolidated'!Q55 -> 24.63157 | Q77: ='Balance Sheet'!F42/'Profit & Loss Consolidated'!V55 -> 13.453295 | V77: ='Balance Sheet'!G42/'Profit & Loss Consolidated'!AA55 -> 37.919048 | AA77: ='Balance Sheet'!H42/'Profit & Loss Consolidated'!AF55 -> 12.844418 | AF77: ='Balance Sheet'!I42/'Profit & Loss Consolidated'!AK55 -> 26.73477 | AK77: ='Balance Sheet'!J42/'Profit & Loss Consolidated'!AP55 -> 49.610512
A80: Valuation Metrics
A82: EBITDA Margin (%) | B82: =B51 -> 0.15620695 | C82: =C51 -> 0.18187275 | D82: =D51 -> 0.14665047 | E82: =E51 -> 0.15783608 | F82: =F51 -> 0.19506138 | G82: =G51 -> 0.17058406 | H82: =H51 -> 0.16410815 | I82: =I51 -> 0.17773177 | ... AK82: =AK51 -> 0.16630556
A83: EBIT Margin (%) | B83: =B48 -> 0.11189128 | C83: =C48 -> 0.14065038 | D83: =D48 -> 0.10924193 | E83: =E48 -> 0.11588194 | F83: =F48 -> 0.15769719 | G83: =G48 -> 0.13125468 | H83: =H48 -> 0.12585068 | I83: =I48 -> 0.13790984 | ... AK83: =AK48 -> 0.14408243
A84: Net Profit Margin (%) | B84: =B62 -> 0.089302379 | C84: =C62 -> 0.10899654 | D84: =D62 -> 0.093049058 | E84: =E62 -> 0.073042823 | F84: =F62 -> 0.098955835 | G84: =G62 -> 0.093445494 | H84: =H62 -> 0.023231794 | I84: =I62 -> -0.053064134 | ... AK84: =AK62 -> 0.10870194
A86: Interest Cover | B86: =B50/B53 -> 7.7491182 | C86: =C50/C53 -> 9.6914393 | D86: =D50/D53 -> 8.4246339 | E86: =E50/E53 -> 9.5356436 | F86: =F50/F53 -> 12.682569 | G86: =G50/G53 -> 10.068918 | H86: =H50/H53 -> 8.7539623 | I86: =I50/I53 -> 8.2324376 | ... AK86: =AK50/AK53 -> 8.6899576
A87: ROE | B87: =B61/B71 -> 0.22680331 | C87: Quarterly data not available | G87: =G61/G71 -> 0.21218484 | H87: Quarterly data not available | L87: =L61/L71 -> 0.081617729 | M87: Quarterly data not available | Q87: =Q61/Q71 -> 0.27706017 | R87: Quarterly data not available | V87: =V61/V71 -> 0.20947993 | W87: Quarterly data not available | AA87: =AA61/AA71 -> 0.19058262 | AB87: Quarterly data not available | AF87: =AF61/AF71 -> 0.20965795 | AG87: Quarterly data not available | AK87: =AK61/AK71 -> 0.20190176
A88: EV/Sales | N88: ='DCF Valuation'!$E$13/(N31*4) -> 1.5507274 | O88: ='DCF Valuation'!$E$13/(O31*4) -> 1.5507274 | P88: ='DCF Valuation'!$E$13/(P31*4) -> 1.5507274 | Q88: ='DCF Valuation'!$E$13/(Q31) -> 1.6334143 | R88: ='DCF Valuation'!$E$13/(R31*4) -> 1.4240602 | S88: ='DCF Valuation'!$E$13/(S31*4) -> 1.3902289 | T88: ='DCF Valuation'!$E$13/(T31*4) -> 1.3299758 | U88: ='DCF Valuation'!$E$13/(U31*4) -> 1.1585241 | V88: ='DCF Valuation'!$E$13/(V31) -> 1.3172696 | W88: ='DCF Valuation'!$E$13/(W31*4) -> 1.1484356 | X88: ='DCF Valuation'!$E$13/(X31*4) -> 1.1211523 | Y88: ='DCF Valuation'!$E$13/(Y31*4) -> 1.0725612 | Z88: ='DCF Valuation'!$E$13/(Z31*4) -> 0.93429361 | AA88: ='DCF Valuation'!$E$13/(AA31) -> 1.0623142 | AB88: ='DCF Valuation'!$E$13/(AB31*4) -> 0.94134066 | AC88: ='DCF Valuation'!$E$13/(AC31*4) -> 0.91897732 | AD88: ='DCF Valuation'!$E$13/(AD31*4) -> 0.8791485 | AE88: ='DCF Valuation'!$E$13/(AE31*4) -> 0.76581444 | AF88: ='DCF Valuation'!$E$13/(AF31) -> 0.87074935 | AG88: ='DCF Valuation'!$E$13/(AG31*4) -> 0.78445055 | AH88: ='DCF Valuation'!$E$13/(AH31*4) -> 0.76581444 | AI88: ='DCF Valuation'!$E$13/(AI31*4) -> 0.73262375 | AJ88: ='DCF Valuation'!$E$13/(AJ31*4) -> 0.6381787 | AK88: ='DCF Valuation'!$E$13/(AK31) -> 0.72562446
A89: EV/EBITDA | N89: ='DCF Valuation'!$E$13/(N50*4) -> 8.9823775 | O89: ='DCF Valuation'!$E$13/(O50*4) -> 8.5048756 | P89: ='DCF Valuation'!$E$13/(P50*4) -> 7.8818402 | Q89: ='DCF Valuation'!$E$13/(Q50) -> 8.3522736 | R89: ='DCF Valuation'!$E$13/(R50*4) -> 6.3363601 | S89: ='DCF Valuation'!$E$13/(S50*4) -> 8.1100267 | T89: ='DCF Valuation'!$E$13/(T50*4) -> 7.8437573 | U89: ='DCF Valuation'!$E$13/(U50*4) -> 6.3961085 | V89: ='DCF Valuation'!$E$13/(V50) -> 7.0801666 | W89: ='DCF Valuation'!$E$13/(W50*4) -> 5.2930165 | X89: ='DCF Valuation'!$E$13/(X50*4) -> 6.6193293 | Y89: ='DCF Valuation'!$E$13/(Y50*4) -> 6.9349026 | Z89: ='DCF Valuation'!$E$13/(Z50*4) -> 5.4256064 | AA89: ='DCF Valuation'!$E$13/(AA50) -> 5.9834538 | AB89: ='DCF Valuation'!$E$13/(AB50*4) -> 4.4585413 | AC89: ='DCF Valuation'!$E$13/(AC50*4) -> 5.4753629 | AD89: ='DCF Valuation'!$E$13/(AD50*4) -> 6.127834 | AE89: ='DCF Valuation'!$E$13/(AE50*4) -> 4.627501 | AF89: ='DCF Valuation'!$E$13/(AF50) -> 5.087673 | AG89: ='DCF Valuation'!$E$13/(AG50*4) -> 3.7949725 | AH89: ='DCF Valuation'!$E$13/(AH50*4) -> 4.5946764 | AI89: ='DCF Valuation'!$E$13/(AI50*4) -> 5.4273117 | AJ89: ='DCF Valuation'!$E$13/(AJ50*4) -> 3.9784317 | AK89: ='DCF Valuation'!$E$13/(AK50) -> 4.3632001
A90: P/E | N90: ='DCF Valuation'!$E$7/(N63*4) -> 13.410042 | O90: ='DCF Valuation'!$E$7/(O63*4) -> 12.231305 | P90: ='DCF Valuation'!$E$7/(P63*4) -> 10.817427 | Q90: ='DCF Valuation'!$E$7/(Q63) -> 10.373144 | R90: ='DCF Valuation'!$E$7/(R63*4) -> 8.3979009 | S90: ='DCF Valuation'!$E$7/(S63*4) -> 12.5954 | T90: ='DCF Valuation'!$E$7/(T63*4) -> 11.875556 | U90: ='DCF Valuation'!$E$7/(U63*4) -> 8.5191663 | V90: ='DCF Valuation'!$E$7/(V63) -> 9.5356334 | W90: ='DCF Valuation'!$E$7/(W63*4) -> 6.29956 | X90: ='DCF Valuation'!$E$7/(X63*4) -> 9.0574912 | Y90: ='DCF Valuation'!$E$7/(Y63*4) -> 9.839797 | Z90: ='DCF Valuation'!$E$7/(Z63*4) -> 6.5425294 | AA90: ='DCF Valuation'!$E$7/(AA63) -> 7.6391088 | AB90: ='DCF Valuation'!$E$7/(AB63*4) -> 4.5951138 | AC90: ='DCF Valuation'!$E$7/(AC63*4) -> 6.0812778 | AD90: ='DCF Valuation'!$E$7/(AD63*4) -> 7.1628591 | AE90: ='DCF Valuation'!$E$7/(AE63*4) -> 4.8270443 | AF90: ='DCF Valuation'!$E$7/(AF63) -> 5.4881974 | AG90: ='DCF Valuation'!$E$7/(AG63*4) -> 3.792541 | AH90: ='DCF Valuation'!$E$7/(AH63*4) -> 4.8753065 | AI90: ='DCF Valuation'!$E$7/(AI63*4) -> 6.1545377 | AJ90: ='DCF Valuation'!$E$7/(AJ63*4) -> 4.0296529 | AK90: ='DCF Valuation'!$E$7/(AK63) -> 4.548386

Sheet Profit & Loss Consolidated
A1: Aurobindo Pharma
A2: Profit & Loss Consolidated
A3: (In Rs Millions, Except per share items)
A4: For the Fiscal Period Ending | B4: FY2006 A | C4: 3 months Jun-30-2006 | D4: 3 months Sep-30-2006 | E4: 3 months Dec-31-2006 | F4: 3 months Mar-31-2007 | G4: FY2007 A | H4: 3 months Jun-30-2007 | I4: 3 months Sep-30-2007 | J4: 3 months Dec-31-2007 | K4: 3 months Mar-31-2008 | L4: FY2008 A | M4: 3 months Jun-30-2008 | N4: 3 months Sep-30-2008 | O4: 3 months Dec-31-2008 | P4: 3 months Mar-31-2009 | Q4: FY2009 A | R4: 3 months Jun-30-2009 | S4: 3 months Sep-30-2009 | T4: 3 months Dec-31-2009 | U4: 3 months Mar-31-2010 | V4: FY2010 E | W4: 3 months Jun-30-2010 | X4: 3 months Sep-30-2010 | Y4: 3 months Dec-31-2010 | Z4: 3 months Mar-31-2011 | AA4: FY2011 E | AB4: 3 months Jun-30-2011 | AC4: 3 months Sep-30-2011 | AD4: 3 months Dec-31-2011 | AE4: 3 months Mar-31-2012 | AF4: FY2012 E | AG4: 3 months Jun-30-2012 | AH4: 3 months Sep-30-2012 | AI4: 3 months Dec-31-2012 | AJ4: 3 months Mar-31-2013 | AK4: FY2013 E | AL4: 3 months Jun-30-2013 | AM4: 3 months Sep-30-2013 | AN4: 3 months Dec-31-2013 | AO4: 3 months Mar-31-2014 | AP4: FY2014 E
A7: Profit & Loss Consolidated | C7: Numbers for these Quarters are Stand Alone as Consolidated data was not available
A9: Sales (including excise duty) | B9: 16955 | F9: 5611 | G9: ='Segment Revenue Model'!B25 -> 22502.2 | H9: ='Segment Revenue Model'!C25+0.4 -> 5664.4 | I9: ='Segment Revenue Model'!D25-0.4 -> 6669.6 | J9: ='Segment Revenue Model'!E25-0.1 -> 6101.9 | K9: =L9-SUM(H9:J9) -> 7087 | L9: ='Segment Revenue Model'!G25-1.1 -> 25522.9 | M9: ='Segment Revenue Model'!H25-0.1 -> 7067.9 | N9: ='Segment Revenue Model'!I25-0.27 -> 7239.73 | O9: ='Segment Revenue Model'!J25-0.2 -> 7567.8 | P9: =Q9-SUM(M9:O9) -> 8688.3 | Q9: ='Segment Revenue Model'!L25-0.27 -> 30563.73 | R9: ='Segment Revenue Model'!M25 -> 8267.1 | S9: ='Segment Revenue Model'!N25 -> 10366.121 | T9: ='Segment Revenue Model'!O25 -> 10366.121 | U9: ='Segment Revenue Model'!P25 -> 10366.121 | V9: ='Segment Revenue Model'!Q25 -> 39365.462 | W9: ='Segment Revenue Model'!R25 -> 11288.166 | X9: ='Segment Revenue Model'!S25 -> 11562.864 | Y9: ='Segment Revenue Model'!T25 -> 12086.706 | ... AP9: ='Segment Revenue Model'!AK25 -> 88613.481
A10: Less: Excise Duty | B10: 1018.9 | F10: 288 | G10: 1273 | H10: 341 | I10: 385.8 | J10: 406.3 | K10: =L10-SUM(H10:J10) -> 30.8 | L10: 1163.9 | M10: 271.3 | N10: 229.8 | O10: 216.7 | P10: =Q10-SUM(M10:O10) -> 187.8 | Q10: 905.6 | R10: 170.6 | S10: =S9*'Cost Model'!S10 -> 329.03637 | T10: =T9*'Cost Model'!T10 -> 296.82845 | U10: =U9*'Cost Model'!U10 -> 224.06655 | V10: =SUM(R10:U10) -> 1020.5314 | W10: =W9*'Cost Model'!W10 -> 232.94276 | X10: =X9*'Cost Model'!X10 -> 367.02282 | Y10: =Y9*'Cost Model'!Y10 -> 346.09652 | Z10: =Z9*'Cost Model'!Z10 -> 299.92139 | AA10: =SUM(W10:Z10) -> 1245.9835 | AB10: =AB9*'Cost Model'!AB10 -> 288.84903 | AC10: =AC9*'Cost Model'!AC10 -> 455.10829 | AD10: =AD9*'Cost Model'!AD10 -> 429.15969 | AE10: =AE9*'Cost Model'!AE10 -> 371.90252 | AF10: =SUM(AB10:AE10) -> 1545.0195 | AG10: =AG9*'Cost Model'!AG10 -> 352.39581 | AH10: =AH9*'Cost Model'!AH10 -> 555.23212 | AI10: =AI9*'Cost Model'!AI10 -> 523.57482 | AJ10: =AJ9*'Cost Model'!AJ10 -> 453.72107 | AK10: =SUM(AG10:AJ10) -> 1884.9238 | AL10: =AL9*'Cost Model'!AL10 -> 422.87497 | AM10: =AM9*'Cost Model'!AM10 -> 666.27854 | AN10: =AN9*'Cost Model'!AN10 -> 628.28978 | AO10: =AO9*'Cost Model'!AO10 -> 544.46529 | AP10: =SUM(AL10:AO10) -> 2261.9086
A11: Net Sales | B11: =B9-B10 -> 15936.1 | C11: 4385.6 | D11: 4800 | E11: 5284 | F11: =F9-F10 -> 5323 | G11: =G9-G10 -> 21229.2 | H11: =H9-H10 -> 5323.4 | I11: =I9-I10 -> 6283.8 | J11: =J9-J10 -> 5695.6 | K11: =L11-SUM(H11:J11) -> 7056.2 | L11: =L9-L10 -> 24359 | M11: =M9-M10 -> 6796.6 | N11: =N9-N10 -> 7009.93 | O11: =O9-O10 -> 7351.1 | P11: =Q11-SUM(M11:O11) -> 8500.5 | Q11: =Q9-Q10 -> 29658.13 | R11: =R9-R10 -> 8096.5 | S11: =S9-S10 -> 10037.084 | T11: =T9-T10 -> 10069.292 | U11: =U9-U10 -> 10142.054 | V11: =V9-V10 -> 38344.93 | W11: =W9-W10 -> 11055.223 | X11: =X9-X10 -> 11195.841 | ... AP11: =AP9-AP10 -> 86351.572
A12: Other Operating Income | B12: 0 | C12: 0 | D12: 0 | F12: 33 | G12: 0 | H12: 0 | I12: 18.2 | J12: 0 | K12: 0 | L12: 0 | M12: 35.8 | N12: 84.6 | O12: 877.1 | P12: =Q12-SUM(M12:O12) -> 586.8 | Q12: 1584.3 | R12: 431 | S12: =N12 -> 84.6 | T12: =O12 -> 877.1 | U12: =P12 -> 586.8 | V12: =SUM(R12:U12) -> 1979.5 | W12: =R12 -> 431 | X12: =S12 -> 84.6 | Y12: =T12 -> 877.1 | Z12: =U12 -> 586.8 | AA12: =SUM(W12:Z12) -> 1979.5 | AB12: =W12 -> 431 | AC12: =X12 -> 84.6 | AD12: =Y12 -> 877.1 | AE12: =Z12 -> 586.8 | AF12: =SUM(AB12:AE12) -> 1979.5 | AG12: =AB12 -> 431 | AH12: =AC12 -> 84.6 | AI12: =AD12 -> 877.1 | AJ12: =AE12 -> 586.8 | AK12: =SUM(AG12:AJ12) -> 1979.5 | AL12: =AG12 -> 431 | AM12: =AH12 -> 84.6 | AN12: =AI12 -> 877.1 | AO12: =AJ12 -> 586.8 | AP12: =SUM(AL12:AO12) -> 1979.5
A13: Total Income | B13: =B11+B12 -> 15936.1 | C13: =C11+C12 -> 4385.6 | D13: =D11+D12 -> 4800 | E13: =E11+E12 -> 5284 | F13: =F11+F12 -> 5356 | G13: =G11+G12 -> 21229.2 | H13: =H11+H12 -> 5323.4 | I13: =I11+I12 -> 6302 | ... L13: =L11+L12 -> 24359 | M13: =SUM(M11:M12) -> 6832.4 | N13: =N11+N12 -> 7094.53 | O13: =O11+O12 -> 8228.2 | P13: =Q13-SUM(M13:O13) -> 9087.3 | Q13: =SUM(Q11:Q12) -> 31242.43 | R13: =SUM(R11:R12) -> 8527.5 | S13: =SUM(S11:S12) -> 10121.684 | T13: =SUM(T11:T12) -> 10946.392 | U13: =SUM(U11:U12) -> 10728.854 | V13: =SUM(V11:V12) -> 40324.43 | W13: =SUM(W11:W12) -> 11486.223 | X13: =SUM(X11:X12) -> 11280.441 | ... AP13: =SUM(AP11:AP12) -> 88331.072
A15: Expenditure
A16: a. (Increase) / Decrease in Stocks | B16: -518.3 | C16: -445.1 | D16: 84.4 | E16: -222.9 | F16: -440 | G16: -890.5 | H16: -439.6 | I16: -327.4 | J16: -433.5 | K16: =L16-SUM(H16:J16) -> 488.1 | L16: -712.4 | M16: -99.7 | N16: -580.7 | O16: -170.9 | P16: =Q16-SUM(M16:O16) -> 644.1 | Q16: -207.2 | R16: -101.8 | S16: =S9*'Cost Model'!S12 -> -831.46833 | T16: =T9*'Cost Model'!T12 -> -234.09313 | U16: =U9*'Cost Model'!U12 -> 768.48386 | V16: =SUM(R16:U16) -> -398.87761 | W16: =W9*'Cost Model'!W12 -> -139.00102 | X16: =X9*'Cost Model'!X12 -> -927.45931 | Y16: =Y9*'Cost Model'!Y12 -> -272.94829 | Z16: =Z9*'Cost Model'!Z12 -> 1028.6441 | AA16: =SUM(W16:Z16) -> -310.7645 | AB16: =AB9*'Cost Model'!AB12 -> -172.36126 | AC16: =AC9*'Cost Model'!AC12 -> -1150.0495 | AD16: =AD9*'Cost Model'!AD12 -> -338.45588 | AE16: =AE9*'Cost Model'!AE12 -> 1275.5187 | AF16: =SUM(AB16:AE16) -> -385.34799 | AG16: =AG9*'Cost Model'!AG12 -> -210.28074 | AH16: =AH9*'Cost Model'!AH12 -> -1403.0605 | AI16: =AI9*'Cost Model'!AI12 -> -412.91618 | AJ16: =AJ9*'Cost Model'!AJ12 -> 1556.1328 | AK16: =SUM(AG16:AJ16) -> -470.12454 | AL16: =AL9*'Cost Model'!AL12 -> -252.33688 | AM16: =AM9*'Cost Model'!AM12 -> -1683.6725 | AN16: =AN9*'Cost Model'!AN12 -> -495.49942 | AO16: =AO9*'Cost Model'!AO12 -> 1867.3594 | AP16: =SUM(AL16:AO16) -> -564.14945
A17: b. Material Consumed | B17: 9146.3 | C17: 2921.2 | D17: 2541.7 | E17: 3284.6 | F17: 3037 | G17: 11755.7 | H17: 3036.9 | I17: 3309.3 | J17: 2974.7 | K17: =L17-SUM(H17:J17) -> 3290.8 | L17: 12611.7 | M17: 3572.4 | N17: 3995 | O17: 4281.4 | P17: =Q17-SUM(M17:O17) -> 3650.2 | Q17: 15499 | R17: 4013.1 | S17: =S9*'Cost Model'!S13 -> 5720.1929 | T17: =T9*'Cost Model'!T13 -> 5864.5192 | U17: =U9*'Cost Model'!U13 -> 4355.0998 | V17: =SUM(R17:U17) -> 19952.912 | W17: =W9*'Cost Model'!W13 -> 5479.6166 | X17: =X9*'Cost Model'!X13 -> 6380.5751 | Y17: =Y9*'Cost Model'!Y13 -> 6837.9218 | Z17: =Z9*'Cost Model'!Z13 -> 5829.4625 | AA17: =SUM(W17:Z17) -> 24527.576 | AB17: =AB9*'Cost Model'!AB13 -> 6794.7246 | AC17: =AC9*'Cost Model'!AC13 -> 7911.9131 | AD17: =AD9*'Cost Model'!AD13 -> 8479.023 | AE17: =AE9*'Cost Model'!AE13 -> 7228.5334 | AF17: =SUM(AB17:AE17) -> 30414.194 | AG17: =AG9*'Cost Model'!AG13 -> 8289.5641 | AH17: =AH9*'Cost Model'!AH13 -> 9652.534 | AI17: =AI9*'Cost Model'!AI13 -> 10344.408 | AJ17: =AJ9*'Cost Model'!AJ13 -> 8818.8108 | AK17: =SUM(AG17:AJ17) -> 37105.317 | AL17: =AL9*'Cost Model'!AL13 -> 9947.4769 | AM17: =AM9*'Cost Model'!AM13 -> 11583.041 | AN17: =AN9*'Cost Model'!AN13 -> 12413.29 | AO17: =AO9*'Cost Model'!AO13 -> 10582.573 | AP17: =SUM(AL17:AO17) -> 44526.38
A18: C. Purchase of traded goods | B18: 908.5 | C18: 0 | D18: 0 | E18: 0 | F18: 330 | G18: 1351.1 | H18: 330.2 | I18: 452.6 | J18: 488 | K18: =L18-SUM(H18:J18) -> 343.9 | L18: 1614.7 | M18: 216.4 | N18: 200.4 | O18: 157.4 | P18: =Q18-SUM(M18:O18) -> 417.4 | Q18: 991.6 | R18: 302.5 | S18: =S9*'Cost Model'!S14 -> 286.94034 | T18: =T9*'Cost Model'!T14 -> 215.60128 | U18: =U9*'Cost Model'!U14 -> 498.00522 | V18: =SUM(R18:U18) -> 1303.0468 | W18: =W9*'Cost Model'!W14 -> 413.04329 | X18: =X9*'Cost Model'!X14 -> 320.0669 | Y18: =Y9*'Cost Model'!Y14 -> 251.38714 | Z18: =Z9*'Cost Model'!Z14 -> 666.59844 | AA18: =SUM(W18:Z18) -> 1651.0958 | AB18: =AB9*'Cost Model'!AB14 -> 512.17368 | AC18: =AC9*'Cost Model'!AC14 -> 396.88295 | AD18: =AD9*'Cost Model'!AD14 -> 311.72005 | AE18: =AE9*'Cost Model'!AE14 -> 826.58207 | AF18: =SUM(AB18:AE18) -> 2047.3587 | AG18: =AG9*'Cost Model'!AG14 -> 624.85189 | AH18: =AH9*'Cost Model'!AH14 -> 484.1972 | AI18: =AI9*'Cost Model'!AI14 -> 380.29846 | AJ18: =AJ9*'Cost Model'!AJ14 -> 1008.4301 | AK18: =SUM(AG18:AJ18) -> 2497.7777 | AL18: =AL9*'Cost Model'!AL14 -> 749.82227 | AM18: =AM9*'Cost Model'!AM14 -> 581.03664 | AN18: =AN9*'Cost Model'!AN14 -> 456.35815 | AO18: =AO9*'Cost Model'!AO14 -> 1210.1161 | AP18: =SUM(AL18:AO18) -> 2997.3332
A19: d. Staff Cost | B19: 1024.2 | C19: 258 | D19: 288.1 | E19: 262.7 | F19: 442 | G19: 1504.2 | H19: 442.3 | I19: 492.9 | J19: 497.9 | K19: =L19-SUM(H19:J19) -> 496.9 | L19: 1930 | M19: 573.7 | N19: 589.6 | O19: 653.6 | P19: =Q19-SUM(M19:O19) -> 617.8 | Q19: 2434.7 | R19: 690.6 | S19: =S9*'Cost Model'!S15 -> 844.21169 | T19: =T9*'Cost Model'!T15 -> 895.27953 | U19: =U9*'Cost Model'!U15 -> 737.10499 | V19: =SUM(R19:U19) -> 3167.1962 | W19: =W9*'Cost Model'!W15 -> 942.9676 | X19: =X9*'Cost Model'!X15 -> 941.67386 | Y19: =Y9*'Cost Model'!Y15 -> 1043.8795 | Z19: =Z9*'Cost Model'!Z15 -> 986.64235 | AA19: =SUM(W19:Z19) -> 3915.1633 | AB19: =AB9*'Cost Model'!AB15 -> 1169.2798 | AC19: =AC9*'Cost Model'!AC15 -> 1167.6756 | AD19: =AD9*'Cost Model'!AD15 -> 1294.4106 | AE19: =AE9*'Cost Model'!AE15 -> 1223.4365 | AF19: =SUM(AB19:AE19) -> 4854.8025 | AG19: =AG9*'Cost Model'!AG15 -> 1426.5214 | AH19: =AH9*'Cost Model'!AH15 -> 1424.5642 | AI19: =AI9*'Cost Model'!AI15 -> 1579.1809 | AJ19: =AJ9*'Cost Model'!AJ15 -> 1492.5925 | AK19: =SUM(AG19:AJ19) -> 5922.859 | AL19: =AL9*'Cost Model'!AL15 -> 1711.8257 | AM19: =AM9*'Cost Model'!AM15 -> 1709.4771 | AN19: =AN9*'Cost Model'!AN15 -> 1895.0171 | AO19: =AO9*'Cost Model'!AO15 -> 1791.1111 | AP19: =SUM(AL19:AO19) -> 7107.4308
A20: e. Depreciation / Amortization | B20: 721.3 | C20: 142.8 | D20: 149.9 | E20: 162.9 | F20: 234 | G20: 997.2 | H20: 233.5 | I20: 249.5 | J20: 256 | K20: =L20-SUM(H20:J20) -> 264.8 | L20: 1003.8 | M20: 270.4 | N20: 288.3 | O20: 310.8 | P20: =Q20-SUM(M20:O20) -> 351.7 | Q20: 1221.2 | R20: 332.6 | S20: =($V$20-$R$20)/3 -> 292.40251 | T20: =($V$20-$R$20)/3 -> 292.40251 | U20: =($V$20-$R$20)/3 -> 292.40251 | V20: ='Fixed Asset'!H13 -> 1209.8075 | W20: =$AA$20/4 -> 339.18104 | X20: =$AA$20/4 -> 339.18104 | Y20: =$AA$20/4 -> 339.18104 | Z20: =$AA$20/4 -> 339.18104 | AA20: ='Fixed Asset'!I13 -> 1356.7242 | AB20: =$AF$20/4 -> 381.60896 | AC20: =$AF$20/4 -> 381.60896 | AD20: =$AF$20/4 -> 381.60896 | AE20: =$AF$20/4 -> 381.60896 | AF20: ='Fixed Asset'!J13 -> 1526.4359 | AG20: =$AK$20/4 -> 430.63647 | AH20: =$AK$20/4 -> 430.63647 | AI20: =$AK$20/4 -> 430.63647 | AJ20: =$AK$20/4 -> 430.63647 | AK20: ='Fixed Asset'!K13 -> 1722.5459 | AL20: =$AP$20/4 -> 492.31735 | AM20: =$AP$20/4 -> 492.31735 | AN20: =$AP$20/4 -> 492.31735 | AO20: =$AP$20/4 -> 492.31735 | AP20: ='Fixed Asset'!L13 -> 1969.2694
A21: f. Other Expenditure | B21: 3600.5 | C21: 992.7 | D21: 1194.9 | E21: 1174.9 | F21: 1259 | G21: 4486.8 | H21: 1258.7 | I21: 1422.6 | J21: 1380.6 | K21: =L21-SUM(H21:J21) -> 1441.7 | L21: 5503.6 | M21: 1424.7 | N21: 1641.1 | O21: 1728.9 | P21: =Q21-SUM(M21:O21) -> 1998.1 | Q21: 6792.8 | R21: 1666.1 | S21: =S9*'Cost Model'!S17 -> 2349.7894 | T21: =T9*'Cost Model'!T17 -> 2368.1897 | U21: =U9*'Cost Model'!U17 -> 2383.9584 | V21: =SUM(R21:U21) -> 8768.0374 | W21: =W9*'Cost Model'!W17 -> 2274.9469 | X21: =X9*'Cost Model'!X17 -> 2621.0668 | Y21: =Y9*'Cost Model'!Y17 -> 2761.2657 | Z21: =Z9*'Cost Model'!Z17 -> 3191.0166 | AA21: =SUM(W21:Z21) -> 10848.296 | AB21: =AB9*'Cost Model'!AB17 -> 2820.9341 | AC21: =AC9*'Cost Model'!AC17 -> 3250.1228 | AD21: =AD9*'Cost Model'!AD17 -> 3423.9695 | AE21: =AE9*'Cost Model'!AE17 -> 3956.8606 | AF21: =SUM(AB21:AE21) -> 13451.887 | AG21: =AG9*'Cost Model'!AG17 -> 3441.5396 | AH21: =AH9*'Cost Model'!AH17 -> 3965.1498 | AI21: =AI9*'Cost Model'!AI17 -> 4177.2427 | AJ21: =AJ9*'Cost Model'!AJ17 -> 4827.37 | AK21: =SUM(AG21:AJ21) -> 16411.302 | AL21: =AL9*'Cost Model'!AL17 -> 4129.8476 | AM21: =AM9*'Cost Model'!AM17 -> 4758.1798 | AN21: =AN9*'Cost Model'!AN17 -> 5012.6913 | AO21: =AO9*'Cost Model'!AO17 -> 5792.844 | AP21: =SUM(AL21:AO21) -> 19693.563
A22: Total Expenditure | B22: =SUM(B16:B21) -> 14882.5 | C22: =SUM(C16:C21) -> 3869.6 | D22: =SUM(D16:D21) -> 4259 | E22: =SUM(E16:E21) -> 4662.2 | F22: =SUM(F16:F21) -> 4862 | G22: =SUM(G16:G21) -> 19204.5 | H22: =SUM(H16:H21) -> 4862 | I22: =SUM(I16:I21) -> 5599.5 | J22: =SUM(J16:J21) -> 5163.7 | K22: =L22-SUM(H22:J22) -> 6326.2 | L22: =SUM(L16:L21) -> 21951.4 | M22: =SUM(M16:M21) -> 5957.9 | N22: =SUM(N16:N21) -> 6133.7 | O22: =SUM(O16:O21) -> 6961.2 | P22: =Q22-SUM(M22:O22) -> 7679.3 | Q22: =SUM(Q16:Q21) -> 26732.1 | R22: =SUM(R16:R21) -> 6903.1 | S22: =SUM(S16:S21) -> 8662.0684 | T22: =SUM(T16:T21) -> 9401.8991 | U22: =SUM(U16:U21) -> 9035.0547 | V22: =SUM(V16:V21) -> 34002.122 | W22: =SUM(W16:W21) -> 9310.7544 | X22: =SUM(X16:X21) -> 9675.1044 | ... AP22: =SUM(AP16:AP21) -> 75729.827
A23: Operating Income (Profit from Operations before other income) | B23: =B13-B22 -> 1053.6 | C23: =C13-C22 -> 516 | D23: =D13-D22 -> 541 | E23: =E13-E22 -> 621.8 | F23: =F13-F22 -> 494 | G23: =G13-G22 -> 2024.7 | H23: =H13-H22 -> 461.4 | I23: =I13-I22 -> 702.5 | J23: =J13-J22 -> 531.9 | K23: =L23-SUM(H23:J23) -> 711.8 | L23: =L13-L22 -> 2407.6 | M23: =M13-M22 -> 874.5 | N23: =N13-N22 -> 960.83 | O23: =O13-O22 -> 1267 | P23: =Q23-SUM(M23:O23) -> 1408 | Q23: =Q13-Q22 -> 4510.33 | R23: =R13-R22 -> 1624.4 | S23: =S13-S22 -> 1459.6158 | T23: =T13-T22 -> 1544.493 | U23: =U13-U22 -> 1693.7993 | V23: =V13-V22 -> 6322.3081 | W23: =W13-W22 -> 2175.4688 | X23: =X13-X22 -> 1605.3366 | ... AP23: =AP13-AP22 -> 12601.246
A24: Other Income | B24: 225.7 | C24: 171.1 | D24: 267 | E24: 263.3 | F24: 8 | G24: 493.1 | H24: 335.3 | I24: 26.1 | J24: 175.2 | K24: =L24-SUM(H24:J24) -> 405.8 | L24: 942.4 | M24: 15 | N24: 37.6 | O24: 53.2 | P24: =Q24-SUM(M24:O24) -> 53.3 | Q24: 159.1 | R24: 22.3 | S24: =N24 -> 37.6 | T24: =O24 -> 53.2 | U24: =P24 -> 53.3 | V24: =SUM(R24:U24) -> 166.4 | W24: =R24 -> 22.3 | X24: =S24 -> 37.6 | Y24: =T24 -> 53.2 | Z24: =U24 -> 53.3 | AA24: =SUM(W24:Z24) -> 166.4 | AB24: =W24 -> 22.3 | AC24: =X24 -> 37.6 | AD24: =Y24 -> 53.2 | AE24: =Z24 -> 53.3 | AF24: =SUM(AB24:AE24) -> 166.4 | AG24: =W24 -> 22.3 | AH24: =X24 -> 37.6 | AI24: =Y24 -> 53.2 | AJ24: =Z24 -> 53.3 | AK24: =SUM(AG24:AJ24) -> 166.4 | AL24: =AG24 -> 22.3 | AM24: =AH24 -> 37.6 | AN24: =AI24 -> 53.2 | AO24: =AJ24 -> 53.3 | AP24: =SUM(AL24:AO24) -> 166.4
A25: Profit Before Interest and Tax (PBIT) | B25: =B23+B24 -> 1279.3 | C25: =C23+C24 -> 687.1 | D25: =D23+D24 -> 808 | E25: =E23+E24 -> 885.1 | F25: =F23+F24 -> 502 | G25: =G23+G24 -> 2517.8 | H25: =H24+H23 -> 796.7 | I25: =I24+I23 -> 728.6 | J25: =J24+J23 -> 707.1 | K25: =L25-SUM(H25:J25) -> 1117.6 | L25: =L24+L23 -> 3350 | M25: =M24+M23 -> 889.5 | N25: =N23+N24 -> 998.43 | O25: =O23+O24 -> 1320.2 | P25: =Q25-SUM(M25:O25) -> 1461.3 | Q25: =Q23+Q24 -> 4669.43 | R25: =R23+R24 -> 1646.7 | S25: =S23+S24 -> 1497.2158 | T25: =T23+T24 -> 1597.693 | U25: =U23+U24 -> 1747.0993 | V25: =V23+V24 -> 6488.7081 | W25: =W23+W24 -> 2197.7688 | X25: =X23+X24 -> 1642.9366 | ... AP25: =AP23+AP24 -> 12767.646
A27: PBIT Margin (%) | B27: =B25/B9 -> 0.075452669 | C27: =C25/C11 -> 0.15667184 | D27: =D25/D11 -> 0.16833333 | E27: =E25/E11 -> 0.16750568 | F27: =F25/F9 -> 0.089467118 | G27: =G25/G9 -> 0.11189128 | H27: =H25/H9 -> 0.14065038 | I27: =I25/I9 -> 0.10924193 | J27: =J25/J9 -> 0.11588194 | K27: =K25/K9 -> 0.15769719 | L27: =L25/L9 -> 0.13125468 | M27: =M25/M9 -> 0.12585068 | ... AP27: =AP25/AP9 -> 0.14408243
A29: Interest (net) | B29: 604.1 | C29: 180.9 | D29: 202.4 | E29: 196.7 | F29: 106 | G29: 453.6 | H29: 106.3 | I29: 116.1 | J29: 101 | K29: =L29-SUM(H29:J29) -> 109 | L29: 432.4 | M29: 132.5 | N29: 156.3 | O29: 254.7 | P29: =Q29-SUM(M29:O29) -> 267.4 | Q29: 810.9 | R29: 226.8 | S29: =($V$29-$R$29)/3 -> 544.03279 | T29: =($V$29-$R$29)/3 -> 544.03279 | U29: =($V$29-$R$29)/3 -> 544.03279 | V29: ='Debt Schedule'!G33+('Debt Schedule'!$D$220/3) -> 1858.8984 | W29: =$AA$29/4 -> 532.88879 | X29: =$AA$29/4 -> 532.88879 | Y29: =$AA$29/4 -> 532.88879 | Z29: =$AA$29/4 -> 532.88879 | AA29: ='Debt Schedule'!H33+('Debt Schedule'!$D$220/3) -> 2131.5552 | AB29: =$AF$29/4 -> 656.91318 | AC29: =$AF$29/4 -> 656.91318 | AD29: =$AF$29/4 -> 656.91318 | AE29: =$AF$29/4 -> 656.91318 | AF29: ='Debt Schedule'!I33+('Debt Schedule'!$D$220/3) -> 2627.6527 | AG29: =$AK$29/4 -> 435.00881 | AH29: =$AK$29/4 -> 435.00881 | AI29: =$AK$29/4 -> 435.00881 | AJ29: =$AK$29/4 -> 435.00881 | AK29: ='Debt Schedule'!J33 -> 1740.0352 | AL29: =$AP$29/4 -> 423.96395 | AM29: =$AP$29/4 -> 423.96395 | AN29: =$AP$29/4 -> 423.96395 | AO29: =$AP$29/4 -> 423.96395 | AP29: ='Debt Schedule'!K33 -> 1695.8558
A30: Foreign Exchange (Gain) / Loss (net) | B30: 0 | C30: 0 | D30: 0 | F30: -294 | G30: 0 | H30: 0 | I30: -225.7 | J30: 0 | K30: 0 | L30: 0 | M30: 537.1 | N30: 1051 | O30: 570.5 | P30: =Q30-SUM(M30:O30) -> 388.1 | Q30: 2546.7 | R30: -575.4 | S30: =($V$30-$R$30)/3 -> -89.430933 | T30: =($V$30-$R$30)/3 -> -89.430933 | U30: =($V$30-$R$30)/3 -> -89.430933 | V30: ='Debt Schedule'!G48 -> -843.6928 | W30: 0 | X30: 0 | Y30: 0 | Z30: 0 | AA30: ='Debt Schedule'!H48 -> -69.6 | AB30: 0 | AC30: 0 | AD30: 0 | AE30: 0 | AF30: 0 | AG30: 0 | AH30: 0 | AI30: 0 | AJ30: 0 | AK30: 0 | AL30: 0 | AM30: 0 | AN30: 0 | AO30: 0 | AP30: 0
A31: Exceptional Item | B31: 309.8 | C31: 0 | D31: 0 | E31: 0 | F31: 0 | G31: 0 | H31: 0 | I31: 0 | J31: 0 | K31: 0 | L31: 0 | M31: 0 | N31: 0 | O31: 0 | P31: 0 | Q31: 0 | R31: 0 | S31: 0 | T31: 0 | U31: 0 | V31: 0 | W31: 0 | X31: 0 | Y31: 0 | Z31: 0 | AA31: =SUM('Debt Schedule'!B208:B209)+'Debt Schedule'!H40 -> -166.60851 | AB31: 0 | AC31: 0 | AD31: 0 | AE31: 0 | AF31: 0 | AG31: 0 | AH31: 0 | AI31: 0 | AJ31: 0 | AK31: 0 | AL31: 0 | AM31: 0 | AN31: 0 | AO31: 0 | AP31: 0
A32: Profit from Ordinary Activities before Tax (PBT) | B32: =B25-B29-B30+B31 -> 985 | C32: =C25-C29-C30 -> 506.2 | D32: =D25-D29-D30 -> 605.6 | E32: =E25-E29-E30 -> 688.4 | F32: =F25-F29-F30 -> 690 | G32: =G25-G29-G30 -> 2064.2 | H32: =H25-H29-H30 -> 690.4 | I32: =I25-I29-I30 -> 838.2 | J32: =J25-J29-J30 -> 606.1 | K32: =L32-SUM(H32:J32) -> 782.9 | L32: =L25-L29-L30 -> 2917.6 | M32: =M25-M29-M30 -> 219.9 | N32: =N25-N29-N30 -> -208.87 | O32: =O25-O29-O30 -> 495 | P32: =Q32-SUM(M32:O32) -> 805.8 | Q32: =Q25-Q29-Q30 -> 1311.83 | R32: =R25-R29-R30 -> 1995.3 | S32: =S25-S29-S30 -> 1042.614 | T32: =T25-T29-T30 -> 1143.0912 | U32: =U25-U29-U30 -> 1292.4975 | V32: =V25-V29-V30 -> 5473.5026 | W32: =W25-W29-W30 -> 1664.88 | X32: =X25-X29-X30 -> 1110.0478 | ... Z32: =Z25-Z29-Z30 -> 1641.1814 | AA32: =AA25-AA29-AA30-AA31 -> 5829.6518 | AB32: =AB25-AB29-AB30 -> 1998.5036 | AC32: =AC25-AC29-AC30 -> 1389.9758 | AD32: =AD25-AD29-AD30 -> 1279.4668 | AE32: =AE25-AE29-AE30 -> 1924.2853 | AF32: =AF25-AF29-AF30 -> 6592.2315 | AG32: =AG25-AG29-AG30 -> 2739.8001 | AH32: =AH25-AH29-AH30 -> 2070.2382 | AI32: =AI25-AI29-AI30 -> 1757.6352 | ... AP32: =AP25-AP29-AP30 -> 11071.79
A34: PBT Margin (%) | B34: =B32/B9 -> 0.058094957 | C34: =C32/C11 -> 0.1154232 | D34: =D32/D11 -> 0.12616667 | E34: =E32/E11 -> 0.13028009 | F34: =F32/F9 -> 0.12297273 | G34: =G32/G9 -> 0.091733253 | H34: =H32/H9 -> 0.12188405 | I34: =I32/I9 -> 0.1256747 | J34: =J32/J9 -> 0.099329717 | K34: =K32/K9 -> 0.11046987 | L34: =L32/L9 -> 0.11431303 | M34: =M32/M9 -> 0.031112495 | ... AP34: =AP32/AP9 -> 0.12494476
A36: Provision for Taxation
A37: a. Current Tax | B37: 128.4 | C37: 58.1 | D37: 60.5 | E37: 40 | F37: 81 | G37: 203.4 | H37: 80.6 | I37: 199.1 | J37: 153.7 | K37: =L37-SUM(H37:J37) -> 45.8 | L37: 479.2 | M37: 65.3 | N37: 188.3 | O37: 33.9 | P37: =Q37-SUM(M37:O37) -> -5.9 | Q37: 281.6 | R37: 320.1 | S37: 0 | T37: 0 | U37: 0 | W37: 0 | X37: 0 | Y37: 0 | Z37: 0 | AB37: 0 | AC37: 0 | AD37: 0 | AE37: 0 | AG37: 0 | AH37: 0 | AI37: 0 | AJ37: 0 | AL37: 0 | AM37: 0 | AN37: 0 | AO37: 0
A38: b. MAT Credit Entitlement | B38: -80.9 | C38: -52.2 | D38: -13.7 | E38: 11.3 | F38: -4 | G38: -145.4 | H38: -3.8 | I38: 3.9 | J38: 0 | K38: 0 | L38: 0 | M38: -40.8 | N38: 40.8 | O38: 0 | P38: =Q38-SUM(M38:O38) -> 0 | Q38: 0 | R38: 0 | S38: 0 | T38: 0 | U38: 0 | W38: 0 | X38: 0 | Y38: 0 | Z38: 0 | AB38: 0 | AC38: 0 | AD38: 0 | AE38: 0 | AG38: 0 | AH38: 0 | AI38: 0 | AJ38: 0 | AL38: 0 | AM38: 0 | AN38: 0 | AO38: 0
A39: c. Defferred Tax | B39: 159 | C39: 137.4 | D39: 11.5 | E39: 44 | F39: -8 | G39: -40.6 | H39: -7.7 | I39: 10.7 | J39: 6.4 | K39: =L39-SUM(H39:J39) -> 42.7 | L39: 52.1 | M39: 10.1 | N39: -2.9 | O39: 41.6 | P39: =Q39-SUM(M39:O39) -> 10.6 | Q39: 59.4 | R39: 10.7 | S39: 0 | T39: 0 | U39: 0 | W39: 0 | X39: 0 | Y39: 0 | Z39: 0 | AB39: 0 | AC39: 0 | AD39: 0 | AE39: 0 | AG39: 0 | AH39: 0 | AI39: 0 | AJ39: 0 | AL39: 0 | AM39: 0 | AN39: 0 | AO39: 0
A40: d. Fringe Benefit Tax (net of recovery) | B40: 2.8 | C40: 0.8 | D40: 0.9 | E40: 1.1 | F40: 1 | G40: 3.9 | H40: 1 | I40: 1.3 | J40: 1.6 | K40: =L40-SUM(H40:J40) -> 0.8 | L40: 4.7 | M40: 0.9 | N40: 1.7 | O40: 1.6 | P40: =Q40-SUM(M40:O40) -> 1 | Q40: 5.2 | R40: 0 | S40: 0 | T40: 0 | U40: 0 | W40: 0 | X40: 0 | Y40: 0 | Z40: 0 | AB40: 0 | AC40: 0 | AD40: 0 | AE40: 0 | AG40: 0 | AH40: 0 | AI40: 0 | AJ40: 0 | AL40: 0 | AM40: 0 | AN40: 0 | AO40: 0
A41: e. Tax adjustment of previous years | B41: 64.6 | C41: 0 | D41: 0 | E41: -9.2 | F41: 0 | G41: 22.4 | H41: 0 | I41: 0 | J41: 0 | K41: =L41-SUM(H41:J41) -> 0 | L41: 0 | M41: 19.8 | N41: -54.6 | O41: 1.5 | P41: =Q41-SUM(M41:O41) -> 0 | Q41: -33.3 | R41: 0 | S41: 0 | T41: 0 | U41: 0 | W41: 0 | X41: 0 | Y41: 0 | Z41: 0 | AB41: 0 | AC41: 0 | AD41: 0 | AE41: 0 | AG41: 0 | AH41: 0 | AI41: 0 | AJ41: 0 | AL41: 0 | AM41: 0 | AN41: 0 | AO41: 0
A42: Total Tax | B42: =SUM(B37:B41) -> 273.9 | C42: =SUM(C37:C41) -> 144.1 | D42: =SUM(D37:D41) -> 59.2 | E42: =SUM(E37:E41) -> 87.2 | F42: =SUM(F37:F41) -> 70 | G42: =SUM(G37:G41) -> 43.7 | H42: =SUM(H37:H41) -> 70.1 | I42: =SUM(I37:I41) -> 215 | J42: =SUM(J37:J41) -> 161.7 | K42: =L42-SUM(H42:J42) -> 89.2 | L42: =SUM(L37:L41) -> 536 | M42: =SUM(M37:M41) -> 55.3 | N42: =SUM(N37:N41) -> 173.3 | O42: =SUM(O37:O41) -> 78.6 | P42: =Q42-SUM(M42:O42) -> 5.7 | Q42: =SUM(Q37:Q41) -> 312.9 | R42: =SUM(R37:R41) -> 330.8 | S42: =S32*'Cost Model'!S20 -> 135.53981 | T42: =T32*'Cost Model'!T20 -> 148.60185 | U42: =U32*'Cost Model'!U20 -> 168.02467 | V42: =SUM(R42:U42) -> 782.96634 | W42: =W32*'Cost Model'!W20 -> 216.43439 | X42: =X32*'Cost Model'!X20 -> 144.30622 | Y42: =Y32*'Cost Model'!Y20 -> 153.05344 | Z42: =Z32*'Cost Model'!Z20 -> 213.35358 | AA42: =SUM(W42:Z42) -> 727.14763 | AB42: =AB32*'Cost Model'!AB20 -> 259.80547 | AC42: =AC32*'Cost Model'!AC20 -> 180.69685 | AD42: =AD32*'Cost Model'!AD20 -> 166.33068 | AE42: =AE32*'Cost Model'!AE20 -> 250.1571 | AF42: =SUM(AB42:AE42) -> 856.9901 | AG42: =AG32*'Cost Model'!AG20 -> 356.17402 | AH42: =AH32*'Cost Model'!AH20 -> 269.13096 | AI42: =AI32*'Cost Model'!AI20 -> 228.49258 | AJ42: =AJ32*'Cost Model'!AJ20 -> 339.06052 | AK42: =SUM(AG42:AJ42) -> 1192.8581 | AL42: =AL32*'Cost Model'!AL20 -> 431.54712 | AM42: =AM32*'Cost Model'!AM20 -> 335.70405 | AN42: =AN32*'Cost Model'!AN20 -> 265.92739 | AO42: =AO32*'Cost Model'!AO20 -> 406.15412 | AP42: =SUM(AL42:AO42) -> 1439.3327
A43: Profit before Minority Interest | B43: =B32-B42 -> 711.1 | C43: =C32-C42 -> 362.1 | D43: =D32-D42 -> 546.4 | E43: =E32-E42 -> 601.2 | F43: =F32-F42 -> 620 | G43: =G32-G42 -> 2020.5 | H43: =H32-H42 -> 620.3 | I43: =I32-I42 -> 623.2 | J43: =J32-J42 -> 444.4 | K43: =L43-SUM(H43:J43) -> 693.7 | L43: =L32-L42 -> 2381.6 | M43: =M32-M42 -> 164.6 | N43: =N32-N42 -> -382.17 | O43: =O32-O42 -> 416.4 | P43: =Q43-SUM(M43:O43) -> 800.1 | Q43: =Q32-Q42 -> 998.93 | R43: =R32-R42 -> 1664.5 | S43: =S32-S42 -> 907.07414 | T43: =T32-T42 -> 994.48932 | U43: =U32-U42 -> 1124.4728 | V43: =V32-V42 -> 4690.5362 | W43: =W32-W42 -> 1448.4456 | X43: =X32-X42 -> 965.74162 | ... AP43: =AP32-AP42 -> 9632.4571
A44: Minority Interest | B44: -14.1 | C44: 0 | D44: 0 | E44: 0 | F44: 3 | G44: 11 | H44: 2.9 | I44: 2.6 | J44: -1.3 | K44: =L44-SUM(H44:J44) -> -7.6 | L44: -3.4 | M44: 0.4 | N44: 2 | O44: -2 | P44: =Q44-SUM(M44:O44) -> -0.4 | Q44: 0 | R44: 0 | S44: 0 | T44: 0 | U44: 0 | V44: 0 | W44: 0 | X44: 0 | Y44: 0 | Z44: 0 | AA44: 0 | AB44: 0 | AC44: 0 | AD44: 0 | AE44: 0 | AF44: 0 | AG44: 0 | AH44: 0 | AI44: 0 | AJ44: 0 | AK44: 0 | AL44: 0 | AM44: 0 | AN44: 0 | AO44: 0 | AP44: 0
A45: Net Profit for the Period (PAT) | B45: =B43+B44 -> 697 | C45: =C43-C44 -> 362.1 | D45: =D43-D44 -> 546.4 | E45: =E43-E44 -> 601.2 | F45: =F43-F44 -> 617 | G45: =G43-G44 -> 2009.5 | H45: =H43-H44 -> 617.4 | I45: =I43-I44 -> 620.6 | J45: =J43-J44 -> 445.7 | K45: =L45-SUM(H45:J45) -> 701.3 | L45: =L43-L44 -> 2385 | M45: =M43-M44 -> 164.2 | N45: =N43-N44 -> -384.17 | O45: =O43-O44 -> 418.4 | P45: =Q45-SUM(M45:O45) -> 800.5 | Q45: =Q43-Q44 -> 998.93 | R45: =R43-R44 -> 1664.5 | S45: =S43-S44 -> 907.07414 | T45: =T43-T44 -> 994.48932 | U45: =U43-U44 -> 1124.4728 | V45: =V43-V44 -> 4690.5362 | W45: =W43-W44 -> 1448.4456 | X45: =X43-X44 -> 965.74162 | ... AP45: =AP43-AP44 -> 9632.4571
A46: Net Profit Margin (%) | B46: =B45/B9 -> 0.041108817 | C46: =C45/C11 -> 0.082565669 | D46: =D45/D11 -> 0.11383333 | E46: =E45/E11 -> 0.11377744 | F46: =F45/F9 -> 0.10996257 | G46: =G45/G9 -> 0.089302379 | H46: =H45/H9 -> 0.10899654 | I46: =I45/I9 -> 0.093049058 | J46: =J45/J9 -> 0.073042823 | K46: =K45/K9 -> 0.098955835 | L46: =L45/L9 -> 0.093445494 | M46: =M45/M9 -> 0.023231794 | ... AP46: =AP45/AP9 -> 0.10870194
A48: Paid up Equity Share Capital | B48: 266.35 | C48: 266.35 | D48: 266.47 | E48: 266.74 | F48: 266.74 | G48: 266.74 | H48: 266.74 | I48: 268.697 | J48: 268.826 | K48: 268.826 | L48: 268.826 | M48: 268.826 | N48: 268.826 | O48: 268.826 | P48: 268.826 | Q48: 268.826 | R48: 268.826 | S48: =R48 -> 268.826 | T48: =S48 -> 268.826 | U48: =T48 -> 268.826 | V48: =U48 -> 268.826 | W48: =V48 -> 268.826 | X48: ='Balance Sheet'!$G$12 -> 291.07616 | Y48: =X48 -> 291.07616 | Z48: =Y48 -> 291.07616 | AA48: =Z48 -> 291.07616 | AB48: =AA48 -> 291.07616 | AC48: =AB48 -> 291.07616 | AD48: =AC48 -> 291.07616 | AE48: =AD48 -> 291.07616 | AF48: =AE48 -> 291.07616 | ... AP48: =AO48 -> 291.07616
A49: (Face value Rs 5/- per share)
A51: Basic EPS | B51: 13.28 | C51: 6.8 | D51: 10.25 | E51: 11.28 | F51: 11.57 | G51: 37.7 | H51: 11.57 | I51: 11.56 | J51: 8.29 | K51: 13.04 | L51: 44.46 | M51: 3.06 | N51: -7.15 | O51: 7.78 | P51: 14.89 | Q51: 18.58 | R51: 30.98 | S51: =S45/S54 -> 16.882642 | T51: =T45/T54 -> 18.50963 | U51: =U45/U54 -> 20.928908 | V51: =V45/V54 -> 87.301179 | W51: =W45/W54 -> 26.958753 | X51: =X45/X54 -> 16.59822 | Y51: =Y45/Y54 -> 17.604333 | Z51: =Z45/Z54 -> 24.540104 | ... AP51: =AP45/AP54 -> 165.55323
A52: Diluted EPS | B52: 12.52 | C52: 5.73 | D52: 7.99 | E52: 8.79 | F52: 9.13 | G52: 30.27 | H52: 9.13 | I52: 9.19 | J52: 6.59 | K52: 10.37 | L52: 35.33 | M52: 2.43 | N52: -7.15 | O52: 6.19 | P52: 12.37 | Q52: 15.43 | R52: 25.76 | S52: =S45/S55 -> 14.037987 | T52: =T45/T55 -> 15.390835 | U52: =U45/U55 -> 17.402475 | V52: =V45/V55 -> 72.591297 | W52: =W45/W55 -> 22.416316 | X52: =X45/X55 -> 14.945932 | Y52: =Y45/Y55 -> 15.85189 | Z52: =Z45/Z55 -> 22.097233 | ... AP52: =AP45/AP55 -> 165.55323
A54: No of Shares -Basic | B54: =B45/B51 -> 52.48494 | C54: =C45/C51 -> 53.25 | D54: =D45/D51 -> 53.307317 | E54: =E45/E51 -> 53.297872 | F54: =F45/F51 -> 53.327571 | G54: =G45/G51 -> 53.302387 | H54: =H45/H51 -> 53.362143 | I54: =I45/I51 -> 53.685121 | ... R54: =R45/R51 -> 53.728212 | S54: =R54 -> 53.728212 | T54: =S54 -> 53.728212 | U54: =T54 -> 53.728212 | V54: =AVERAGE($R$54:$U$54) -> 53.728212 | W54: =U54 -> 53.728212 | X54: =W54+'Debt Schedule'!$B$210 -> 58.183444 | Y54: =X54 -> 58.183444 | Z54: =Y54 -> 58.183444 | AA54: =AVERAGE($W$54:$Z$54) -> 57.069636 | AB54: =Z54 -> 58.183444 | AC54: =AB54 -> 58.183444 | AD54: =AC54 -> 58.183444 | AE54: =AD54 -> 58.183444 | AF54: =AVERAGE($AB$54:$AE$54) -> 58.183444 | AG54: =AE54 -> 58.183444 | AH54: =AG54 -> 58.183444 | AI54: =AH54 -> 58.183444 | AJ54: =AI54 -> 58.183444 | AK54: =AVERAGE($AG$54:$AJ$54) -> 58.183444 | AL54: =AJ54 -> 58.183444 | AM54: =AL54 -> 58.183444 | AN54: =AM54 -> 58.183444 | AO54: =AN54 -> 58.183444 | AP54: =AVERAGE($AL$54:$AO$54) -> 58.183444
A55: No of Shares - Diluted | B55: =B45/B52 -> 55.670927 | C55: =C45/C52 -> 63.193717 | D55: =D45/D52 -> 68.385482 | E55: =E45/E52 -> 68.395904 | F55: =F45/F52 -> 67.579409 | G55: =G45/G52 -> 66.385861 | H55: =H45/H52 -> 67.62322 | I55: =I45/I52 -> 67.529924 | ... R55: =R45/R52 -> 64.615683 | S55: =R55 -> 64.615683 | T55: =S55 -> 64.615683 | U55: =T55 -> 64.615683 | V55: =AVERAGE($R$55:$U$55) -> 64.615683 | W55: =U55 -> 64.615683 | X55: =W55 -> 64.615683 | Y55: =X55 -> 64.615683 | Z55: =Y55 -> 64.615683 | AA55: =AVERAGE($W$55:$Z$55) -> 64.615683 | AB55: 58.183444 | AC55: =AB55 -> 58.183444 | AD55: =AC55 -> 58.183444 | AE55: =AD55 -> 58.183444 | AF55: =AVERAGE($AB$55:$AE$55) -> 58.183444 | AG55: =AE55 -> 58.183444 | AH55: =AG55 -> 58.183444 | AI55: =AH55 -> 58.183444 | AJ55: =AI55 -> 58.183444 | AK55: =AVERAGE($AG$55:$AJ$55) -> 58.183444 | AL55: =AJ55 -> 58.183444 | AM55: =AL55 -> 58.183444 | AN55: =AM55 -> 58.183444 | AO55: =AN55 -> 58.183444 | AP55: =AVERAGE($AL$55:$AO$55) -> 58.183444
A58: One Time / Proforma Adjustments
A60: Foreign Exchange (Gain) / Loss (net) | B60: =B30 -> 0 | C60: =-C24 -> -171.1 | D60: =-D24 -> -267 | E60: =-E24 -> -263.3 | F60: =F30 -> -294 | G60: =SUM(C60:F60) -> -995.4 | H60: =-H24 -> -335.3 | I60: =I30 -> -225.7 | J60: =-J24 -> -175.2 | K60: =-K24 -> -405.8 | L60: =SUM(H60:K60) -> -1142 | M60: =M30 -> 537.1 | N60: =N30 -> 1051 | O60: =O30 -> 570.5 | P60: =P30 -> 388.1 | Q60: =Q30 -> 2546.7 | R60: =R30 -> -575.4 | S60: 0 | T60: 0 | U60: 0 | V60: 0 | W60: 0 | X60: 0 | Y60: 0 | Z60: 0 | AA60: 0 | AB60: 0 | AC60: 0 | AD60: 0 | AE60: 0 | AF60: 0 | AG60: 0 | AH60: 0 | AI60: 0 | AJ60: 0 | AK60: 0 | AL60: 0 | AM60: 0 | AN60: 0 | AO60: 0 | AP60: 0
A61: Exceptional Item | B61: =-B31 -> -309.8 | C61: =C31 -> 0 | D61: =D31 -> 0 | E61: =E31 -> 0 | F61: =F31 -> 0 | G61: =G31 -> 0 | H61: =H31 -> 0 | I61: =I31 -> 0 | J61: =J31 -> 0 | ... R61: =R31 -> 0 | S61: 0 | T61: 0 | U61: 0 | V61: 0 | W61: 0 | X61: 0 | Y61: 0 | Z61: 0 | AA61: 0 | AB61: 0 | AC61: 0 | AD61: 0 | AE61: 0 | AF61: 0 | AG61: 0 | AH61: 0 | AI61: 0 | AJ61: 0 | AK61: 0 | AL61: 0 | AM61: 0 | AN61: 0 | AO61: 0 | AP61: 0
A62: Total Adjustments before Tax | B62: =SUM(B60:B61) -> -309.8 | C62: =SUM(C60:C61) -> -171.1 | D62: =SUM(D60:D61) -> -267 | E62: =SUM(E60:E61) -> -263.3 | F62: =SUM(F60:F61) -> -294 | G62: =SUM(G60:G61) -> -995.4 | H62: =SUM(H60:H61) -> -335.3 | I62: =SUM(I60:I61) -> -225.7 | ... AP62: =SUM(AP60:AP61) -> 0
A63: Less: Income Tax Effect | B63: =B62*'Cost Model'!B20 -> -86.146416 | C63: =C62*'Cost Model'!C20 -> -48.707053 | D63: =D62*'Cost Model'!D20 -> -26.100396 | E63: =E62*'Cost Model'!E20 -> -33.352353 | F63: =F62*'Cost Model'!F20 -> -29.826087 | G63: =G62*'Cost Model'!G20 -> -21.073045 | H63: =H62*'Cost Model'!H20 -> -34.0448 | I63: =I62*'Cost Model'!I20 -> -57.892508 | ... AP63: =AP62*'Cost Model'!AP20 -> 0
A64: Adjusted Net Profit for the Period (PAT) | B64: =B32+B62-B63 -> 761.34642 | C64: =C45+C62-C63 -> 239.70705 | D64: =D45+D62-D63 -> 305.5004 | E64: =E45+E62-E63 -> 371.25235 | F64: =F45+F62-F63 -> 352.82609 | G64: =G45+G62-G63 -> 1035.173 | H64: =H45+H62-H63 -> 316.1448 | I64: =I45+I62-I63 -> 452.79251 | J64: =J45+J62-J63 -> 317.2412 | ... AP64: =AP45+AP62-AP63 -> 9632.4571
A65: Adjusted Net Profit Margin (%) | B65: =B64/B9 -> 0.044903947 | C65: =C64/C11 -> 0.054657756 | D65: =D64/D11 -> 0.063645916 | E65: =E64/E11 -> 0.070259719 | F65: =F64/F9 -> 0.062881142 | G65: =G64/G9 -> 0.046003193 | H65: =H64/H9 -> 0.055812584 | I65: =I64/I9 -> 0.067889005 | J65: =J64/J9 -> 0.05199056 | K65: =K64/K9 -> 0.048219976 | L65: =L64/L9 -> 0.056921425 | M65: =M64/M9 -> 0.080113074 | ... AP65: =AP64/AP9 -> 0.10870194
A67: No of Shares - Diluted | B67: 55.670927 | C67: 63.193717 | D67: 68.385482 | E67: 68.395904 | F67: 67.579409 | G67: 66.389164 | H67: 67.62322 | I67: 67.529924 | J67: 67.632777 | K67: 67.627772 | L67: 67.506369 | M67: 67.572016 | N67: 53.73007 | O67: 67.592892 | P67: 64.713015 | Q67: 64.739469 | R67: 64.662267 | S67: =S55 -> 64.615683 | T67: =T55 -> 64.615683 | U67: =U55 -> 64.615683 | V67: =V55 -> 64.615683 | W67: =W55 -> 64.615683 | X67: =X55 -> 64.615683 | Y67: =Y55 -> 64.615683 | Z67: =Z55 -> 64.615683 | ... AP67: =AP55 -> 58.183444
A68: Diluted EPS - Adjusted | B68: =B64/B67 -> 13.675835 | C68: =C64/C67 -> 3.7932102 | D68: =D64/D67 -> 4.4673283 | E68: =E64/E67 -> 5.427991 | F68: =F64/F67 -> 5.2209111 | G68: =G64/G67 -> 15.5925 | H68: =H64/H67 -> 4.6750924 | I68: =I64/I67 -> 6.7050647 | ... AP68: =AP64/AP67 -> 165.55323

Sheet Balance Sheet
A1: Aurobindo Pharma
A2: Balance Sheet
A3: (In Rs Millions, Except per share items)
A4: For the Fiscal Period Ending | B4: FY 2006 A | C4: FY2007 A | D4: FY2008 A | E4: FY2009 E | F4: FY2010 E | G4: FY2011 E | H4: FY2012 E | I4: FY2013 E | J4: FY2014 E
A7: Balance Sheet
A9: I. SOURCES OF FUNDS
A11: Share holder's Fund
A12: Share Capital | B12: 266.3 | C12: 266.7 | D12: 268.8 | E12: =D12+'Cash Flow Statement'!E54 -> 268.8 | F12: =E12+'Cash Flow Statement'!F54 -> 268.8 | G12: =F12+'Cash Flow Statement'!G54+'Debt Schedule'!B208 -> 291.07616 | H12: =G12+'Cash Flow Statement'!H54 -> 291.07616 | I12: =H12+'Cash Flow Statement'!I54 -> 291.07616 | J12: =I12+'Cash Flow Statement'!J54 -> 291.07616
A13: Share Application Money | B13: 0.4 | C13: 0.2 | D13: 0 | E13: 0 | F13: 0 | G13: 0 | H13: 0 | I13: 0 | J13: 0
A14: Reserves & Surplus | B14: 7882 | C14: 8593.2 | D14: 10971.4 | E14: =D14+'Profit & Loss Consolidated'!Q45 -> 11970.33 | F14: =E14+'Profit & Loss Consolidated'!V45 -> 16660.866 | G14: =F14+'Profit & Loss Consolidated'!AA45+'Debt Schedule'!B209 -> 24066.886 | H14: =G14+'Profit & Loss Consolidated'!AF45 -> 29802.127 | I14: =H14+'Profit & Loss Consolidated'!AK45 -> 37785.1 | J14: =I14+'Profit & Loss Consolidated'!AP45 -> 47417.558
B15: =SUM(B12:B14) -> 8148.7 | C15: =SUM(C12:C14) -> 8860.1 | D15: =SUM(D12:D14) -> 11240.2 | E15: =SUM(E12:E14) -> 12239.13 | F15: =SUM(F12:F14) -> 16929.666 | G15: =SUM(G12:G14) -> 24357.962 | H15: =SUM(H12:H14) -> 30093.203 | I15: =SUM(I12:I14) -> 38076.177 | J15: =SUM(J12:J14) -> 47708.634
A16: Minority Interest | B16: 24.3 | C16: 35.4 | D16: 32 | E16: =D16 -> 32 | F16: =E16 -> 32 | G16: =F16 -> 32 | H16: =G16 -> 32 | I16: =H16 -> 32 | J16: =I16 -> 32
A18: Loan Funds
A19: Secured Funds | B19: 7502.5 | C19: 7390.7 | D19: 6334.3 | E19: ='Debt Schedule'!F14 -> 6334.3 | F19: ='Debt Schedule'!G14 -> 6334.3 | G19: ='Debt Schedule'!H14 -> 8334.3 | H19: ='Debt Schedule'!I14 -> 13334.3 | I19: ='Debt Schedule'!J14 -> 13334.3 | J19: ='Debt Schedule'!K14 -> 13334.3
A20: Unsecured Funds | B20: 6228.2 | C20: 13390.7 | D20: 12135.9 | E20: ='Debt Schedule'!F24 -> 12135.9 | F20: ='Debt Schedule'!G24 -> 11200.63 | G20: ='Debt Schedule'!H24 -> 8638.6304 | H20: ='Debt Schedule'!I24 -> 2235.4304 | I20: ='Debt Schedule'!J24 -> 2235.4304 | J20: ='Debt Schedule'!K24 -> 2235.4304
B21: =SUM(B19:B20) -> 13730.7 | C21: =SUM(C19:C20) -> 20781.4 | D21: =SUM(D19:D20) -> 18470.2 | E21: =SUM(E19:E20) -> 18470.2 | F21: =SUM(F19:F20) -> 17534.93 | G21: =SUM(G19:G20) -> 16972.93 | H21: =SUM(H19:H20) -> 15569.73 | I21: =SUM(I19:I20) -> 15569.73 | J21: =SUM(J19:J20) -> 15569.73
A22: Deferred Tax Liability (Net) | B22: 725.6 | C22: 681.9 | D22: 733.4 | E22: =D22 -> 733.4 | F22: =E22 -> 733.4 | G22: =F22 -> 733.4 | H22: =G22 -> 733.4 | I22: =H22 -> 733.4 | J22: =I22 -> 733.4
A23: Total | B23: =B15+B16+B21+B22 -> 22629.3 | C23: =C15+C16+C21+C22 -> 30358.8 | D23: =D15+D16+D21+D22 -> 30475.8 | E23: =E15+E16+E21+E22 -> 31474.73 | F23: =F15+F16+F21+F22 -> 35229.997 | G23: =G15+G16+G21+G22 -> 42096.292 | H23: =H15+H16+H21+H22 -> 46428.334 | I23: =I15+I16+I21+I22 -> 54411.307 | J23: =J15+J16+J21+J22 -> 64043.764
A25: II. APPLICATION OF FUNDS
A27: Fixed Assets
A28: Gross Block | B28: 13561.6 | C28: 14681.4 | D28: 17179.9 | E28: ='Fixed Asset'!G7 -> 19472.18 | F28: ='Fixed Asset'!H7 -> 22227.762 | G28: ='Fixed Asset'!I7 -> 25644.684 | H28: ='Fixed Asset'!J7 -> 29276.384 | I28: ='Fixed Asset'!K7 -> 33707.058 | J28: ='Fixed Asset'!L7 -> 39023.867
A29: Less: Accumulated Depreciation/Amortization | B29: 2724.1 | C29: 3155.3 | D29: 4176.9 | E29: ='Fixed Asset'!G12 -> 5398.1 | F29: ='Fixed Asset'!H12 -> 6607.9075 | G29: ='Fixed Asset'!I12 -> 7964.6317 | H29: ='Fixed Asset'!J12 -> 9491.0676 | I29: ='Fixed Asset'!K12 -> 11213.613 | J29: ='Fixed Asset'!L12 -> 13182.883
A30: Net Block | B30: =B28-B29 -> 10837.5 | C30: =C28-C29 -> 11526.1 | D30: =D28-D29 -> 13003 | E30: =E28-E29 -> 14074.08 | F30: =F28-F29 -> 15619.855 | G30: =G28-G29 -> 17680.052 | H30: =H28-H29 -> 19785.317 | I30: =I28-I29 -> 22493.445 | J30: =J28-J29 -> 25840.984
A31: Capital Work-in-progress (including capital advances) | B31: 1497.4 | C31: 2187.1 | D31: 2145.5 | E31: =D31 -> 2145.5 | F31: =E31 -> 2145.5 | G31: =F31 -> 2145.5 | H31: =G31 -> 2145.5 | I31: =H31 -> 2145.5 | J31: =I31 -> 2145.5
B32: =B30+B31 -> 12334.9 | C32: =C30+C31 -> 13713.2 | D32: =D30+D31 -> 15148.5 | E32: =E30+E31 -> 16219.58 | F32: =F30+F31 -> 17765.355 | G32: =G30+G31 -> 19825.552 | H32: =H30+H31 -> 21930.817 | I32: =I30+I31 -> 24638.945 | J32: =J30+J31 -> 27986.484
A34: Investments | B34: 2.8 | C34: 2.7 | D34: 604.3 | E34: =D34+'Cash Flow Statement'!E47 -> 604.3 | F34: =E34+'Cash Flow Statement'!F47 -> 604.3 | G34: =F34+'Cash Flow Statement'!G47 -> 604.3 | H34: =G34+'Cash Flow Statement'!H47 -> 604.3 | I34: =H34+'Cash Flow Statement'!I47 -> 604.3 | J34: =I34+'Cash Flow Statement'!J47 -> 604.3
A36: Deferred Tax Asset | B36: 0.1 | C36: 0 | D36: 1.2 | E36: =D36 -> 1.2 | F36: =E36 -> 1.2 | G36: =F36 -> 1.2 | H36: =G36 -> 1.2 | I36: =H36 -> 1.2 | J36: =I36 -> 1.2
A38: Current Assets, Loans and Advances
A39: Interest Accrued on Investments | B39: 0.5 | C39: 0.5 | D39: 0.6 | E39: =D39 -> 0.6 | F39: =E39 -> 0.6 | G39: =F39 -> 0.6 | H39: =G39 -> 0.6 | I39: =H39 -> 0.6 | J39: =I39 -> 0.6
A40: Inventories | B40: 4718.1 | C40: 6544 | D40: 7950.3 | E40: =E60*'Profit & Loss Consolidated'!Q9/365 -> 8678.4784 | F40: =F60*'Profit & Loss Consolidated'!V9/365 -> 11177.703 | G40: =G60*'Profit & Loss Consolidated'!AA9/365 -> 13860.352 | H40: =H60*'Profit & Loss Consolidated'!AF9/365 -> 17186.837 | I40: =I60*'Profit & Loss Consolidated'!AK9/365 -> 20967.941 | J40: =J60*'Profit & Loss Consolidated'!AP9/365 -> 25161.529
A41: Sundry Debtors | B41: 5822.3 | C41: 6261.1 | D41: 6650.1 | E41: =E59*'Profit & Loss Consolidated'!Q9/365 -> 7963.5097 | F41: =F59*'Profit & Loss Consolidated'!V9/365 -> 10256.838 | G41: =G59*'Profit & Loss Consolidated'!AA9/365 -> 12718.479 | H41: =H59*'Profit & Loss Consolidated'!AF9/365 -> 15770.915 | I41: =I59*'Profit & Loss Consolidated'!AK9/365 -> 19240.516 | J41: =J59*'Profit & Loss Consolidated'!AP9/365 -> 23088.619
A42: Cash & Bank Balances | B42: 2019.3 | C42: 5824.6 | D42: 2825.7 | E42: ='Cash Flow Statement'!E70 -> 1594.6348 | F42: ='Cash Flow Statement'!F70 -> 869.29382 | G42: ='Cash Flow Statement'!G70 -> 2450.1652 | H42: ='Cash Flow Statement'!H70 -> 747.33248 | I42: ='Cash Flow Statement'!I70 -> 1555.521 | J42: ='Cash Flow Statement'!J70 -> 2886.5104
A43: Loan and Advances | B43: 1996.6 | C43: 2718.9 | D43: 3164.1 | E43: =D43 -> 3164.1 | F43: =E43 -> 3164.1 | G43: =F43 -> 3164.1 | H43: =G43 -> 3164.1 | I43: =H43 -> 3164.1 | J43: =I43 -> 3164.1
A44: (A) | B44: =SUM(B39:B43) -> 14556.8 | C44: =SUM(C39:C43) -> 21349.1 | D44: =SUM(D39:D43) -> 20590.8 | E44: =SUM(E39:E43) -> 21401.323 | F44: =SUM(F39:F43) -> 25468.536 | G44: =SUM(G39:G43) -> 32193.697 | H44: =SUM(H39:H43) -> 36869.784 | I44: =SUM(I39:I43) -> 44928.678 | J44: =SUM(J39:J43) -> 54301.358
A45: Less: Current Liabilities and Provisions
A46: Liabilities | B46: 4090.2 | C46: 4442.4 | D46: 5546 | E46: =E61*SUM('Profit & Loss Consolidated'!Q17:Q18)/365 -> 6428.6726 | F46: =F61*SUM('Profit & Loss Consolidated'!V17:V18)/365 -> 8286.3934 | G46: =G61*SUM('Profit & Loss Consolidated'!AA17:AA18)/365 -> 10205.457 | H46: =H61*SUM('Profit & Loss Consolidated'!AF17:AF18)/365 -> 12654.767 | I46: =I61*SUM('Profit & Loss Consolidated'!AK17:AK18)/365 -> 15438.815 | J46: =J61*SUM('Profit & Loss Consolidated'!AP17:AP18)/365 -> 18526.578
A47: Provisions | B47: 175.1 | C47: 263.8 | D47: 323 | E47: =D47 -> 323 | F47: =E47 -> 323 | G47: =F47 -> 323 | H47: =G47 -> 323 | I47: =H47 -> 323 | J47: =I47 -> 323
A48: (B) | B48: =SUM(B46:B47) -> 4265.3 | C48: =SUM(C46:C47) -> 4706.2 | D48: =SUM(D46:D47) -> 5869 | E48: =SUM(E46:E47) -> 6751.6726 | F48: =SUM(F46:F47) -> 8609.3934 | G48: =SUM(G46:G47) -> 10528.457 | H48: =SUM(H46:H47) -> 12977.767 | I48: =SUM(I46:I47) -> 15761.815 | J48: =SUM(J46:J47) -> 18849.578
A49: Net Current Assets (A-B) | B49: =B44-B48 -> 10291.5 | C49: =C44-C48 -> 16642.9 | D49: =D44-D48 -> 14721.8 | E49: =E44-E48 -> 14649.65 | F49: =F44-F48 -> 16859.142 | G49: =G44-G48 -> 21665.24 | H49: =H44-H48 -> 23892.017 | I49: =I44-I48 -> 29166.862 | J49: =J44-J48 -> 35451.78
A50: Total | B50: =B32+B34+B36+B49 -> 22629.3 | C50: =C32+C34+C36+C49 -> 30358.8 | D50: =D32+D34+D36+D49 -> 30475.8 | E50: =E32+E34+E36+E49 -> 31474.73 | F50: =F32+F34+F36+F49 -> 35229.997 | G50: =G32+G34+G36+G49 -> 42096.292 | H50: =H32+H34+H36+H49 -> 46428.334 | I50: =I32+I34+I36+I49 -> 54411.307 | J50: =J32+J34+J36+J49 -> 64043.764
A52: Check Sum | B52: =B23-B50 -> 0 | C52: =C23-C50 -> 0 | D52: =D23-D50 -> 0 | E52: =E23-E50 -> 0 | F52: =F23-F50 -> 0 | G52: =G23-G50 -> 0 | H52: =H23-H50 -> 0 | I52: =I23-I50 -> 0 | J52: =J23-J50 -> 0
A55: Balance Sheet Metrics
A57: Current Ratio | B57: =B44/B48 -> 3.4128432 | C57: =C44/C48 -> 4.5363775 | D57: =D44/D48 -> 3.5084001 | E57: =E44/E48 -> 3.1697809 | F57: =F44/F48 -> 2.9582265 | G57: =G44/G48 -> 3.0577792 | H57: =H44/H48 -> 2.840996 | I57: =I44/I48 -> 2.8504761 | J57: =J44/J48 -> 2.8807731
A58: Quick Ratio | B58: =(B44-B40)/B48 -> 2.3066842 | C58: =(C44-C40)/C48 -> 3.1458714 | D58: =(D44-D40)/D48 -> 2.1537741 | E58: =(E44-E40)/E48 -> 1.8843989 | F58: =(F44-F40)/F48 -> 1.6599116 | G58: =(G44-G40)/G48 -> 1.7413135 | H58: =(H44-H40)/H48 -> 1.5166667 | I58: =(I44-I40)/I48 -> 1.5201762 | J58: =(J44-J40)/J48 -> 1.5459141
A59: Days Sales Outstanding (DSO) | B59: =B41/'Profit & Loss Consolidated'!B9*365 -> 125.33999 | C59: =C41/'Profit & Loss Consolidated'!G9*365 -> 101.55903 | D59: =D41/'Profit & Loss Consolidated'!L9*365 -> 95.1023 | E59: =D59 -> 95.1023 | F59: =E59 -> 95.1023 | G59: =F59 -> 95.1023 | H59: =G59 -> 95.1023 | I59: =H59 -> 95.1023 | J59: =I59 -> 95.1023
A60: Inventory Days | C60: =(AVERAGE(B40:C40)/'Profit & Loss Consolidated'!G9)*365 -> 91.339213 | D60: =(AVERAGE(C40:D40)/'Profit & Loss Consolidated'!L9)*365 -> 103.64064 | E60: =D60 -> 103.64064 | F60: =E60 -> 103.64064 | G60: =F60 -> 103.64064 | H60: =G60 -> 103.64064 | I60: =H60 -> 103.64064 | J60: =I60 -> 103.64064
A61: Payable Days | B61: =B46/SUM('Profit & Loss Consolidated'!B17:B18)*365 -> 148.47864 | C61: =C46/SUM('Profit & Loss Consolidated'!G17:G18)*365 -> 123.71258 | D61: =D46/SUM('Profit & Loss Consolidated'!L17:L18)*365 -> 142.29109 | E61: =D61 -> 142.29109 | F61: =E61 -> 142.29109 | G61: =F61 -> 142.29109 | H61: =G61 -> 142.29109 | I61: =H61 -> 142.29109 | J61: =I61 -> 142.29109
A62: Total Debt | B62: =B21 -> 13730.7 | C62: =C21 -> 20781.4 | D62: =D21 -> 18470.2 | E62: =E21 -> 18470.2 | F62: =F21 -> 17534.93 | G62: =G21 -> 16972.93 | H62: =H21 -> 15569.73 | I62: =I21 -> 15569.73 | J62: =J21 -> 15569.73
A63: Net Debt | B63: =B62-B42 -> 11711.4 | C63: =C62-C42 -> 14956.8 | D63: =D62-D42 -> 15644.5 | E63: =E62-E42 -> 16875.565 | F63: =F62-F42 -> 16665.637 | G63: =G62-G42 -> 14522.765 | H63: =H62-H42 -> 14822.398 | I63: =I62-I42 -> 14014.209 | J63: =J62-J42 -> 12683.22
A64: Book Value Per Share | B64: =B15/'Profit & Loss Consolidated'!B55 -> 146.37263 | C64: =C15/'Profit & Loss Consolidated'!G55 -> 133.46366 | D64: =D15/'Profit & Loss Consolidated'!L55 -> 166.50577 | E64: =E15/'Profit & Loss Consolidated'!Q55 -> 189.05206 | F64: =F15/'Profit & Loss Consolidated'!V55 -> 262.00553 | G64: =G15/'Profit & Loss Consolidated'!AA55 -> 376.96672 | H64: =H15/'Profit & Loss Consolidated'!AF55 -> 517.21248 | I64: =I15/'Profit & Loss Consolidated'!AK55 -> 654.416 | J64: =J15/'Profit & Loss Consolidated'!AP55 -> 819.96923

Sheet Cash Flow Statement
A1: Aurobindo Pharma
A2: Cash Flow Statement
A3: (In Rs Millions)
A4: For the Fiscal Period Ending | B4: FY 2006 A | C4: FY2007 A | D4: FY2008 A | E4: FY2009 E | F4: FY2010 E | G4: FY2011 E | H4: FY2012 E | I4: FY2013 E | J4: FY2014 E
A7: Cash Flow Statement
A9: A. Cash Flow from Operating Activities
A11: Net Profit before Tax, Minority Interest and prior period items | B11: 985 | C11: 2064.2 | D11: 2917.4 | E11: ='Profit & Loss Consolidated'!Q32 -> 1311.83 | F11: ='Profit & Loss Consolidated'!V32 -> 5473.5026 | G11: ='Profit & Loss Consolidated'!AA32 -> 5829.6518 | H11: ='Profit & Loss Consolidated'!AF32 -> 6592.2315 | I11: ='Profit & Loss Consolidated'!AK32 -> 9175.8314 | J11: ='Profit & Loss Consolidated'!AP32 -> 11071.79
A12: Adjustments for:-
A13: Depreciation and Amortization | B13: 721.3 | C13: 997.2 | D13: 1003.8 | E13: ='Profit & Loss Consolidated'!Q20 -> 1221.2 | F13: ='Profit & Loss Consolidated'!V20 -> 1209.8075 | G13: ='Profit & Loss Consolidated'!AA20 -> 1356.7242 | H13: ='Profit & Loss Consolidated'!AF20 -> 1526.4359 | I13: ='Profit & Loss Consolidated'!AK20 -> 1722.5459 | J13: ='Profit & Loss Consolidated'!AP20 -> 1969.2694
A14: Miscellaneous Expenditure written off | B14: 0 | C14: 0.1 | D14: 0 | E14: 0 | F14: 0 | G14: 0 | H14: 0 | I14: 0 | J14: 0
A15: Provision for Doubtfull debts | B15: 136.1 | C15: 82.5 | D15: 4.3 | E15: 0 | F15: 0 | G15: 0 | H15: 0 | I15: 0 | J15: 0
A16: Loss / Gain on sale of fixed assets | B16: -28.7 | C16: -41.2 | D16: 3.5 | E16: 0 | F16: 0 | G16: 0 | H16: 0 | I16: 0 | J16: 0
A17: Export incentives accrued | B17: -88.2 | C17: -45.1 | D17: -124.1 | E17: 0 | F17: 0 | G17: 0 | H17: 0 | I17: 0 | J17: 0
A18: Claims / bad debts written off | B18: 16.1 | C18: 39.2 | D18: 45.1 | E18: 0 | F18: 0 | G18: 0 | H18: 0 | I18: 0 | J18: 0
A19: Balances no longer required written back | B19: -39.5 | C19: -52.9 | D19: -64.4 | E19: 0 | F19: 0 | G19: 0 | H19: 0 | I19: 0 | J19: 0
A20: Provision for Retirement benefits | B20: -39.9 | C20: 2.3 | D20: 32.3 | E20: 0 | F20: 0 | G20: 0 | H20: 0 | I20: 0 | J20: 0
A21: Investments written off / Diminution | B21: 0.1 | C21: 0.1 | D21: 0.1 | E21: 0 | F21: 0 | G21: 0 | H21: 0 | I21: 0 | J21: 0
A22: Write off / other adjustments of Fixed Assets | B22: 13.7 | C22: 1 | D22: 0 | E22: 0 | F22: 0 | G22: 0 | H22: 0 | I22: 0 | J22: 0
A23: Foreign Exchange loss (Net) | B23: 8.6 | C23: -327 | D23: -878.9 | E23: 0 | F23: ='Debt Schedule'!G48 -> -843.6928 | G23: ='Profit & Loss Consolidated'!AA30 -> -69.6 | H23: 0 | I23: 0 | J23: 0
A24: Interest Income | B24: -86.9 | C24: -410.9 | D24: -261.8 | E24: 0 | F24: 0 | G24: 0 | H24: 0 | I24: 0 | J24: 0
A25: Sales tax deferment loan availed | B25: 64.3 | C25: -28.5 | D25: 19.1 | E25: 0 | F25: 0 | G25: 0 | H25: 0 | I25: 0 | J25: 0
A26: Profit on sale of Investments in subsidiary | B26: 0 | C26: -58.5 | D26: 0 | E26: 0 | F26: 0 | G26: 0 | H26: 0 | I26: 0 | J26: 0
A27: Exceptional Item | B27: -309.8 | C27: 0 | D27: 0 | E27: 0 | F27: 0 | G27: ='Profit & Loss Consolidated'!AA31 -> -166.60851 | H27: 0 | I27: 0 | J27: 0
A28: Interest expense | B28: 691 | C28: 864.5 | D28: 621.1 | E28: 0 | F28: 0 | G28: 0 | H28: 0 | I28: 0 | J28: 0
A29: Operating Profit before working capital changes | B29: =SUM(B11:B28) -> 2043.2 | C29: =SUM(C11:C28) -> 3087 | D29: =SUM(D11:D28) -> 3317.5 | E29: =SUM(E11:E28) -> 2533.03 | F29: =SUM(F11:F28) -> 5839.6173 | G29: =SUM(G11:G28) -> 6950.1675 | H29: =SUM(H11:H28) -> 8118.6674 | I29: =SUM(I11:I28) -> 10898.377 | J29: =SUM(J11:J28) -> 13041.059
A30: Movement in working capital:
A31: Increase in Sundry Debtors | B31: -1411.6 | C31: -796.4 | D31: -297.2 | E31: =-('Balance Sheet'!E41-'Balance Sheet'!D41) -> -1313.4097 | F31: =-('Balance Sheet'!F41-'Balance Sheet'!E41) -> -2293.3286 | G31: =-('Balance Sheet'!G41-'Balance Sheet'!F41) -> -2461.6412 | H31: =-('Balance Sheet'!H41-'Balance Sheet'!G41) -> -3052.4351 | I31: =-('Balance Sheet'!I41-'Balance Sheet'!H41) -> -3469.6012 | J31: =-('Balance Sheet'!J41-'Balance Sheet'!I41) -> -3848.1031
A32: Increase in Inventories | B32: -926.4 | C32: -1832.2 | D32: -1406.3 | E32: =-('Balance Sheet'!E40-'Balance Sheet'!D40) -> -728.17838 | F32: =-('Balance Sheet'!F40-'Balance Sheet'!E40) -> -2499.225 | G32: =-('Balance Sheet'!G40-'Balance Sheet'!F40) -> -2682.6488 | H32: =-('Balance Sheet'!H40-'Balance Sheet'!G40) -> -3326.4845 | I32: =-('Balance Sheet'!I40-'Balance Sheet'!H40) -> -3781.1041 | J32: =-('Balance Sheet'!J40-'Balance Sheet'!I40) -> -4193.5882
A33: Increase in Loans and Advances | B33: -426.2 | C33: -684.5 | D33: -692.4 | E33: 0 | F33: 0 | G33: 0 | H33: 0 | I33: 0 | J33: 0
A34: Increase in Current Liabilities | B34: 1202.2 | C34: 645.7 | D34: 1124.2 | E34: =('Balance Sheet'!E46-'Balance Sheet'!D46) -> 882.67258 | F34: =('Balance Sheet'!F46-'Balance Sheet'!E46) -> 1857.7208 | G34: =('Balance Sheet'!G46-'Balance Sheet'!F46) -> 1919.0636 | H34: =('Balance Sheet'!H46-'Balance Sheet'!G46) -> 2449.3097 | I34: =('Balance Sheet'!I46-'Balance Sheet'!H46) -> 2784.0487 | J34: =('Balance Sheet'!J46-'Balance Sheet'!I46) -> 3087.7631
A35: Cash Generated from operations | B35: =B29+SUM(B31:B34) -> 481.2 | C35: =C29+SUM(C31:C34) -> 419.6 | D35: =D29+SUM(D31:D34) -> 2045.8 | E35: =E29+SUM(E31:E34) -> 1374.1145 | F35: =F29+SUM(F31:F34) -> 2904.7845 | G35: =G29+SUM(G31:G34) -> 3724.9411 | H35: =H29+SUM(H31:H34) -> 4189.0574 | I35: =I29+SUM(I31:I34) -> 6431.7206 | J35: =J29+SUM(J31:J34) -> 8087.131
A36: Direct Taxes paid (Net of refund) | B36: -320.7 | C36: -233.1 | D36: -458.6 | E36: =-'Profit & Loss Consolidated'!Q42 -> -312.9 | F36: =-'Profit & Loss Consolidated'!V42 -> -782.96634 | G36: =-'Profit & Loss Consolidated'!AA42 -> -727.14763 | H36: =-'Profit & Loss Consolidated'!AF42 -> -856.9901 | I36: =-'Profit & Loss Consolidated'!AK42 -> -1192.8581 | J36: =-'Profit & Loss Consolidated'!AP42 -> -1439.3327
A37: Net Cash (Used In) / From Operating Activities (A) | B37: =SUM(B35:B36) -> 160.5 | C37: =SUM(C35:C36) -> 186.5 | D37: =SUM(D35:D36) -> 1587.2 | E37: =SUM(E35:E36) -> 1061.2145 | F37: =SUM(F35:F36) -> 2121.8182 | G37: =SUM(G35:G36) -> 2997.7934 | H37: =SUM(H35:H36) -> 3332.0673 | I37: =SUM(I35:I36) -> 5238.8626 | J37: =SUM(J35:J36) -> 6647.7983
A39: B. Cash Flow From Investing Activities
A41: Purchase of Fixed Assets and Intangibles | B41: -2224 | C41: -3318.7 | D41: -2462.9 | E41: =-('Balance Sheet'!E28-'Balance Sheet'!D28) -> -2292.2798 | F41: =-('Balance Sheet'!F28-'Balance Sheet'!E28) -> -2755.5823 | G41: =-('Balance Sheet'!G28-'Balance Sheet'!F28) -> -3416.9221 | H41: =-('Balance Sheet'!H28-'Balance Sheet'!G28) -> -3631.7 | I41: =-('Balance Sheet'!I28-'Balance Sheet'!H28) -> -4430.6741 | J41: =-('Balance Sheet'!J28-'Balance Sheet'!I28) -> -5316.8089
A42: Proceeds from sale of Fixed Assets | B42: 56.5 | C42: 155.3 | D42: 19.4 | E42: 0 | F42: 0 | G42: 0 | H42: 0 | I42: 0 | J42: 0
A43: Payment for Net Assets acquired of Subsidiary, Net of cash | B43: -358.4 | C43: -284.7 | D43: 0 | E43: 0 | F43: 0 | G43: 0 | H43: 0 | I43: 0 | J43: 0
A44: Payment for Purchase of Sundry Debtors | B44: -19.9 | C44: 0 | D44: 0 | E44: 0 | F44: 0 | G44: 0 | H44: 0 | I44: 0 | J44: 0
A45: On disposal of Joint Venture entity | B45: -18.8 | C45: 0 | D45: 0 | E45: 0 | F45: 0 | G45: 0 | H45: 0 | I45: 0 | J45: 0
A46: Proceeds from sale of investment in Subsidiary,net of cash | B46: 0 | C46: -24.5 | D46: 168.2 | E46: 0 | F46: 0 | G46: 0 | H46: 0 | I46: 0 | J46: 0
A47: Proceeds from sale/(purchase) of Investments (Net) | B47: 13 | C47: -2026.6 | D47: 1108.2 | E47: 0 | F47: 0 | G47: 0 | H47: 0 | I47: 0 | J47: 0
A48: Loans to Joint Ventures | B48: -20.4 | C48: 0 | D48: -36 | E48: 0 | F48: 0 | G48: 0 | H48: 0 | I48: 0 | J48: 0
A49: Interest Received | B49: 86.7 | C49: 366 | D49: 453 | E49: 0 | F49: 0 | G49: 0 | H49: 0 | I49: 0 | J49: 0
A50: Net Cash Used in Investing Activities (B) | B50: =SUM(B41:B49) -> -2485.3 | C50: =SUM(C41:C49) -> -5133.2 | D50: =SUM(D41:D49) -> -750.1 | E50: =SUM(E41:E49) -> -2292.2798 | F50: =SUM(F41:F49) -> -2755.5823 | G50: =SUM(G41:G49) -> -3416.9221 | H50: =SUM(H41:H49) -> -3631.7 | I50: =SUM(I41:I49) -> -4430.6741 | J50: =SUM(J41:J49) -> -5316.8089
A52: C. Cash Flow From Financing Activities
A54: Proceeds from Issuance of Share capital | B54: 587.5 | C54: 28.4 | D54: 15.3 | E54: 0 | F54: 0 | G54: 0 | H54: 0 | I54: 0 | J54: 0
A55: Proceeds from Long-Term borrowings | B55: 0.4 | C55: 382.8 | D55: 29.8 | E55: 0 | F55: 0 | G55: ='Debt Schedule'!H43 -> 2000 | H55: ='Debt Schedule'!I43 -> 5000 | I55: 0 | J55: 0
A56: Proceeds from FCCB's | B56: 70.3 | C56: 9102 | D56: 0 | E56: 0 | F56: 0 | G56: 0 | H56: 0 | I56: 0 | J56: 0
A57: Repayment of Long-Term Borrowings | B57: -680.5 | C57: -2327.6 | D57: -1179.8 | E57: 0 | F57: ='Debt Schedule'!G41 -> -91.5768 | G57: 0 | H57: 0 | I57: 0 | J57: 0
A58: Repayment of FCCB's (Redemption) | B58: 0 | C58: 0 | D58: 0 | E58: 0 | F58: 0 | G58: 0 | H58: =SUM('Debt Schedule'!I41:I42) -> -6403.2
A59: Proceeds from Short term borrowings (Net) | B59: 4477.6 | C59: 757 | D59: -258.8 | E59: 0 | F59: 0 | G59: 0 | H59: 0 | I59: 0 | J59: 0
A60: Interest Paid | B60: -690.8 | C60: -875.9 | D60: -624.9 | E60: 0 | F60: 0 | G60: 0 | H60: 0 | I60: 0 | J60: 0
A61: FCCB Issue Expenses | B61: -70.2 | C61: -135.6 | D61: 0 | E61: 0 | F61: 0 | G61: 0 | H61: 0 | I61: 0 | J61: 0
A62: Dividends and dividend tax paid | B62: -30.3 | C62: -92.3 | D62: -157.1 | E62: 0 | F62: 0 | G62: 0 | H62: 0 | I62: 0 | J62: 0
A63: Net Cash Flow From Financing Activities (C) | B63: =SUM(B54:B62) -> 3664 | C63: =SUM(C54:C62) -> 6838.8 | D63: =SUM(D54:D62) -> -2175.5 | E63: =SUM(E54:E62) -> 0 | F63: =SUM(F54:F62) -> -91.5768 | G63: =SUM(G54:G62) -> 2000 | H63: =SUM(H54:H62) -> -1403.2 | I63: =SUM(I54:I62) -> 0 | J63: =SUM(J54:J62) -> 0
A65: D. Effect of Exchange rate changes on Cash & Cash equivalents (D) | B65: 43.4 | C65: 7.6 | D65: -9.7 | E65: 0 | F65: 0 | G65: 0 | H65: 0 | I65: 0 | J65: 0
A67: Net Increase / (Decrease) in Cash and Cash Equivalents (A+B+C+D) | B67: =B37+B50+B63+B65 -> 1382.6 | C67: =C37+C50+C63+C65 -> 1899.7 | D67: =D37+D50+D63+D65 -> -1348.1 | E67: =E37+E50+E63+E65 -> -1231.0652 | F67: =F37+F50+F63+F65 -> -725.34096 | G67: =G37+G50+G63+G65 -> 1580.8714 | H67: =H37+H50+H63+H65 -> -1702.8327 | I67: =I37+I50+I63+I65 -> 808.18852 | J67: =J37+J50+J63+J65 -> 1330.9894
A68: Cash and Cash Equivalents at the beginning of the year | B68: 593.8 | C68: 1961.7 | D68: 3747.5 | E68: =D77 -> 2825.7 | F68: =E70 -> 1594.6348 | G68: =F70 -> 869.29382 | H68: =G70 -> 2450.1652 | I68: =H70 -> 747.33248 | J68: =I70 -> 1555.521
A69: Add: On Amalgamation | B69: 0 | C69: 0.1 | D69: 0 | E69: 0 | F69: 0 | G69: 0 | H69: 0 | I69: 0 | J69: 0
A70: Cash and Cash Equivalents at the end of the year | B70: =SUM(B67:B69) -> 1976.4 | C70: =SUM(C67:C69) -> 3861.5 | D70: =SUM(D67:D69) -> 2399.4 | E70: =SUM(E67:E69) -> 1594.6348 | F70: =SUM(F67:F69) -> 869.29382 | G70: =SUM(G67:G69) -> 2450.1652 | H70: =SUM(H67:H69) -> 747.33248 | I70: =SUM(I67:I69) -> 1555.521 | J70: =SUM(J67:J69) -> 2886.5104
A72: Cash and Cheques on Hand | B72: 50.5 | C72: 9.3 | D72: 5
A73: With Banks - on Current Accounts | B73: 796.3 | C73: 765.9 | D73: 249.1
A74: on Deposit Accounts | B74: 138.7 | C74: 5046.6 | D74: 2568.6
A75: on Unpaid Dividend Accounts | B75: 2.6 | C75: 2.8 | D75: 3
A76: on Fixed Deposits Accounts | B76: 1031.2 | C76: 0 | D76: 0
A77: Cash and Cash Equivalents as per Balance Sheet | B77: =SUM(B72:B76) -> 2019.3 | C77: =SUM(C72:C76) -> 5824.6 | D77: =SUM(D72:D76) -> 2825.7
A78: Less: Overdraft | B78: -57.6 | C78: -66.3 | D78: -103.6
A79: Less: Fixed Deposits considered as Investments | B79: 13.4 | C79: -2010.8 | D79: -301
A80: Effect of Unrealized exchange loss as on Balance sheet date | B80: 1.3 | C80: 114 | D80: -21.7
A81: Cash and Cash Equivalents considered for cash flows | B81: =SUM(B77:B80) -> 1976.4 | C81: =SUM(C77:C80) -> 3861.5 | D81: =SUM(D77:D80) -> 2399.4

Sheet Geographic Revenue Model
A1: Aurobindo Pharma
A2: Geographic Revenue Model
A3: (In Rs Millions)
B5: FY2005 A | C5: FY2006 A | D5: FY2007 A | E5: FY2008 A | F5: FY2009 A | G5: FY2010 E | H5: FY2011 E | I5: FY2012 E | J5: FY2013 E | K5: FY2014 E
A7: Geographic Revenue
A8: India | B8: 10664.4 | C8: 12507.4 | D8: 16023.4 | E8: 19058.3 | F8: =F$11*F36 -> 24443.844 | G8: =G$11*G36 -> 31492.369 | H8: =H$11*H36 -> 39538.67 | I8: =I$11*I36 -> 47817.384 | J8: =J$11*J36 -> 57598.763 | K8: =K$11*K36 -> 70890.785
A9: China | B9: 1232.5 | C9: 1306.6 | D9: 976 | E9: 285.8 | F9: =F$11*F37 -> 366.56211 | G9: =G$11*G37 -> 461.86826 | H9: =H$11*H37 -> 572.71664 | I9: =I$11*I37 -> 710.16864 | J9: =J$11*J37 -> 866.40574 | K9: =K$11*K37 -> 1039.6869
A10: Rest of the World | B10: 1319.1 | C10: 2122.1 | D10: 4229.8 | E10: 5014.9 | F10: =F$11*F38 -> 6432.0236 | G10: =G$11*G38 -> 7479.4377 | H10: =H$11*H38 -> 8786.3711 | I10: =I$11*I38 -> 12105.667 | J10: =J$11*J38 -> 15507.359 | K10: =K$11*K38 -> 16836.561
A11: Consolidated | B11: =SUM(B8:B10) -> 13216 | C11: =SUM(C8:C10) -> 15936.1 | D11: =SUM(D8:D10) -> 21229.2 | E11: =SUM(E8:E10) -> 24359 | F11: ='Profit & Loss Consolidated'!Q13 -> 31242.43 | G11: =F11*(1+G46) -> 39365.462 | H11: =G11*(1+H46) -> 48813.173 | I11: =H11*(1+I46) -> 60528.334 | J11: =I11*(1+J46) -> 73844.568 | K11: =J11*(1+K46) -> 88613.481
A13: Segment Results (EBIT)
A14: India | B14: 572.8 | C14: 1357.5 | D14: 2450.4 | E14: 3545.1
A15: China | B15: -32.8 | C15: -101.7 | D15: -129 | E15: 525.9
A16: Rest of the World | B16: -104.1 | C16: 82 | D16: -18.1 | E16: -332.4
A17: Add: Eliminations (for inter-segment sales) | B17: 47.1 | C17: 208.7 | D17: 139.1 | E17: -453.6
A18: Consolidated | B18: =SUM(B14:B16)+B17 -> 483 | C18: =SUM(C14:C16)+C17 -> 1546.5 | D18: =SUM(D14:D16)+D17 -> 2442.4 | E18: =SUM(E14:E16)+E17 -> 3285
A20: Capital Expenditure
A21: India | B21: 2275.2 | C21: 1549 | D21: 1801.3 | E21: 1322.2
A22: China | B22: 459.2 | C22: 262.8 | D22: 191.4 | E22: 494.2
A23: Rest of the World | B23: 568.1 | C23: 257.7 | D23: 1494.8 | E23: 707.8
A24: Less: Eliminations (for inter-segment sales) | B24: 0 | C24: 0 | D24: 0 | E24: 0
A25: Consolidated | B25: =SUM(B21:B23)-B24 -> 3302.5 | C25: =SUM(C21:C23)-C24 -> 2069.5 | D25: =SUM(D21:D23)-D24 -> 3487.5 | E25: =SUM(E21:E23)-E24 -> 2524.2
A27: Depreciation / Amortization
A28: India | B28: 445.1 | C28: 511.3 | D28: 718.4 | E28: 746
A29: China | B29: 177.2 | C29: 200.8 | D29: 258.9 | E29: 225.4
A30: Rest of the World | B30: 24.4 | C30: 9.2 | D30: 19.9 | E30: 77.6
A31: Less: Eliminations (for inter-segment sales) | B31: 0 | C31: 0 | D31: 0 | E31: -45.2
A32: Consolidated | B32: =SUM(B28:B30)+B31 -> 646.7 | C32: =SUM(C28:C30)+C31 -> 721.3 | D32: =SUM(D28:D30)+D31 -> 997.2 | E32: =SUM(E28:E30)+E31 -> 1003.8
A35: Geographic Revenues as a % of Total
A36: India | B36: =B8/B$11 -> 0.80693099 | C36: =C8/C$11 -> 0.78484698 | D36: =D8/D$11 -> 0.75478115 | E36: =E8/E$11 -> 0.78239254 | F36: =E36 -> 0.78239254 | G36: 0.8 | H36: 0.81 | I36: 0.79 | J36: 0.78 | K36: 0.8
A37: China | B37: =B9/B$11 -> 0.093258172 | C37: =C9/C$11 -> 0.081989947 | D37: =D9/D$11 -> 0.045974413 | E37: =E9/E$11 -> 0.01173283 | F37: =E37 -> 0.01173283 | G37: =F37 -> 0.01173283 | H37: =G37 -> 0.01173283 | I37: =H37 -> 0.01173283 | J37: =I37 -> 0.01173283 | K37: =J37 -> 0.01173283
A38: Rest of the World | B38: =B10/B$11 -> 0.099810835 | C38: =C10/C$11 -> 0.13316307 | D38: =D10/D$11 -> 0.19924444 | E38: =E10/E$11 -> 0.20587463 | F38: =E38 -> 0.20587463 | G38: 0.19 | H38: 0.18 | I38: 0.2 | J38: 0.21 | K38: 0.19
A39: Consolidated | B39: =B11/B$11 -> 1 | C39: =C11/C$11 -> 1 | D39: =D11/D$11 -> 1 | E39: =E11/E$11 -> 1 | F39: =F11/F$11 -> 1 | G39: =G11/G$11 -> 1 | H39: =H11/H$11 -> 1 | I39: =I11/I$11 -> 1 | ... K39: =K11/K$11 -> 1
A42: Y/Y (%) Growth in Geographic Revenues
A43: India | C43: =C8/B8-1 -> 0.17281797 | D43: =D8/C8-1 -> 0.28111358 | E43: =E8/D8-1 -> 0.18940425 | F43: =F8/E8-1 -> 0.28258262 | G43: =G8/F8-1 -> 0.28835583 | H43: =H8/G8-1 -> 0.2555 | I43: =I8/H8-1 -> 0.20938272 | J43: =J8/I8-1 -> 0.20455696 | K43: =K8/J8-1 -> 0.23076923
A44: China | C44: =C9/B9-1 -> 0.060121704 | D44: =D9/C9-1 -> -0.25302311 | E44: =E9/D9-1 -> -0.70717213 | F44: =F9/E9-1 -> 0.28258262 | G44: =G9/F9-1 -> 0.26 | H44: =H9/G9-1 -> 0.24 | I44: =I9/H9-1 -> 0.24 | J44: =J9/I9-1 -> 0.22 | K44: =K9/J9-1 -> 0.2
A45: Rest of the World | C45: =C10/B10-1 -> 0.60874839 | D45: =D10/C10-1 -> 0.99321427 | E45: =E10/D10-1 -> 0.18561161 | F45: =F10/E10-1 -> 0.28258262 | G45: =G10/F10-1 -> 0.16284365 | H45: =H10/G10-1 -> 0.17473684 | I45: =I10/H10-1 -> 0.37777778 | J45: =J10/I10-1 -> 0.281 | K45: =K10/J10-1 -> 0.085714286
A46: Consolidated | C46: =C11/B11-1 -> 0.2058187 | D46: =D11/C11-1 -> 0.33214526 | E46: =E11/D11-1 -> 0.14742901 | F46: =F11/E11-1 -> 0.28258262 | G46: 0.26 | H46: 0.24 | I46: 0.24 | J46: 0.22 | K46: 0.2

Sheet Segment Revenue Model
A1: Aurobindo Pharma
A2: Segment Revenue Model
A3: (In Rs Millions)
A4: For the Fiscal Period Ending | B4: FY2007 A | C4: 3 months Jun-30-2007 | D4: 3 months Sep-30-2007 | E4: 3 months Dec-31-2007 | F4: 3 months Mar-31-2008 | G4: FY2008 A | H4: 3 months Jun-30-2008 | I4: 3 months Sep-30-2008 | J4: 3 months Dec-31-2008 | K4: 3 months Mar-31-2009 | L4: FY2009 A | M4: 3 months Jun-30-2009 | N4: 3 months Sep-30-2009 | O4: 3 months Dec-31-2009 | P4: 3 months Mar-31-2010 | Q4: FY2010 E | R4: 3 months Jun-30-2010 | S4: 3 months Sep-30-2010 | T4: 3 months Dec-31-2010 | U4: 3 months Mar-31-2011 | V4: FY2011 E | W4: 3 months Jun-30-2011 | X4: 3 months Sep-30-2011 | Y4: 3 months Dec-31-2011 | Z4: 3 months Mar-31-2012 | AA4: FY2012 E | AB4: 3 months Jun-30-2012 | AC4: 3 months Sep-30-2012 | AD4: 3 months Dec-31-2012 | AE4: 3 months Mar-31-2013 | AF4: FY2013 E | AG4: 3 months Jun-30-2013 | AH4: 3 months Sep-30-2013 | AI4: 3 months Dec-31-2013 | AJ4: 3 months Mar-31-2014 | AK4: FY2014 E
A7: Segment Revenues
A9: Formulations
A10: USA | B10: 1563 | C10: 546 | D10: 518 | E10: 497 | F10: 798 | G10: =SUM(C10:F10) -> 2359 | H10: 817 | I10: 1051 | J10: 1427 | K10: 2289 | L10: =SUM(H10:K10) -> 5584 | M10: 2310 | N10: =N69*N$14 -> 1777.7726 | O10: =O69*O$14 -> 2247.8572 | P10: =P69*P$14 -> 2943.1287 | Q10: =SUM(M10:P10) -> 9278.7584 | R10: =R69*R$14 -> 3265.367 | S10: =S69*S$14 -> 2135.2522 | T10: =T69*T$14 -> 2767.4999 | U10: =U69*U$14 -> 4152.3138 | V10: =SUM(R10:U10) -> 12320.433 | W10: =W69*W$14 -> 4049.0551 | X10: =X69*X$14 -> 2647.7127 | Y10: =Y69*Y$14 -> 3431.6999 | Z10: =Z69*Z$14 -> 5148.8691 | AA10: =SUM(W10:Z10) -> 15277.337 | AB10: =AB69*AB$14 -> 4939.8472 | AC10: =AC69*AC$14 -> 3230.2095 | AD10: =AD69*AD$14 -> 4186.6739 | AE10: =AE69*AE$14 -> 6281.6203 | AF10: =SUM(AB10:AE10) -> 18638.351 | AG10: =AG69*AG$14 -> 5927.8166 | AH10: =AH69*AH$14 -> 3876.2514 | AI10: =AI69*AI$14 -> 5024.0087 | AJ10: =AJ69*AJ$14 -> 7537.9444 | AK10: =SUM(AG10:AJ10) -> 22366.021
A11: Europe | B11: 1280 | C11: 362 | D11: 562 | E11: 641 | F11: 446 | G11: =SUM(C11:F11) -> 2011 | H11: 447 | I11: 557 | J11: 467 | K11: 452 | L11: =SUM(H11:K11) -> 1923 | M11: 464 | N11: =N70*N$14 -> 942.16871 | O11: =O70*O$14 -> 735.6337 | P11: =P70*P$14 -> 581.16827 | Q11: =SUM(M11:P11) -> 2722.9707 | R11: =R70*R$14 -> 655.90055 | S11: =S70*S$14 -> 1131.6227 | T11: =T70*T$14 -> 905.69199 | U11: =U70*U$14 -> 819.94139 | V11: =SUM(R11:U11) -> 3513.1566 | W11: =W70*W$14 -> 813.31669 | X11: =X70*X$14 -> 1403.2122 | Y11: =Y70*Y$14 -> 1123.0581 | Z11: =Z70*Z$14 -> 1016.7273 | AA11: =SUM(W11:Z11) -> 4356.3142 | AB11: =AB70*AB$14 -> 992.24636 | AC11: =AC70*AC$14 -> 1711.9188 | AD11: =AD70*AD$14 -> 1370.1308 | AE11: =AE70*AE$14 -> 1240.4073 | AF11: =SUM(AB11:AE11) -> 5314.7034 | AG11: =AG70*AG$14 -> 1190.6956 | AH11: =AH70*AH$14 -> 2054.3026 | AI11: =AI70*AI$14 -> 1644.157 | AJ11: =AJ70*AJ$14 -> 1488.4888 | AK11: =SUM(AG11:AJ11) -> 6377.644
A12: ARV's | B12: 2875 | C12: 642 | D12: 1072 | E12: 939 | F12: 1391 | G12: =SUM(C12:F12) -> 4044 | H12: 1249 | I12: 858 | J12: 1215 | K12: 1318 | L12: =SUM(H12:K12) -> 4640 | M12: 1375.1 | N12: =N71*N$14 -> 1451.3119 | O12: =O71*O$14 -> 1913.9078 | P12: =P71*P$14 -> 1694.6455 | Q12: =SUM(M12:P12) -> 6434.9653 | R12: =R71*R$14 -> 1943.8122 | S12: =S71*S$14 -> 1743.1459 | T12: =T71*T$14 -> 2356.3507 | U12: =U71*U$14 -> 2390.891 | V12: =SUM(R12:U12) -> 8434.1998 | W12: =W71*W$14 -> 2410.3271 | X12: =X71*X$14 -> 2161.501 | Y12: =Y71*Y$14 -> 2921.8748 | Z12: =Z71*Z$14 -> 2964.7049 | AA12: =SUM(W12:Z12) -> 10458.408 | AB12: =AB71*AB$14 -> 2940.5991 | AC12: =AC71*AC$14 -> 2637.0312 | AD12: =AD71*AD$14 -> 3564.6873 | AE12: =AE71*AE$14 -> 3616.94 | AF12: =SUM(AB12:AE12) -> 12759.258 | AG12: =AG71*AG$14 -> 3528.7189 | AH12: =AH71*AH$14 -> 3164.4374 | AI12: =AI71*AI$14 -> 4277.6248 | AJ12: =AJ71*AJ$14 -> 4340.3279 | AK12: =SUM(AG12:AJ12) -> 15311.109
A13: Rest of the World | B13: 1478.2 | C13: 246 | D13: 245 | E13: 389 | F13: 754 | G13: =SUM(C13:F13) -> 1634 | H13: 384 | I13: 727 | J13: 422 | K13: 418 | L13: =SUM(H13:K13) -> 1951 | M13: 540 | N13: =N72*N$14 -> 1229.7247 | O13: =O72*O$14 -> 664.74823 | P13: =P72*P$14 -> 537.45207 | Q13: =SUM(M13:P13) -> 2971.925 | R13: =R72*R$14 -> 763.33254 | S13: =S72*S$14 -> 1477.0013 | T13: =T72*T$14 -> 818.41974 | U13: =U72*U$14 -> 758.26438 | V13: =SUM(R13:U13) -> 3817.0179 | W13: =W72*W$14 -> 946.53235 | X13: =X72*X$14 -> 1831.4816 | Y13: =Y72*Y$14 -> 1014.8405 | Z13: =Z72*Z$14 -> 940.24783 | AA13: =SUM(W13:Z13) -> 4733.1023 | AB13: =AB72*AB$14 -> 1154.7695 | AC13: =AC72*AC$14 -> 2234.4075 | AD13: =AD72*AD$14 -> 1238.1054 | AE13: =AE72*AE$14 -> 1147.1024 | AF13: =SUM(AB13:AE13) -> 5774.3847 | AG13: =AG72*AG$14 -> 1385.7234 | AH13: =AH72*AH$14 -> 2681.289 | AI13: =AI72*AI$14 -> 1485.7265 | AJ13: =AJ72*AJ$14 -> 1376.5228 | AK13: =SUM(AG13:AJ13) -> 6929.2617
A14: Total | B14: =SUM(B10:B13) -> 7196.2 | C14: =SUM(C10:C13) -> 1796 | D14: =SUM(D10:D13) -> 2397 | E14: =SUM(E10:E13) -> 2466 | F14: =SUM(F10:F13) -> 3389 | G14: =SUM(C14:F14) -> 10048 | H14: =SUM(H10:H13) -> 2897 | I14: =SUM(I10:I13) -> 3193 | J14: =SUM(J10:J13) -> 3531 | K14: =SUM(K10:K13) -> 4477 | L14: =SUM(H14:K14) -> 14098 | M14: =SUM(M10:M13) -> 4689.1 | N14: =N23 -> 5400.9779 | O14: =O23 -> 5562.1469 | P14: =P23 -> 5756.3946 | Q14: =Q23 -> 21408.619 | R14: =R23 -> 6628.4122 | S14: =S23 -> 6487.0221 | T14: =T23 -> 6847.9624 | U14: =U23 -> 8121.4106 | ... AK14: =AK23 -> 50984.036
A16: Active Ingredients
A17: SSPs | B17: 5913 | C17: 2123 | D17: 2278 | E17: 1748 | F17: 1892 | G17: =SUM(C17:F17) -> 8041 | H17: 2140 | I17: 1856 | J17: 1744 | K17: 1639 | L17: =SUM(H17:K17) -> 7379 | M17: 1517 | N17: =N76*N$20 -> 2277.0706 | O17: =O76*O$20 -> 2075.3357 | P17: =P76*P$20 -> 1794.1916 | Q17: =SUM(M17:P17) -> 7663.5979 | R17: =R76*R$20 -> 1975.6418 | S17: =S76*S$20 -> 2327.8384 | T17: =T76*T$20 -> 2263.1581 | U17: =U76*U$20 -> 2239.5746 | V17: =SUM(R17:U17) -> 8806.213 | W17: =W76*W$20 -> 2449.7958 | X17: =X76*X$20 -> 2886.5197 | Y17: =Y76*Y$20 -> 2806.3161 | Z17: =Z76*Z$20 -> 2777.0725 | AA17: =SUM(W17:Z17) -> 10919.704 | AB17: =AB76*AB$20 -> 2988.7509 | AC17: =AC76*AC$20 -> 3521.554 | AD17: =AD76*AD$20 -> 3423.7056 | AE17: =AE76*AE$20 -> 3388.0284 | AF17: =SUM(AB17:AE17) -> 13322.039 | AG17: =AG76*AG$20 -> 3586.5011 | AH17: =AH76*AH$20 -> 4225.8648 | AI17: =AI76*AI$20 -> 4108.4467 | AJ17: =AJ76*AJ$20 -> 4065.6341 | AK17: =SUM(AG17:AJ17) -> 15986.447
A18: Cephs | B18: 6429 | C18: 1309 | D18: 1577 | E18: 1620 | F18: 1412 | G18: =SUM(C18:F18) -> 5918 | H18: 1564 | I18: 1560 | J18: 1543 | K18: 1677 | L18: =SUM(H18:K18) -> 6344 | M18: 1390 | N18: =N77*N$20 -> 1913.9171 | O18: =O77*O$20 -> 1836.1485 | P18: =P77*P$20 -> 1835.7897 | Q18: =SUM(M18:P18) -> 6975.8553 | R18: =R77*R$20 -> 1810.2453 | S18: =S77*S$20 -> 1956.5883 | T18: =T77*T$20 -> 2002.324 | U18: =U77*U$20 -> 2291.4988 | V18: =SUM(R18:U18) -> 8060.6564 | W18: =W77*W$20 -> 2244.7042 | X18: =X77*X$20 -> 2426.1695 | Y18: =Y77*Y$20 -> 2482.8817 | Z18: =Z77*Z$20 -> 2841.4586 | AA18: =SUM(W18:Z18) -> 9995.214 | AB18: =AB77*AB$20 -> 2738.5391 | AC18: =AC77*AC$20 -> 2959.9268 | AD18: =AD77*AD$20 -> 3029.1157 | AE18: =AE77*AE$20 -> 3466.5794 | AF18: =SUM(AB18:AE18) -> 12194.161 | AG18: =AG77*AG$20 -> 3286.2469 | AH18: =AH77*AH$20 -> 3551.9122 | AI18: =AI77*AI$20 -> 3634.9388 | AJ18: =AJ77*AJ$20 -> 4159.8953 | AK18: =SUM(AG18:AJ18) -> 14632.993
A19: ARVs & Others | B19: 2964 | C19: 436 | D19: 418 | E19: 268 | F19: 395 | G19: =SUM(C19:F19) -> 1517 | H19: 467 | I19: 631 | J19: 750 | K19: 895 | L19: =SUM(H19:K19) -> 2743 | M19: 671 | N19: =N78*N$20 -> 774.15494 | O19: =O78*O$20 -> 892.48954 | P19: =P78*P$20 -> 979.74466 | Q19: =SUM(M19:P19) -> 3317.3891 | R19: =R78*R$20 -> 873.86661 | S19: =S78*S$20 -> 791.4149 | T19: =T78*T$20 -> 973.26181 | U19: =U78*U$20 -> 1222.9526 | V19: =SUM(R19:U19) -> 3861.4959 | W19: =W78*W$20 -> 1083.5946 | X19: =X78*X$20 -> 981.35448 | Y19: =Y78*Y$20 -> 1206.8446 | Z19: =Z78*Z$20 -> 1516.4612 | AA19: =SUM(W19:Z19) -> 4788.2549 | AB19: =AB78*AB$20 -> 1321.9854 | AC19: =AC78*AC$20 -> 1197.2525 | AD19: =AD78*AD$20 -> 1472.3505 | AE19: =AE78*AE$20 -> 1850.0826 | AF19: =SUM(AB19:AE19) -> 5841.671 | AG19: =AG78*AG$20 -> 1586.3825 | AH19: =AH78*AH$20 -> 1436.703 | AI19: =AI78*AI$20 -> 1766.8206 | AJ19: =AJ78*AJ$20 -> 2220.0992 | AK19: =SUM(AG19:AJ19) -> 7010.0052
A20: Total | B20: =SUM(B17:B19) -> 15306 | C20: =SUM(C17:C19) -> 3868 | D20: =SUM(D17:D19) -> 4273 | E20: =SUM(E17:E19) -> 3636 | F20: =SUM(F17:F19) -> 3699 | G20: =SUM(C20:F20) -> 15476 | H20: =SUM(H17:H19) -> 4171 | I20: =SUM(I17:I19) -> 4047 | J20: =SUM(J17:J19) -> 4037 | K20: =SUM(K17:K19) -> 4211 | L20: =SUM(H20:K20) -> 16466 | M20: =SUM(M17:M19) -> 3578 | N20: =N24 -> 4965.1427 | O20: =O24 -> 4803.9737 | P20: =P24 -> 4609.726 | Q20: =Q24 -> 17956.842 | R20: =R24 -> 4659.7537 | S20: =S24 -> 5075.8417 | T20: =T24 -> 5238.7439 | U20: =U24 -> 5754.026 | ... AK20: =AK24 -> 37629.445
A23: Formulations | B23: =B14 -> 7196.2 | C23: =C14 -> 1796 | D23: =D14 -> 2397 | E23: =E14 -> 2466 | F23: =F14 -> 3389 | G23: =SUM(C23:F23) -> 10048 | H23: =H14 -> 2897 | I23: =I14 -> 3193 | J23: =J14 -> 3531 | K23: =K14 -> 4477 | L23: =SUM(H23:K23) -> 14098 | M23: =M14 -> 4689.1 | N23: =N$25*N82 -> 5400.9779 | O23: =O$25*O82 -> 5562.1469 | P23: =P$25*P82 -> 5756.3946 | Q23: =SUM(M23:P23) -> 21408.619 | R23: =R82*R$25 -> 6628.4122 | S23: =S82*S$25 -> 6487.0221 | T23: =T82*T$25 -> 6847.9624 | U23: =U82*U$25 -> 8121.4106 | V23: =SUM(R23:U23) -> 28084.807 | W23: =W82*W$25 -> 8219.2312 | X23: =X82*X$25 -> 8043.9074 | Y23: =Y82*Y$25 -> 8491.4733 | Z23: =Z82*Z$25 -> 10070.549 | AA23: =SUM(W23:Z23) -> 34825.161 | AB23: =AB82*AB$25 -> 10027.462 | AC23: =AC82*AC$25 -> 9813.5671 | AD23: =AD82*AD$25 -> 10359.597 | AE23: =AE82*AE$25 -> 12286.07 | AF23: =SUM(AB23:AE23) -> 42486.697 | AG23: =AG82*AG$25 -> 12032.954 | AH23: =AH82*AH$25 -> 11776.281 | AI23: =AI82*AI$25 -> 12431.517 | AJ23: =AJ82*AJ$25 -> 14743.284 | AK23: =SUM(AG23:AJ23) -> 50984.036
A24: Active Ingredients | B24: =B20 -> 15306 | C24: =C20 -> 3868 | D24: =D20 -> 4273 | E24: =E20 -> 3636 | F24: =F20 -> 3699 | G24: =SUM(C24:F24) -> 15476 | H24: =H20 -> 4171 | I24: =I20 -> 4047 | J24: =J20 -> 4037 | K24: =K20 -> 4211 | L24: =SUM(H24:K24) -> 16466 | M24: =M20 -> 3578 | N24: =N$25*N83 -> 4965.1427 | O24: =O$25*O83 -> 4803.9737 | P24: =P$25*P83 -> 4609.726 | Q24: =SUM(M24:P24) -> 17956.842 | R24: =R83*R$25 -> 4659.7537 | S24: =S83*S$25 -> 5075.8417 | T24: =T83*T$25 -> 5238.7439 | U24: =U83*U$25 -> 5754.026 | V24: =SUM(R24:U24) -> 20728.365 | W24: =W83*W$25 -> 5778.0946 | X24: =X83*X$25 -> 6294.0437 | Y24: =Y83*Y$25 -> 6496.0424 | Z24: =Z83*Z$25 -> 7134.9922 | AA24: =SUM(W24:Z24) -> 25703.173 | AB24: =AB83*AB$25 -> 7049.2754 | AC24: =AC83*AC$25 -> 7678.7333 | AD24: =AD83*AD$25 -> 7925.1718 | AE24: =AE83*AE$25 -> 8704.6905 | AF24: =SUM(AB24:AE24) -> 31357.871 | AG24: =AG83*AG$25 -> 8459.1305 | AH24: =AH83*AH$25 -> 9214.48 | AI24: =AI83*AI$25 -> 9510.2061 | AJ24: =AJ83*AJ$25 -> 10445.629 | AK24: =SUM(AG24:AJ24) -> 37629.445
A25: Total | B25: =SUM(B23:B24) -> 22502.2 | C25: =SUM(C23:C24) -> 5664 | D25: =SUM(D23:D24) -> 6670 | E25: =SUM(E23:E24) -> 6102 | F25: =SUM(F23:F24) -> 7088 | G25: =SUM(G23:G24) -> 25524 | H25: =SUM(H23:H24) -> 7068 | I25: =SUM(I23:I24) -> 7240 | ... M25: =SUM(M23:M24) -> 8267.1 | N25: =($Q$25-$M$25)/3 -> 10366.121 | O25: =($Q$25-$M$25)/3 -> 10366.121 | P25: =($Q$25-$M$25)/3 -> 10366.121 | Q25: ='Geographic Revenue Model'!G11 -> 39365.462 | R25: =$V25*R89 -> 11288.166 | S25: =$V25*S89 -> 11562.864 | T25: =$V25*T89 -> 12086.706 | U25: =$V25*U89 -> 13875.437 | V25: ='Geographic Revenue Model'!H11 -> 48813.173 | W25: =$AA25*W89 -> 13997.326 | X25: =$AA25*X89 -> 14337.951 | Y25: =$AA25*Y89 -> 14987.516 | Z25: =$AA25*Z89 -> 17205.541 | AA25: ='Geographic Revenue Model'!I11 -> 60528.334 | AB25: =$AF25*AB89 -> 17076.737 | AC25: =$AF25*AC89 -> 17492.3 | AD25: =$AF25*AD89 -> 18284.769 | AE25: =$AF25*AE89 -> 20990.76 | AF25: ='Geographic Revenue Model'!J11 -> 73844.568 | AG25: =$AK25*AG89 -> 20492.085 | AH25: =$AK25*AH89 -> 20990.76 | AI25: =$AK25*AI89 -> 21941.723 | AJ25: =$AK25*AJ89 -> 25188.913 | AK25: ='Geographic Revenue Model'!K11 -> 88613.481
A28: Y/Y (%) Growth
A30: Formulations
A31: USA | G31: =G10/B10-1 -> 0.50927703 | H31: =H10/C10-1 -> 0.496337 | I31: =I10/D10-1 -> 1.0289575 | J31: =J10/E10-1 -> 1.8712274 | K31: =K10/F10-1 -> 1.8684211 | L31: =L10/G10-1 -> 1.3671047 | M31: =M10/H10-1 -> 1.8274174 | N31: =N10/I10-1 -> 0.69150577 | ... AK31: =AK10/AF10-1 -> 0.2
A32: Europe | G32: =G11/B11-1 -> 0.57109375 | H32: =H11/C11-1 -> 0.23480663 | I32: =I11/D11-1 -> -0.0088967972 | J32: =J11/E11-1 -> -0.27145086 | K32: =K11/F11-1 -> 0.013452915 | L32: =L11/G11-1 -> -0.043759324 | M32: =M11/H11-1 -> 0.03803132 | N32: =N11/I11-1 -> 0.69150577 | ... AK32: =AK11/AF11-1 -> 0.2
A33: ARV's | G33: =G12/B12-1 -> 0.4066087 | H33: =H12/C12-1 -> 0.94548287 | I33: =I12/D12-1 -> -0.19962687 | J33: =J12/E12-1 -> 0.29392971 | K33: =K12/F12-1 -> -0.05248023 | L33: =L12/G12-1 -> 0.14737883 | M33: =M12/H12-1 -> 0.10096077 | N33: =N12/I12-1 -> 0.69150577 | ... AK33: =AK12/AF12-1 -> 0.2
A34: Rest of the World | G34: =G13/B13-1 -> 0.10539846 | H34: =H13/C13-1 -> 0.56097561 | I34: =I13/D13-1 -> 1.9673469 | J34: =J13/E13-1 -> 0.084832905 | K34: =K13/F13-1 -> -0.44562334 | L34: =L13/G13-1 -> 0.19400245 | M34: =M13/H13-1 -> 0.40625 | N34: =N13/I13-1 -> 0.69150577 | ... AK34: =AK13/AF13-1 -> 0.2
A35: Total | G35: =G14/B14-1 -> 0.39629249 | H35: =H14/C14-1 -> 0.61302895 | I35: =I14/D14-1 -> 0.33208177 | J35: =J14/E14-1 -> 0.43187348 | K35: =K14/F14-1 -> 0.32103865 | L35: =L14/G14-1 -> 0.40306529 | M35: =M14/H14-1 -> 0.61860545 | N35: =N14/I14-1 -> 0.69150577 | ... AK35: =AK14/AF14-1 -> 0.2
A37: Active Ingredients
A38: SSPs | G38: =G17/B17-1 -> 0.359885 | H38: =H17/C17-1 -> 0.0080075365 | I38: =I17/D17-1 -> -0.18525022 | J38: =J17/E17-1 -> -0.0022883295 | K38: =K17/F17-1 -> -0.13372093 | L38: =L17/G17-1 -> -0.082328069 | M38: =M17/H17-1 -> -0.2911215 | N38: =N17/I17-1 -> 0.22686995 | ... AK38: =AK17/AF17-1 -> 0.2
A39: Cephs | G39: =G18/B18-1 -> -0.07948359 | H39: =H18/C18-1 -> 0.19480519 | I39: =I18/D18-1 -> -0.010779962 | J39: =J18/E18-1 -> -0.047530864 | K39: =K18/F18-1 -> 0.18767705 | L39: =L18/G18-1 -> 0.071983778 | M39: =M18/H18-1 -> -0.1112532 | N39: =N18/I18-1 -> 0.22686995 | ... AK39: =AK18/AF18-1 -> 0.2
A40: ARVs & Others | G40: =G19/B19-1 -> -0.48819163 | H40: =H19/C19-1 -> 0.071100917 | I40: =I19/D19-1 -> 0.50956938 | J40: =J19/E19-1 -> 1.7985075 | K40: =K19/F19-1 -> 1.2658228 | L40: =L19/G19-1 -> 0.80817403 | M40: =M19/H19-1 -> 0.43683084 | N40: =N19/I19-1 -> 0.22686995 | ... AK40: =AK19/AF19-1 -> 0.2
A41: Total | G41: =G20/B20-1 -> 0.011106756 | H41: =H20/C20-1 -> 0.078335057 | I41: =I20/D20-1 -> -0.052890241 | J41: =J20/E20-1 -> 0.11028603 | K41: =K20/F20-1 -> 0.13841579 | L41: =L20/G20-1 -> 0.063970018 | M41: =M20/H20-1 -> -0.14217214 | N41: =N20/I20-1 -> 0.22686995 | ... AK41: =AK20/AF20-1 -> 0.2
A44: Formulations | G44: =G23/B23-1 -> 0.39629249 | H44: =H23/C23-1 -> 0.61302895 | I44: =I23/D23-1 -> 0.33208177 | J44: =J23/E23-1 -> 0.43187348 | K44: =K23/F23-1 -> 0.32103865 | L44: =L23/G23-1 -> 0.40306529 | M44: =M23/H23-1 -> 0.61860545 | N44: =N23/I23-1 -> 0.69150577 | ... AK44: =AK23/AF23-1 -> 0.2
A45: Active Ingredients | G45: =G24/B24-1 -> 0.011106756 | H45: =H24/C24-1 -> 0.078335057 | I45: =I24/D24-1 -> -0.052890241 | J45: =J24/E24-1 -> 0.11028603 | K45: =K24/F24-1 -> 0.13841579 | L45: =L24/G24-1 -> 0.063970018 | M45: =M24/H24-1 -> -0.14217214 | N45: =N24/I24-1 -> 0.22686995 | ... AK45: =AK24/AF24-1 -> 0.2
A46: Total | G46: =G25/B25-1 -> 0.13428909 | H46: =H25/C25-1 -> 0.24788136 | I46: =I25/D25-1 -> 0.085457271 | J46: =J25/E25-1 -> 0.2402491 | K46: =K25/F25-1 -> 0.22573363 | L46: =L25/G25-1 -> 0.19746121 | M46: =M25/H25-1 -> 0.16965195 | N46: =N25/I25-1 -> 0.43178461 | ... AK46: =AK25/AF25-1 -> 0.2
A50: Sequential - Q/Q (%) Growth
A52: Formulations
A53: USA | D53: =D10/C10-1 -> -0.051282051 | E53: =E10/D10-1 -> -0.040540541 | F53: =F10/E10-1 -> 0.6056338 | G53: =G10/B10-1 -> 0.50927703 | H53: =H10/F10-1 -> 0.023809524 | I53: =I10/H10-1 -> 0.28641371 | J53: =J10/I10-1 -> 0.35775452 | K53: =K10/J10-1 -> 0.60406447 | L53: =L10/G10-1 -> 1.3671047 | M53: =M10/K10-1 -> 0.0091743119
A54: Europe | D54: =D11/C11-1 -> 0.55248619 | E54: =E11/D11-1 -> 0.1405694 | F54: =F11/E11-1 -> -0.30421217 | G54: =G11/B11-1 -> 0.57109375 | H54: =H11/F11-1 -> 0.0022421525 | I54: =I11/H11-1 -> 0.24608501 | J54: =J11/I11-1 -> -0.16157989 | K54: =K11/J11-1 -> -0.032119914 | L54: =L11/G11-1 -> -0.043759324 | M54: =M11/K11-1 -> 0.026548673
A55: ARV's | D55: =D12/C12-1 -> 0.66978193 | E55: =E12/D12-1 -> -0.12406716 | F55: =F12/E12-1 -> 0.48136315 | G55: =G12/B12-1 -> 0.4066087 | H55: =H12/F12-1 -> -0.10208483 | I55: =I12/H12-1 -> -0.31305044 | J55: =J12/I12-1 -> 0.41608392 | K55: =K12/J12-1 -> 0.084773663 | L55: =L12/G12-1 -> 0.14737883 | M55: =M12/K12-1 -> 0.043323217
A56: Rest of the World | D56: =D13/C13-1 -> -0.0040650407 | E56: =E13/D13-1 -> 0.5877551 | F56: =F13/E13-1 -> 0.93830334 | G56: =G13/B13-1 -> 0.10539846 | H56: =H13/F13-1 -> -0.49071618 | I56: =I13/H13-1 -> 0.89322917 | J56: =J13/I13-1 -> -0.41953232 | K56: =K13/J13-1 -> -0.009478673 | L56: =L13/G13-1 -> 0.19400245 | M56: =M13/K13-1 -> 0.29186603
A57: Total | D57: =D14/C14-1 -> 0.33463252 | E57: =E14/D14-1 -> 0.028785982 | F57: =F14/E14-1 -> 0.37429035 | G57: =G14/B14-1 -> 0.39629249 | H57: =H14/F14-1 -> -0.14517557 | I57: =I14/H14-1 -> 0.10217466 | J57: =J14/I14-1 -> 0.10585656 | K57: =K14/J14-1 -> 0.26791277 | L57: =L14/G14-1 -> 0.40306529 | M57: =M14/K14-1 -> 0.047375475
A59: Active Ingredients
A60: SSPs | D60: =D17/C17-1 -> 0.073009892 | E60: =E17/D17-1 -> -0.23266023 | F60: =F17/E17-1 -> 0.082379863 | G60: =G17/B17-1 -> 0.359885 | H60: =H17/F17-1 -> 0.13107822 | I60: =I17/H17-1 -> -0.13271028 | J60: =J17/I17-1 -> -0.060344828 | K60: =K17/J17-1 -> -0.060206422 | L60: =L17/G17-1 -> -0.082328069 | M60: =M17/K17-1 -> -0.074435631
A61: Cephs | D61: =D18/C18-1 -> 0.20473644 | E61: =E18/D18-1 -> 0.027266963 | F61: =F18/E18-1 -> -0.12839506 | G61: =G18/B18-1 -> -0.07948359 | H61: =H18/F18-1 -> 0.10764873 | I61: =I18/H18-1 -> -0.0025575448 | J61: =J18/I18-1 -> -0.010897436 | K61: =K18/J18-1 -> 0.086843811 | L61: =L18/G18-1 -> 0.071983778 | M61: =M18/K18-1 -> -0.17113894
A62: ARVs & Others | D62: =D19/C19-1 -> -0.041284404 | E62: =E19/D19-1 -> -0.35885167 | F62: =F19/E19-1 -> 0.4738806 | G62: =G19/B19-1 -> -0.48819163 | H62: =H19/F19-1 -> 0.18227848 | I62: =I19/H19-1 -> 0.35117773 | J62: =J19/I19-1 -> 0.18858954 | K62: =K19/J19-1 -> 0.19333333 | L62: =L19/G19-1 -> 0.80817403 | M62: =M19/K19-1 -> -0.25027933
A63: Total | D63: =D20/C20-1 -> 0.10470527 | E63: =E20/D20-1 -> -0.14907559 | F63: =F20/E20-1 -> 0.017326733 | G63: =G20/B20-1 -> 0.011106756 | H63: =H20/F20-1 -> 0.12760205 | I63: =I20/H20-1 -> -0.029729082 | J63: =J20/I20-1 -> -0.0024709661 | K63: =K20/J20-1 -> 0.043101313 | L63: =L20/G20-1 -> 0.063970018 | M63: =M20/K20-1 -> -0.15032059
A66: Segment Revenues as (%) of Total
A68: Formulations
A69: USA | B69: =B10/B$14 -> 0.21719797 | C69: =C10/C$14 -> 0.30400891 | D69: =D10/D$14 -> 0.21610346 | E69: =E10/E$14 -> 0.20154096 | F69: =F10/F$14 -> 0.23546769 | G69: =G10/G$14 -> 0.23477309 | H69: =H10/H$14 -> 0.28201588 | I69: =I10/I$14 -> 0.32915753 | ... M69: =M10/M$14 -> 0.49263185 | N69: =I69 -> 0.32915753 | O69: =J69 -> 0.40413481 | P69: =K69 -> 0.51127987 | Q69: =Q10/Q$14 -> 0.43341227 | R69: =M69 -> 0.49263185 | S69: =N69 -> 0.32915753 | T69: =O69 -> 0.40413481 | U69: =P69 -> 0.51127987 | V69: =V10/V$14 -> 0.43868675 | W69: =R69 -> 0.49263185 | X69: =S69 -> 0.32915753 | Y69: =T69 -> 0.40413481 | Z69: =U69 -> 0.51127987 | AA69: =AA10/AA$14 -> 0.43868675 | AB69: =W69 -> 0.49263185 | AC69: =X69 -> 0.32915753 | AD69: =Y69 -> 0.40413481 | AE69: =Z69 -> 0.51127987 | AF69: =AF10/AF$14 -> 0.43868675 | AG69: =AB69 -> 0.49263185 | AH69: =AC69 -> 0.32915753 | AI69: =AD69 -> 0.40413481 | AJ69: =AE69 -> 0.51127987 | AK69: =AK10/AK$14 -> 0.43868675
A70: Europe | B70: =B11/B$14 -> 0.17787165 | C70: =C11/C$14 -> 0.20155902 | D70: =D11/D$14 -> 0.23445974 | E70: =E11/E$14 -> 0.25993512 | F70: =F11/F$14 -> 0.13160224 | G70: =G11/G$14 -> 0.20013933 | H70: =H11/H$14 -> 0.15429755 | I70: =I11/I$14 -> 0.1744441 | ... M70: =M11/M$14 -> 0.098952891 | N70: =I70 -> 0.1744441 | O70: =J70 -> 0.13225715 | P70: =K70 -> 0.10096046 | Q70: =Q11/Q$14 -> 0.12719039 | R70: =M70 -> 0.098952891 | S70: =N70 -> 0.1744441 | T70: =O70 -> 0.13225715 | U70: =P70 -> 0.10096046 | V70: =V11/V$14 -> 0.125091 | W70: =R70 -> 0.098952891 | X70: =S70 -> 0.1744441 | Y70: =T70 -> 0.13225715 | Z70: =U70 -> 0.10096046 | AA70: =AA11/AA$14 -> 0.125091 | AB70: =W70 -> 0.098952891 | AC70: =X70 -> 0.1744441 | AD70: =Y70 -> 0.13225715 | AE70: =Z70 -> 0.10096046 | AF70: =AF11/AF$14 -> 0.125091 | AG70: =AB70 -> 0.098952891 | AH70: =AC70 -> 0.1744441 | AI70: =AD70 -> 0.13225715 | AJ70: =AE70 -> 0.10096046 | AK70: =AK11/AK$14 -> 0.125091
A71: ARV's | B71: =B12/B$14 -> 0.39951641 | C71: =C12/C$14 -> 0.35746102 | D71: =D12/D$14 -> 0.4472257 | E71: =E12/E$14 -> 0.38077859 | F71: =F12/F$14 -> 0.41044556 | G71: =G12/G$14 -> 0.40246815 | H71: =H12/H$14 -> 0.43113566 | I71: =I12/I$14 -> 0.26871281 | ... M71: =M12/M$14 -> 0.29325457 | N71: =I71 -> 0.26871281 | O71: =J71 -> 0.34409516 | P71: =K71 -> 0.29439357 | Q71: =Q12/Q$14 -> 0.30057825 | R71: =M71 -> 0.29325457 | S71: =N71 -> 0.26871281 | T71: =O71 -> 0.34409516 | U71: =P71 -> 0.29439357 | V71: =V12/V$14 -> 0.30031183 | W71: =R71 -> 0.29325457 | X71: =S71 -> 0.26871281 | Y71: =T71 -> 0.34409516 | Z71: =U71 -> 0.29439357 | AA71: =AA12/AA$14 -> 0.30031183 | AB71: =W71 -> 0.29325457 | AC71: =X71 -> 0.26871281 | AD71: =Y71 -> 0.34409516 | AE71: =Z71 -> 0.29439357 | AF71: =AF12/AF$14 -> 0.30031183 | AG71: =AB71 -> 0.29325457 | AH71: =AC71 -> 0.26871281 | AI71: =AD71 -> 0.34409516 | AJ71: =AE71 -> 0.29439357 | AK71: =AK12/AK$14 -> 0.30031183
A72: Rest of the World | B72: =B13/B$14 -> 0.20541397 | C72: =C13/C$14 -> 0.13697105 | D72: =D13/D$14 -> 0.1022111 | E72: =E13/E$14 -> 0.15774534 | F72: =F13/F$14 -> 0.22248451 | G72: =G13/G$14 -> 0.16261943 | H72: =H13/H$14 -> 0.13255091 | I72: =I13/I$14 -> 0.22768556 | ... M72: =M13/M$14 -> 0.11516069 | N72: =I72 -> 0.22768556 | O72: =J72 -> 0.11951289 | P72: =K72 -> 0.093366093 | Q72: =Q13/Q$14 -> 0.13881909 | R72: =M72 -> 0.11516069 | S72: =N72 -> 0.22768556 | T72: =O72 -> 0.11951289 | U72: =P72 -> 0.093366093 | V72: =V13/V$14 -> 0.13591042 | W72: =R72 -> 0.11516069 | X72: =S72 -> 0.22768556 | Y72: =T72 -> 0.11951289 | Z72: =U72 -> 0.093366093 | AA72: =AA13/AA$14 -> 0.13591042 | AB72: =W72 -> 0.11516069 | AC72: =X72 -> 0.22768556 | AD72: =Y72 -> 0.11951289 | AE72: =Z72 -> 0.093366093 | AF72: =AF13/AF$14 -> 0.13591042 | AG72: =AB72 -> 0.11516069 | AH72: =AC72 -> 0.22768556 | AI72: =AD72 -> 0.11951289 | AJ72: =AE72 -> 0.093366093 | AK72: =AK13/AK$14 -> 0.13591042
A73: Total | B73: =B14/B$14 -> 1 | C73: =C14/C$14 -> 1 | D73: =D14/D$14 -> 1 | E73: =E14/E$14 -> 1 | F73: =F14/F$14 -> 1 | G73: =G14/G$14 -> 1 | H73: =H14/H$14 -> 1 | I73: =I14/I$14 -> 1 | ... M73: =M14/M$14 -> 1 | N73: =I73 -> 1 | O73: =J73 -> 1 | P73: =K73 -> 1 | Q73: =Q14/Q$14 -> 1 | R73: =M73 -> 1 | S73: =N73 -> 1 | T73: =O73 -> 1 | U73: =P73 -> 1 | V73: =V14/V$14 -> 1 | W73: =R73 -> 1 | X73: =S73 -> 1 | Y73: =T73 -> 1 | Z73: =U73 -> 1 | AA73: =AA14/AA$14 -> 1 | AB73: =W73 -> 1 | AC73: =X73 -> 1 | AD73: =Y73 -> 1 | AE73: =Z73 -> 1 | AF73: =AF14/AF$14 -> 1 | AG73: =AB73 -> 1 | AH73: =AC73 -> 1 | AI73: =AD73 -> 1 | AJ73: =AE73 -> 1 | AK73: =AK14/AK$14 -> 1
A75: Active Ingredients
A76: SSPs | B76: =B17/B$20 -> 0.38631909 | C76: =C17/C$20 -> 0.54886246 | D76: =D17/D$20 -> 0.53311491 | E76: =E17/E$20 -> 0.48074807 | F76: =F17/F$20 -> 0.51148959 | G76: =G17/G$20 -> 0.5195787 | H76: =H17/H$20 -> 0.51306641 | I76: =I17/I$20 -> 0.45861132 | ... M76: =M17/M$20 -> 0.42397988 | N76: =I76 -> 0.45861132 | O76: =J76 -> 0.43200396 | P76: =K76 -> 0.38921871 | Q76: =Q17/Q$20 -> 0.4267787 | R76: =M76 -> 0.42397988 | S76: =N76 -> 0.45861132 | T76: =O76 -> 0.43200396 | U76: =P76 -> 0.38921871 | V76: =V17/V$20 -> 0.42483876 | W76: =R76 -> 0.42397988 | X76: =S76 -> 0.45861132 | Y76: =T76 -> 0.43200396 | Z76: =U76 -> 0.38921871 | AA76: =AA17/AA$20 -> 0.42483876 | AB76: =W76 -> 0.42397988 | AC76: =X76 -> 0.45861132 | AD76: =Y76 -> 0.43200396 | AE76: =Z76 -> 0.38921871 | AF76: =AF17/AF$20 -> 0.42483876 | AG76: =AB76 -> 0.42397988 | AH76: =AC76 -> 0.45861132 | AI76: =AD76 -> 0.43200396 | AJ76: =AE76 -> 0.38921871 | AK76: =AK17/AK$20 -> 0.42483876
A77: Cephs | B77: =B18/B$20 -> 0.42003136 | C77: =C18/C$20 -> 0.33841779 | D77: =D18/D$20 -> 0.36906155 | E77: =E18/E$20 -> 0.44554455 | F77: =F18/F$20 -> 0.38172479 | G77: =G18/G$20 -> 0.38239855 | H77: =H18/H$20 -> 0.37497003 | I77: =I18/I$20 -> 0.38547072 | ... M77: =M18/M$20 -> 0.38848519 | N77: =I77 -> 0.38547072 | O77: =J77 -> 0.38221452 | P77: =K77 -> 0.3982427 | Q77: =Q18/Q$20 -> 0.38847895 | R77: =M77 -> 0.38848519 | S77: =N77 -> 0.38547072 | T77: =O77 -> 0.38221452 | U77: =P77 -> 0.3982427 | V77: =V18/V$20 -> 0.38887082 | W77: =R77 -> 0.38848519 | X77: =S77 -> 0.38547072 | Y77: =T77 -> 0.38221452 | Z77: =U77 -> 0.3982427 | AA77: =AA18/AA$20 -> 0.38887082 | AB77: =W77 -> 0.38848519 | AC77: =X77 -> 0.38547072 | AD77: =Y77 -> 0.38221452 | AE77: =Z77 -> 0.3982427 | AF77: =AF18/AF$20 -> 0.38887082 | AG77: =AB77 -> 0.38848519 | AH77: =AC77 -> 0.38547072 | AI77: =AD77 -> 0.38221452 | AJ77: =AE77 -> 0.3982427 | AK77: =AK18/AK$20 -> 0.38887082
A78: ARVs & Others | B78: =B19/B$20 -> 0.19364955 | C78: =C19/C$20 -> 0.11271975 | D78: =D19/D$20 -> 0.097823543 | E78: =E19/E$20 -> 0.073707371 | F78: =F19/F$20 -> 0.10678562 | G78: =G19/G$20 -> 0.098022745 | H78: =H19/H$20 -> 0.11196356 | I78: =I19/I$20 -> 0.15591796 | ... M78: =M19/M$20 -> 0.18753494 | N78: =I78 -> 0.15591796 | O78: =J78 -> 0.18578152 | P78: =K78 -> 0.21253859 | Q78: =Q19/Q$20 -> 0.18474234 | R78: =M78 -> 0.18753494 | S78: =N78 -> 0.15591796 | T78: =O78 -> 0.18578152 | U78: =P78 -> 0.21253859 | V78: =V19/V$20 -> 0.18629042 | W78: =R78 -> 0.18753494 | X78: =S78 -> 0.15591796 | Y78: =T78 -> 0.18578152 | Z78: =U78 -> 0.21253859 | AA78: =AA19/AA$20 -> 0.18629042 | AB78: =W78 -> 0.18753494 | AC78: =X78 -> 0.15591796 | AD78: =Y78 -> 0.18578152 | AE78: =Z78 -> 0.21253859 | AF78: =AF19/AF$20 -> 0.18629042 | AG78: =AB78 -> 0.18753494 | AH78: =AC78 -> 0.15591796 | AI78: =AD78 -> 0.18578152 | AJ78: =AE78 -> 0.21253859 | AK78: =AK19/AK$20 -> 0.18629042
A79: Total | B79: =B20/B$20 -> 1 | C79: =C20/C$20 -> 1 | D79: =D20/D$20 -> 1 | E79: =E20/E$20 -> 1 | F79: =F20/F$20 -> 1 | G79: =G20/G$20 -> 1 | H79: =H20/H$20 -> 1 | I79: =I20/I$20 -> 1 | ... M79: =M20/M$20 -> 1 | N79: =I79 -> 1 | O79: =J79 -> 1 | P79: =K79 -> 1 | Q79: =Q20/Q$20 -> 1 | R79: =M79 -> 1 | S79: =N79 -> 1 | T79: =O79 -> 1 | U79: =P79 -> 1 | V79: =V20/V$20 -> 1 | W79: =R79 -> 1 | X79: =S79 -> 1 | Y79: =T79 -> 1 | Z79: =U79 -> 1 | AA79: =AA20/AA$20 -> 1 | AB79: =W79 -> 1 | AC79: =X79 -> 1 | AD79: =Y79 -> 1 | AE79: =Z79 -> 1 | AF79: =AF20/AF$20 -> 1 | AG79: =AB79 -> 1 | AH79: =AC79 -> 1 | AI79: =AD79 -> 1 | AJ79: =AE79 -> 1 | AK79: =AK20/AK$20 -> 1
A82: Formulations | B82: =B23/B$25 -> 0.31979984 | C82: =C23/C$25 -> 0.3170904 | D82: =D23/D$25 -> 0.35937031 | E82: =E23/E$25 -> 0.40412979 | F82: =F23/F$25 -> 0.47813205 | G82: =G23/G$25 -> 0.3936687 | H82: =H23/H$25 -> 0.4098755 | I82: =I23/I$25 -> 0.4410221 | ... M82: =M23/M$25 -> 0.56720011 | N82: =I82+8% -> 0.5210221 | O82: =J82+7% -> 0.53656977 | P82: =K82+4% -> 0.55530847 | Q82: =Q23/Q$25 -> 0.54384271 | R82: =M82+2% -> 0.58720011 | S82: =N82+4% -> 0.5610221 | T82: =O82+3% -> 0.56656977 | U82: =P82+3% -> 0.58530847 | V82: =V23/V$25 -> 0.57535304 | W82: =R82 -> 0.58720011 | X82: =S82 -> 0.5610221 | Y82: =T82 -> 0.56656977 | Z82: =U82 -> 0.58530847 | AA82: =AA23/AA$25 -> 0.57535304 | AB82: =W82 -> 0.58720011 | AC82: =X82 -> 0.5610221 | AD82: =Y82 -> 0.56656977 | AE82: =Z82 -> 0.58530847 | AF82: =AF23/AF$25 -> 0.57535304 | AG82: =AB82 -> 0.58720011 | AH82: =AC82 -> 0.5610221 | AI82: =AD82 -> 0.56656977 | AJ82: =AE82 -> 0.58530847 | AK82: =AK23/AK$25 -> 0.57535304
A83: Active Ingredients | B83: =B24/B$25 -> 0.68020016 | C83: =C24/C$25 -> 0.6829096 | D83: =D24/D$25 -> 0.64062969 | E83: =E24/E$25 -> 0.59587021 | F83: =F24/F$25 -> 0.52186795 | G83: =G24/G$25 -> 0.6063313 | H83: =H24/H$25 -> 0.5901245 | I83: =I24/I$25 -> 0.5589779 | ... M83: =M24/M$25 -> 0.43279989 | N83: =I83-8% -> 0.4789779 | O83: =J83-7% -> 0.46343023 | P83: =K83-4% -> 0.44469153 | Q83: =Q24/Q$25 -> 0.45615729 | R83: =M83-2% -> 0.41279989 | S83: =N83-4% -> 0.4389779 | T83: =O83-3% -> 0.43343023 | U83: =P83-3% -> 0.41469153 | V83: =V24/V$25 -> 0.42464696 | W83: =R83 -> 0.41279989 | X83: =S83 -> 0.4389779 | Y83: =T83 -> 0.43343023 | Z83: =U83 -> 0.41469153 | AA83: =AA24/AA$25 -> 0.42464696 | AB83: =W83 -> 0.41279989 | AC83: =X83 -> 0.4389779 | AD83: =Y83 -> 0.43343023 | AE83: =Z83 -> 0.41469153 | AF83: =AF24/AF$25 -> 0.42464696 | AG83: =AB83 -> 0.41279989 | AH83: =AC83 -> 0.4389779 | AI83: =AD83 -> 0.43343023 | AJ83: =AE83 -> 0.41469153 | AK83: =AK24/AK$25 -> 0.42464696
A84: Total | B84: =B25/B$25 -> 1 | C84: =C25/C$25 -> 1 | D84: =D25/D$25 -> 1 | E84: =E25/E$25 -> 1 | F84: =F25/F$25 -> 1 | G84: =G25/G$25 -> 1 | H84: =H25/H$25 -> 1 | I84: =I25/I$25 -> 1 | ... M84: =M25/M$25 -> 1 | N84: =SUM(N82:N83) -> 1 | O84: =SUM(O82:O83) -> 1 | P84: =SUM(P82:P83) -> 1 | Q84: =SUM(Q82:Q83) -> 1 | R84: =SUM(R82:R83) -> 1 | S84: =SUM(S82:S83) -> 1 | T84: =SUM(T82:T83) -> 1 | U84: =SUM(U82:U83) -> 1 | V84: =V25/V$25 -> 1 | W84: =SUM(W82:W83) -> 1 | X84: =SUM(X82:X83) -> 1 | Y84: =SUM(Y82:Y83) -> 1 | Z84: =SUM(Z82:Z83) -> 1 | AA84: =SUM(AA82:AA83) -> 1 | AB84: =W84 -> 1 | AC84: =X84 -> 1 | AD84: =Y84 -> 1 | AE84: =Z84 -> 1 | AF84: =AF25/AF$25 -> 1 | AG84: =AB84 -> 1 | AH84: =AC84 -> 1 | AI84: =AD84 -> 1 | AJ84: =AE84 -> 1 | AK84: =AK25/AK$25 -> 1
A89: Share of Each Quarter in the Total sales | H89: =H25/$L25 -> 0.23125245 | I89: =I25/$L25 -> 0.23687999 | J89: =J25/$L25 -> 0.24761157 | K89: =K25/$L25 -> 0.28425599 | R89: 0.23125245 | S89: 0.23687999 | T89: 0.24761157 | U89: 0.28425599 | W89: 0.23125245 | X89: 0.23687999 | Y89: 0.24761157 | Z89: 0.28425599 | AB89: 0.23125245 | AC89: 0.23687999 | AD89: 0.24761157 | AE89: 0.28425599 | AG89: 0.23125245 | AH89: 0.23687999 | AI89: 0.24761157 | AJ89: 0.28425599

Sheet Cost Model
A1: Aurobindo Pharma
A2: Cost Model
A4: For the Fiscal Period Ending | B4: FY2006 A | C4: 3 months Jun 30 2006 | D4: 3 months Sep-30-2006 | E4: 3 months Dec-31-2006 | F4: 3 months Mar-31-2007 | G4: FY2007 A | H4: 3 months Jun-30-2007 | I4: 3 months Sep-30-2007 | J4: 3 months Dec-31-2007 | K4: 3 months Mar-31-2008 | L4: FY2008 A | M4: 3 months Jun-30-2008 | N4: 3 months Sep-30-2008 | O4: 3 months Dec-31-2008 | P4: 3 months Mar-31-2009 | Q4: FY2009 A | R4: 3 months Jun-30-2009 | S4: 3 months Sep-30-2009 | T4: 3 months Dec-31-2009 | U4: 3 months Mar-31-2010 | V4: FY2010 E | W4: 3 months Jun-30-2010 | X4: 3 months Sep-30-2010 | Y4: 3 months Dec-31-2010 | Z4: 3 months Mar-31-2011 | AA4: FY2011 E | AB4: 3 months Jun-30-2011 | AC4: 3 months Sep-30-2011 | AD4: 3 months Dec-31-2011 | AE4: 3 months Mar-31-2012 | AF4: FY2012 E | AG4: 3 months Jun-30-2012 | AH4: 3 months Sep-30-2012 | AI4: 3 months Dec-31-2012 | AJ4: 3 months Mar-31-2013 | AK4: FY2013 E | AL4: 3 months Jun-30-2013 | AM4: 3 months Sep-30-2013 | AN4: 3 months Dec-31-2013 | AO4: 3 months Mar-31-2014 | AP4: FY2014 E
A6: Cost Model
A8: As % of Revenues
A10: Excise Duty | B10: ='Profit & Loss Consolidated'!B10/'Profit & Loss Consolidated'!B9 -> 0.060094367 | C10: 0 | D10: 0 | E10: 0 | F10: ='Profit & Loss Consolidated'!F10/'Profit & Loss Consolidated'!F9 -> 0.051327749 | G10: ='Profit & Loss Consolidated'!G10/'Profit & Loss Consolidated'!G9 -> 0.056572246 | H10: ='Profit & Loss Consolidated'!H10/'Profit & Loss Consolidated'!H9 -> 0.060200551 | I10: ='Profit & Loss Consolidated'!I10/'Profit & Loss Consolidated'!I9 -> 0.057844548 | J10: ='Profit & Loss Consolidated'!J10/'Profit & Loss Consolidated'!J9 -> 0.066585818 | K10: ='Profit & Loss Consolidated'!K10/'Profit & Loss Consolidated'!K9 -> 0.0043459856 | L10: ='Profit & Loss Consolidated'!L10/'Profit & Loss Consolidated'!L9 -> 0.045602185 | M10: ='Profit & Loss Consolidated'!M10/'Profit & Loss Consolidated'!M9 -> 0.03838481 | ... R10: ='Profit & Loss Consolidated'!R10/'Profit & Loss Consolidated'!R9 -> 0.020636015 | S10: =N10 -> 0.031741515 | T10: =O10 -> 0.028634478 | U10: =P10 -> 0.021615276 | V10: ='Profit & Loss Consolidated'!V10/'Profit & Loss Consolidated'!V9 -> 0.025924537 | W10: =R10 -> 0.020636015 | X10: =S10 -> 0.031741515 | Y10: =T10 -> 0.028634478 | Z10: =U10 -> 0.021615276 | AA10: ='Profit & Loss Consolidated'!AA10/'Profit & Loss Consolidated'!AA9 -> 0.025525558 | AB10: =W10 -> 0.020636015 | AC10: =X10 -> 0.031741515 | AD10: =Y10 -> 0.028634478 | AE10: =Z10 -> 0.021615276 | AF10: ='Profit & Loss Consolidated'!AF10/'Profit & Loss Consolidated'!AF9 -> 0.025525558 | AG10: =AB10 -> 0.020636015 | AH10: =AC10 -> 0.031741515 | AI10: =AD10 -> 0.028634478 | AJ10: =AE10 -> 0.021615276 | AK10: ='Profit & Loss Consolidated'!AK10/'Profit & Loss Consolidated'!AK9 -> 0.025525558 | AL10: =AG10 -> 0.020636015 | AM10: =AH10 -> 0.031741515 | AN10: =AI10 -> 0.028634478 | AO10: =AJ10 -> 0.021615276 | AP10: ='Profit & Loss Consolidated'!AP10/'Profit & Loss Consolidated'!AP9 -> 0.025525558
A11: Other Operating Income | F11: ='Profit & Loss Consolidated'!F12/'Profit & Loss Consolidated'!F13 -> 0.0061613144 | G11: ='Profit & Loss Consolidated'!G12/'Profit & Loss Consolidated'!G13 -> 0 | H11: ='Profit & Loss Consolidated'!H12/'Profit & Loss Consolidated'!H13 -> 0 | I11: ='Profit & Loss Consolidated'!I12/'Profit & Loss Consolidated'!I13 -> 0.0028879721 | J11: ='Profit & Loss Consolidated'!J12/'Profit & Loss Consolidated'!J13 -> 0 | K11: ='Profit & Loss Consolidated'!K12/'Profit & Loss Consolidated'!K13 -> 0 | L11: ='Profit & Loss Consolidated'!L12/'Profit & Loss Consolidated'!L13 -> 0 | M11: ='Profit & Loss Consolidated'!M12/'Profit & Loss Consolidated'!M13 -> 0.0052397401 | ... R11: ='Profit & Loss Consolidated'!R12/'Profit & Loss Consolidated'!R13 -> 0.050542363 | S11: =R11 -> 0.050542363 | T11: =S11 -> 0.050542363 | U11: =T11 -> 0.050542363 | V11: ='Profit & Loss Consolidated'!V12/'Profit & Loss Consolidated'!V13 -> 0.049089348 | W11: =R11 -> 0.050542363 | X11: =S11 -> 0.050542363 | Y11: =T11 -> 0.050542363 | Z11: =U11 -> 0.050542363 | AA11: ='Profit & Loss Consolidated'!AA12/'Profit & Loss Consolidated'!AA13 -> 0.039952215 | AB11: =W11 -> 0.050542363 | AC11: =X11 -> 0.050542363 | AD11: =Y11 -> 0.050542363 | AE11: =Z11 -> 0.050542363 | AF11: ='Profit & Loss Consolidated'!AF12/'Profit & Loss Consolidated'!AF13 -> 0.032470614 | AG11: =AB11 -> 0.050542363 | AH11: =AC11 -> 0.050542363 | AI11: =AD11 -> 0.050542363 | AJ11: =AE11 -> 0.050542363 | AK11: ='Profit & Loss Consolidated'!AK12/'Profit & Loss Consolidated'!AK13 -> 0.026772017 | AL11: =AG11 -> 0.050542363 | AM11: =AH11 -> 0.050542363 | AN11: =AI11 -> 0.050542363 | AO11: =AJ11 -> 0.050542363 | AP11: ='Profit & Loss Consolidated'!AP12/'Profit & Loss Consolidated'!AP13 -> 0.022410008
A12: (Increase) / Decrease in Stocks | B12: ='Profit & Loss Consolidated'!B16/'Profit & Loss Consolidated'!B9 -> -0.030569154 | C12: ='Profit & Loss Consolidated'!C16/'Profit & Loss Consolidated'!C11 -> -0.10149124 | D12: ='Profit & Loss Consolidated'!D16/'Profit & Loss Consolidated'!D11 -> 0.017583333 | E12: ='Profit & Loss Consolidated'!E16/'Profit & Loss Consolidated'!E11 -> -0.042183952 | F12: ='Profit & Loss Consolidated'!F16/'Profit & Loss Consolidated'!F9 -> -0.078417394 | G12: ='Profit & Loss Consolidated'!G16/'Profit & Loss Consolidated'!G9 -> -0.039573908 | H12: ='Profit & Loss Consolidated'!H16/'Profit & Loss Consolidated'!H9 -> -0.077607514 | I12: ='Profit & Loss Consolidated'!I16/'Profit & Loss Consolidated'!I9 -> -0.049088401 | J12: ='Profit & Loss Consolidated'!J16/'Profit & Loss Consolidated'!J9 -> -0.071043445 | K12: ='Profit & Loss Consolidated'!K16/'Profit & Loss Consolidated'!K9 -> 0.068872584 | L12: ='Profit & Loss Consolidated'!L16/'Profit & Loss Consolidated'!L9 -> -0.027912189 | M12: ='Profit & Loss Consolidated'!M16/'Profit & Loss Consolidated'!M9 -> -0.014106029 | ... R12: ='Profit & Loss Consolidated'!R16/'Profit & Loss Consolidated'!R9 -> -0.012313871 | S12: =N12 -> -0.080210174 | T12: =O12 -> -0.022582521 | U12: =P12 -> 0.07413418 | V12: ='Profit & Loss Consolidated'!V16/'Profit & Loss Consolidated'!V9 -> -0.01013268 | W12: =R12 -> -0.012313871 | X12: =S12 -> -0.080210174 | Y12: =T12 -> -0.022582521 | Z12: =U12 -> 0.07413418 | AA12: ='Profit & Loss Consolidated'!AA16/'Profit & Loss Consolidated'!AA9 -> -0.0063664066 | AB12: =W12 -> -0.012313871 | AC12: =X12 -> -0.080210174 | AD12: =Y12 -> -0.022582521 | AE12: =Z12 -> 0.07413418 | AF12: ='Profit & Loss Consolidated'!AF16/'Profit & Loss Consolidated'!AF9 -> -0.0063664066 | AG12: =AB12 -> -0.012313871 | AH12: =AC12 -> -0.080210174 | AI12: =AD12 -> -0.022582521 | AJ12: =AE12 -> 0.07413418 | AK12: ='Profit & Loss Consolidated'!AK16/'Profit & Loss Consolidated'!AK9 -> -0.0063664066 | AL12: =AG12 -> -0.012313871 | AM12: =AH12 -> -0.080210174 | AN12: =AI12 -> -0.022582521 | AO12: =AJ12 -> 0.07413418 | AP12: ='Profit & Loss Consolidated'!AP16/'Profit & Loss Consolidated'!AP9 -> -0.0063664066
A13: Material Consumed | B13: ='Profit & Loss Consolidated'!B17/'Profit & Loss Consolidated'!B9 -> 0.53944559 | C13: ='Profit & Loss Consolidated'!C17/'Profit & Loss Consolidated'!C11 -> 0.66608902 | D13: ='Profit & Loss Consolidated'!D17/'Profit & Loss Consolidated'!D11 -> 0.52952083 | E13: ='Profit & Loss Consolidated'!E17/'Profit & Loss Consolidated'!E11 -> 0.62161241 | F13: ='Profit & Loss Consolidated'!F17/'Profit & Loss Consolidated'!F9 -> 0.54125824 | G13: ='Profit & Loss Consolidated'!G17/'Profit & Loss Consolidated'!G9 -> 0.52242447 | H13: ='Profit & Loss Consolidated'!H17/'Profit & Loss Consolidated'!H9 -> 0.53613798 | I13: ='Profit & Loss Consolidated'!I17/'Profit & Loss Consolidated'!I9 -> 0.49617668 | J13: ='Profit & Loss Consolidated'!J17/'Profit & Loss Consolidated'!J9 -> 0.48750389 | K13: ='Profit & Loss Consolidated'!K17/'Profit & Loss Consolidated'!K9 -> 0.46434316 | L13: ='Profit & Loss Consolidated'!L17/'Profit & Loss Consolidated'!L9 -> 0.49413272 | M13: ='Profit & Loss Consolidated'!M17/'Profit & Loss Consolidated'!M9 -> 0.50544009 | ... R13: ='Profit & Loss Consolidated'!R17/'Profit & Loss Consolidated'!R9 -> 0.4854302 | S13: =N13 -> 0.55181616 | T13: =O13 -> 0.56573905 | U13: =P13 -> 0.42012822 | V13: ='Profit & Loss Consolidated'!V17/'Profit & Loss Consolidated'!V9 -> 0.5068634 | W13: =R13 -> 0.4854302 | X13: =S13 -> 0.55181616 | Y13: =T13 -> 0.56573905 | Z13: =U13 -> 0.42012822 | AA13: ='Profit & Loss Consolidated'!AA17/'Profit & Loss Consolidated'!AA9 -> 0.50247863 | AB13: =W13 -> 0.4854302 | AC13: =X13 -> 0.55181616 | AD13: =Y13 -> 0.56573905 | AE13: =Z13 -> 0.42012822 | AF13: ='Profit & Loss Consolidated'!AF17/'Profit & Loss Consolidated'!AF9 -> 0.50247863 | AG13: =AB13 -> 0.4854302 | AH13: =AC13 -> 0.55181616 | AI13: =AD13 -> 0.56573905 | AJ13: =AE13 -> 0.42012822 | AK13: ='Profit & Loss Consolidated'!AK17/'Profit & Loss Consolidated'!AK9 -> 0.50247863 | AL13: =AG13 -> 0.4854302 | AM13: =AH13 -> 0.55181616 | AN13: =AI13 -> 0.56573905 | AO13: =AJ13 -> 0.42012822 | AP13: ='Profit & Loss Consolidated'!AP17/'Profit & Loss Consolidated'!AP9 -> 0.50247863
A14: Purchase of traded goods | B14: ='Profit & Loss Consolidated'!B18/'Profit & Loss Consolidated'!B9 -> 0.053583014 | C14: 0 | D14: 0 | E14: 0 | F14: ='Profit & Loss Consolidated'!F18/'Profit & Loss Consolidated'!F9 -> 0.058813046 | G14: ='Profit & Loss Consolidated'!G18/'Profit & Loss Consolidated'!G9 -> 0.060043018 | H14: ='Profit & Loss Consolidated'!H18/'Profit & Loss Consolidated'!H9 -> 0.058293906 | I14: ='Profit & Loss Consolidated'!I18/'Profit & Loss Consolidated'!I9 -> 0.067860142 | J14: ='Profit & Loss Consolidated'!J18/'Profit & Loss Consolidated'!J9 -> 0.07997509 | K14: ='Profit & Loss Consolidated'!K18/'Profit & Loss Consolidated'!K9 -> 0.048525469 | L14: ='Profit & Loss Consolidated'!L18/'Profit & Loss Consolidated'!L9 -> 0.063264754 | M14: ='Profit & Loss Consolidated'!M18/'Profit & Loss Consolidated'!M9 -> 0.030617298 | ... R14: ='Profit & Loss Consolidated'!R18/'Profit & Loss Consolidated'!R9 -> 0.036590824 | S14: =N14 -> 0.02768059 | T14: =O14 -> 0.020798647 | U14: =P14 -> 0.048041619 | V14: ='Profit & Loss Consolidated'!V18/'Profit & Loss Consolidated'!V9 -> 0.033101271 | W14: =R14 -> 0.036590824 | X14: =S14 -> 0.02768059 | Y14: =T14 -> 0.020798647 | Z14: =U14 -> 0.048041619 | AA14: ='Profit & Loss Consolidated'!AA18/'Profit & Loss Consolidated'!AA9 -> 0.033824799 | AB14: =W14 -> 0.036590824 | AC14: =X14 -> 0.02768059 | AD14: =Y14 -> 0.020798647 | AE14: =Z14 -> 0.048041619 | AF14: ='Profit & Loss Consolidated'!AF18/'Profit & Loss Consolidated'!AF9 -> 0.033824799 | AG14: =AB14 -> 0.036590824 | AH14: =AC14 -> 0.02768059 | AI14: =AD14 -> 0.020798647 | AJ14: =AE14 -> 0.048041619 | AK14: ='Profit & Loss Consolidated'!AK18/'Profit & Loss Consolidated'!AK9 -> 0.033824799 | AL14: =AG14 -> 0.036590824 | AM14: =AH14 -> 0.02768059 | AN14: =AI14 -> 0.020798647 | AO14: =AJ14 -> 0.048041619 | AP14: ='Profit & Loss Consolidated'!AP18/'Profit & Loss Consolidated'!AP9 -> 0.033824799
A15: Staff Cost | B15: ='Profit & Loss Consolidated'!B19/'Profit & Loss Consolidated'!B9 -> 0.06040696 | C15: ='Profit & Loss Consolidated'!C19/'Profit & Loss Consolidated'!C11 -> 0.058828895 | D15: ='Profit & Loss Consolidated'!D19/'Profit & Loss Consolidated'!D11 -> 0.060020833 | E15: ='Profit & Loss Consolidated'!E19/'Profit & Loss Consolidated'!E11 -> 0.049716124 | F15: ='Profit & Loss Consolidated'!F19/'Profit & Loss Consolidated'!F9 -> 0.078773837 | G15: ='Profit & Loss Consolidated'!G19/'Profit & Loss Consolidated'!G9 -> 0.066846797 | H15: ='Profit & Loss Consolidated'!H19/'Profit & Loss Consolidated'!H9 -> 0.078084175 | I15: ='Profit & Loss Consolidated'!I19/'Profit & Loss Consolidated'!I9 -> 0.073902483 | J15: ='Profit & Loss Consolidated'!J19/'Profit & Loss Consolidated'!J9 -> 0.081597535 | K15: ='Profit & Loss Consolidated'!K19/'Profit & Loss Consolidated'!K9 -> 0.070114294 | L15: ='Profit & Loss Consolidated'!L19/'Profit & Loss Consolidated'!L9 -> 0.075618366 | M15: ='Profit & Loss Consolidated'!M19/'Profit & Loss Consolidated'!M9 -> 0.081169796 | ... R15: ='Profit & Loss Consolidated'!R19/'Profit & Loss Consolidated'!R9 -> 0.083535944 | S15: =N15 -> 0.081439501 | T15: =O15 -> 0.086365919 | U15: =P15 -> 0.071107121 | V15: ='Profit & Loss Consolidated'!V19/'Profit & Loss Consolidated'!V9 -> 0.080456219 | W15: =R15 -> 0.083535944 | X15: =S15 -> 0.081439501 | Y15: =T15 -> 0.086365919 | Z15: =U15 -> 0.071107121 | AA15: ='Profit & Loss Consolidated'!AA19/'Profit & Loss Consolidated'!AA9 -> 0.080207106 | AB15: =W15 -> 0.083535944 | AC15: =X15 -> 0.081439501 | AD15: =Y15 -> 0.086365919 | AE15: =Z15 -> 0.071107121 | AF15: ='Profit & Loss Consolidated'!AF19/'Profit & Loss Consolidated'!AF9 -> 0.080207106 | AG15: =AB15 -> 0.083535944 | AH15: =AC15 -> 0.081439501 | AI15: =AD15 -> 0.086365919 | AJ15: =AE15 -> 0.071107121 | AK15: ='Profit & Loss Consolidated'!AK19/'Profit & Loss Consolidated'!AK9 -> 0.080207106 | AL15: =AG15 -> 0.083535944 | AM15: =AH15 -> 0.081439501 | AN15: =AI15 -> 0.086365919 | AO15: =AJ15 -> 0.071107121 | AP15: ='Profit & Loss Consolidated'!AP19/'Profit & Loss Consolidated'!AP9 -> 0.080207106
A16: Depreciation / Amortization | B16: ='Profit & Loss Consolidated'!B20/'Profit & Loss Consolidated'!B9 -> 0.042542023 | C16: ='Profit & Loss Consolidated'!C20/'Profit & Loss Consolidated'!C11 -> 0.032561109 | D16: ='Profit & Loss Consolidated'!D20/'Profit & Loss Consolidated'!D11 -> 0.031229167 | E16: ='Profit & Loss Consolidated'!E20/'Profit & Loss Consolidated'!E11 -> 0.030828917 | F16: ='Profit & Loss Consolidated'!F20/'Profit & Loss Consolidated'!F9 -> 0.041703796 | G16: ='Profit & Loss Consolidated'!G20/'Profit & Loss Consolidated'!G9 -> 0.044315667 | H16: ='Profit & Loss Consolidated'!H20/'Profit & Loss Consolidated'!H9 -> 0.041222371 | I16: ='Profit & Loss Consolidated'!I20/'Profit & Loss Consolidated'!I9 -> 0.03740854 | J16: ='Profit & Loss Consolidated'!J20/'Profit & Loss Consolidated'!J9 -> 0.041954145 | K16: ='Profit & Loss Consolidated'!K20/'Profit & Loss Consolidated'!K9 -> 0.037364188 | L16: ='Profit & Loss Consolidated'!L20/'Profit & Loss Consolidated'!L9 -> 0.039329387 | M16: ='Profit & Loss Consolidated'!M20/'Profit & Loss Consolidated'!M9 -> 0.038257474 | ... R16: ='Profit & Loss Consolidated'!R20/'Profit & Loss Consolidated'!R9 -> 0.040231762 | V16: ='Profit & Loss Consolidated'!V20/'Profit & Loss Consolidated'!V9 -> 0.030732715 | AA16: ='Profit & Loss Consolidated'!AA20/'Profit & Loss Consolidated'!AA9 -> 0.027794222 | AF16: ='Profit & Loss Consolidated'!AF20/'Profit & Loss Consolidated'!AF9 -> 0.025218534 | AK16: ='Profit & Loss Consolidated'!AK20/'Profit & Loss Consolidated'!AK9 -> 0.023326643 | AP16: ='Profit & Loss Consolidated'!AP20/'Profit & Loss Consolidated'!AP9 -> 0.022223136
A17: Other Expenditure | B17: ='Profit & Loss Consolidated'!B21/'Profit & Loss Consolidated'!B9 -> 0.21235624 | C17: ='Profit & Loss Consolidated'!C21/'Profit & Loss Consolidated'!C11 -> 0.22635443 | D17: ='Profit & Loss Consolidated'!D21/'Profit & Loss Consolidated'!D11 -> 0.2489375 | E17: ='Profit & Loss Consolidated'!E21/'Profit & Loss Consolidated'!E11 -> 0.22235049 | F17: ='Profit & Loss Consolidated'!F21/'Profit & Loss Consolidated'!F9 -> 0.22438068 | G17: ='Profit & Loss Consolidated'!G21/'Profit & Loss Consolidated'!G9 -> 0.19939384 | H17: ='Profit & Loss Consolidated'!H21/'Profit & Loss Consolidated'!H9 -> 0.22221241 | I17: ='Profit & Loss Consolidated'!I21/'Profit & Loss Consolidated'!I9 -> 0.21329615 | J17: ='Profit & Loss Consolidated'!J21/'Profit & Loss Consolidated'!J9 -> 0.2262574 | K17: ='Profit & Loss Consolidated'!K21/'Profit & Loss Consolidated'!K9 -> 0.20342881 | L17: ='Profit & Loss Consolidated'!L21/'Profit & Loss Consolidated'!L9 -> 0.2156338 | M17: ='Profit & Loss Consolidated'!M21/'Profit & Loss Consolidated'!M9 -> 0.20157331 | ... R17: ='Profit & Loss Consolidated'!R21/'Profit & Loss Consolidated'!R9 -> 0.20153379 | S17: =N17 -> 0.22667972 | T17: =O17 -> 0.22845477 | U17: =P17 -> 0.22997594 | V17: ='Profit & Loss Consolidated'!V21/'Profit & Loss Consolidated'!V9 -> 0.22273427 | W17: =R17 -> 0.20153379 | X17: =S17 -> 0.22667972 | Y17: =T17 -> 0.22845477 | Z17: =U17 -> 0.22997594 | AA17: ='Profit & Loss Consolidated'!AA21/'Profit & Loss Consolidated'!AA9 -> 0.22224116 | AB17: =W17 -> 0.20153379 | AC17: =X17 -> 0.22667972 | AD17: =Y17 -> 0.22845477 | AE17: =Z17 -> 0.22997594 | AF17: ='Profit & Loss Consolidated'!AF21/'Profit & Loss Consolidated'!AF9 -> 0.22224116 | AG17: =AB17 -> 0.20153379 | AH17: =AC17 -> 0.22667972 | AI17: =AD17 -> 0.22845477 | AJ17: =AE17 -> 0.22997594 | AK17: ='Profit & Loss Consolidated'!AK21/'Profit & Loss Consolidated'!AK9 -> 0.22224116 | AL17: =AG17 -> 0.20153379 | AM17: =AH17 -> 0.22667972 | AN17: =AI17 -> 0.22845477 | AO17: =AJ17 -> 0.22997594 | AP17: ='Profit & Loss Consolidated'!AP21/'Profit & Loss Consolidated'!AP9 -> 0.22224116
A20: Total Tax / Profit Before Tax | B20: ='Profit & Loss Consolidated'!B42/'Profit & Loss Consolidated'!B32 -> 0.27807107 | C20: ='Profit & Loss Consolidated'!C42/'Profit & Loss Consolidated'!C32 -> 0.28467009 | D20: ='Profit & Loss Consolidated'!D42/'Profit & Loss Consolidated'!D32 -> 0.097754293 | E20: ='Profit & Loss Consolidated'!E42/'Profit & Loss Consolidated'!E32 -> 0.12667054 | F20: ='Profit & Loss Consolidated'!F42/'Profit & Loss Consolidated'!F32 -> 0.10144928 | G20: ='Profit & Loss Consolidated'!G42/'Profit & Loss Consolidated'!G32 -> 0.021170429 | H20: ='Profit & Loss Consolidated'!H42/'Profit & Loss Consolidated'!H32 -> 0.10153534 | I20: ='Profit & Loss Consolidated'!I42/'Profit & Loss Consolidated'!I32 -> 0.25650203 | ... R20: ='Profit & Loss Consolidated'!R42/'Profit & Loss Consolidated'!R32 -> 0.16578961 | S20: 0.13 | T20: 0.13 | U20: 0.13 | V20: ='Profit & Loss Consolidated'!V42/'Profit & Loss Consolidated'!V32 -> 0.14304667 | W20: =U20 -> 0.13 | X20: =W20 -> 0.13 | Y20: =X20 -> 0.13 | Z20: =Y20 -> 0.13 | AA20: ='Profit & Loss Consolidated'!AA42/'Profit & Loss Consolidated'!AA32 -> 0.1247326 | AB20: =W20 -> 0.13 | AC20: =X20 -> 0.13 | AD20: =Y20 -> 0.13 | AE20: =Z20 -> 0.13 | AF20: ='Profit & Loss Consolidated'!AF42/'Profit & Loss Consolidated'!AF32 -> 0.13 | AG20: =AB20 -> 0.13 | AH20: =AC20 -> 0.13 | AI20: =AD20 -> 0.13 | AJ20: =AE20 -> 0.13 | AK20: ='Profit & Loss Consolidated'!AK42/'Profit & Loss Consolidated'!AK32 -> 0.13 | AL20: =AG20 -> 0.13 | AM20: =AH20 -> 0.13 | AN20: =AI20 -> 0.13 | AO20: =AJ20 -> 0.13 | AP20: ='Profit & Loss Consolidated'!AP42/'Profit & Loss Consolidated'!AP32 -> 0.13

Sheet Debt Schedule
A1: Aurobindo Pharma
A2: Debt Schedule
A3: (In Rs Millions)
A4: For the Fiscal Period Ending | B4: FY2005 A | C4: FY2006 A | D4: FY2007 A | E4: FY2008 A | F4: FY2009 E | G4: FY2010 E | H4: FY2011 E | I4: FY2012 E | J4: FY2013 E | K4: FY2014 E
A5: Debt Schedule
A7: (I) Secured Loans
A8: Non Convertible Debentures | B8: 750.7 | C8: 0 | D8: 0 | E8: 0 | F8: 0 | G8: 0 | H8: 0 | I8: 0 | J8: 0 | K8: 0
A9: Term Loans -From Banks | B9: 4072.6 | C9: 4183.1 | D9: 2028.5 | E9: 996.8 | F9: =E9+F43 -> 996.8 | G9: =F9+G43 -> 996.8 | H9: =G9+H43 -> 2996.8 | I9: =H9+I43 -> 7996.8 | J9: =I9+J43 -> 7996.8 | K9: =J9+K43 -> 7996.8
A10: Other Loans:-
A11: From Banks - Working Capital Loans | B11: 2726 | C11: 3316.5 | D11: 5360.2 | E11: 5336.3 | F11: =E11 -> 5336.3 | G11: =F11 -> 5336.3 | H11: =G11 -> 5336.3 | I11: =H11 -> 5336.3 | J11: =I11 -> 5336.3 | K11: =J11 -> 5336.3
A12: Interest Accrued | B12: 1.6 | C12: 2.4 | D12: 0.8 | E12: 0 | F12: =E12 -> 0 | G12: =F12 -> 0 | H12: =G12 -> 0 | I12: =H12 -> 0 | J12: =I12 -> 0 | K12: =J12 -> 0
A13: Hire Purchase Loans From Banks | B13: 0.7 | C13: 0.5 | D13: 1.2 | E13: 1.2 | F13: =E13 -> 1.2 | G13: =F13 -> 1.2 | H13: =G13 -> 1.2 | I13: =H13 -> 1.2 | J13: =I13 -> 1.2 | K13: =J13 -> 1.2
A14: Total | B14: =SUM(B8:B13) -> 7551.6 | C14: =SUM(C8:C13) -> 7502.5 | D14: =SUM(D9:D13) -> 7390.7 | E14: =SUM(E9:E13) -> 6334.3 | F14: =SUM(F8:F13) -> 6334.3 | G14: =SUM(G8:G13) -> 6334.3 | H14: =SUM(H8:H13) -> 8334.3 | I14: =SUM(I8:I13) -> 13334.3 | J14: =SUM(J8:J13) -> 13334.3 | K14: =SUM(K8:K13) -> 13334.3
A16: (II) Unsecured Loans
A17: Short Term Loans - From Banks | B17: 1350.8 | C17: 2175 | D17: 900 | E17: 771.8 | F17: =E17 -> 771.8 | G17: =F17 -> 771.8 | H17: =G17 -> 771.8 | I17: =H17 -> 771.8 | J17: =I17 -> 771.8 | K17: =J17 -> 771.8
A18: Other Loans:-
A19: From Banks | B19: 330 | C19: 329.7 | D19: 158.9 | E19: 23.5 | F19: =E19+(E21-F21) -> 368.6304 | G19: =F19 -> 368.6304 | H19: =G19 -> 368.6304 | I19: =H19 -> 368.6304 | J19: =I19 -> 368.6304 | K19: =J19 -> 368.6304
A20: Interest Accrued and Due | B20: 5.7 | C20: 11.2 | D20: 18 | E20: 25.5 | F20: =E20 -> 25.5 | G20: =F20 -> 25.5 | H20: =G20 -> 25.5 | I20: =H20 -> 25.5 | J20: =I20 -> 25.5 | K20: =J20 -> 25.5
A21: Zero Coupon FCCBS | B21: 0 | C21: 2677.2 | D21: 11299.6 | E21: =E45 -> 10245.6 | F21: =F46*F47+SUM(F40:F42) -> 9900.4696 | G21: =(F46*F47)+SUM(G40:G42)+G48 -> 8965.2 | H21: =(G46*G47)+SUM(H40:H42)+H48 -> 6403.2 | I21: =(H46*H47)+SUM(I40:I42)+I48 -> 0 | J21: =I45+SUM(J40:J42)+J48 -> 0 | K21: =J45+SUM(K40:K42)+K48 -> 0
A22: From Others | B22: 297.2 | C22: 87.3 | D22: 99.6 | E22: 121 | F22: =E22 -> 121 | G22: =F22 -> 121 | H22: =G22 -> 121 | I22: =H22 -> 121 | J22: =I22 -> 121 | K22: =J22 -> 121
A23: Sales Tax Deferment Loan | B23: 805 | C23: 947.8 | D23: 914.6 | E23: 948.5 | F23: =E23 -> 948.5 | G23: =F23 -> 948.5 | H23: =G23 -> 948.5 | I23: =H23 -> 948.5 | J23: =I23 -> 948.5 | K23: =J23 -> 948.5
A24: Total | B24: =SUM(B17:B23) -> 2788.7 | C24: =SUM(C17:C23) -> 6228.2 | D24: =SUM(D17:D23) -> 13390.7 | E24: =SUM(E17:E23) -> 12135.9 | F24: =SUM(F17:F23) -> 12135.9 | G24: =SUM(G17:G23) -> 11200.63 | H24: =SUM(H17:H23) -> 8638.6304 | I24: =SUM(I17:I23) -> 2235.4304 | ... K24: =SUM(K17:K23) -> 2235.4304
A26: Total Loans | B26: =B14+B24 -> 10340.3 | C26: =C14+C24 -> 13730.7 | D26: =D14+D24 -> 20781.4 | E26: =E14+E24 -> 18470.2 | F26: =F14+F24 -> 18470.2 | G26: =G14+G24 -> 17534.93 | H26: =H14+H24 -> 16972.93 | I26: =I14+I24 -> 15569.73 | ... K26: =K14+K24 -> 15569.73
A27: Total Loans: Less FCCB | B27: =B26-B21 -> 10340.3 | C27: =C26-C21 -> 11053.5 | D27: =D26-D21 -> 9481.8 | E27: =E26-E21 -> 8224.6 | F27: =F26-F21 -> 8569.7304 | G27: =G26-G21 -> 8569.7304 | H27: =H26-H21 -> 10569.73 | I27: =I26-I21 -> 15569.73 | ... K27: =K26-K21 -> 15569.73
A29: Interest Income, Net
A31: Interest Income | B31: 17.2 | C31: 86.9 | D31: 410.9 | E31: 261.8 | F31: =E54*F55 -> 187.5002 | G31: =F54*G55 -> 120.20429 | H31: =G54*H55 -> 80.553685 | I31: =H54*I55 -> 166.97167 | J31: =I54*J55 -> 73.886694 | K31: =J54*K55 -> 118.06614
A32: Interest Expense | B32: 499.2 | C32: 691 | D32: 864.5 | E32: 694.2 | F32: =F33+F31 -> 998.4002 | G32: =G27*G36 -> 998.4002 | H32: =H27*H36 -> 1231.4064 | I32: =I27*I36 -> 1813.9219 | J32: =J27*J36 -> 1813.9219 | K32: =K27*K36 -> 1813.9219
A33: Interest Expense, Net | B33: =-(B31-B32) -> 482 | C33: =-(C31-C32) -> 604.1 | D33: =-(D31-D32) -> 453.6 | E33: =-(E31-E32) -> 432.4 | F33: 810.9 | G33: =-(G31-G32) -> 878.19591 | H33: =-(H31-H32) -> 1150.8527 | I33: =-(I31-I32) -> 1646.9503 | J33: =-(J31-J32) -> 1740.0352 | K33: =-(K31-K32) -> 1695.8558
A35: Interest Expense Rate (Total Loans) | B35: =B32/B26 -> 0.048277129 | C35: =C32/C26 -> 0.050325184 | D35: =D32/D26 -> 0.0415997 | E35: =E32/E26 -> 0.037584866
A36: Interest Expense Rate (Total Loans: Less FCCB) | B36: =B32/B27 -> 0.048277129 | C36: =C32/C27 -> 0.062514136 | D36: =D32/D27 -> 0.091174671 | E36: =E32/E27 -> 0.084405321 | F36: =F32/F27 -> 0.11650311 | G36: =$F$36 -> 0.11650311 | H36: =$F$36 -> 0.11650311 | I36: =$F$36 -> 0.11650311 | J36: =$F$36 -> 0.11650311 | K36: =$F$36 -> 0.11650311
A38: Additional Borrowing / (Repayment)
A40: FCCB's Due in Aug 2010 | B40: 0 | C40: 0 | D40: 0 | E40: 0 | F40: 0 | G40: 0 | H40: =-(G46-H46)*G47 -> -2492.4 | J40: 0 | K40: 0
A41: FCCB's Due in May 2011 -Tranche A Bonds | B41: 0 | C41: 0 | D41: 0 | E41: 0 | F41: 0 | G41: =-(F46-G46)*F47 -> -91.5768 | H41: 0 | I41: =-((B63*1000)/1000000)*H47 -> -4885.2 | J41: 0 | K41: 0
A42: FCCB's Due in May 2011 -Tranche B Bonds | B42: 0 | C42: 0 | D42: 0 | E42: 0 | F42: 0 | G42: 0 | H42: 0 | I42: =-((B64*1000)/1000000)*H47 -> -1518 | J42: 0 | K42: 0
A43: Term Loans -From Banks | B43: 0 | C43: 0 | D43: 0 | E43: 0 | F43: 0 | G43: 0 | H43: 2000 | I43: 5000 | J43: 0 | K43: 0
A45: Outstanding FCCB's at Year End (in Rs Million ) | B45: 0 | C45: 0 | D45: 0 | E45: 10245.6 | F45: =F46*F47 -> 9900.4696 | G45: =G46*G47 -> 8965.2 | H45: =H46*H47 -> 6403.2 | I45: =I46*I47 -> 0 | J45: 0 | K45: 0
A46: Outstanding FCCB's at Year End (in Million USD) | B46: 0 | C46: 0 | D46: 0 | E46: 255.5 | F46: 194.6 | G46: =(B66*1000)/1000000 -> 192.8 | H46: =G46-((B62*1000)/1000000) -> 139.2 | I46: =H46-(SUM(B63:B64)*1000/1000000) -> 0 | J46: 0 | K46: 0
A47: USD/INR (At Balance sheet date i.e 31 March ) | B47: 0 | C47: 0 | D47: 0 | E47: 40.1002 | F47: 50.876 | G47: 46.5 | H47: 46 | I47: 45.5 | J47: 0 | K47: 0
A48: Forex (Gain) / Loss on restating of FCCB's | G48: =(G47-F47)*G46 -> -843.6928 | H48: =(H47-G47)*H46 -> -69.6
A50: Interest Income Calculation
A52: Cash and Cash Equivalent | B52: 593.9 | C52: ='Balance Sheet'!B42 -> 2019.3 | D52: ='Balance Sheet'!C42 -> 5824.6 | E52: ='Balance Sheet'!D42 -> 2825.7 | F52: ='Balance Sheet'!E42 -> 1594.6348 | G52: ='Balance Sheet'!F42 -> 869.29382 | H52: ='Balance Sheet'!G42 -> 2450.1652 | I52: ='Balance Sheet'!H42 -> 747.33248 | J52: ='Balance Sheet'!I42 -> 1555.521 | K52: ='Balance Sheet'!J42 -> 2886.5104
A53: Investments | B53: 2.4 | C53: ='Balance Sheet'!B34 -> 2.8 | D53: ='Balance Sheet'!C34 -> 2.7 | E53: ='Balance Sheet'!D34 -> 604.3 | F53: ='Balance Sheet'!E34 -> 604.3 | G53: ='Balance Sheet'!F34 -> 604.3 | H53: ='Balance Sheet'!G34 -> 604.3 | I53: ='Balance Sheet'!H34 -> 604.3 | J53: ='Balance Sheet'!I34 -> 604.3 | K53: ='Balance Sheet'!J34 -> 604.3
A54: Total | B54: =SUM(B52:B53) -> 596.3 | C54: =SUM(C52:C53) -> 2022.1 | D54: =SUM(D52:D53) -> 5827.3 | E54: =SUM(E52:E53) -> 3430 | F54: =SUM(F52:F53) -> 2198.9348 | G54: =SUM(G52:G53) -> 1473.5938 | H54: =SUM(H52:H53) -> 3054.4652 | I54: =SUM(I52:I53) -> 1351.6325 | ... K54: =SUM(K52:K53) -> 3490.8104
A55: Interest Income Rate | B55: =B31/B54 -> 0.028844541 | C55: =C31/C54 -> 0.042975125 | D55: =D31/D54 -> 0.070512931 | E55: =E31/E54 -> 0.076326531 | F55: =AVERAGE($B$55:$E$55) -> 0.054664782 | G55: =AVERAGE($B$55:$E$55) -> 0.054664782 | H55: =AVERAGE($B$55:$E$55) -> 0.054664782 | I55: =AVERAGE($B$55:$E$55) -> 0.054664782 | J55: =AVERAGE($B$55:$E$55) -> 0.054664782 | K55: =AVERAGE($B$55:$E$55) -> 0.054664782
A60: FCCB Scenario
A61: (In Actuals) | B61: No of FCCBs Outstanding | C61: Price per Bond (USD) | D61: Premium Payable on due | E61: Outstanding Amount in USD | F61: Dilution Effect on Outstanding Shares
A62: Due in Aug 2010 | B62: 53600 | C62: 1000 | D62: 1.39954 | E62: =(C62*D62)*B62 -> 75015344 | F62: 4500000
A63: Due in May 2011 -Tranche A Bonds | B63: 106200 | C63: 1000 | D63: 1.46285 | E63: =(C63*D63)*B63 -> 155354670 | F63: 4700000
A64: Due in May 2011 -Tranche B Bonds | B64: 33000 | C64: 1000 | D64: 1.46991 | E64: =(C64*D64)*B64 -> 48507030 | F64: 1700000
A66: Total | B66: =SUM(B62:B64) -> 192800 | E66: =SUM(E62:E64) -> 278877044 | F66: =SUM(F62:F64) -> 10900000
A68: Terms of FCCB Issue
A70: Due in Aug 2010 (Issued in 2005-2006) | B70: Convertible on or before August 2010. Each $1000 bond to be converted into 83.12 fully paid equity shares at a fixed price of Rs 522.036 at a fixed exchange conversion of Rs 43.3925 = US $1. OR REDEEMABLE on Maturity @ 139.954% of its principal amount.
A72: Due in May 2011 -Tranche A Bonds (Issued in 2006-07) | B72: Convertible on or before May 2011. Each $1000 bond to be converted into 44.52 fully paid equity shares at a fixed price of Rs 1014.06 at a fixed exchange conversion of Rs 45.145 = US $1. OR REDEEMABLE on Maturity @ 146.285% of its principal amount.
A74: Due in May 2011 -Tranche B Bonds (Issued in 2006-07) | B74: Convertible on or before May 2011. Each $1000 bond to be converted into 51.51 fully paid equity shares at a fixed price of Rs 879 at a fixed exchange conversion of Rs 45.145 = US $1. OR REDEEMABLE on Maturity @ 146.991% of its principal amount.
B77: Conversion @ Rs | C77: 46
A79: (In USD) | B79: Due in August 2010 | C79: Due in May 2011 (Tranche -A) | D79: Due in May 2011(Tranche-B)
A80: Face Value of FCCB | B80: 1000 | C80: 1000 | D80: 1000
A81: Premium (%) | B81: 1.39954 | C81: 1.46285 | D81: 1.46991
A82: Redemption value | B82: =B80*B81 -> 1399.54 | C82: =C80*C81 -> 1462.85 | D82: =D80*D81 -> 1469.91
A83: Premium Component | B83: =B82-B80 -> 399.54 | C83: =C82-C80 -> 462.85 | D83: =D82-D80 -> 469.91
A85: (In Millions)
A86: Interest Component (USD) | B86: =(B83*B62)/1000000 -> 21.415344 | C86: =(C83*B63)/1000000 -> 49.15467 | D86: =(D83*B64)/1000000 -> 15.50703
A87: Interest Component (In INR) | B87: =B86*C77 -> 985.10582 | C87: =C86*$C$77 -> 2261.1148 | D87: =D86*$C$77 -> 713.32338
A89: Principal Component (In INR) | B89: =(B62*B80*C77)/1000000 -> 2465.6 | C89: =(B63*C80*$C$77)/1000000 -> 4885.2 | D89: =(B64*D80*$C$77)/1000000 -> 1518
A92: Scenario Analysis
A93: FCCB - Due in August 2010
B94: Each Bond (in $) | C94: Premium | D94: Payable on Redemption (in $)
B95: 1000 | C95: 1.39954 | D95: =B95*C95 -> 1399.54
A97: Proceeds to Investor per Bond in USD if Converted to Equity shares | C97: Each $ 1000 Bond is convertible into | D97: 83.12 | E97: If Share Price is | F97: 850 | G97: USD/INR | H97: 46
B98: USD /INR
B99: =D97*F97/H97 -> 1535.913 | C99: 44 | D99: 45 | E99: 46 | F99: 47 | G99: 48
B100: 500 | C100: =TABLE($B$99,$F$97,$B100,$H$97,C$99) -> 944.54545 | D100: =TABLE($B$99,$F$97,$B100,$H$97,D$99) -> 923.55556 | E100: =TABLE($B$99,$F$97,$B100,$H$97,E$99) -> 903.47826 | F100: =TABLE($B$99,$F$97,$B100,$H$97,F$99) -> 884.25532 | G100: =TABLE($B$99,$F$97,$B100,$H$97,G$99) -> 865.83333
B101: 550 | C101: =TABLE($B$99,$F$97,$B101,$H$97,C$99) -> 1039 | D101: =TABLE($B$99,$F$97,$B101,$H$97,D$99) -> 1015.9111 | E101: =TABLE($B$99,$F$97,$B101,$H$97,E$99) -> 993.82609 | F101: =TABLE($B$99,$F$97,$B101,$H$97,F$99) -> 972.68085 | G101: =TABLE($B$99,$F$97,$B101,$H$97,G$99) -> 952.41667
B102: 600 | C102: =TABLE($B$99,$F$97,$B102,$H$97,C$99) -> 1133.4545 | D102: =TABLE($B$99,$F$97,$B102,$H$97,D$99) -> 1108.2667 | E102: =TABLE($B$99,$F$97,$B102,$H$97,E$99) -> 1084.1739 | F102: =TABLE($B$99,$F$97,$B102,$H$97,F$99) -> 1061.1064 | G102: =TABLE($B$99,$F$97,$B102,$H$97,G$99) -> 1039
B103: 650 | C103: =TABLE($B$99,$F$97,$B103,$H$97,C$99) -> 1227.9091 | D103: =TABLE($B$99,$F$97,$B103,$H$97,D$99) -> 1200.6222 | E103: =TABLE($B$99,$F$97,$B103,$H$97,E$99) -> 1174.5217 | F103: =TABLE($B$99,$F$97,$B103,$H$97,F$99) -> 1149.5319 | G103: =TABLE($B$99,$F$97,$B103,$H$97,G$99) -> 1125.5833
A104: Share Price in INR | B104: 700 | C104: =TABLE($B$99,$F$97,$B104,$H$97,C$99) -> 1322.3636 | D104: =TABLE($B$99,$F$97,$B104,$H$97,D$99) -> 1292.9778 | E104: =TABLE($B$99,$F$97,$B104,$H$97,E$99) -> 1264.8696 | F104: =TABLE($B$99,$F$97,$B104,$H$97,F$99) -> 1237.9574 | G104: =TABLE($B$99,$F$97,$B104,$H$97,G$99) -> 1212.1667
B105: 750 | C105: =TABLE($B$99,$F$97,$B105,$H$97,C$99) -> 1416.8182 | D105: =TABLE($B$99,$F$97,$B105,$H$97,D$99) -> 1385.3333 | E105: =TABLE($B$99,$F$97,$B105,$H$97,E$99) -> 1355.2174 | F105: =TABLE($B$99,$F$97,$B105,$H$97,F$99) -> 1326.383 | G105: =TABLE($B$99,$F$97,$B105,$H$97,G$99) -> 1298.75
B106: 800 | C106: =TABLE($B$99,$F$97,$B106,$H$97,C$99) -> 1511.2727 | D106: =TABLE($B$99,$F$97,$B106,$H$97,D$99) -> 1477.6889 | E106: =TABLE($B$99,$F$97,$B106,$H$97,E$99) -> 1445.5652 | F106: =TABLE($B$99,$F$97,$B106,$H$97,F$99) -> 1414.8085 | G106: =TABLE($B$99,$F$97,$B106,$H$97,G$99) -> 1385.3333
B107: 850 | C107: =TABLE($B$99,$F$97,$B107,$H$97,C$99) -> 1605.7273 | D107: =TABLE($B$99,$F$97,$B107,$H$97,D$99) -> 1570.0444 | E107: =TABLE($B$99,$F$97,$B107,$H$97,E$99) -> 1535.913 | F107: =TABLE($B$99,$F$97,$B107,$H$97,F$99) -> 1503.234 | G107: =TABLE($B$99,$F$97,$B107,$H$97,G$99) -> 1471.9167
B108: 900 | C108: =TABLE($B$99,$F$97,$B108,$H$97,C$99) -> 1700.1818 | D108: =TABLE($B$99,$F$97,$B108,$H$97,D$99) -> 1662.4 | E108: =TABLE($B$99,$F$97,$B108,$H$97,E$99) -> 1626.2609 | F108: =TABLE($B$99,$F$97,$B108,$H$97,F$99) -> 1591.6596 | G108: =TABLE($B$99,$F$97,$B108,$H$97,G$99) -> 1558.5
B109: 950 | C109: =TABLE($B$99,$F$97,$B109,$H$97,C$99) -> 1794.6364 | D109: =TABLE($B$99,$F$97,$B109,$H$97,D$99) -> 1754.7556 | E109: =TABLE($B$99,$F$97,$B109,$H$97,E$99) -> 1716.6087 | F109: =TABLE($B$99,$F$97,$B109,$H$97,F$99) -> 1680.0851 | G109: =TABLE($B$99,$F$97,$B109,$H$97,G$99) -> 1645.0833
B110: 1000 | C110: =TABLE($B$99,$F$97,$B110,$H$97,C$99) -> 1889.0909 | D110: =TABLE($B$99,$F$97,$B110,$H$97,D$99) -> 1847.1111 | E110: =TABLE($B$99,$F$97,$B110,$H$97,E$99) -> 1806.9565 | F110: =TABLE($B$99,$F$97,$B110,$H$97,F$99) -> 1768.5106 | G110: =TABLE($B$99,$F$97,$B110,$H$97,G$99) -> 1731.6667
B111: 1050 | C111: =TABLE($B$99,$F$97,$B111,$H$97,C$99) -> 1983.5455 | D111: =TABLE($B$99,$F$97,$B111,$H$97,D$99) -> 1939.4667 | E111: =TABLE($B$99,$F$97,$B111,$H$97,E$99) -> 1897.3043 | F111: =TABLE($B$99,$F$97,$B111,$H$97,F$99) -> 1856.9362 | G111: =TABLE($B$99,$F$97,$B111,$H$97,G$99) -> 1818.25
B112: 1100 | C112: =TABLE($B$99,$F$97,$B112,$H$97,C$99) -> 2078 | D112: =TABLE($B$99,$F$97,$B112,$H$97,D$99) -> 2031.8222 | E112: =TABLE($B$99,$F$97,$B112,$H$97,E$99) -> 1987.6522 | F112: =TABLE($B$99,$F$97,$B112,$H$97,F$99) -> 1945.3617 | G112: =TABLE($B$99,$F$97,$B112,$H$97,G$99) -> 1904.8333
B113: 1150 | C113: =TABLE($B$99,$F$97,$B113,$H$97,C$99) -> 2172.4545 | D113: =TABLE($B$99,$F$97,$B113,$H$97,D$99) -> 2124.1778 | E113: =TABLE($B$99,$F$97,$B113,$H$97,E$99) -> 2078 | F113: =TABLE($B$99,$F$97,$B113,$H$97,F$99) -> 2033.7872 | G113: =TABLE($B$99,$F$97,$B113,$H$97,G$99) -> 1991.4167
B114: 1200 | C114: =TABLE($B$99,$F$97,$B114,$H$97,C$99) -> 2266.9091 | D114: =TABLE($B$99,$F$97,$B114,$H$97,D$99) -> 2216.5333 | E114: =TABLE($B$99,$F$97,$B114,$H$97,E$99) -> 2168.3478 | F114: =TABLE($B$99,$F$97,$B114,$H$97,F$99) -> 2122.2128 | G114: =TABLE($B$99,$F$97,$B114,$H$97,G$99) -> 2078
B115: 1250 | C115: =TABLE($B$99,$F$97,$B115,$H$97,C$99) -> 2361.3636 | D115: =TABLE($B$99,$F$97,$B115,$H$97,D$99) -> 2308.8889 | E115: =TABLE($B$99,$F$97,$B115,$H$97,E$99) -> 2258.6957 | F115: =TABLE($B$99,$F$97,$B115,$H$97,F$99) -> 2210.6383 | G115: =TABLE($B$99,$F$97,$B115,$H$97,G$99) -> 2164.5833
B116: 1300 | C116: =TABLE($B$99,$F$97,$B116,$H$97,C$99) -> 2455.8182 | D116: =TABLE($B$99,$F$97,$B116,$H$97,D$99) -> 2401.2444 | E116: =TABLE($B$99,$F$97,$B116,$H$97,E$99) -> 2349.0435 | F116: =TABLE($B$99,$F$97,$B116,$H$97,F$99) -> 2299.0638 | G116: =TABLE($B$99,$F$97,$B116,$H$97,G$99) -> 2251.1667
... B126: 1800 | C126: =TABLE($B$99,$F$97,$B126,$H$97,C$99) -> 3400.3636 | D126: =TABLE($B$99,$F$97,$B126,$H$97,D$99) -> 3324.8 | E126: =TABLE($B$99,$F$97,$B126,$H$97,E$99) -> 3252.5217 | F126: =TABLE($B$99,$F$97,$B126,$H$97,F$99) -> 3183.3191 | G126: =TABLE($B$99,$F$97,$B126,$H$97,G$99) -> 3117
A129: FCCB - Due in May 2011 - Tranche A
B130: Each Bond (in $) | C130: Premium | D130: Payable on Redemption (in $)
B131: 1000 | C131: 1.46285 | D131: =B131*C131 -> 1462.85
A133: Proceeds to Investor per Bond in USD if Converted to Equity shares | C133: Each $ 1000 Bond is convertible into | D133: 44.52 | E133: If Share Price is | F133: 850 | G133: USD/INR | H133: 46
B134: USD /INR
B135: =(D133*F133)/H133 -> 822.65217 | C135: 44 | D135: 45 | E135: 46 | F135: 47 | G135: 48
B136: 500 | C136: =TABLE($B$135,$F$133,$B136,$H$133,C$135) -> 505.90909 | D136: =TABLE($B$135,$F$133,$B136,$H$133,D$135) -> 494.66667 | E136: =TABLE($B$135,$F$133,$B136,$H$133,E$135) -> 483.91304 | F136: =TABLE($B$135,$F$133,$B136,$H$133,F$135) -> 473.61702 | G136: =TABLE($B$135,$F$133,$B136,$H$133,G$135) -> 463.75
B137: 550 | C137: =TABLE($B$135,$F$133,$B137,$H$133,C$135) -> 556.5 | D137: =TABLE($B$135,$F$133,$B137,$H$133,D$135) -> 544.13333 | E137: =TABLE($B$135,$F$133,$B137,$H$133,E$135) -> 532.30435 | F137: =TABLE($B$135,$F$133,$B137,$H$133,F$135) -> 520.97872 | G137: =TABLE($B$135,$F$133,$B137,$H$133,G$135) -> 510.125
B138: 600 | C138: =TABLE($B$135,$F$133,$B138,$H$133,C$135) -> 607.09091 | D138: =TABLE($B$135,$F$133,$B138,$H$133,D$135) -> 593.6 | E138: =TABLE($B$135,$F$133,$B138,$H$133,E$135) -> 580.69565 | F138: =TABLE($B$135,$F$133,$B138,$H$133,F$135) -> 568.34043 | G138: =TABLE($B$135,$F$133,$B138,$H$133,G$135) -> 556.5
B139: 650 | C139: =TABLE($B$135,$F$133,$B139,$H$133,C$135) -> 657.68182 | D139: =TABLE($B$135,$F$133,$B139,$H$133,D$135) -> 643.06667 | E139: =TABLE($B$135,$F$133,$B139,$H$133,E$135) -> 629.08696 | F139: =TABLE($B$135,$F$133,$B139,$H$133,F$135) -> 615.70213 | G139: =TABLE($B$135,$F$133,$B139,$H$133,G$135) -> 602.875
A140: Share Price in INR | B140: 700 | C140: =TABLE($B$135,$F$133,$B140,$H$133,C$135) -> 708.27273 | D140: =TABLE($B$135,$F$133,$B140,$H$133,D$135) -> 692.53333 | E140: =TABLE($B$135,$F$133,$B140,$H$133,E$135) -> 677.47826 | F140: =TABLE($B$135,$F$133,$B140,$H$133,F$135) -> 663.06383 | G140: =TABLE($B$135,$F$133,$B140,$H$133,G$135) -> 649.25
...

Sheet Fixed Asset
A1: Aurobindo Pharma
A2: Fixed Asset
A3: (In Rs Millions)
A4: For the Fiscal Period Ending | B4: FY2004 A | C4: FY2005 A | D4: FY2006 A | E4: FY2007 A | F4: FY2008 A | G4: FY2009 E | H4: FY2010 E | I4: FY2011 E | J4: FY2012 E | K4: FY2013 E | L4: FY2014 E
A5: Fixed Asset
A7: Gross Block (C/B) | B7: 8900.4 | C7: 10726.9 | D7: ='Balance Sheet'!B28 -> 13561.6 | E7: ='Balance Sheet'!C28 -> 14681.4 | F7: ='Balance Sheet'!D28 -> 17179.9 | G7: =F7+G10 -> 19472.18 | H7: =G7+H10 -> 22227.762 | I7: =H7+I10 -> 25644.684 | J7: =I7+J10 -> 29276.384 | K7: =J7+K10 -> 33707.058 | L7: =K7+L10 -> 39023.867
A8: Capital Work-in-progress | B8: 1594.2 | C8: 2525.4 | D8: ='Balance Sheet'!B31 -> 1497.4 | E8: ='Balance Sheet'!C31 -> 2187.1 | F8: ='Balance Sheet'!D31 -> 2145.5 | G8: . | H8: 0 | I8: 0 | J8: 0 | K8: 0 | L8: 0
A9: Total | B9: =SUM(B7:B8) -> 10494.6 | C9: =SUM(C7:C8) -> 13252.3 | D9: =SUM(D7:D8) -> 15059 | E9: =SUM(E7:E8) -> 16868.5 | F9: =SUM(F7:F8) -> 19325.4 | G9: 0 | H9: 0 | I9: 0 | J9: 0 | K9: 0 | L9: 0
A10: Additions (Capex) | C10: =C9-B9 -> 2757.7 | D10: =D9-C9 -> 1806.7 | E10: =E9-D9 -> 1809.5 | F10: =F9-E9 -> 2456.9 | G10: =G17 -> 2292.2798 | H10: =H17 -> 2755.5823 | I10: =I17 -> 3416.9221 | J10: =J17 -> 3631.7 | K10: =K17 -> 4430.6741 | L10: =L17 -> 5316.8089
A12: Depreciation (B/S) | B12: 1482.7 | C12: 2144.2 | D12: ='Balance Sheet'!B29 -> 2724.1 | E12: ='Balance Sheet'!C29 -> 3155.3 | F12: ='Balance Sheet'!D29 -> 4176.9 | G12: =F12+G13 -> 5398.1 | H12: =G12+H13 -> 6607.9075 | I12: =H12+I13 -> 7964.6317 | J12: =I12+J13 -> 9491.0676 | K12: =J12+K13 -> 11213.613 | L12: =K12+L13 -> 13182.883
A13: Depreciation (I/S) | B13: 589.8 | C13: 646.7 | D13: ='Profit & Loss Consolidated'!B20 -> 721.3 | E13: ='Profit & Loss Consolidated'!G20 -> 997.2 | F13: ='Profit & Loss Consolidated'!L20 -> 1003.8 | G13: ='Profit & Loss Consolidated'!Q20 -> 1221.2 | H13: =H14*(G16+H10/2) -> 1209.8075 | I13: =I14*(H16+I10/2) -> 1356.7242 | J13: =J14*(I16+J10/2) -> 1526.4359 | K13: =K14*(J16+K10/2) -> 1722.5459 | L13: =L14*(K16+L10/2) -> 1969.2694
A14: Depreciation Rate | C14: =C13/(B16+C10/2) -> 0.073517459 | D14: =D13/(C16+D10/2) -> 0.076037972 | E14: =E13/(D16+E10/2) -> 0.084924099 | F14: =F13/(E16+F10/2) -> 0.078701326 | G14: =AVERAGE($C$14:$F$14) -> 0.078295214 | H14: =AVERAGE($C$14:$F$14) -> 0.078295214 | I14: =AVERAGE($C$14:$F$14) -> 0.078295214 | J14: =AVERAGE($C$14:$F$14) -> 0.078295214 | K14: =AVERAGE($C$14:$F$14) -> 0.078295214 | L14: =AVERAGE($C$14:$F$14) -> 0.078295214
A16: Net Block | B16: =B7-B12 -> 7417.7 | C16: =C7-C12 -> 8582.7 | D16: =D7-D12 -> 10837.5 | E16: =E7-E12 -> 11526.1 | F16: =F7-F12 -> 13003 | G16: =G7-G12 -> 14074.08 | H16: =H7-H12 -> 15619.855 | I16: =I7-I12 -> 17680.052 | ... L16: =L7-L12 -> 25840.984
A17: Capex | C17: =C10 -> 2757.7 | D17: =D10 -> 1806.7 | E17: =E10 -> 1809.5 | F17: =F10 -> 2456.9 | G17: =G18*'Profit & Loss Consolidated'!Q9 -> 2292.2798 | H17: =H18*'Profit & Loss Consolidated'!V9 -> 2755.5823 | I17: =I18*'Profit & Loss Consolidated'!AA9 -> 3416.9221 | J17: =J18*'Profit & Loss Consolidated'!AF9 -> 3631.7 | K17: =K18*'Profit & Loss Consolidated'!AK9 -> 4430.6741 | L17: =L18*'Profit & Loss Consolidated'!AP9 -> 5316.8089
A18: Capex as % of revenue | C18: =C17/14167.3 -> 0.19465247 | D18: =D17/'Profit & Loss Consolidated'!B9 -> 0.10655854 | E18: =E17/'Profit & Loss Consolidated'!G9 -> 0.080414359 | F18: =F17/'Profit & Loss Consolidated'!L9 -> 0.096262572 | G18: 0.075 | H18: 0.07 | I18: 0.07 | J18: 0.06 | K18: =$J$18 -> 0.06 | L18: =$J$18 -> 0.06

Sheet DCF Valuation
A1: Aurobindo Pharma
A2: Valuation
A3: (In Rs Millions, Except per share items)
A5: Growth Assumptions | D5: Enterprise Value (EV) | G5: Debt Equity Weightage
A6: Long term World GDP growth rate | B6: 0.041 | G6: E/(D+E) @ Enterprise Value | H6: =E9/E13 -> 0.75669559
D7: Current Market Price | E7: 753 | G7: D/(D+E) @ Enterprise Value | H7: =E12/E13 -> 0.24330441
D8: Diluted Shares | E8: ='Profit & Loss Consolidated'!S55 -> 64.615683
A9: CAPM Assumptions | D9: Market Capitalisation | E9: =E7*E8 -> 48655.609 | G9: Interest Rate (%) | H9: ='Debt Schedule'!G36 -> 0.11650311
A10: Ke | B10: =B11+(B12*B13) -> 0.118006 | D10: Long Term Liabilities | E10: ='Balance Sheet'!D62 -> 18470.2 | G10: Tax Rate (@) | H10: ='Cost Model'!W20 -> 0.13
A11: RFR | B11: 0.07 | D11: Less: Cash & Cash Equivalents | E11: ='Balance Sheet'!D42 -> 2825.7
A12: Beta | B12: 0.6858 | D12: Net Debt | E12: =E10-E11 -> 15644.5 | G12: WACC Calculation
A13: Rp | B13: 0.07 | D13: Enterprise Value (EV) | E13: =E9+E12 -> 64300.109 | G13: WACC | H13: =B10*H6+((H9*H7)*(1-H10)) -> 0.1139554
A15: Calculation of Free Cash Flow
C16: Explicit Forecast Period (First Stage) | I16: Second Stage of Valuation | N16: Third Stage of Valuation
B17: FY2008 A | C17: FY2009 A | D17: FY2010 E | E17: FY2011 E | F17: FY2012 E | G17: FY2013 E | H17: FY2014 E | I17: FY2015 E | J17: FY2016 E | K17: FY2017 E | L17: FY2018 E | M17: FY2019 E | N17: Terminal Year
A19: Revenues | B19: ='Profit & Loss Consolidated'!L13 -> 24359 | C19: ='Profit & Loss Consolidated'!Q13 -> 31242.43 | D19: ='Profit & Loss Consolidated'!V13 -> 40324.43 | E19: ='Profit & Loss Consolidated'!AA13 -> 49546.689 | F19: ='Profit & Loss Consolidated'!AF13 -> 60962.815 | G19: ='Profit & Loss Consolidated'!AK13 -> 73939.144 | H19: ='Profit & Loss Consolidated'!AP13 -> 88331.072 | I19: =H19*(1+I37) -> 102968.99 | J19: =I19*(1+J37) -> 117053.84 | K19: =J19*(1+K37) -> 129679.06 | L19: =K19*(1+L37) -> 139914.52 | M19: =L19*(1+M37) -> 146910.24 | N19: =M19*(1+N37) -> 152933.56
A20: EBITDA | B20: ='Profit & Loss Consolidated'!L25+'Profit & Loss Consolidated'!L20 -> 4353.8 | C20: ='Profit & Loss Consolidated'!Q25+'Profit & Loss Consolidated'!Q20 -> 5890.63 | D20: ='Profit & Loss Consolidated'!V25+'Profit & Loss Consolidated'!V20 -> 7698.5157 | E20: ='Profit & Loss Consolidated'!AA25+'Profit & Loss Consolidated'!AA20 -> 9081.7227 | F20: ='Profit & Loss Consolidated'!AF25+'Profit & Loss Consolidated'!AF20 -> 10746.32 | G20: ='Profit & Loss Consolidated'!AK25+'Profit & Loss Consolidated'!AK20 -> 12638.413 | H20: ='Profit & Loss Consolidated'!AP25+'Profit & Loss Consolidated'!AP20 -> 14736.915 | I20: =I21+I24 -> 17179.065 | J20: =J21+J24 -> 19528.944 | K20: =K21+K24 -> 21635.301 | L20: =L21+L24 -> 23342.956 | M20: =M21+M24 -> 24510.104 | N20: =N21+N24 -> 25515.018
A21: EBIT | B21: ='Profit & Loss Consolidated'!L25 -> 3350 | C21: ='Profit & Loss Consolidated'!Q25 -> 4669.43 | D21: ='Profit & Loss Consolidated'!V25 -> 6488.7081 | E21: ='Profit & Loss Consolidated'!AA25 -> 7724.9985 | F21: ='Profit & Loss Consolidated'!AF25 -> 9219.8842 | G21: ='Profit & Loss Consolidated'!AK25 -> 10915.867 | H21: ='Profit & Loss Consolidated'!AP25 -> 12767.646 | I21: =I19*I44 -> 14883.455 | J21: =J19*J44 -> 16919.323 | K21: =K19*K44 -> 18744.212 | L21: =L19*L44 -> 20223.676 | M21: =M19*M44 -> 21234.86 | N21: =N19*N44 -> 22105.489
A22: Tax Expense | B22: ='Profit & Loss Consolidated'!L42 -> 536 | C22: ='Profit & Loss Consolidated'!Q42 -> 312.9 | D22: ='Profit & Loss Consolidated'!V42 -> 782.96634 | E22: ='Profit & Loss Consolidated'!AA42 -> 727.14763 | F22: ='Profit & Loss Consolidated'!AF42 -> 856.9901 | G22: ='Profit & Loss Consolidated'!AK42 -> 1192.8581 | H22: ='Profit & Loss Consolidated'!AP42 -> 1439.3327 | I22: =I21*I48 -> 1677.8538 | J22: =J21*J48 -> 1907.363 | K22: =K21*K48 -> 2113.0878 | L22: =L21*L48 -> 2279.872 | M22: =M21*M48 -> 2393.8656 | N22: =N21*N48 -> 2492.0141
A23: Net Operating Profit After Tax | B23: =B21-B22 -> 2814 | C23: =C21-C22 -> 4356.53 | D23: =D21-D22 -> 5705.7418 | E23: =E21-E22 -> 6997.8509 | F23: =F21-F22 -> 8362.8941 | G23: =G21-G22 -> 9723.0085 | H23: =H21-H22 -> 11328.313 | I23: =I21-I22 -> 13205.601 | ... N23: =N21-N22 -> 19613.475
A24: Depreciation & Amortisation | B24: ='Profit & Loss Consolidated'!L20 -> 1003.8 | C24: ='Profit & Loss Consolidated'!Q20 -> 1221.2 | D24: ='Profit & Loss Consolidated'!V20 -> 1209.8075 | E24: ='Profit & Loss Consolidated'!AA20 -> 1356.7242 | F24: ='Profit & Loss Consolidated'!AF20 -> 1526.4359 | G24: ='Profit & Loss Consolidated'!AK20 -> 1722.5459 | H24: ='Profit & Loss Consolidated'!AP20 -> 1969.2694 | I24: =I19*I45 -> 2295.6098 | J24: =J19*J45 -> 2609.6202 | K24: =K19*K45 -> 2891.0892 | L24: =L19*L45 -> 3119.2804 | M24: =M19*M45 -> 3275.2444 | N24: =N19*N45 -> 3409.5294
A25: Working Capital Change | B25: =SUM('Cash Flow Statement'!D31:D34) -> -1271.7 | C25: =SUM('Cash Flow Statement'!E31:E34) -> -1158.9155 | D25: =SUM('Cash Flow Statement'!F31:F34) -> -2934.8328 | E25: =SUM('Cash Flow Statement'!G31:G34) -> -3225.2264 | F25: =SUM('Cash Flow Statement'!H31:H34) -> -3929.6099 | G25: =SUM('Cash Flow Statement'!I31:I34) -> -4466.6566 | H25: =SUM('Cash Flow Statement'!J31:J34) -> -4953.9282 | I25: =H25 -> -4953.9282 | J25: =I25 -> -4953.9282 | K25: =J25 -> -4953.9282 | L25: =K25 -> -4953.9282 | M25: =L25 -> -4953.9282 | N25: =M25 -> -4953.9282
A26: Operating Cash Flow | B26: =B23+B24+B25 -> 2546.1 | C26: =C23+C24+C25 -> 4418.8145 | D26: =D23+D24+D25 -> 3980.7165 | E26: =E23+E24+E25 -> 5129.3486 | F26: =F23+F24+F25 -> 5959.7201 | G26: =G23+G24+G25 -> 6978.8978 | H26: =H23+H24+H25 -> 8343.6541 | I26: =I23+I24+I25 -> 10547.283 | ... N26: =N23+N24+N25 -> 18069.076
A27: Capex | B27: ='Fixed Asset'!F17 -> 2456.9 | C27: ='Fixed Asset'!G17 -> 2292.2798 | D27: ='Fixed Asset'!H17 -> 2755.5823 | E27: ='Fixed Asset'!I17 -> 3416.9221 | F27: ='Fixed Asset'!J17 -> 3631.7 | G27: ='Fixed Asset'!K17 -> 4430.6741 | H27: ='Fixed Asset'!L17 -> 5316.8089 | I27: =I19*I46 -> 6197.8917 | J27: =J19*J46 -> 7045.6849 | K27: =K19*K46 -> 7805.6201 | L27: =L19*L46 -> 8421.7108 | M27: =M19*M46 -> 8842.7964 | N27: =N19*N46 -> 9205.351
A28: FCF | B28: =B26-B27 -> 89.2 | C28: =C26-C27 -> 2126.5348 | D28: =D26-D27 -> 1225.1342 | E28: =E26-E27 -> 1712.4265 | F28: =F26-F27 -> 2328.02 | G28: =G26-G27 -> 2548.2238 | H28: =H26-H27 -> 3026.8452 | I28: =I26-I27 -> 4349.3909 | ... N28: =N26-N27 -> 8863.725
A30: Diluted Shares | B30: ='Profit & Loss Consolidated'!L55 -> 67.506369 | C30: ='Profit & Loss Consolidated'!Q55 -> 64.739469 | D30: ='Profit & Loss Consolidated'!V55 -> 64.615683 | E30: ='Profit & Loss Consolidated'!AA55 -> 64.615683 | F30: ='Profit & Loss Consolidated'!AF55 -> 58.183444 | G30: ='Profit & Loss Consolidated'!AK55 -> 58.183444 | H30: ='Profit & Loss Consolidated'!AP55 -> 58.183444 | I30: =H30 -> 58.183444 | J30: =I30 -> 58.183444 | K30: =J30 -> 58.183444 | L30: =K30 -> 58.183444 | M30: =L30 -> 58.183444
A32: Projection Year | D32: 1 | E32: 2 | F32: 3 | G32: 4 | H32: 5 | I32: 6 | J32: 7 | K32: 8 | L32: 9 | M32: 10
A33: Discount Factor | D33: =1/(1+$H$13)^D32 -> 0.89770201 | E33: =1/(1+$H$13)^E32 -> 0.8058689 | F33: =1/(1+$H$13)^F32 -> 0.72343014 | G33: =1/(1+$H$13)^G32 -> 0.64942469 | H33: =1/(1+$H$13)^H32 -> 0.58298985 | I33: =1/(1+$H$13)^I32 -> 0.52335116 | J33: =1/(1+$H$13)^J32 -> 0.46981339 | K33: =1/(1+$H$13)^K32 -> 0.42175243 | ... M33: =1/(1+$H$13)^M32 -> 0.33987716
A34: Present Value of FCF | D34: =D28*D33 -> 1099.8054 | E34: =E28*E33 -> 1379.9913 | F34: =F28*F33 -> 1684.1598 | G34: =G28*G33 -> 1654.8794 | H34: =H28*H33 -> 1764.62 | I34: =I28*I33 -> 2276.2588 | J34: =J28*J33 -> 2641.2755 | K34: =K28*K33 -> 2852.1703 | ... M34: =M28*M33 -> 2827.6128
A36: Y/Y Growth Analysis
A37: Revenues | C37: =C19/B19-1 -> 0.28258262 | D37: =D19/C19-1 -> 0.29069443 | E37: =E19/D19-1 -> 0.22870152 | F37: =F19/E19-1 -> 0.23041147 | G37: =G19/F19-1 -> 0.21285646 | H37: =H19/G19-1 -> 0.1946456 | I37: =H37-($H$37-$M$37)/5 -> 0.16571648 | J37: =I37-($H$37-$M$37)/5 -> 0.13678736 | K37: =J37-($H$37-$M$37)/5 -> 0.10785824 | L37: =K37-($H$37-$M$37)/5 -> 0.078929119 | M37: 0.05 | N37: =B6 -> 0.041
A38: EBITDA | C38: =C20/B20-1 -> 0.3529859 | D38: =D20/C20-1 -> 0.30690871 | E38: =E20/D20-1 -> 0.1796719 | F38: =F20/E20-1 -> 0.18329094 | G38: =G20/F20-1 -> 0.17606887 | H38: =H20/G20-1 -> 0.16604162 | I38: =I20/H20-1 -> 0.16571648 | J38: =J20/I20-1 -> 0.13678736 | ... N38: =N20/M20-1 -> 0.041
A39: EBIT | C39: =C21/B21-1 -> 0.3938597 | D39: =D21/C21-1 -> 0.38961461 | E39: =E21/D21-1 -> 0.1905295 | F39: =F21/E21-1 -> 0.19351276 | G39: =G21/F21-1 -> 0.18394834 | H39: =H21/G21-1 -> 0.16964104 | I39: =I21/H21-1 -> 0.16571648 | J39: =J21/I21-1 -> 0.13678736 | ... N39: =N21/M21-1 -> 0.041
A40: Depreciation & Amortisation | C40: =C24/B24-1 -> 0.21657701 | D40: =D24/C24-1 -> -0.0093289088 | E40: =E24/D24-1 -> 0.12143802 | F40: =F24/E24-1 -> 0.1250893 | G40: =G24/F24-1 -> 0.12847578 | H40: =H24/G24-1 -> 0.14323191 | I40: =I24/H24-1 -> 0.16571648 | J40: =J24/I24-1 -> 0.13678736 | ... N40: =N24/M24-1 -> 0.041
A42: Margin Analysis (As % of Revenues)
A43: EBITDA Margin | B43: =B20/B$19 -> 0.17873476 | C43: =C20/C$19 -> 0.18854583 | D43: =D20/D$19 -> 0.19091443 | E43: =E20/E$19 -> 0.18329626 | F43: =F20/F$19 -> 0.17627664 | G43: =G20/G$19 -> 0.17092993 | H43: =H20/H$19 -> 0.16683727
A44: EBIT Margin | B44: =B21/B$19 -> 0.13752617 | C44: =C21/C$19 -> 0.14945796 | D44: =D21/D$19 -> 0.16091258 | E44: =E21/E$19 -> 0.15591352 | F44: =F21/F$19 -> 0.15123784 | G44: =G21/G$19 -> 0.14763312 | H44: =H21/H$19 -> 0.14454308 | I44: =H44 -> 0.14454308 | J44: =I44 -> 0.14454308 | K44: =J44 -> 0.14454308 | L44: =K44 -> 0.14454308 | M44: =L44 -> 0.14454308 | N44: =M44 -> 0.14454308
A45: Depreciation & Amortisation | B45: =B24/B$19 -> 0.041208588 | C45: =C24/C$19 -> 0.039087869 | D45: =D24/D$19 -> 0.030001851 | E45: =E24/E$19 -> 0.027382741 | F45: =F24/F$19 -> 0.025038802 | G45: =G24/G$19 -> 0.023296806 | H45: =H24/H$19 -> 0.022294187 | I45: =H45 -> 0.022294187 | J45: =I45 -> 0.022294187 | K45: =J45 -> 0.022294187 | L45: =K45 -> 0.022294187 | M45: =L45 -> 0.022294187 | N45: =M45 -> 0.022294187
A46: Capex | B46: =B27/B$19 -> 0.1008621 | C46: =C27/C$19 -> 0.073370725 | D46: =D27/D$19 -> 0.068335307 | E46: =E27/E$19 -> 0.068963681 | F46: =F27/F$19 -> 0.059572381 | G46: =G27/G$19 -> 0.059923253 | H46: =H27/H$19 -> 0.06019183 | I46: =H46 -> 0.06019183 | J46: =I46 -> 0.06019183 | K46: =J46 -> 0.06019183 | L46: =K46 -> 0.06019183 | M46: =L46 -> 0.06019183 | N46: =M46 -> 0.06019183
A48: Tax Rate (Tax Expense/EBIT) | B48: =B22/B$21 -> 0.16 | C48: =C22/C$21 -> 0.06701032 | D48: =D22/D$21 -> 0.12066598 | E48: =E22/E$21 -> 0.094129161 | F48: =F22/F$21 -> 0.092950202 | G48: =G22/G$21 -> 0.10927745 | H48: =H22/H$21 -> 0.11273282 | I48: =H48 -> 0.11273282 | J48: =I48 -> 0.11273282 | K48: =J48 -> 0.11273282 | L48: =K48 -> 0.11273282 | M48: =L48 -> 0.11273282 | N48: =M48 -> 0.11273282
A51: Terminal Value | D51: Calculated Equity Value | G51: Intrinsic Value
A52: Sum of PV of FCF for explicit forecast | B52: =SUM(D34:M34) -> 21091.302 | D52: Enterprise Value | E52: =B52+B55 -> 62384.72 | G52: Equity Value | H52: =E56 -> 46740.22
A53: WACC | B53: =H13 -> 0.1139554 | D53: - Debt | E53: =-E10 -> -18470.2 | G53: Diluted Shares | H53: =E8 -> 64.615683
A54: Long term growth in EBIT | B54: =B6 -> 0.041 | D54: + Cash | E54: =E11 -> 2825.7
A55: Present Value of terminal value | B55: =N28/($B$53-$B$54)*M33 -> 41293.419 | D55: Net Debt | E55: =E53+E54 -> -15644.5 | G55: Intrinsic Value Rs. | H55: =H52/H53 -> 723.35721
A56: Terminal Value as % of Total Value | B56: =B55/(B52+B55) -> 0.66191559 | D56: Equity Value | E56: =E52+E55 -> 46740.22
A59: Sensitivity - Varying Terminal Growth Rate
D61: PV of Terminal Value | H61: Intrinsic Value
A62: WACC | B62: PV of FCF | C62: =B55 -> 41293.419 | D62: 0.03 | E62: 0.041 | F62: 0.05 | H62: 0.03 | I62: 0.041 | J62: 0.05
A63: 0.1 | B63: =NPV($A63,$D$28:$M$28) -> 22860.636 | C63: 0.1 | D63: =TABLE($C$62,$B$53,$C63,$B$54,D$62) -> 43036.824 | E63: =TABLE($C$62,$B$53,$C63,$B$54,E$62) -> 51060.639 | F63: =TABLE($C$62,$B$53,$C63,$B$54,F$62) -> 60251.554 | H63: =($B63+D63+$E$55)/$H$53 -> 777.72079 | I63: =($B63+E63+$E$55)/$H$53 -> 901.8983 | J63: =($B63+F63+$E$55)/$H$53 -> 1044.138
A64: 0.11 | B64: =NPV($A64,$D$28:$M$28) -> 21573.621 | C64: 0.11 | D64: =TABLE($C$62,$B$53,$C64,$B$54,D$62) -> 37657.221 | E64: =TABLE($C$62,$B$53,$C64,$B$54,E$62) -> 43660.546 | F64: =TABLE($C$62,$B$53,$C64,$B$54,F$62) -> 50209.628 | H64: =($B64+D64+$E$55)/$H$53 -> 674.54742 | I64: =($B64+E64+$E$55)/$H$53 -> 767.4556 | J64: =($B64+F64+$E$55)/$H$53 -> 868.80997
A65: =H13 -> 0.1139554 | B65: =NPV($A65,$D$28:$M$28) -> 21091.302 | C65: 0.1139554 | D65: =TABLE($C$62,$B$53,$C65,$B$54,D$62) -> 35883.074 | E65: =TABLE($C$62,$B$53,$C65,$B$54,E$62) -> 41293.419 | F65: =TABLE($C$62,$B$53,$C65,$B$54,F$62) -> 47104.356 | H65: =($B65+D65+$E$55)/$H$53 -> 639.62608 | I65: =($B65+E65+$E$55)/$H$53 -> 723.35721 | J65: =($B65+F65+$E$55)/$H$53 -> 813.28796
A66: 0.12 | B66: =NPV($A66,$D$28:$M$28) -> 20381.787 | C66: 0.12 | D66: =TABLE($C$62,$B$53,$C66,$B$54,D$62) -> 33473.086 | E66: =TABLE($C$62,$B$53,$C66,$B$54,E$62) -> 38133.895 | F66: =TABLE($C$62,$B$53,$C66,$B$54,F$62) -> 43036.824 | H66: =($B66+D66+$E$55)/$H$53 -> 591.34827 | I66: =($B66+E66+$E$55)/$H$53 -> 663.47951 | J66: =($B66+F66+$E$55)/$H$53 -> 739.35783
A67: 0.13 | B67: =NPV($A67,$D$28:$M$28) -> 19276.908 | C67: 0.13 | D67: =TABLE($C$62,$B$53,$C67,$B$54,D$62) -> 30125.777 | E67: =TABLE($C$62,$B$53,$C67,$B$54,E$62) -> 33849.188 | F67: =TABLE($C$62,$B$53,$C67,$B$54,F$62) -> 37657.221 | H67: =($B67+D67+$E$55)/$H$53 -> 522.44569 | I67: =($B67+E67+$E$55)/$H$53 -> 580.06963 | J67: =($B67+F67+$E$55)/$H$53 -> 639.00321
A69: Sensitivity - EV/EBITDA Exit Multiple
D71: PV of Terminal Value (EV/EBITDA) | H71: Intrinsic Value
A72: WACC | B72: PV of FCF | D72: 4.5 | E72: 5 | F72: 5.5 | H72: =D72 -> 4.5 | I72: =E72 -> 5 | J72: =F72 -> 5.5
A73: 0.1 | B73: 24512.506 | D73: =(D$72*($N$21+$N$24))/(1+$A73)^$M$32 -> 44267.148 | E73: =(E$72*($N$21+$N$24))/(1+$A73)^$M$32 -> 49185.72 | F73: =(F$72*($N$21+$N$24))/(1+$A73)^$M$32 -> 54104.292 | H73: =($B73+D73+$E$55)/$H$53 -> 822.32598 | I73: =($B73+E73+$E$55)/$H$53 -> 898.44638 | J73: =($B73+F73+$E$55)/$H$53 -> 974.56679
A74: 0.11 | B74: 23102.64 | D74: =(D$72*($N$21+$N$24))/(1+$A74)^$M$32 -> 40436.97 | E74: =(E$72*($N$21+$N$24))/(1+$A74)^$M$32 -> 44929.967 | F74: =(F$72*($N$21+$N$24))/(1+$A74)^$M$32 -> 49422.964 | H74: =($B74+D74+$E$55)/$H$53 -> 741.23042 | I74: =($B74+E74+$E$55)/$H$53 -> 810.76458 | J74: =($B74+F74+$E$55)/$H$53 -> 880.29873
A75: 0.11414549 | B75: 21536.42 | D75: =(D$72*($N$21+$N$24))/(1+$A75)^$M$32 -> 38957.344 | E75: =(E$72*($N$21+$N$24))/(1+$A75)^$M$32 -> 43285.937 | F75: =(F$72*($N$21+$N$24))/(1+$A75)^$M$32 -> 47614.531 | H75: =($B75+D75+$E$55)/$H$53 -> 694.09253 | I75: =($B75+E75+$E$55)/$H$53 -> 761.08236 | J75: =($B75+F75+$E$55)/$H$53 -> 828.07219
A76: 0.12 | B76: 20590.717 | D76: =(D$72*($N$21+$N$24))/(1+$A76)^$M$32 -> 36968.189 | E76: =(E$72*($N$21+$N$24))/(1+$A76)^$M$32 -> 41075.765 | F76: =(F$72*($N$21+$N$24))/(1+$A76)^$M$32 -> 45183.342 | H76: =($B76+D76+$E$55)/$H$53 -> 648.67232 | I76: =($B76+E76+$E$55)/$H$53 -> 712.24166 | J76: =($B76+F76+$E$55)/$H$53 -> 775.81101
A77: 0.13 | B77: 20590.717 | D77: =(D$72*($N$21+$N$24))/(1+$A77)^$M$32 -> 33823.922 | E77: =(E$72*($N$21+$N$24))/(1+$A77)^$M$32 -> 37582.135 | F77: =(F$72*($N$21+$N$24))/(1+$A77)^$M$32 -> 41340.349 | H77: =($B77+D77+$E$55)/$H$53 -> 600.01127 | I77: =($B77+E77+$E$55)/$H$53 -> 658.17383 | J77: =($B77+F77+$E$55)/$H$53 -> 716.33639
