Workbook

Sheet Intro
A1: Sheet | B1: Cell | C1: Row | D1: Column | E1: Type | F1: Formula | G1: Value | H1: ValueJSON | I1: NumberFormat | J1: FontBold | K1: FontItalic | L1: FontSize | M1: FontColor | N1: FillColor | O1: HorizontalAlignment | P1: VerticalAlignment | Q1: WrapText | R1: IncludeFlag | S1: GroupID | T1: GroupDirection | U1: GroupSize | V1: PatternFormula | W1: StyleJSON
A2: Intro | B2: A1 | C2: 1 | D2: 1 | E2: Input | H2: {"type": "null", "value": null} | I2: General | J2: FALSE | K2: FALSE | L2: 11 | M2: Values must be of type <class 'str'> | N2: 00000000 | R2: FALSE | W2: {"number_format": "General", "font": {"name": "Calibri", "size": 11.0, "bold": false, "italic": false, "underline": null, "strike": null, "color": {"type": "theme", "rgb": "Values must be of type <class 'str'>", "indexed": null, "theme": 1, "tint": 0.0, "auto": null}, "vert_align": null}, "fill": {"fill_type": null, "fg_color": {"type": "rgb", "rgb": "00000000", "indexed": null, "theme": null, "tint": 0.0, "auto": null}, "bg_color": {"type": "rgb", "rgb": "00000000", "indexed": null, "theme": null, "tint": 0.0, "auto": null}}, "alignment": {"horizontal": null, "vertical": null, "text_rotation": 0, "wrap_text": null, "shrink_to_fit": null, "indent": 0.0}, "border": {"left": {"style": null, "color": null}, "right": {"style": null, "color": null}, "top": {"style": null, "color": null}, "bottom": {"style": null, "color": null}, "diagonal": {"style": null, "color": null}, "diagonal_down": false, "diagonal_up": false, "outline": true, "vertical": null, "horizontal": null}, "protection": {"locked": true, "hidden": false}}
A3: Intro | B3: B1 | C3: 1 | D3: 2 | E3: Input | H3: {"type": "null", "value": null} | I3: General | J3: FALSE | K3: FALSE | L3: 11 | M3: Values must be of type <class 'str'> | N3: 00000000 | R3: FALSE | W3: {"number_format": "General", "font": {"name": "Calibri", "size": 11.0, "bold": false, "italic": false, "underline": null, "strike": null, "color": {"type": "theme", "rgb": "Values must be of type <class 'str'>", "indexed": null, "theme": 1, "tint": 0.0, "auto": null}, "vert_align": null}, "fill": {"fill_type": null, "fg_color": {"type": "rgb", "rgb": "00000000", "indexed": null, "theme": null, "tint": 0.0, "auto": null}, "bg_color": {"type": "rgb", "rgb": "00000000", "indexed": null, "theme": null, "tint": 0.0, "auto": null}}, "alignment": {"horizontal": null, "vertical": null, "text_rotation": 0, "wrap_text": null, "shrink_to_fit": null, "indent": 0.0}, "border": {"left": {"style": null, "color": null}, "right": {"style": null, "color": null}, "top": {"style": null, "color": null}, "bottom": {"style": null, "color": null}, "diagonal": {"style": null, "color": null}, "diagonal_down": false, "diagonal_up": false, "outline": true, "vertical": null, "horizontal": null}, "protection": {"locked": true, "hidden": false}}
A4: Intro | B4: C1 | C4: 1 | D4: 3 | E4: Input | H4: {"type": "null", "value": null} | I4: General | J4: FALSE | K4: FALSE | L4: 11 | M4: Values must be of type <class 'str'> | N4: 00000000 | R4: FALSE | W4: {"number_format": "General", "font": {"name": "Calibri", "size": 11.0, "bold": false, "italic": false, "underline": null, "strike": null, "color": {"type": "theme", "rgb": "Values must be of type <class 'str'>", "indexed": null, "theme": 1, "tint": 0.0, "auto": null}, "vert_align": null}, "fill": {"fill_type": null, "fg_color": {"type": "rgb", "rgb": "00000000", "indexed": null, "theme": null, "tint": 0.0, "auto": null}, "bg_color": {"type": "rgb", "rgb": "00000000", "indexed": null, "theme": null, "tint": 0.0, "auto": null}}, "alignment": {"horizontal": null, "vertical": null, "text_rotation": 0, "wrap_text": null, "shrink_to_fit": null, "indent": 0.0}, "border": {"left": {"style": null, "color": null}, "right": {"style": null, "color": null}, "top": {"style": null, "color": null}, "bottom": {"style": null, "color": null}, "diagonal": {"style": null, "color": null}, "diagonal_down": false, "diagonal_up": false, "outline": true, "vertical": null, "horizontal": null}, "protection": {"locked": true, "hidden": false}}
A5: Intro | B5: D1 | C5: 1 | D5: 4 | E5: Input | H5: {"type": "null", "value": null} | I5: General | J5: FALSE | K5: FALSE | L5: 11 | M5: Values must be of type <class 'str'> | N5: 00000000 | R5: FALSE | W5: {"number_format": "General", "font": {"name": "Calibri", "size": 11.0, "bold": false, "italic": false, "underline": null, "strike": null, "color": {"type": "theme", "rgb": "Values must be of type <class 'str'>", "indexed": null, "theme": 1, "tint": 0.0, "auto": null}, "vert_align": null}, "fill": {"fill_type": null, "fg_color": {"type": "rgb", "rgb": "00000000", "indexed": null, "theme": null, "tint": 0.0, "auto": null}, "bg_color": {"type": "rgb", "rgb": "00000000", "indexed": null, "theme": null, "tint": 0.0, "auto": null}}, "alignment": {"horizontal": null, "vertical": null, "text_rotation": 0, "wrap_text": null, "shrink_to_fit": null, "indent": 0.0}, "border": {"left": {"style": null, "color": null}, "right": {"style": null, "color": null}, "top": {"style": null, "color": null}, "bottom": {"style": null, "color": null}, "diagonal": {"style": null, "color": null}, "diagonal_down": false, "diagonal_up": false, "outline": true, "vertical": null, "horizontal": null}, "protection": {"locked": true, "hidden": false}}
A6: Intro | B6: E1 | C6: 1 | D6: 5 | E6: Input | H6: {"type": "null", "value": null} | I6: General | J6: FALSE | K6: FALSE | L6: 11 | M6: Values must be of type <class 'str'> | N6: 00000000 | R6: FALSE | W6: {"number_format": "General", "font": {"name": "Calibri", "size": 11.0, "bold": false, "italic": false, "underline": null, "strike": null, "color": {"type": "theme", "rgb": "Values must be of type <class 'str'>", "indexed": null, "theme": 1, "tint": 0.0, "auto": null}, "vert_align": null}, "fill": {"fill_type": null, "fg_color": {"type": "rgb", "rgb": "00000000", "indexed": null, "theme": null, "tint": 0.0, "auto": null}, "bg_color": {"type": "rgb", "rgb": "00000000", "indexed": null, "theme": null, "tint": 0.0, "auto": null}}, "alignment": {"horizontal": null, "vertical": null, "text_rotation": 0, "wrap_text": null, "shrink_to_fit": null, "indent": 0.0}, "border": {"left": {"style": null, "color": null}, "right": {"style": null, "color": null}, "top": {"style": null, "color": null}, "bottom": {"style": null, "color": null}, "diagonal": {"style": null, "color": null}, "diagonal_down": false, "diagonal_up": false, "outline": true, "vertical": null, "horizontal": null}, "protection": {"locked": true, "hidden": false}}
A7: Intro | B7: F1 | C7: 1 | D7: 6 | E7: Input | H7: {"type": "null", "value": null} | I7: General | J7: FALSE | K7: FALSE | L7: 11 | M7: Values must be of type <class 'str'> | N7: 00000000 | R7: FALSE | W7: {"number_format": "General", "font": {"name": "Calibri", "size": 11.0, "bold": false, "italic": false, "underline": null, "strike": null, "color": {"type": "theme", "rgb": "Values must be of type <class 'str'>", "indexed": null, "theme": 1, "tint": 0.0, "auto": null}, "vert_align": null}, "fill": {"fill_type": null, "fg_color": {"type": "rgb", "rgb": "00000000", "indexed": null, "theme": null, "tint": 0.0, "auto": null}, "bg_color": {"type": "rgb", "rgb": "00000000", "indexed": null, "theme": null, "tint": 0.0, "auto": null}}, "alignment": {"horizontal": null, "vertical": null, "text_rotation": 0, "wrap_text": null, "shrink_to_fit": null, "indent": 0.0}, "border": {"left": {"style": null, "color": null}, "right": {"style": null, "color": null}, "top": {"style": null, "color": null}, "bottom": {"style": null, "color": null}, "diagonal": {"style": null, "color": null}, "diagonal_down": false, "diagonal_up": false, "outline": true, "vertical": null, "horizontal": null}, "protection": {"locked": true, "hidden": false}}
A8: Intro | B8: G1 | C8: 1 | D8: 7 | E8: Input | H8: {"type": "null", "value": null} | I8: General | J8: FALSE | K8: FALSE | L8: 11 | M8: Values must be of type <class 'str'> | N8: 00000000 | R8: FALSE | W8: {"number_format": "General", "font": {"name": "Calibri", "size": 11.0, "bold": false, "italic": false, "underline": null, "strike": null, "color": {"type": "theme", "rgb": "Values must be of type <class 'str'>", "indexed": null, "theme": 1, "tint": 0.0, "auto": null}, "vert_align": null}, "fill": {"fill_type": null, "fg_color": {"type": "rgb", "rgb": "00000000", "indexed": null, "theme": null, "tint": 0.0, "auto": null}, "bg_color": {"type": "rgb", "rgb": "00000000", "indexed": null, "theme": null, "tint": 0.0, "auto": null}}, "alignment": {"horizontal": null, "vertical": null, "text_rotation": 0, "wrap_text": null, "shrink_to_fit": null, "indent": 0.0}, "border": {"left": {"style": null, "color": null}, "right": {"style": null, "color": null}, "top": {"style": null, "color": null}, "bottom": {"style": null, "color": null}, "diagonal": {"style": null, "color": null}, "diagonal_down": false, "diagonal_up": false, "outline": true, "vertical": null, "horizontal": null}, "protection": {"locked": true, "hidden": false}}
A9: Intro | B9: A2 | C9: 2 | D9: 1 | E9: Input | H9: {"type": "null", "value": null} | I9: General | J9: FALSE | K9: FALSE | L9: 11 | M9: Values must be of type <class 'str'> | N9: 00000000 | R9: FALSE | W9: {"number_format": "General", "font": {"name": "Calibri", "size": 11.0, "bold": false, "italic": false, "underline": null, "strike": null, "color": {"type": "theme", "rgb": "Values must be of type <class 'str'>", "indexed": null, "theme": 1, "tint": 0.0, "auto": null}, "vert_align": null}, "fill": {"fill_type": null, "fg_color": {"type": "rgb", "rgb": "00000000", "indexed": null, "theme": null, "tint": 0.0, "auto": null}, "bg_color": {"type": "rgb", "rgb": "00000000", "indexed": null, "theme": null, "tint": 0.0, "auto": null}}, "alignment": {"horizontal": null, "vertical": null, "text_rotation": 0, "wrap_text": null, "shrink_to_fit": null, "indent": 0.0}, "border": {"left": {"style": null, "color": null}, "right": {"style": null, "color": null}, "top": {"style": null, "color": null}, "bottom": {"style": null, "color": null}, "diagonal": {"style": null, "color": null}, "diagonal_down": false, "diagonal_up": false, "outline": true, "vertical": null, "horizontal": null}, "protection": {"locked": true, "hidden": false}}
A10: Intro | B10: B2 | C10: 2 | D10: 2 | E10: Input | H10: {"type": "null", "value": null} | I10: General | J10: FALSE | K10: FALSE | L10: 11 | M10: Values must be of type <class 'str'> | N10: 00000000 | R10: FALSE | W10: {"number_format": "General", "font": {"name": "Calibri", "size": 11.0, "bold": false, "italic": false, "underline": null, "strike": null, "color": {"type": "theme", "rgb": "Values must be of type <class 'str'>", "indexed": null, "theme": 1, "tint": 0.0, "auto": null}, "vert_align": null}, "fill": {"fill_type": null, "fg_color": {"type": "rgb", "rgb": "00000000", "indexed": null, "theme": null, "tint": 0.0, "auto": null}, "bg_color": {"type": "rgb", "rgb": "00000000", "indexed": null, "theme": null, "tint": 0.0, "auto": null}}, "alignment": {"horizontal": null, "vertical": null, "text_rotation": 0, "wrap_text": null, "shrink_to_fit": null, "indent": 0.0}, "border": {"left": {"style": null, "color": null}, "right": {"style": null, "color": null}, "top": {"style": null, "color": null}, "bottom": {"style": null, "color": null}, "diagonal": {"style": null, "color": null}, "diagonal_down": false, "diagonal_up": false, "outline": true, "vertical": null, "horizontal": null}, "protection": {"locked": true, "hidden": false}}
A11: Intro | B11: C2 | C11: 2 | D11: 3 | E11: Input | H11: {"type": "null", "value": null} | I11: General | J11: FALSE | K11: FALSE | L11: 11 | M11: Values must be of type <class 'str'> | N11: 00000000 | R11: FALSE | W11: {"number_format": "General", "font": {"name": "Calibri", "size": 11.0, "bold": false, "italic": false, "underline": null, "strike": null, "color": {"type": "theme", "rgb": "Values must be of type <class 'str'>", "indexed": null, "theme": 1, "tint": 0.0, "auto": null}, "vert_align": null}, "fill": {"fill_type": null, "fg_color": {"type": "rgb", "rgb": "00000000", "indexed": null, "theme": null, "tint": 0.0, "auto": null}, "bg_color": {"type": "rgb", "rgb": "00000000", "indexed": null, "theme": null, "tint": 0.0, "auto": null}}, "alignment": {"horizontal": null, "vertical": null, "text_rotation": 0, "wrap_text": null, "shrink_to_fit": null, "indent": 0.0}, "border": {"left": {"style": null, "color": null}, "right": {"style": null, "color": null}, "top": {"style": null, "color": null}, "bottom": {"style": null, "color": null}, "diagonal": {"style": null, "color": null}, "diagonal_down": false, "diagonal_up": false, "outline": true, "vertical": null, "horizontal": null}, "protection": {"locked": true, "hidden": false}}
A12: Intro | B12: D2 | C12: 2 | D12: 4 | E12: Input | H12: {"type": "null", "value": null} | I12: General | J12: FALSE | K12: FALSE | L12: 11 | M12: Values must be of type <class 'str'> | N12: 00000000 | R12: FALSE | W12: {"number_format": "General", "font": {"name": "Calibri", "size": 11.0, "bold": false, "italic": false, "underline": null, "strike": null, "color": {"type": "theme", "rgb": "Values must be of type <class 'str'>", "indexed": null, "theme": 1, "tint": 0.0, "auto": null}, "vert_align": null}, "fill": {"fill_type": null, "fg_color": {"type": "rgb", "rgb": "00000000", "indexed": null, "theme": null, "tint": 0.0, "auto": null}, "bg_color": {"type": "rgb", "rgb": "00000000", "indexed": null, "theme": null, "tint": 0.0, "auto": null}}, "alignment": {"horizontal": null, "vertical": null, "text_rotation": 0, "wrap_text": null, "shrink_to_fit": null, "indent": 0.0}, "border": {"left": {"style": null, "color": null}, "right": {"style": null, "color": null}, "top": {"style": null, "color": null}, "bottom": {"style": null, "color": null}, "diagonal": {"style": null, "color": null}, "diagonal_down": false, "diagonal_up": false, "outline": true, "vertical": null, "horizontal": null}, "protection": {"locked": true, "hidden": false}}
A13: Intro | B13: E2 | C13: 2 | D13: 5 | E13: Input | G13: Reference Model | H13: {"type": "str", "value": "Reference Model"} | I13: General | J13: TRUE | K13: FALSE | L13: 22 | M13: FF404040 | N13: 00000000 | O13: center | R13: TRUE | W13: {"number_format": "General", "font": {"name": "Calibri", "size": 22.0, "bold": true, "italic": false, "underline": "single", "strike": null, "color": {"type": "rgb", "rgb": "FF404040", "indexed": null, "theme": null, "tint": 0.0, "auto": null}, "vert_align": null}, "fill": {"fill_type": null, "fg_color": {"type": "rgb", "rgb": "00000000", "indexed": null, "theme": null, "tint": 0.0, "auto": null}, "bg_color": {"type": "rgb", "rgb": "00000000", "indexed": null, "theme": null, "tint": 0.0, "auto": null}}, "alignment": {"horizontal": "center", "vertical": null, "text_rotation": 0, "wrap_text": null, "shrink_to_fit": null, "indent": 0.0}, "border": {"left": {"style": null, "color": null}, "right": {"style": null, "color": null}, "top": {"style": null, "color": null}, "bottom": {"style": null, "color": null}, "diagonal": {"style": null, "color": null}, "diagonal_down": false, "diagonal_up": false, "outline": true, "vertical": null, "horizontal": null}, "protection": {"locked": true, "hidden": false}}
A14: Intro | B14: F2 | C14: 2 | D14: 6 | E14: Input | H14: {"type": "null", "value": null} | I14: General | J14: FALSE | K14: FALSE | L14: 11 | M14: Values must be of type <class 'str'> | N14: 00000000 | R14: FALSE | W14: {"number_format": "General", "font": {"name": "Calibri", "size": 11.0, "bold": false, "italic": false, "underline": null, "strike": null, "color": {"type": "theme", "rgb": "Values must be of type <class 'str'>", "indexed": null, "theme": 1, "tint": 0.0, "auto": null}, "vert_align": null}, "fill": {"fill_type": null, "fg_color": {"type": "rgb", "rgb": "00000000", "indexed": null, "theme": null, "tint": 0.0, "auto": null}, "bg_color": {"type": "rgb", "rgb": "00000000", "indexed": null, "theme": null, "tint": 0.0, "auto": null}}, "alignment": {"horizontal": null, "vertical": null, "text_rotation": 0, "wrap_text": null, "shrink_to_fit": null, "indent": 0.0}, "border": {"left": {"style": null, "color": null}, "right": {"style": null, "color": null}, "top": {"style": null, "color": null}, "bottom": {"style": null, "color": null}, "diagonal": {"style": null, "color": null}, "diagonal_down": false, "diagonal_up": false, "outline": true, "vertical": null, "horizontal": null}, "protection": {"locked": true, "hidden": false}}
A15: Intro | B15: G2 | C15: 2 | D15: 7 | E15: Input | H15: {"type": "null", "value": null} | I15: General | J15: FALSE | K15: FALSE | L15: 11 | M15: Values must be of type <class 'str'> | N15: 00000000 | R15: FALSE | W15: {"number_format": "General", "font": {"name": "Calibri", "size": 11.0, "bold": false, "italic": false, "underline": null, "strike": null, "color": {"type": "theme", "rgb": "Values must be of type <class 'str'>", "indexed": null, "theme": 1, "tint": 0.0, "auto": null}, "vert_align": null}, "fill": {"fill_type": null, "fg_color": {"type": "rgb", "rgb": "00000000", "indexed": null, "theme": null, "tint": 0.0, "auto": null}, "bg_color": {"type": "rgb", "rgb": "00000000", "indexed": null, "theme": null, "tint": 0.0, "auto": null}}, "alignment": {"horizontal": null, "vertical": null, "text_rotation": 0, "wrap_text": null, "shrink_to_fit": null, "indent": 0.0}, "border": {"left": {"style": null, "color": null}, "right": {"style": null, "color": null}, "top": {"style": null, "color": null}, "bottom": {"style": null, "color": null}, "diagonal": {"style": null, "color": null}, "diagonal_down": false, "diagonal_up": false, "outline": true, "vertical": null, "horizontal": null}, "protection": {"locked": true, "hidden": false}}
A16: Intro | B16: A3 | C16: 3 | D16: 1 | E16: Input | H16: {"type": "null", "value": null} | I16: General | J16: FALSE | K16: FALSE | L16: 11 | M16: Values must be of type <class 'str'> | N16: 00000000 | R16: FALSE | W16: {"number_format": "General", "font": {"name": "Calibri", "size": 11.0, "bold": false, "italic": false, "underline": null, "strike": null, "color": {"type": "theme", "rgb": "Values must be of type <class 'str'>", "indexed": null, "theme": 1, "tint": 0.0, "auto": null}, "vert_align": null}, "fill": {"fill_type": null, "fg_color": {"type": "rgb", "rgb": "00000000", "indexed": null, "theme": null, "tint": 0.0, "auto": null}, "bg_color": {"type": "rgb", "rgb": "00000000", "indexed": null, "theme": null, "tint": 0.0, "auto": null}}, "alignment": {"horizontal": null, "vertical": null, "text_rotation": 0, "wrap_text": null, "shrink_to_fit": null, "indent": 0.0}, "border": {"left": {"style": null, "color": null}, "right": {"style": null, "color": null}, "top": {"style": null, "color": null}, "bottom": {"style": null, "color": null}, "diagonal": {"style": null, "color": null}, "diagonal_down": false, "diagonal_up": false, "outline": true, "vertical": null, "horizontal": null}, "protection": {"locked": true, "hidden": false}}
A17: Intro | B17: B3 | C17: 3 | D17: 2 | E17: Input | H17: {"type": "null", "value": null} | I17: General | J17: FALSE | K17: FALSE | L17: 11 | M17: Values must be of type <class 'str'> | N17: 00000000 | R17: FALSE | W17: {"number_format": "General", "font": {"name": "Calibri", "size": 11.0, "bold": false, "italic": false, "underline": null, "strike": null, "color": {"type": "theme", "rgb": "Values must be of type <class 'str'>", "indexed": null, "theme": 1, "tint": 0.0, "auto": null}, "vert_align": null}, "fill": {"fill_type": null, "fg_color": {"type": "rgb", "rgb": "00000000", "indexed": null, "theme": null, "tint": 0.0, "auto": null}, "bg_color": {"type": "rgb", "rgb": "00000000", "indexed": null, "theme": null, "tint": 0.0, "auto": null}}, "alignment": {"horizontal": null, "vertical": null, "text_rotation": 0, "wrap_text": null, "shrink_to_fit": null, "indent": 0.0}, "border": {"left": {"style": null, "color": null}, "right": {"style": null, "color": null}, "top": {"style": null, "color": null}, "bottom": {"style": null, "color": null}, "diagonal": {"style": null, "color": null}, "diagonal_down": false, "diagonal_up": false, "outline": true, "vertical": null, "horizontal": null}, "protection": {"locked": true, "hidden": false}}
A18: Intro | B18: C3 | C18: 3 | D18: 3 | E18: Input | H18: {"type": "null", "value": null} | I18: General | J18: FALSE | K18: FALSE | L18: 11 | M18: Values must be of type <class 'str'> | N18: 00000000 | R18: FALSE | W18: {"number_format": "General", "font": {"name": "Calibri", "size": 11.0, "bold": false, "italic": false, "underline": null, "strike": null, "color": {"type": "theme", "rgb": "Values must be of type <class 'str'>", "indexed": null, "theme": 1, "tint": 0.0, "auto": null}, "vert_align": null}, "fill": {"fill_type": null, "fg_color": {"type": "rgb", "rgb": "00000000", "indexed": null, "theme": null, "tint": 0.0, "auto": null}, "bg_color": {"type": "rgb", "rgb": "00000000", "indexed": null, "theme": null, "tint": 0.0, "auto": null}}, "alignment": {"horizontal": null, "vertical": null, "text_rotation": 0, "wrap_text": null, "shrink_to_fit": null, "indent": 0.0}, "border": {"left": {"style": null, "color": null}, "right": {"style": null, "color": null}, "top": {"style": null, "color": null}, "bottom": {"style": null, "color": null}, "diagonal": {"style": null, "color": null}, "diagonal_down": false, "diagonal_up": false, "outline": true, "vertical": null, "horizontal": null}, "protection": {"locked": true, "hidden": false}}
A19: Intro | B19: D3 | C19: 3 | D19: 4 | E19: Input | H19: {"type": "null", "value": null} | I19: General | J19: FALSE | K19: FALSE | L19: 11 | M19: Values must be of type <class 'str'> | N19: 00000000 | R19: FALSE | W19: {"number_format": "General", "font": {"name": "Calibri", "size": 11.0, "bold": false, "italic": false, "underline": null, "strike": null, "color": {"type": "theme", "rgb": "Values must be of type <class 'str'>", "indexed": null, "theme": 1, "tint": 0.0, "auto": null}, "vert_align": null}, "fill": {"fill_type": null, "fg_color": {"type": "rgb", "rgb": "00000000", "indexed": null, "theme": null, "tint": 0.0, "auto": null}, "bg_color": {"type": "rgb", "rgb": "00000000", "indexed": null, "theme": null, "tint": 0.0, "auto": null}}, "alignment": {"horizontal": null, "vertical": null, "text_rotation": 0, "wrap_text": null, "shrink_to_fit": null, "indent": 0.0}, "border": {"left": {"style": null, "color": null}, "right": {"style": null, "color": null}, "top": {"style": null, "color": null}, "bottom": {"style": null, "color": null}, "diagonal": {"style": null, "color": null}, "diagonal_down": false, "diagonal_up": false, "outline": true, "vertical": null, "horizontal": null}, "protection": {"locked": true, "hidden": false}}
A20: Intro | B20: E3 | C20: 3 | D20: 5 | E20: Input | H20: {"type": "null", "value": null} | I20: General | J20: FALSE | K20: FALSE | L20: 11 | M20: Values must be of type <class 'str'> | N20: 00000000 | R20: FALSE | W20: {"number_format": "General", "font": {"name": "Calibri", "size": 11.0, "bold": false, "italic": false, "underline": null, "strike": null, "color": {"type": "theme", "rgb": "Values must be of type <class 'str'>", "indexed": null, "theme": 1, "tint": 0.0, "auto": null}, "vert_align": null}, "fill": {"fill_type": null, "fg_color": {"type": "rgb", "rgb": "00000000", "indexed": null, "theme": null, "tint": 0.0, "auto": null}, "bg_color": {"type": "rgb", "rgb": "00000000", "indexed": null, "theme": null, "tint": 0.0, "auto": null}}, "alignment": {"horizontal": null, "vertical": null, "text_rotation": 0, "wrap_text": null, "shrink_to_fit": null, "indent": 0.0}, "border": {"left": {"style": null, "color": null}, "right": {"style": null, "color": null}, "top": {"style": null, "color": null}, "bottom": {"style": null, "color": null}, "diagonal": {"style": null, "color": null}, "diagonal_down": false, "diagonal_up": false, "outline": true, "vertical": null, "horizontal": null}, "protection": {"locked": true, "hidden": false}}
A21: Intro | B21: F3 | C21: 3 | D21: 6 | E21: Input | H21: {"type": "null", "value": null} | I21: General | J21: FALSE | K21: FALSE | L21: 11 | M21: Values must be of type <class 'str'> | N21: 00000000 | R21: FALSE | W21: {"number_format": "General", "font": {"name": "Calibri", "size": 11.0, "bold": false, "italic": false, "underline": null, "strike": null, "color": {"type": "theme", "rgb": "Values must be of type <class 'str'>", "indexed": null, "theme": 1, "tint": 0.0, "auto": null}, "vert_align": null}, "fill": {"fill_type": null, "fg_color": {"type": "rgb", "rgb": "00000000", "indexed": null, "theme": null, "tint": 0.0, "auto": null}, "bg_color": {"type": "rgb", "rgb": "00000000", "indexed": null, "theme": null, "tint": 0.0, "auto": null}}, "alignment": {"horizontal": null, "vertical": null, "text_rotation": 0, "wrap_text": null, "shrink_to_fit": null, "indent": 0.0}, "border": {"left": {"style": null, "color": null}, "right": {"style": null, "color": null}, "top": {"style": null, "color": null}, "bottom": {"style": null, "color": null}, "diagonal": {"style": null, "color": null}, "diagonal_down": false, "diagonal_up": false, "outline": true, "vertical": null, "horizontal": null}, "protection": {"locked": true, "hidden": false}}
A22: Intro | B22: G3 | C22: 3 | D22: 7 | E22: Input | H22: {"type": "null", "value": null} | I22: General | J22: FALSE | K22: FALSE | L22: 11 | M22: Values must be of type <class 'str'> | N22: 00000000 | R22: FALSE | W22: {"number_format": "General", "font": {"name": "Calibri", "size": 11.0, "bold": false, "italic": false, "underline": null, "strike": null, "color": {"type": "theme", "rgb": "Values must be of type <class 'str'>", "indexed": null, "theme": 1, "tint": 0.0, "auto": null}, "vert_align": null}, "fill": {"fill_type": null, "fg_color": {"type": "rgb", "rgb": "00000000", "indexed": null, "theme": null, "tint": 0.0, "auto": null}, "bg_color": {"type": "rgb", "rgb": "00000000", "indexed": null, "theme": null, "tint": 0.0, "auto": null}}, "alignment": {"horizontal": null, "vertical": null, "text_rotation": 0, "wrap_text": null, "shrink_to_fit": null, "indent": 0.0}, "border": {"left": {"style": null, "color": null}, "right": {"style": null, "color": null}, "top": {"style": null, "color": null}, "bottom": {"style": null, "color": null}, "diagonal": {"style": null, "color": null}, "diagonal_down": false, "diagonal_up": false, "outline": true, "vertical": null, "horizontal": null}, "protection": {"locked": true, "hidden": false}}
A23: Intro | B23: A4 | C23: 4 | D23: 1 | E23: Input | H23: {"type": "null", "value": null} | I23: General | J23: FALSE | K23: FALSE | L23: 11 | M23: Values must be of type <class 'str'> | N23: 00000000 | R23: FALSE | W23: {"number_format": "General", "font": {"name": "Calibri", "size": 11.0, "bold": false, "italic": false, "underline": null, "strike": null, "color": {"type": "theme", "rgb": "Values must be of type <class 'str'>", "indexed": null, "theme": 1, "tint": 0.0, "auto": null}, "vert_align": null}, "fill": {"fill_type": null, "fg_color": {"type": "rgb", "rgb": "00000000", "indexed": null, "theme": null, "tint": 0.0, "auto": null}, "bg_color": {"type": "rgb", "rgb": "00000000", "indexed": null, "theme": null, "tint": 0.0, "auto": null}}, "alignment": {"horizontal": null, "vertical": null, "text_rotation": 0, "wrap_text": null, "shrink_to_fit": null, "indent": 0.0}, "border": {"left": {"style": null, "color": null}, "right": {"style": null, "color": null}, "top": {"style": null, "color": null}, "bottom": {"style": null, "color": null}, "diagonal": {"style": null, "color": null}, "diagonal_down": false, "diagonal_up": false, "outline": true, "vertical": null, "horizontal": null}, "protection": {"locked": true, "hidden": false}}
A24: Intro | B24: B4 | C24: 4 | D24: 2 | E24: Input | H24: {"type": "null", "value": null} | I24: General | J24: FALSE | K24: FALSE | L24: 11 | M24: Values must be of type <class 'str'> | N24: 00000000 | R24: FALSE | W24: {"number_format": "General", "font": {"name": "Calibri", "size": 11.0, "bold": false, "italic": false, "underline": null, "strike": null, "color": {"type": "theme", "rgb": "Values must be of type <class 'str'>", "indexed": null, "theme": 1, "tint": 0.0, "auto": null}, "vert_align": null}, "fill": {"fill_type": null, "fg_color": {"type": "rgb", "rgb": "00000000", "indexed": null, "theme": null, "tint": 0.0, "auto": null}, "bg_color": {"type": "rgb", "rgb": "00000000", "indexed": null, "theme": null, "tint": 0.0, "auto": null}}, "alignment": {"horizontal": null, "vertical": null, "text_rotation": 0, "wrap_text": null, "shrink_to_fit": null, "indent": 0.0}, "border": {"left": {"style": null, "color": null}, "right": {"style": null, "color": null}, "top": {"style": null, "color": null}, "bottom": {"style": null, "color": null}, "diagonal": {"style": null, "color": null}, "diagonal_down": false, "diagonal_up": false, "outline": true, "vertical": null, "horizontal": null}, "protection": {"locked": true, "hidden": false}}
A25: Intro | B25: C4 | C25: 4 | D25: 3 | E25: Input | H25: {"type": "null", "value": null} | I25: General | J25: FALSE | K25: FALSE | L25: 11 | M25: Values must be of type <class 'str'> | N25: 00000000 | R25: FALSE | W25: {"number_format": "General", "font": {"name": "Calibri", "size": 11.0, "bold": false, "italic": false, "underline": null, "strike": null, "color": {"type": "theme", "rgb": "Values must be of type <class 'str'>", "indexed": null, "theme": 1, "tint": 0.0, "auto": null}, "vert_align": null}, "fill": {"fill_type": null, "fg_color": {"type": "rgb", "rgb": "00000000", "indexed": null, "theme": null, "tint": 0.0, "auto": null}, "bg_color": {"type": "rgb", "rgb": "00000000", "indexed": null, "theme": null, "tint": 0.0, "auto": null}}, "alignment": {"horizontal": null, "vertical": null, "text_rotation": 0, "wrap_text": null, "shrink_to_fit": null, "indent": 0.0}, "border": {"left": {"style": null, "color": null}, "right": {"style": null, "color": null}, "top": {"style": null, "color": null}, "bottom": {"style": null, "color": null}, "diagonal": {"style": null, "color": null}, "diagonal_down": false, "diagonal_up": false, "outline": true, "vertical": null, "horizontal": null}, "protection": {"locked": true, "hidden": false}}
A26: Intro | B26: D4 | C26: 4 | D26: 4 | E26: Input | H26: {"type": "null", "value": null} | I26: General | J26: FALSE | K26: FALSE | L26: 11 | M26: Values must be of type <class 'str'> | N26: 00000000 | R26: FALSE | W26: {"number_format": "General", "font": {"name": "Calibri", "size": 11.0, "bold": false, "italic": false, "underline": null, "strike": null, "color": {"type": "theme", "rgb": "Values must be of type <class 'str'>", "indexed": null, "theme": 1, "tint": 0.0, "auto": null}, "vert_align": null}, "fill": {"fill_type": null, "fg_color": {"type": "rgb", "rgb": "00000000", "indexed": null, "theme": null, "tint": 0.0, "auto": null}, "bg_color": {"type": "rgb", "rgb": "00000000", "indexed": null, "theme": null, "tint": 0.0, "auto": null}}, "alignment": {"horizontal": null, "vertical": null, "text_rotation": 0, "wrap_text": null, "shrink_to_fit": null, "indent": 0.0}, "border": {"left": {"style": null, "color": null}, "right": {"style": null, "color": null}, "top": {"style": null, "color": null}, "bottom": {"style": null, "color": null}, "diagonal": {"style": null, "color": null}, "diagonal_down": false, "diagonal_up": false, "outline": true, "vertical": null, "horizontal": null}, "protection": {"locked": true, "hidden": false}}
A27: Intro | B27: E4 | C27: 4 | D27: 5 | E27: Input | G27: ACC Cement | H27: {"type": "str", "value": "ACC Cement"} | I27: General | J27: TRUE | K27: FALSE | L27: 32 | M27: Values must be of type <class 'str'> | N27: 00000000 | O27: center | R27: TRUE | W27: {"number_format": "General", "font": {"name": "Calibri", "size": 32.0, "bold": true, "italic": false, "underline": null, "strike": null, "color": {"type": "theme", "rgb": "Values must be of type <class 'str'>", "indexed": null, "theme": 1, "tint": 0.0, "auto": null}, "vert_align": null}, "fill": {"fill_type": null, "fg_color": {"type": "rgb", "rgb": "00000000", "indexed": null, "theme": null, "tint": 0.0, "auto": null}, "bg_color": {"type": "rgb", "rgb": "00000000", "indexed": null, "theme": null, "tint": 0.0, "auto": null}}, "alignment": {"horizontal": "center", "vertical": null, "text_rotation": 0, "wrap_text": null, "shrink_to_fit": null, "indent": 0.0}, "border": {"left": {"style": null, "color": null}, "right": {"style": null, "color": null}, "top": {"style": null, "color": null}, "bottom": {"style": null, "color": null}, "diagonal": {"style": null, "color": null}, "diagonal_down": false, "diagonal_up": false, "outline": true, "vertical": null, "horizontal": null}, "protection": {"locked": true, "hidden": false}}
A28: Intro | B28: F4 | C28: 4 | D28: 6 | E28: Input | H28: {"type": "null", "value": null} | I28: General | J28: FALSE | K28: FALSE | L28: 11 | M28: Values must be of type <class 'str'> | N28: 00000000 | R28: FALSE | W28: {"number_format": "General", "font": {"name": "Calibri", "size": 11.0, "bold": false, "italic": false, "underline": null, "strike": null, "color": {"type": "theme", "rgb": "Values must be of type <class 'str'>", "indexed": null, "theme": 1, "tint": 0.0, "auto": null}, "vert_align": null}, "fill": {"fill_type": null, "fg_color": {"type": "rgb", "rgb": "00000000", "indexed": null, "theme": null, "tint": 0.0, "auto": null}, "bg_color": {"type": "rgb", "rgb": "00000000", "indexed": null, "theme": null, "tint": 0.0, "auto": null}}, "alignment": {"horizontal": null, "vertical": null, "text_rotation": 0, "wrap_text": null, "shrink_to_fit": null, "indent": 0.0}, "border": {"left": {"style": null, "color": null}, "right": {"style": null, "color": null}, "top": {"style": null, "color": null}, "bottom": {"style": null, "color": null}, "diagonal": {"style": null, "color": null}, "diagonal_down": false, "diagonal_up": false, "outline": true, "vertical": null, "horizontal": null}, "protection": {"locked": true, "hidden": false}}
A29: Intro | B29: G4 | C29: 4 | D29: 7 | E29: Input | H29: {"type": "null", "value": null} | I29: General | J29: FALSE | K29: FALSE | L29: 11 | M29: Values must be of type <class 'str'> | N29: 00000000 | R29: FALSE | W29: {"number_format": "General", "font": {"name": "Calibri", "size": 11.0, "bold": false, "italic": false, "underline": null, "strike": null, "color": {"type": "theme", "rgb": "Values must be of type <class 'str'>", "indexed": null, "theme": 1, "tint": 0.0, "auto": null}, "vert_align": null}, "fill": {"fill_type": null, "fg_color": {"type": "rgb", "rgb": "00000000", "indexed": null, "theme": null, "tint": 0.0, "auto": null}, "bg_color": {"type": "rgb", "rgb": "00000000", "indexed": null, "theme": null, "tint": 0.0, "auto": null}}, "alignment": {"horizontal": null, "vertical": null, "text_rotation": 0, "wrap_text": null, "shrink_to_fit": null, "indent": 0.0}, "border": {"left": {"style": null, "color": null}, "right": {"style": null, "color": null}, "top": {"style": null, "color": null}, "bottom": {"style": null, "color": null}, "diagonal": {"style": null, "color": null}, "diagonal_down": false, "diagonal_up": false, "outline": true, "vertical": null, "horizontal": null}, "protection": {"locked": true, "hidden": false}}
A30: Intro | B30: A5 | C30: 5 | D30: 1 | E30: Input | H30: {"type": "null", "value": null} | I30: General | J30: FALSE | K30: FALSE | L30: 11 | M30: Values must be of type <class 'str'> | N30: 00000000 | R30: FALSE | W30: {"number_format": "General", "font": {"name": "Calibri", "size": 11.0, "bold": false, "italic": false, "underline": null, "strike": null, "color": {"type": "theme", "rgb": "Values must be of type <class 'str'>", "indexed": null, "theme": 1, "tint": 0.0, "auto": null}, "vert_align": null}, "fill": {"fill_type": null, "fg_color": {"type": "rgb", "rgb": "00000000", "indexed": null, "theme": null, "tint": 0.0, "auto": null}, "bg_color": {"type": "rgb", "rgb": "00000000", "indexed": null, "theme": null, "tint": 0.0, "auto": null}}, "alignment": {"horizontal": null, "vertical": null, "text_rotation": 0, "wrap_text": null, "shrink_to_fit": null, "indent": 0.0}, "border": {"left": {"style": null, "color": null}, "right": {"style": null, "color": null}, "top": {"style": null, "color": null}, "bottom": {"style": null, "color": null}, "diagonal": {"style": null, "color": null}, "diagonal_down": false, "diagonal_up": false, "outline": true, "vertical": null, "horizontal": null}, "protection": {"locked": true, "hidden": false}}
A31: Intro | B31: B5 | C31: 5 | D31: 2 | E31: Input | H31: {"type": "null", "value": null} | I31: General | J31: FALSE | K31: FALSE | L31: 11 | M31: Values must be of type <class 'str'> | N31: 00000000 | R31: FALSE | W31: {"number_format": "General", "font": {"name": "Calibri", "size": 11.0, "bold": false, "italic": false, "underline": null, "strike": null, "color": {"type": "theme", "rgb": "Values must be of type <class 'str'>", "indexed": null, "theme": 1, "tint": 0.0, "auto": null}, "vert_align": null}, "fill": {"fill_type": null, "fg_color": {"type": "rgb", "rgb": "00000000", "indexed": null, "theme": null, "tint": 0.0, "auto": null}, "bg_color": {"type": "rgb", "rgb": "00000000", "indexed": null, "theme": null, "tint": 0.0, "auto": null}}, "alignment": {"horizontal": null, "vertical": null, "text_rotation": 0, "wrap_text": null, "shrink_to_fit": null, "indent": 0.0}, "border": {"left": {"style": null, "color": null}, "right": {"style": null, "color": null}, "top": {"style": null, "color": null}, "bottom": {"style": null, "color": null}, "diagonal": {"style": null, "color": null}, "diagonal_down": false, "diagonal_up": false, "outline": true, "vertical": null, "horizontal": null}, "protection": {"locked": true, "hidden": false}}
A32: Intro | B32: C5 | C32: 5 | D32: 3 | E32: Input | H32: {"type": "null", "value": null} | I32: General | J32: FALSE | K32: FALSE | L32: 11 | M32: Values must be of type <class 'str'> | N32: 00000000 | R32: FALSE | W32: {"number_format": "General", "font": {"name": "Calibri", "size": 11.0, "bold": false, "italic": false, "underline": null, "strike": null, "color": {"type": "theme", "rgb": "Values must be of type <class 'str'>", "indexed": null, "theme": 1, "tint": 0.0, "auto": null}, "vert_align": null}, "fill": {"fill_type": null, "fg_color": {"type": "rgb", "rgb": "00000000", "indexed": null, "theme": null, "tint": 0.0, "auto": null}, "bg_color": {"type": "rgb", "rgb": "00000000", "indexed": null, "theme": null, "tint": 0.0, "auto": null}}, "alignment": {"horizontal": null, "vertical": null, "text_rotation": 0, "wrap_text": null, "shrink_to_fit": null, "indent": 0.0}, "border": {"left": {"style": null, "color": null}, "right": {"style": null, "color": null}, "top": {"style": null, "color": null}, "bottom": {"style": null, "color": null}, "diagonal": {"style": null, "color": null}, "diagonal_down": false, "diagonal_up": false, "outline": true, "vertical": null, "horizontal": null}, "protection": {"locked": true, "hidden": false}}
A33: Intro | B33: D5 | C33: 5 | D33: 4 | E33: Input | G33: Prepared By: | H33: {"type": "str", "value": "Prepared By: "} | I33: General | J33: TRUE | K33: FALSE | L33: 11 | M33: Values must be of type <class 'str'> | N33: 00000000 | O33: center | R33: TRUE | W33: {"number_format": "General", "font": {"name": "Calibri", "size": 11.0, "bold": true, "italic": false, "underline": null, "strike": null, "color": {"type": "theme", "rgb": "Values must be of type <class 'str'>", "indexed": null, "theme": 1, "tint": 0.249977111117893, "auto": null}, "vert_align": null}, "fill": {"fill_type": null, "fg_color": {"type": "rgb", "rgb": "00000000", "indexed": null, "theme": null, "tint": 0.0, "auto": null}, "bg_color": {"type": "rgb", "rgb": "00000000", "indexed": null, "theme": null, "tint": 0.0, "auto": null}}, "alignment": {"horizontal": "center", "vertical": null, "text_rotation": 0, "wrap_text": null, "shrink_to_fit": null, "indent": 0.0}, "border": {"left": {"style": null, "color": null}, "right": {"style": null, "color": null}, "top": {"style": null, "color": null}, "bottom": {"style": null, "color": null}, "diagonal": {"style": null, "color": null}, "diagonal_down": false, "diagonal_up": false, "outline": true, "vertical": null, "horizontal": null}, "protection": {"locked": true, "hidden": false}}
A34: Intro | B34: E5 | C34: 5 | D34: 5 | E34: Input | G34: Suvin Shetty , Yogesh Choudhari , Akshada Joshi | H34: {"type": "str", "value": "Suvin Shetty , Yogesh Choudhari , Akshada Joshi "} | I34: General | J34: FALSE | K34: FALSE | L34: 11 | M34: FF000000 | N34: 00000000 | R34: TRUE | W34: {"number_format": "General", "font": {"name": "Calibri", "size": 11.0, "bold": false, "italic": false, "underline": null, "strike": null, "color": {"type": "rgb", "rgb": "FF000000", "indexed": null, "theme": null, "tint": 0.0, "auto": null}, "vert_align": null}, "fill": {"fill_type": null, "fg_color": {"type": "rgb", "rgb": "00000000", "indexed": null, "theme": null, "tint": 0.0, "auto": null}, "bg_color": {"type": "rgb", "rgb": "00000000", "indexed": null, "theme": null, "tint": 0.0, "auto": null}}, "alignment": {"horizontal": null, "vertical": null, "text_rotation": 0, "wrap_text": null, "shrink_to_fit": null, "indent": 0.0}, "border": {"left": {"style": null, "color": null}, "right": {"style": null, "color": null}, "top": {"style": null, "color": null}, "bottom": {"style": null, "color": null}, "diagonal": {"style": null, "color": null}, "diagonal_down": false, "diagonal_up": false, "outline": true, "vertical": null, "horizontal": null}, "protection": {"locked": true, "hidden": false}}
A35: Intro | B35: F5 | C35: 5 | D35: 6 | E35: Input | H35: {"type": "null", "value": null} | I35: General | J35: FALSE | K35: FALSE | L35: 11 | M35: Values must be of type <class 'str'> | N35: 00000000 | R35: FALSE | W35: {"number_format": "General", "font": {"name": "Calibri", "size": 11.0, "bold": false, "italic": false, "underline": null, "strike": null, "color": {"type": "theme", "rgb": "Values must be of type <class 'str'>", "indexed": null, "theme": 1, "tint": 0.0, "auto": null}, "vert_align": null}, "fill": {"fill_type": null, "fg_color": {"type": "rgb", "rgb": "00000000", "indexed": null, "theme": null, "tint": 0.0, "auto": null}, "bg_color": {"type": "rgb", "rgb": "00000000", "indexed": null, "theme": null, "tint": 0.0, "auto": null}}, "alignment": {"horizontal": null, "vertical": null, "text_rotation": 0, "wrap_text": null, "shrink_to_fit": null, "indent": 0.0}, "border": {"left": {"style": null, "color": null}, "right": {"style": null, "color": null}, "top": {"style": null, "color": null}, "bottom": {"style": null, "color": null}, "diagonal": {"style": null, "color": null}, "diagonal_down": false, "diagonal_up": false, "outline": true, "vertical": null, "horizontal": null}, "protection": {"locked": true, "hidden": false}}
A36: Intro | B36: G5 | C36: 5 | D36: 7 | E36: Input | H36: {"type": "null", "value": null} | I36: General | J36: FALSE | K36: FALSE | L36: 11 | M36: Values must be of type <class 'str'> | N36: 00000000 | R36: FALSE | W36: {"number_format": "General", "font": {"name": "Calibri", "size": 11.0, "bold": false, "italic": false, "underline": null, "strike": null, "color": {"type": "theme", "rgb": "Values must be of type <class 'str'>", "indexed": null, "theme": 1, "tint": 0.0, "auto": null}, "vert_align": null}, "fill": {"fill_type": null, "fg_color": {"type": "rgb", "rgb": "00000000", "indexed": null, "theme": null, "tint": 0.0, "auto": null}, "bg_color": {"type": "rgb", "rgb": "00000000", "indexed": null, "theme": null, "tint": 0.0, "auto": null}}, "alignment": {"horizontal": null, "vertical": null, "text_rotation": 0, "wrap_text": null, "shrink_to_fit": null, "indent": 0.0}, "border": {"left": {"style": null, "color": null}, "right": {"style": null, "color": null}, "top": {"style": null, "color": null}, "bottom": {"style": null, "color": null}, "diagonal": {"style": null, "color": null}, "diagonal_down": false, "diagonal_up": false, "outline": true, "vertical": null, "horizontal": null}, "protection": {"locked": true, "hidden": false}}
A37: Intro | B37: A6 | C37: 6 | D37: 1 | E37: Input | H37: {"type": "null", "value": null} | I37: General | J37: FALSE | K37: FALSE | L37: 11 | M37: Values must be of type <class 'str'> | N37: 00000000 | R37: FALSE | W37: {"number_format": "General", "font": {"name": "Calibri", "size": 11.0, "bold": false, "italic": false, "underline": null, "strike": null, "color": {"type": "theme", "rgb": "Values must be of type <class 'str'>", "indexed": null, "theme": 1, "tint": 0.0, "auto": null}, "vert_align": null}, "fill": {"fill_type": null, "fg_color": {"type": "rgb", "rgb": "00000000", "indexed": null, "theme": null, "tint": 0.0, "auto": null}, "bg_color": {"type": "rgb", "rgb": "00000000", "indexed": null, "theme": null, "tint": 0.0, "auto": null}}, "alignment": {"horizontal": null, "vertical": null, "text_rotation": 0, "wrap_text": null, "shrink_to_fit": null, "indent": 0.0}, "border": {"left": {"style": null, "color": null}, "right": {"style": null, "color": null}, "top": {"style": null, "color": null}, "bottom": {"style": null, "color": null}, "diagonal": {"style": null, "color": null}, "diagonal_down": false, "diagonal_up": false, "outline": true, "vertical": null, "horizontal": null}, "protection": {"locked": true, "hidden": false}}
A38: Intro | B38: B6 | C38: 6 | D38: 2 | E38: Input | H38: {"type": "null", "value": null} | I38: General | J38: FALSE | K38: FALSE | L38: 11 | M38: Values must be of type <class 'str'> | N38: 00000000 | R38: FALSE | W38: {"number_format": "General", "font": {"name": "Calibri", "size": 11.0, "bold": false, "italic": false, "underline": null, "strike": null, "color": {"type": "theme", "rgb": "Values must be of type <class 'str'>", "indexed": null, "theme": 1, "tint": 0.0, "auto": null}, "vert_align": null}, "fill": {"fill_type": null, "fg_color": {"type": "rgb", "rgb": "00000000", "indexed": null, "theme": null, "tint": 0.0, "auto": null}, "bg_color": {"type": "rgb", "rgb": "00000000", "indexed": null, "theme": null, "tint": 0.0, "auto": null}}, "alignment": {"horizontal": null, "vertical": null, "text_rotation": 0, "wrap_text": null, "shrink_to_fit": null, "indent": 0.0}, "border": {"left": {"style": null, "color": null}, "right": {"style": null, "color": null}, "top": {"style": null, "color": null}, "bottom": {"style": null, "color": null}, "diagonal": {"style": null, "color": null}, "diagonal_down": false, "diagonal_up": false, "outline": true, "vertical": null, "horizontal": null}, "protection": {"locked": true, "hidden": false}}
A39: Intro | B39: C6 | C39: 6 | D39: 3 | E39: Input | H39: {"type": "null", "value": null} | I39: General | J39: FALSE | K39: FALSE | L39: 11 | M39: Values must be of type <class 'str'> | N39: 00000000 | R39: FALSE | W39: {"number_format": "General", "font": {"name": "Calibri", "size": 11.0, "bold": false, "italic": false, "underline": null, "strike": null, "color": {"type": "theme", "rgb": "Values must be of type <class 'str'>", "indexed": null, "theme": 1, "tint": 0.0, "auto": null}, "vert_align": null}, "fill": {"fill_type": null, "fg_color": {"type": "rgb", "rgb": "00000000", "indexed": null, "theme": null, "tint": 0.0, "auto": null}, "bg_color": {"type": "rgb", "rgb": "00000000", "indexed": null, "theme": null, "tint": 0.0, "auto": null}}, "alignment": {"horizontal": null, "vertical": null, "text_rotation": 0, "wrap_text": null, "shrink_to_fit": null, "indent": 0.0}, "border": {"left": {"style": null, "color": null}, "right": {"style": null, "color": null}, "top": {"style": null, "color": null}, "bottom": {"style": null, "color": null}, "diagonal": {"style": null, "color": null}, "diagonal_down": false, "diagonal_up": false, "outline": true, "vertical": null, "horizontal": null}, "protection": {"locked": true, "hidden": false}}
A40: Intro | B40: D6 | C40: 6 | D40: 4 | E40: Input | G40: Year | H40: {"type": "str", "value": "Year"} | I40: General | J40: TRUE | K40: FALSE | L40: 11 | M40: Values must be of type <class 'str'> | N40: 00000000 | O40: center | R40: TRUE | W40: {"number_format": "General", "font": {"name": "Calibri", "size": 11.0, "bold": true, "italic": false, "underline": null, "strike": null, "color": {"type": "theme", "rgb": "Values must be of type <class 'str'>", "indexed": null, "theme": 1, "tint": 0.0, "auto": null}, "vert_align": null}, "fill": {"fill_type": null, "fg_color": {"type": "rgb", "rgb": "00000000", "indexed": null, "theme": null, "tint": 0.0, "auto": null}, "bg_color": {"type": "rgb", "rgb": "00000000", "indexed": null, "theme": null, "tint": 0.0, "auto": null}}, "alignment": {"horizontal": "center", "vertical": null, "text_rotation": 0, "wrap_text": null, "shrink_to_fit": null, "indent": 0.0}, "border": {"left": {"style": null, "color": null}, "right": {"style": null, "color": null}, "top": {"style": null, "color": null}, "bottom": {"style": null, "color": null}, "diagonal": {"style": null, "color": null}, "diagonal_down": false, "diagonal_up": false, "outline": true, "vertical": null, "horizontal": null}, "protection": {"locked": true, "hidden": false}}
A41: Intro | B41: E6 | C41: 6 | D41: 5 | E41: Input | G41: 2017 | H41: {"type": "int", "value": 2017} | I41: General | J41: TRUE | K41: FALSE | L41: 11 | M41: Values must be of type <class 'str'> | N41: 00000000 | O41: center | R41: TRUE | W41: {"number_format": "General", "font": {"name": "Calibri", "size": 11.0, "bold": true, "italic": false, "underline": null, "strike": null, "color": {"type": "theme", "rgb": "Values must be of type <class 'str'>", "indexed": null, "theme": 1, "tint": 0.0, "auto": null}, "vert_align": null}, "fill": {"fill_type": null, "fg_color": {"type": "rgb", "rgb": "00000000", "indexed": null, "theme": null, "tint": 0.0, "auto": null}, "bg_color": {"type": "rgb", "rgb": "00000000", "indexed": null, "theme": null, "tint": 0.0, "auto": null}}, "alignment": {"horizontal": "center", "vertical": null, "text_rotation": 0, "wrap_text": null, "shrink_to_fit": null, "indent": 0.0}, "border": {"left": {"style": null, "color": null}, "right": {"style": null, "color": null}, "top": {"style": null, "color": null}, "bottom": {"style": null, "color": null}, "diagonal": {"style": null, "color": null}, "diagonal_down": false, "diagonal_up": false, "outline": true, "vertical": null, "horizontal": null}, "protection": {"locked": true, "hidden": false}}
A42: Intro | B42: F6 | C42: 6 | D42: 6 | E42: Input | H42: {"type": "null", "value": null} | I42: General | J42: FALSE | K42: FALSE | L42: 11 | M42: Values must be of type <class 'str'> | N42: 00000000 | R42: FALSE | W42: {"number_format": "General", "font": {"name": "Calibri", "size": 11.0, "bold": false, "italic": false, "underline": null, "strike": null, "color": {"type": "theme", "rgb": "Values must be of type <class 'str'>", "indexed": null, "theme": 1, "tint": 0.0, "auto": null}, "vert_align": null}, "fill": {"fill_type": null, "fg_color": {"type": "rgb", "rgb": "00000000", "indexed": null, "theme": null, "tint": 0.0, "auto": null}, "bg_color": {"type": "rgb", "rgb": "00000000", "indexed": null, "theme": null, "tint": 0.0, "auto": null}}, "alignment": {"horizontal": null, "vertical": null, "text_rotation": 0, "wrap_text": null, "shrink_to_fit": null, "indent": 0.0}, "border": {"left": {"style": null, "color": null}, "right": {"style": null, "color": null}, "top": {"style": null, "color": null}, "bottom": {"style": null, "color": null}, "diagonal": {"style": null, "color": null}, "diagonal_down": false, "diagonal_up": false, "outline": true, "vertical": null, "horizontal": null}, "protection": {"locked": true, "hidden": false}}
A43: Intro | B43: G6 | C43: 6 | D43: 7 | E43: Input | H43: {"type": "null", "value": null} | I43: General | J43: FALSE | K43: FALSE | L43: 11 | M43: Values must be of type <class 'str'> | N43: 00000000 | R43: FALSE | W43: {"number_format": "General", "font": {"name": "Calibri", "size": 11.0, "bold": false, "italic": false, "underline": null, "strike": null, "color": {"type": "theme", "rgb": "Values must be of type <class 'str'>", "indexed": null, "theme": 1, "tint": 0.0, "auto": null}, "vert_align": null}, "fill": {"fill_type": null, "fg_color": {"type": "rgb", "rgb": "00000000", "indexed": null, "theme": null, "tint": 0.0, "auto": null}, "bg_color": {"type": "rgb", "rgb": "00000000", "indexed": null, "theme": null, "tint": 0.0, "auto": null}}, "alignment": {"horizontal": null, "vertical": null, "text_rotation": 0, "wrap_text": null, "shrink_to_fit": null, "indent": 0.0}, "border": {"left": {"style": null, "color": null}, "right": {"style": null, "color": null}, "top": {"style": null, "color": null}, "bottom": {"style": null, "color": null}, "diagonal": {"style": null, "color": null}, "diagonal_down": false, "diagonal_up": false, "outline": true, "vertical": null, "horizontal": null}, "protection": {"locked": true, "hidden": false}}
A44: Intro | B44: A7 | C44: 7 | D44: 1 | E44: Input | H44: {"type": "null", "value": null} | I44: General | J44: FALSE | K44: FALSE | L44: 11 | M44: Values must be of type <class 'str'> | N44: 00000000 | R44: FALSE | W44: {"number_format": "General", "font": {"name": "Calibri", "size": 11.0, "bold": false, "italic": false, "underline": null, "strike": null, "color": {"type": "theme", "rgb": "Values must be of type <class 'str'>", "indexed": null, "theme": 1, "tint": 0.0, "auto": null}, "vert_align": null}, "fill": {"fill_type": null, "fg_color": {"type": "rgb", "rgb": "00000000", "indexed": null, "theme": null, "tint": 0.0, "auto": null}, "bg_color": {"type": "rgb", "rgb": "00000000", "indexed": null, "theme": null, "tint": 0.0, "auto": null}}, "alignment": {"horizontal": null, "vertical": null, "text_rotation": 0, "wrap_text": null, "shrink_to_fit": null, "indent": 0.0}, "border": {"left": {"style": null, "color": null}, "right": {"style": null, "color": null}, "top": {"style": null, "color": null}, "bottom": {"style": null, "color": null}, "diagonal": {"style": null, "color": null}, "diagonal_down": false, "diagonal_up": false, "outline": true, "vertical": null, "horizontal": null}, "protection": {"locked": true, "hidden": false}}
A45: Intro | B45: B7 | C45: 7 | D45: 2 | E45: Input | H45: {"type": "null", "value": null} | I45: General | J45: FALSE | K45: FALSE | L45: 11 | M45: Values must be of type <class 'str'> | N45: 00000000 | R45: FALSE | W45: {"number_format": "General", "font": {"name": "Calibri", "size": 11.0, "bold": false, "italic": false, "underline": null, "strike": null, "color": {"type": "theme", "rgb": "Values must be of type <class 'str'>", "indexed": null, "theme": 1, "tint": 0.0, "auto": null}, "vert_align": null}, "fill": {"fill_type": null, "fg_color": {"type": "rgb", "rgb": "00000000", "indexed": null, "theme": null, "tint": 0.0, "auto": null}, "bg_color": {"type": "rgb", "rgb": "00000000", "indexed": null, "theme": null, "tint": 0.0, "auto": null}}, "alignment": {"horizontal": null, "vertical": null, "text_rotation": 0, "wrap_text": null, "shrink_to_fit": null, "indent": 0.0}, "border": {"left": {"style": null, "color": null}, "right": {"style": null, "color": null}, "top": {"style": null, "color": null}, "bottom": {"style": null, "color": null}, "diagonal": {"style": null, "color": null}, "diagonal_down": false, "diagonal_up": false, "outline": true, "vertical": null, "horizontal": null}, "protection": {"locked": true, "hidden": false}}
A46: Intro | B46: C7 | C46: 7 | D46: 3 | E46: Input | H46: {"type": "null", "value": null} | I46: General | J46: FALSE | K46: FALSE | L46: 11 | M46: Values must be of type <class 'str'> | N46: 00000000 | R46: FALSE | W46: {"number_format": "General", "font": {"name": "Calibri", "size": 11.0, "bold": false, "italic": false, "underline": null, "strike": null, "color": {"type": "theme", "rgb": "Values must be of type <class 'str'>", "indexed": null, "theme": 1, "tint": 0.0, "auto": null}, "vert_align": null}, "fill": {"fill_type": null, "fg_color": {"type": "rgb", "rgb": "00000000", "indexed": null, "theme": null, "tint": 0.0, "auto": null}, "bg_color": {"type": "rgb", "rgb": "00000000", "indexed": null, "theme": null, "tint": 0.0, "auto": null}}, "alignment": {"horizontal": null, "vertical": null, "text_rotation": 0, "wrap_text": null, "shrink_to_fit": null, "indent": 0.0}, "border": {"left": {"style": null, "color": null}, "right": {"style": null, "color": null}, "top": {"style": null, "color": null}, "bottom": {"style": null, "color": null}, "diagonal": {"style": null, "color": null}, "diagonal_down": false, "diagonal_up": false, "outline": true, "vertical": null, "horizontal": null}, "protection": {"locked": true, "hidden": false}}
A47: Intro | B47: D7 | C47: 7 | D47: 4 | E47: Input | H47: {"type": "null", "value": null} | I47: General | J47: FALSE | K47: FALSE | L47: 11 | M47: Values must be of type <class 'str'> | N47: 00000000 | R47: FALSE | W47: {"number_format": "General", "font": {"name": "Calibri", "size": 11.0, "bold": false, "italic": false, "underline": null, "strike": null, "color": {"type": "theme", "rgb": "Values must be of type <class 'str'>", "indexed": null, "theme": 1, "tint": 0.0, "auto": null}, "vert_align": null}, "fill": {"fill_type": null, "fg_color": {"type": "rgb", "rgb": "00000000", "indexed": null, "theme": null, "tint": 0.0, "auto": null}, "bg_color": {"type": "rgb", "rgb": "00000000", "indexed": null, "theme": null, "tint": 0.0, "auto": null}}, "alignment": {"horizontal": null, "vertical": null, "text_rotation": 0, "wrap_text": null, "shrink_to_fit": null, "indent": 0.0}, "border": {"left": {"style": null, "color": null}, "right": {"style": null, "color": null}, "top": {"style": null, "color": null}, "bottom": {"style": null, "color": null}, "diagonal": {"style": null, "color": null}, "diagonal_down": false, "diagonal_up": false, "outline": true, "vertical": null, "horizontal": null}, "protection": {"locked": true, "hidden": false}}
A48: Intro | B48: E7 | C48: 7 | D48: 5 | E48: Input | H48: {"type": "null", "value": null} | I48: General | J48: FALSE | K48: FALSE | L48: 11 | M48: Values must be of type <class 'str'> | N48: 00000000 | R48: FALSE | W48: {"number_format": "General", "font": {"name": "Calibri", "size": 11.0, "bold": false, "italic": false, "underline": null, "strike": null, "color": {"type": "theme", "rgb": "Values must be of type <class 'str'>", "indexed": null, "theme": 1, "tint": 0.0, "auto": null}, "vert_align": null}, "fill": {"fill_type": null, "fg_color": {"type": "rgb", "rgb": "00000000", "indexed": null, "theme": null, "tint": 0.0, "auto": null}, "bg_color": {"type": "rgb", "rgb": "00000000", "indexed": null, "theme": null, "tint": 0.0, "auto": null}}, "alignment": {"horizontal": null, "vertical": null, "text_rotation": 0, "wrap_text": null, "shrink_to_fit": null, "indent": 0.0}, "border": {"left": {"style": null, "color": null}, "right": {"style": null, "color": null}, "top": {"style": null, "color": null}, "bottom": {"style": null, "color": null}, "diagonal": {"style": null, "color": null}, "diagonal_down": false, "diagonal_up": false, "outline": true, "vertical": null, "horizontal": null}, "protection": {"locked": true, "hidden": false}}
A49: Intro | B49: F7 | C49: 7 | D49: 6 | E49: Input | H49: {"type": "null", "value": null} | I49: General | J49: FALSE | K49: FALSE | L49: 11 | M49: Values must be of type <class 'str'> | N49: 00000000 | R49: FALSE | W49: {"number_format": "General", "font": {"name": "Calibri", "size": 11.0, "bold": false, "italic": false, "underline": null, "strike": null, "color": {"type": "theme", "rgb": "Values must be of type <class 'str'>", "indexed": null, "theme": 1, "tint": 0.0, "auto": null}, "vert_align": null}, "fill": {"fill_type": null, "fg_color": {"type": "rgb", "rgb": "00000000", "indexed": null, "theme": null, "tint": 0.0, "auto": null}, "bg_color": {"type": "rgb", "rgb": "00000000", "indexed": null, "theme": null, "tint": 0.0, "auto": null}}, "alignment": {"horizontal": null, "vertical": null, "text_rotation": 0, "wrap_text": null, "shrink_to_fit": null, "indent": 0.0}, "border": {"left": {"style": null, "color": null}, "right": {"style": null, "color": null}, "top": {"style": null, "color": null}, "bottom": {"style": null, "color": null}, "diagonal": {"style": null, "color": null}, "diagonal_down": false, "diagonal_up": false, "outline": true, "vertical": null, "horizontal": null}, "protection": {"locked": true, "hidden": false}}
A50: Intro | B50: G7 | C50: 7 | D50: 7 | E50: Input | H50: {"type": "null", "value": null} | I50: General | J50: FALSE | K50: FALSE | L50: 11 | M50: Values must be of type <class 'str'> | N50: 00000000 | R50: FALSE | W50: {"number_format": "General", "font": {"name": "Calibri", "size": 11.0, "bold": false, "italic": false, "underline": null, "strike": null, "color": {"type": "theme", "rgb": "Values must be of type <class 'str'>", "indexed": null, "theme": 1, "tint": 0.0, "auto": null}, "vert_align": null}, "fill": {"fill_type": null, "fg_color": {"type": "rgb", "rgb": "00000000", "indexed": null, "theme": null, "tint": 0.0, "auto": null}, "bg_color": {"type": "rgb", "rgb": "00000000", "indexed": null, "theme": null, "tint": 0.0, "auto": null}}, "alignment": {"horizontal": null, "vertical": null, "text_rotation": 0, "wrap_text": null, "shrink_to_fit": null, "indent": 0.0}, "border": {"left": {"style": null, "color": null}, "right": {"style": null, "color": null}, "top": {"style": null, "color": null}, "bottom": {"style": null, "color": null}, "diagonal": {"style": null, "color": null}, "diagonal_down": false, "diagonal_up": false, "outline": true, "vertical": null, "horizontal": null}, "protection": {"locked": true, "hidden": false}}
A51: Intro | B51: A8 | C51: 8 | D51: 1 | E51: Input | H51: {"type": "null", "value": null} | I51: General | J51: FALSE | K51: FALSE | L51: 11 | M51: Values must be of type <class 'str'> | N51: 00000000 | R51: FALSE | W51: {"number_format": "General", "font": {"name": "Calibri", "size": 11.0, "bold": false, "italic": false, "underline": null, "strike": null, "color": {"type": "theme", "rgb": "Values must be of type <class 'str'>", "indexed": null, "theme": 1, "tint": 0.0, "auto": null}, "vert_align": null}, "fill": {"fill_type": null, "fg_color": {"type": "rgb", "rgb": "00000000", "indexed": null, "theme": null, "tint": 0.0, "auto": null}, "bg_color": {"type": "rgb", "rgb": "00000000", "indexed": null, "theme": null, "tint": 0.0, "auto": null}}, "alignment": {"horizontal": null, "vertical": null, "text_rotation": 0, "wrap_text": null, "shrink_to_fit": null, "indent": 0.0}, "border": {"left": {"style": null, "color": null}, "right": {"style": null, "color": null}, "top": {"style": null, "color": null}, "bottom": {"style": null, "color": null}, "diagonal": {"style": null, "color": null}, "diagonal_down": false, "diagonal_up": false, "outline": true, "vertical": null, "horizontal": null}, "protection": {"locked": true, "hidden": false}}
A52: Intro | B52: B8 | C52: 8 | D52: 2 | E52: Input | H52: {"type": "null", "value": null} | I52: General | J52: FALSE | K52: FALSE | L52: 11 | M52: Values must be of type <class 'str'> | N52: 00000000 | R52: FALSE | W52: {"number_format": "General", "font": {"name": "Calibri", "size": 11.0, "bold": false, "italic": false, "underline": null, "strike": null, "color": {"type": "theme", "rgb": "Values must be of type <class 'str'>", "indexed": null, "theme": 1, "tint": 0.0, "auto": null}, "vert_align": null}, "fill": {"fill_type": null, "fg_color": {"type": "rgb", "rgb": "00000000", "indexed": null, "theme": null, "tint": 0.0, "auto": null}, "bg_color": {"type": "rgb", "rgb": "00000000", "indexed": null, "theme": null, "tint": 0.0, "auto": null}}, "alignment": {"horizontal": null, "vertical": null, "text_rotation": 0, "wrap_text": null, "shrink_to_fit": null, "indent": 0.0}, "border": {"left": {"style": null, "color": null}, "right": {"style": null, "color": null}, "top": {"style": null, "color": null}, "bottom": {"style": null, "color": null}, "diagonal": {"style": null, "color": null}, "diagonal_down": false, "diagonal_up": false, "outline": true, "vertical": null, "horizontal": null}, "protection": {"locked": true, "hidden": false}}
A53: Intro | B53: C8 | C53: 8 | D53: 3 | E53: Input | H53: {"type": "null", "value": null} | I53: General | J53: FALSE | K53: FALSE | L53: 11 | M53: Values must be of type <class 'str'> | N53: 00000000 | R53: FALSE | W53: {"number_format": "General", "font": {"name": "Calibri", "size": 11.0, "bold": false, "italic": false, "underline": null, "strike": null, "color": {"type": "theme", "rgb": "Values must be of type <class 'str'>", "indexed": null, "theme": 1, "tint": 0.0, "auto": null}, "vert_align": null}, "fill": {"fill_type": null, "fg_color": {"type": "rgb", "rgb": "00000000", "indexed": null, "theme": null, "tint": 0.0, "auto": null}, "bg_color": {"type": "rgb", "rgb": "00000000", "indexed": null, "theme": null, "tint": 0.0, "auto": null}}, "alignment": {"horizontal": null, "vertical": null, "text_rotation": 0, "wrap_text": null, "shrink_to_fit": null, "indent": 0.0}, "border": {"left": {"style": null, "color": null}, "right": {"style": null, "color": null}, "top": {"style": null, "color": null}, "bottom": {"style": null, "color": null}, "diagonal": {"style": null, "color": null}, "diagonal_down": false, "diagonal_up": false, "outline": true, "vertical": null, "horizontal": null}, "protection": {"locked": true, "hidden": false}}
... A89: Intro | B89: D13 | C89: 13 | D89: 4 | E89: Input | H89: {"type": "null", "value": null} | I89: General | J89: FALSE | K89: FALSE | L89: 11 | M89: Values must be of type <class 'str'> | N89: 00000000 | R89: FALSE | W89: {"number_format": "General", "font": {"name": "Calibri", "size": 11.0, "bold": false, "italic": false, "underline": null, "strike": null, "color": {"type": "theme", "rgb": "Values must be of type <class 'str'>", "indexed": null, "theme": 1, "tint": 0.0, "auto": null}, "vert_align": null}, "fill": {"fill_type": null, "fg_color": {"type": "rgb", "rgb": "00000000", "indexed": null, "theme": null, "tint": 0.0, "auto": null}, "bg_color": {"type": "rgb", "rgb": "00000000", "indexed": null, "theme": null, "tint": 0.0, "auto": null}}, "alignment": {"horizontal": null, "vertical": null, "text_rotation": 0, "wrap_text": null, "shrink_to_fit": null, "indent": 0.0}, "border": {"left": {"style": null, "color": null}, "right": {"style": null, "color": null}, "top": {"style": null, "color": null}, "bottom": {"style": null, "color": null}, "diagonal": {"style": null, "color": null}, "diagonal_down": false, "diagonal_up": false, "outline": true, "vertical": null, "horizontal": null}, "protection": {"locked": true, "hidden": false}}
A90: Intro | B90: E13 | C90: 13 | D90: 5 | E90: Input | G90: http://proschoolonline.com | H90: {"type": "str", "value": "http://proschoolonline.com"} | I90: General | J90: FALSE | K90: FALSE | L90: 11 | M90: FF0000FF | N90: 00000000 | O90: center | R90: TRUE | W90: {"number_format": "General", "font": {"name": "Calibri", "size": 11.0, "bold": false, "italic": false, "underline": "single", "strike": null, "color": {"type": "rgb", "rgb": "FF0000FF", "indexed": null, "theme": null, "tint": 0.0, "auto": null}, "vert_align": null}, "fill": {"fill_type": null, "fg_color": {"type": "rgb", "rgb": "00000000", "indexed": null, "theme": null, "tint": 0.0, "auto": null}, "bg_color": {"type": "rgb", "rgb": "00000000", "indexed": null, "theme": null, "tint": 0.0, "auto": null}}, "alignment": {"horizontal": "center", "vertical": null, "text_rotation": 0, "wrap_text": null, "shrink_to_fit": null, "indent": 0.0}, "border": {"left": {"style": null, "color": null}, "right": {"style": null, "color": null}, "top": {"style": null, "color": null}, "bottom": {"style": null, "color": null}, "diagonal": {"style": null, "color": null}, "diagonal_down": false, "diagonal_up": false, "outline": true, "vertical": null, "horizontal": null}, "protection": {"locked": true, "hidden": false}}
A91: Intro | B91: F13 | C91: 13 | D91: 6 | E91: Input | H91: {"type": "null", "value": null} | I91: General | J91: FALSE | K91: FALSE | L91: 11 | M91: Values must be of type <class 'str'> | N91: 00000000 | R91: FALSE | W91: {"number_format": "General", "font": {"name": "Calibri", "size": 11.0, "bold": false, "italic": false, "underline": null, "strike": null, "color": {"type": "theme", "rgb": "Values must be of type <class 'str'>", "indexed": null, "theme": 1, "tint": 0.0, "auto": null}, "vert_align": null}, "fill": {"fill_type": null, "fg_color": {"type": "rgb", "rgb": "00000000", "indexed": null, "theme": null, "tint": 0.0, "auto": null}, "bg_color": {"type": "rgb", "rgb": "00000000", "indexed": null, "theme": null, "tint": 0.0, "auto": null}}, "alignment": {"horizontal": null, "vertical": null, "text_rotation": 0, "wrap_text": null, "shrink_to_fit": null, "indent": 0.0}, "border": {"left": {"style": null, "color": null}, "right": {"style": null, "color": null}, "top": {"style": null, "color": null}, "bottom": {"style": null, "color": null}, "diagonal": {"style": null, "color": null}, "diagonal_down": false, "diagonal_up": false, "outline": true, "vertical": null, "horizontal": null}, "protection": {"locked": true, "hidden": false}}
A92: Intro | B92: G13 | C92: 13 | D92: 7 | E92: Input | H92: {"type": "null", "value": null} | I92: General | J92: FALSE | K92: FALSE | L92: 11 | M92: Values must be of type <class 'str'> | N92: 00000000 | R92: FALSE | W92: {"number_format": "General", "font": {"name": "Calibri", "size": 11.0, "bold": false, "italic": false, "underline": null, "strike": null, "color": {"type": "theme", "rgb": "Values must be of type <class 'str'>", "indexed": null, "theme": 1, "tint": 0.0, "auto": null}, "vert_align": null}, "fill": {"fill_type": null, "fg_color": {"type": "rgb", "rgb": "00000000", "indexed": null, "theme": null, "tint": 0.0, "auto": null}, "bg_color": {"type": "rgb", "rgb": "00000000", "indexed": null, "theme": null, "tint": 0.0, "auto": null}}, "alignment": {"horizontal": null, "vertical": null, "text_rotation": 0, "wrap_text": null, "shrink_to_fit": null, "indent": 0.0}, "border": {"left": {"style": null, "color": null}, "right": {"style": null, "color": null}, "top": {"style": null, "color": null}, "bottom": {"style": null, "color": null}, "diagonal": {"style": null, "color": null}, "diagonal_down": false, "diagonal_up": false, "outline": true, "vertical": null, "horizontal": null}, "protection": {"locked": true, "hidden": false}}
A93: Intro | B93: A14 | C93: 14 | D93: 1 | E93: Input | H93: {"type": "null", "value": null} | I93: General | J93: FALSE | K93: FALSE | L93: 11 | M93: Values must be of type <class 'str'> | N93: 00000000 | R93: FALSE | W93: {"number_format": "General", "font": {"name": "Calibri", "size": 11.0, "bold": false, "italic": false, "underline": null, "strike": null, "color": {"type": "theme", "rgb": "Values must be of type <class 'str'>", "indexed": null, "theme": 1, "tint": 0.0, "auto": null}, "vert_align": null}, "fill": {"fill_type": null, "fg_color": {"type": "rgb", "rgb": "00000000", "indexed": null, "theme": null, "tint": 0.0, "auto": null}, "bg_color": {"type": "rgb", "rgb": "00000000", "indexed": null, "theme": null, "tint": 0.0, "auto": null}}, "alignment": {"horizontal": null, "vertical": null, "text_rotation": 0, "wrap_text": null, "shrink_to_fit": null, "indent": 0.0}, "border": {"left": {"style": null, "color": null}, "right": {"style": null, "color": null}, "top": {"style": null, "color": null}, "bottom": {"style": null, "color": null}, "diagonal": {"style": null, "color": null}, "diagonal_down": false, "diagonal_up": false, "outline": true, "vertical": null, "horizontal": null}, "protection": {"locked": true, "hidden": false}}
A94: Intro | B94: B14 | C94: 14 | D94: 2 | E94: Input | H94: {"type": "null", "value": null} | I94: General | J94: FALSE | K94: FALSE | L94: 11 | M94: Values must be of type <class 'str'> | N94: 00000000 | R94: FALSE | W94: {"number_format": "General", "font": {"name": "Calibri", "size": 11.0, "bold": false, "italic": false, "underline": null, "strike": null, "color": {"type": "theme", "rgb": "Values must be of type <class 'str'>", "indexed": null, "theme": 1, "tint": 0.0, "auto": null}, "vert_align": null}, "fill": {"fill_type": null, "fg_color": {"type": "rgb", "rgb": "00000000", "indexed": null, "theme": null, "tint": 0.0, "auto": null}, "bg_color": {"type": "rgb", "rgb": "00000000", "indexed": null, "theme": null, "tint": 0.0, "auto": null}}, "alignment": {"horizontal": null, "vertical": null, "text_rotation": 0, "wrap_text": null, "shrink_to_fit": null, "indent": 0.0}, "border": {"left": {"style": null, "color": null}, "right": {"style": null, "color": null}, "top": {"style": null, "color": null}, "bottom": {"style": null, "color": null}, "diagonal": {"style": null, "color": null}, "diagonal_down": false, "diagonal_up": false, "outline": true, "vertical": null, "horizontal": null}, "protection": {"locked": true, "hidden": false}}
A95: Intro | B95: C14 | C95: 14 | D95: 3 | E95: Input | H95: {"type": "null", "value": null} | I95: General | J95: FALSE | K95: FALSE | L95: 11 | M95: Values must be of type <class 'str'> | N95: 00000000 | R95: FALSE | W95: {"number_format": "General", "font": {"name": "Calibri", "size": 11.0, "bold": false, "italic": false, "underline": null, "strike": null, "color": {"type": "theme", "rgb": "Values must be of type <class 'str'>", "indexed": null, "theme": 1, "tint": 0.0, "auto": null}, "vert_align": null}, "fill": {"fill_type": null, "fg_color": {"type": "rgb", "rgb": "00000000", "indexed": null, "theme": null, "tint": 0.0, "auto": null}, "bg_color": {"type": "rgb", "rgb": "00000000", "indexed": null, "theme": null, "tint": 0.0, "auto": null}}, "alignment": {"horizontal": null, "vertical": null, "text_rotation": 0, "wrap_text": null, "shrink_to_fit": null, "indent": 0.0}, "border": {"left": {"style": null, "color": null}, "right": {"style": null, "color": null}, "top": {"style": null, "color": null}, "bottom": {"style": null, "color": null}, "diagonal": {"style": null, "color": null}, "diagonal_down": false, "diagonal_up": false, "outline": true, "vertical": null, "horizontal": null}, "protection": {"locked": true, "hidden": false}}
A96: Intro | B96: D14 | C96: 14 | D96: 4 | E96: Input | H96: {"type": "null", "value": null} | I96: General | J96: FALSE | K96: FALSE | L96: 11 | M96: Values must be of type <class 'str'> | N96: 00000000 | R96: FALSE | W96: {"number_format": "General", "font": {"name": "Calibri", "size": 11.0, "bold": false, "italic": false, "underline": null, "strike": null, "color": {"type": "theme", "rgb": "Values must be of type <class 'str'>", "indexed": null, "theme": 1, "tint": 0.0, "auto": null}, "vert_align": null}, "fill": {"fill_type": null, "fg_color": {"type": "rgb", "rgb": "00000000", "indexed": null, "theme": null, "tint": 0.0, "auto": null}, "bg_color": {"type": "rgb", "rgb": "00000000", "indexed": null, "theme": null, "tint": 0.0, "auto": null}}, "alignment": {"horizontal": null, "vertical": null, "text_rotation": 0, "wrap_text": null, "shrink_to_fit": null, "indent": 0.0}, "border": {"left": {"style": null, "color": null}, "right": {"style": null, "color": null}, "top": {"style": null, "color": null}, "bottom": {"style": null, "color": null}, "diagonal": {"style": null, "color": null}, "diagonal_down": false, "diagonal_up": false, "outline": true, "vertical": null, "horizontal": null}, "protection": {"locked": true, "hidden": false}}
A97: Intro | B97: E14 | C97: 14 | D97: 5 | E97: Input | G97: Email ID : mumbai@proschoolonline.com | H97: {"type": "str", "value": "Email ID :\u00a0mumbai@proschoolonline.com"} | I97: General | J97: TRUE | K97: FALSE | L97: 9 | M97: FF444444 | N97: 00000000 | O97: center | R97: TRUE | W97: {"number_format": "General", "font": {"name": "Tahoma", "size": 9.0, "bold": true, "italic": false, "underline": null, "strike": null, "color": {"type": "rgb", "rgb": "FF444444", "indexed": null, "theme": null, "tint": 0.0, "auto": null}, "vert_align": null}, "fill": {"fill_type": null, "fg_color": {"type": "rgb", "rgb": "00000000", "indexed": null, "theme": null, "tint": 0.0, "auto": null}, "bg_color": {"type": "rgb", "rgb": "00000000", "indexed": null, "theme": null, "tint": 0.0, "auto": null}}, "alignment": {"horizontal": "center", "vertical": null, "text_rotation": 0, "wrap_text": null, "shrink_to_fit": null, "indent": 0.0}, "border": {"left": {"style": null, "color": null}, "right": {"style": null, "color": null}, "top": {"style": null, "color": null}, "bottom": {"style": null, "color": null}, "diagonal": {"style": null, "color": null}, "diagonal_down": false, "diagonal_up": false, "outline": true, "vertical": null, "horizontal": null}, "protection": {"locked": true, "hidden": false}}
A98: Intro | B98: F14 | C98: 14 | D98: 6 | E98: Input | H98: {"type": "null", "value": null} | I98: General | J98: FALSE | K98: FALSE | L98: 11 | M98: Values must be of type <class 'str'> | N98: 00000000 | R98: FALSE | W98: {"number_format": "General", "font": {"name": "Calibri", "size": 11.0, "bold": false, "italic": false, "underline": null, "strike": null, "color": {"type": "theme", "rgb": "Values must be of type <class 'str'>", "indexed": null, "theme": 1, "tint": 0.0, "auto": null}, "vert_align": null}, "fill": {"fill_type": null, "fg_color": {"type": "rgb", "rgb": "00000000", "indexed": null, "theme": null, "tint": 0.0, "auto": null}, "bg_color": {"type": "rgb", "rgb": "00000000", "indexed": null, "theme": null, "tint": 0.0, "auto": null}}, "alignment": {"horizontal": null, "vertical": null, "text_rotation": 0, "wrap_text": null, "shrink_to_fit": null, "indent": 0.0}, "border": {"left": {"style": null, "color": null}, "right": {"style": null, "color": null}, "top": {"style": null, "color": null}, "bottom": {"style": null, "color": null}, "diagonal": {"style": null, "color": null}, "diagonal_down": false, "diagonal_up": false, "outline": true, "vertical": null, "horizontal": null}, "protection": {"locked": true, "hidden": false}}
A99: Intro | B99: G14 | C99: 14 | D99: 7 | E99: Input | H99: {"type": "null", "value": null} | I99: General | J99: FALSE | K99: FALSE | L99: 11 | M99: Values must be of type <class 'str'> | N99: 00000000 | R99: FALSE | W99: {"number_format": "General", "font": {"name": "Calibri", "size": 11.0, "bold": false, "italic": false, "underline": null, "strike": null, "color": {"type": "theme", "rgb": "Values must be of type <class 'str'>", "indexed": null, "theme": 1, "tint": 0.0, "auto": null}, "vert_align": null}, "fill": {"fill_type": null, "fg_color": {"type": "rgb", "rgb": "00000000", "indexed": null, "theme": null, "tint": 0.0, "auto": null}, "bg_color": {"type": "rgb", "rgb": "00000000", "indexed": null, "theme": null, "tint": 0.0, "auto": null}}, "alignment": {"horizontal": null, "vertical": null, "text_rotation": 0, "wrap_text": null, "shrink_to_fit": null, "indent": 0.0}, "border": {"left": {"style": null, "color": null}, "right": {"style": null, "color": null}, "top": {"style": null, "color": null}, "bottom": {"style": null, "color": null}, "diagonal": {"style": null, "color": null}, "diagonal_down": false, "diagonal_up": false, "outline": true, "vertical": null, "horizontal": null}, "protection": {"locked": true, "hidden": false}}
A100: Intro | B100: A15 | C100: 15 | D100: 1 | E100: Input | H100: {"type": "null", "value": null} | I100: General | J100: FALSE | K100: FALSE | L100: 11 | M100: Values must be of type <class 'str'> | N100: 00000000 | R100: FALSE | W100: {"number_format": "General", "font": {"name": "Calibri", "size": 11.0, "bold": false, "italic": false, "underline": null, "strike": null, "color": {"type": "theme", "rgb": "Values must be of type <class 'str'>", "indexed": null, "theme": 1, "tint": 0.0, "auto": null}, "vert_align": null}, "fill": {"fill_type": null, "fg_color": {"type": "rgb", "rgb": "00000000", "indexed": null, "theme": null, "tint": 0.0, "auto": null}, "bg_color": {"type": "rgb", "rgb": "00000000", "indexed": null, "theme": null, "tint": 0.0, "auto": null}}, "alignment": {"horizontal": null, "vertical": null, "text_rotation": 0, "wrap_text": null, "shrink_to_fit": null, "indent": 0.0}, "border": {"left": {"style": null, "color": null}, "right": {"style": null, "color": null}, "top": {"style": null, "color": null}, "bottom": {"style": null, "color": null}, "diagonal": {"style": null, "color": null}, "diagonal_down": false, "diagonal_up": false, "outline": true, "vertical": null, "horizontal": null}, "protection": {"locked": true, "hidden": false}}
A101: Intro | B101: B15 | C101: 15 | D101: 2 | E101: Input | H101: {"type": "null", "value": null} | I101: General | J101: FALSE | K101: FALSE | L101: 11 | M101: Values must be of type <class 'str'> | N101: 00000000 | R101: FALSE | W101: {"number_format": "General", "font": {"name": "Calibri", "size": 11.0, "bold": false, "italic": false, "underline": null, "strike": null, "color": {"type": "theme", "rgb": "Values must be of type <class 'str'>", "indexed": null, "theme": 1, "tint": 0.0, "auto": null}, "vert_align": null}, "fill": {"fill_type": null, "fg_color": {"type": "rgb", "rgb": "00000000", "indexed": null, "theme": null, "tint": 0.0, "auto": null}, "bg_color": {"type": "rgb", "rgb": "00000000", "indexed": null, "theme": null, "tint": 0.0, "auto": null}}, "alignment": {"horizontal": null, "vertical": null, "text_rotation": 0, "wrap_text": null, "shrink_to_fit": null, "indent": 0.0}, "border": {"left": {"style": null, "color": null}, "right": {"style": null, "color": null}, "top": {"style": null, "color": null}, "bottom": {"style": null, "color": null}, "diagonal": {"style": null, "color": null}, "diagonal_down": false, "diagonal_up": false, "outline": true, "vertical": null, "horizontal": null}, "protection": {"locked": true, "hidden": false}}
A102: Intro | B102: C15 | C102: 15 | D102: 3 | E102: Input | H102: {"type": "null", "value": null} | I102: General | J102: FALSE | K102: FALSE | L102: 11 | M102: Values must be of type <class 'str'> | N102: 00000000 | R102: FALSE | W102: {"number_format": "General", "font": {"name": "Calibri", "size": 11.0, "bold": false, "italic": false, "underline": null, "strike": null, "color": {"type": "theme", "rgb": "Values must be of type <class 'str'>", "indexed": null, "theme": 1, "tint": 0.0, "auto": null}, "vert_align": null}, "fill": {"fill_type": null, "fg_color": {"type": "rgb", "rgb": "00000000", "indexed": null, "theme": null, "tint": 0.0, "auto": null}, "bg_color": {"type": "rgb", "rgb": "00000000", "indexed": null, "theme": null, "tint": 0.0, "auto": null}}, "alignment": {"horizontal": null, "vertical": null, "text_rotation": 0, "wrap_text": null, "shrink_to_fit": null, "indent": 0.0}, "border": {"left": {"style": null, "color": null}, "right": {"style": null, "color": null}, "top": {"style": null, "color": null}, "bottom": {"style": null, "color": null}, "diagonal": {"style": null, "color": null}, "diagonal_down": false, "diagonal_up": false, "outline": true, "vertical": null, "horizontal": null}, "protection": {"locked": true, "hidden": false}}
A103: Intro | B103: D15 | C103: 15 | D103: 4 | E103: Input | H103: {"type": "null", "value": null} | I103: General | J103: FALSE | K103: FALSE | L103: 11 | M103: Values must be of type <class 'str'> | N103: 00000000 | R103: FALSE | W103: {"number_format": "General", "font": {"name": "Calibri", "size": 11.0, "bold": false, "italic": false, "underline": null, "strike": null, "color": {"type": "theme", "rgb": "Values must be of type <class 'str'>", "indexed": null, "theme": 1, "tint": 0.0, "auto": null}, "vert_align": null}, "fill": {"fill_type": null, "fg_color": {"type": "rgb", "rgb": "00000000", "indexed": null, "theme": null, "tint": 0.0, "auto": null}, "bg_color": {"type": "rgb", "rgb": "00000000", "indexed": null, "theme": null, "tint": 0.0, "auto": null}}, "alignment": {"horizontal": null, "vertical": null, "text_rotation": 0, "wrap_text": null, "shrink_to_fit": null, "indent": 0.0}, "border": {"left": {"style": null, "color": null}, "right": {"style": null, "color": null}, "top": {"style": null, "color": null}, "bottom": {"style": null, "color": null}, "diagonal": {"style": null, "color": null}, "diagonal_down": false, "diagonal_up": false, "outline": true, "vertical": null, "horizontal": null}, "protection": {"locked": true, "hidden": false}}
A104: Intro | B104: E15 | C104: 15 | D104: 5 | E104: Input | H104: {"type": "null", "value": null} | I104: General | J104: TRUE | K104: FALSE | L104: 9 | M104: FF444444 | N104: 00000000 | O104: center | R104: FALSE | W104: {"number_format": "General", "font": {"name": "Tahoma", "size": 9.0, "bold": true, "italic": false, "underline": null, "strike": null, "color": {"type": "rgb", "rgb": "FF444444", "indexed": null, "theme": null, "tint": 0.0, "auto": null}, "vert_align": null}, "fill": {"fill_type": null, "fg_color": {"type": "rgb", "rgb": "00000000", "indexed": null, "theme": null, "tint": 0.0, "auto": null}, "bg_color": {"type": "rgb", "rgb": "00000000", "indexed": null, "theme": null, "tint": 0.0, "auto": null}}, "alignment": {"horizontal": "center", "vertical": null, "text_rotation": 0, "wrap_text": null, "shrink_to_fit": null, "indent": 0.0}, "border": {"left": {"style": null, "color": null}, "right": {"style": null, "color": null}, "top": {"style": null, "color": null}, "bottom": {"style": null, "color": null}, "diagonal": {"style": null, "color": null}, "diagonal_down": false, "diagonal_up": false, "outline": true, "vertical": null, "horizontal": null}, "protection": {"locked": true, "hidden": false}}
A105: Intro | B105: F15 | C105: 15 | D105: 6 | E105: Input | H105: {"type": "null", "value": null} | I105: General | J105: FALSE | K105: FALSE | L105: 11 | M105: Values must be of type <class 'str'> | N105: 00000000 | R105: FALSE | W105: {"number_format": "General", "font": {"name": "Calibri", "size": 11.0, "bold": false, "italic": false, "underline": null, "strike": null, "color": {"type": "theme", "rgb": "Values must be of type <class 'str'>", "indexed": null, "theme": 1, "tint": 0.0, "auto": null}, "vert_align": null}, "fill": {"fill_type": null, "fg_color": {"type": "rgb", "rgb": "00000000", "indexed": null, "theme": null, "tint": 0.0, "auto": null}, "bg_color": {"type": "rgb", "rgb": "00000000", "indexed": null, "theme": null, "tint": 0.0, "auto": null}}, "alignment": {"horizontal": null, "vertical": null, "text_rotation": 0, "wrap_text": null, "shrink_to_fit": null, "indent": 0.0}, "border": {"left": {"style": null, "color": null}, "right": {"style": null, "color": null}, "top": {"style": null, "color": null}, "bottom": {"style": null, "color": null}, "diagonal": {"style": null, "color": null}, "diagonal_down": false, "diagonal_up": false, "outline": true, "vertical": null, "horizontal": null}, "protection": {"locked": true, "hidden": false}}
A106: Intro | B106: G15 | C106: 15 | D106: 7 | E106: Input | H106: {"type": "null", "value": null} | I106: General | J106: FALSE | K106: FALSE | L106: 11 | M106: Values must be of type <class 'str'> | N106: 00000000 | R106: FALSE | W106: {"number_format": "General", "font": {"name": "Calibri", "size": 11.0, "bold": false, "italic": false, "underline": null, "strike": null, "color": {"type": "theme", "rgb": "Values must be of type <class 'str'>", "indexed": null, "theme": 1, "tint": 0.0, "auto": null}, "vert_align": null}, "fill": {"fill_type": null, "fg_color": {"type": "rgb", "rgb": "00000000", "indexed": null, "theme": null, "tint": 0.0, "auto": null}, "bg_color": {"type": "rgb", "rgb": "00000000", "indexed": null, "theme": null, "tint": 0.0, "auto": null}}, "alignment": {"horizontal": null, "vertical": null, "text_rotation": 0, "wrap_text": null, "shrink_to_fit": null, "indent": 0.0}, "border": {"left": {"style": null, "color": null}, "right": {"style": null, "color": null}, "top": {"style": null, "color": null}, "bottom": {"style": null, "color": null}, "diagonal": {"style": null, "color": null}, "diagonal_down": false, "diagonal_up": false, "outline": true, "vertical": null, "horizontal": null}, "protection": {"locked": true, "hidden": false}}
A107: Intro | B107: A16 | C107: 16 | D107: 1 | E107: Input | H107: {"type": "null", "value": null} | I107: General | J107: FALSE | K107: FALSE | L107: 11 | M107: Values must be of type <class 'str'> | N107: 00000000 | R107: FALSE | W107: {"number_format": "General", "font": {"name": "Calibri", "size": 11.0, "bold": false, "italic": false, "underline": null, "strike": null, "color": {"type": "theme", "rgb": "Values must be of type <class 'str'>", "indexed": null, "theme": 1, "tint": 0.0, "auto": null}, "vert_align": null}, "fill": {"fill_type": null, "fg_color": {"type": "rgb", "rgb": "00000000", "indexed": null, "theme": null, "tint": 0.0, "auto": null}, "bg_color": {"type": "rgb", "rgb": "00000000", "indexed": null, "theme": null, "tint": 0.0, "auto": null}}, "alignment": {"horizontal": null, "vertical": null, "text_rotation": 0, "wrap_text": null, "shrink_to_fit": null, "indent": 0.0}, "border": {"left": {"style": null, "color": null}, "right": {"style": null, "color": null}, "top": {"style": null, "color": null}, "bottom": {"style": null, "color": null}, "diagonal": {"style": null, "color": null}, "diagonal_down": false, "diagonal_up": false, "outline": true, "vertical": null, "horizontal": null}, "protection": {"locked": true, "hidden": false}}
A108: Intro | B108: B16 | C108: 16 | D108: 2 | E108: Input | H108: {"type": "null", "value": null} | I108: General | J108: FALSE | K108: FALSE | L108: 11 | M108: Values must be of type <class 'str'> | N108: 00000000 | R108: FALSE | W108: {"number_format": "General", "font": {"name": "Calibri", "size": 11.0, "bold": false, "italic": false, "underline": null, "strike": null, "color": {"type": "theme", "rgb": "Values must be of type <class 'str'>", "indexed": null, "theme": 1, "tint": 0.0, "auto": null}, "vert_align": null}, "fill": {"fill_type": null, "fg_color": {"type": "rgb", "rgb": "00000000", "indexed": null, "theme": null, "tint": 0.0, "auto": null}, "bg_color": {"type": "rgb", "rgb": "00000000", "indexed": null, "theme": null, "tint": 0.0, "auto": null}}, "alignment": {"horizontal": null, "vertical": null, "text_rotation": 0, "wrap_text": null, "shrink_to_fit": null, "indent": 0.0}, "border": {"left": {"style": null, "color": null}, "right": {"style": null, "color": null}, "top": {"style": null, "color": null}, "bottom": {"style": null, "color": null}, "diagonal": {"style": null, "color": null}, "diagonal_down": false, "diagonal_up": false, "outline": true, "vertical": null, "horizontal": null}, "protection": {"locked": true, "hidden": false}}
A109: Intro | B109: C16 | C109: 16 | D109: 3 | E109: Input | H109: {"type": "null", "value": null} | I109: General | J109: FALSE | K109: FALSE | L109: 11 | M109: Values must be of type <class 'str'> | N109: 00000000 | R109: FALSE | W109: {"number_format": "General", "font": {"name": "Calibri", "size": 11.0, "bold": false, "italic": false, "underline": null, "strike": null, "color": {"type": "theme", "rgb": "Values must be of type <class 'str'>", "indexed": null, "theme": 1, "tint": 0.0, "auto": null}, "vert_align": null}, "fill": {"fill_type": null, "fg_color": {"type": "rgb", "rgb": "00000000", "indexed": null, "theme": null, "tint": 0.0, "auto": null}, "bg_color": {"type": "rgb", "rgb": "00000000", "indexed": null, "theme": null, "tint": 0.0, "auto": null}}, "alignment": {"horizontal": null, "vertical": null, "text_rotation": 0, "wrap_text": null, "shrink_to_fit": null, "indent": 0.0}, "border": {"left": {"style": null, "color": null}, "right": {"style": null, "color": null}, "top": {"style": null, "color": null}, "bottom": {"style": null, "color": null}, "diagonal": {"style": null, "color": null}, "diagonal_down": false, "diagonal_up": false, "outline": true, "vertical": null, "horizontal": null}, "protection": {"locked": true, "hidden": false}}
A110: Intro | B110: D16 | C110: 16 | D110: 4 | E110: Input | H110: {"type": "null", "value": null} | I110: General | J110: FALSE | K110: FALSE | L110: 11 | M110: Values must be of type <class 'str'> | N110: 00000000 | R110: FALSE | W110: {"number_format": "General", "font": {"name": "Calibri", "size": 11.0, "bold": false, "italic": false, "underline": null, "strike": null, "color": {"type": "theme", "rgb": "Values must be of type <class 'str'>", "indexed": null, "theme": 1, "tint": 0.0, "auto": null}, "vert_align": null}, "fill": {"fill_type": null, "fg_color": {"type": "rgb", "rgb": "00000000", "indexed": null, "theme": null, "tint": 0.0, "auto": null}, "bg_color": {"type": "rgb", "rgb": "00000000", "indexed": null, "theme": null, "tint": 0.0, "auto": null}}, "alignment": {"horizontal": null, "vertical": null, "text_rotation": 0, "wrap_text": null, "shrink_to_fit": null, "indent": 0.0}, "border": {"left": {"style": null, "color": null}, "right": {"style": null, "color": null}, "top": {"style": null, "color": null}, "bottom": {"style": null, "color": null}, "diagonal": {"style": null, "color": null}, "diagonal_down": false, "diagonal_up": false, "outline": true, "vertical": null, "horizontal": null}, "protection": {"locked": true, "hidden": false}}
A111: Intro | B111: E16 | C111: 16 | D111: 5 | E111: Input | G111: Mumbai | H111: {"type": "str", "value": "Mumbai"} | I111: General | J111: TRUE | K111: FALSE | L111: 9 | M111: FF444444 | N111: 00000000 | O111: center | R111: TRUE | W111: {"number_format": "General", "font": {"name": "Tahoma", "size": 9.0, "bold": true, "italic": false, "underline": null, "strike": null, "color": {"type": "rgb", "rgb": "FF444444", "indexed": null, "theme": null, "tint": 0.0, "auto": null}, "vert_align": null}, "fill": {"fill_type": null, "fg_color": {"type": "rgb", "rgb": "00000000", "indexed": null, "theme": null, "tint": 0.0, "auto": null}, "bg_color": {"type": "rgb", "rgb": "00000000", "indexed": null, "theme": null, "tint": 0.0, "auto": null}}, "alignment": {"horizontal": "center", "vertical": null, "text_rotation": 0, "wrap_text": null, "shrink_to_fit": null, "indent": 0.0}, "border": {"left": {"style": null, "color": null}, "right": {"style": null, "color": null}, "top": {"style": null, "color": null}, "bottom": {"style": null, "color": null}, "diagonal": {"style": null, "color": null}, "diagonal_down": false, "diagonal_up": false, "outline": true, "vertical": null, "horizontal": null}, "protection": {"locked": true, "hidden": false}}
A112: Intro | B112: F16 | C112: 16 | D112: 6 | E112: Input | H112: {"type": "null", "value": null} | I112: General | J112: FALSE | K112: FALSE | L112: 11 | M112: Values must be of type <class 'str'> | N112: 00000000 | R112: FALSE | W112: {"number_format": "General", "font": {"name": "Calibri", "size": 11.0, "bold": false, "italic": false, "underline": null, "strike": null, "color": {"type": "theme", "rgb": "Values must be of type <class 'str'>", "indexed": null, "theme": 1, "tint": 0.0, "auto": null}, "vert_align": null}, "fill": {"fill_type": null, "fg_color": {"type": "rgb", "rgb": "00000000", "indexed": null, "theme": null, "tint": 0.0, "auto": null}, "bg_color": {"type": "rgb", "rgb": "00000000", "indexed": null, "theme": null, "tint": 0.0, "auto": null}}, "alignment": {"horizontal": null, "vertical": null, "text_rotation": 0, "wrap_text": null, "shrink_to_fit": null, "indent": 0.0}, "border": {"left": {"style": null, "color": null}, "right": {"style": null, "color": null}, "top": {"style": null, "color": null}, "bottom": {"style": null, "color": null}, "diagonal": {"style": null, "color": null}, "diagonal_down": false, "diagonal_up": false, "outline": true, "vertical": null, "horizontal": null}, "protection": {"locked": true, "hidden": false}}
A113: Intro | B113: G16 | C113: 16 | D113: 7 | E113: Input | H113: {"type": "null", "value": null} | I113: General | J113: FALSE | K113: FALSE | L113: 11 | M113: Values must be of type <class 'str'> | N113: 00000000 | R113: FALSE | W113: {"number_format": "General", "font": {"name": "Calibri", "size": 11.0, "bold": false, "italic": false, "underline": null, "strike": null, "color": {"type": "theme", "rgb": "Values must be of type <class 'str'>", "indexed": null, "theme": 1, "tint": 0.0, "auto": null}, "vert_align": null}, "fill": {"fill_type": null, "fg_color": {"type": "rgb", "rgb": "00000000", "indexed": null, "theme": null, "tint": 0.0, "auto": null}, "bg_color": {"type": "rgb", "rgb": "00000000", "indexed": null, "theme": null, "tint": 0.0, "auto": null}}, "alignment": {"horizontal": null, "vertical": null, "text_rotation": 0, "wrap_text": null, "shrink_to_fit": null, "indent": 0.0}, "border": {"left": {"style": null, "color": null}, "right": {"style": null, "color": null}, "top": {"style": null, "color": null}, "bottom": {"style": null, "color": null}, "diagonal": {"style": null, "color": null}, "diagonal_down": false, "diagonal_up": false, "outline": true, "vertical": null, "horizontal": null}, "protection": {"locked": true, "hidden": false}}
A114: Intro | B114: A17 | C114: 17 | D114: 1 | E114: Input | H114: {"type": "null", "value": null} | I114: General | J114: FALSE | K114: FALSE | L114: 11 | M114: Values must be of type <class 'str'> | N114: 00000000 | R114: FALSE | W114: {"number_format": "General", "font": {"name": "Calibri", "size": 11.0, "bold": false, "italic": false, "underline": null, "strike": null, "color": {"type": "theme", "rgb": "Values must be of type <class 'str'>", "indexed": null, "theme": 1, "tint": 0.0, "auto": null}, "vert_align": null}, "fill": {"fill_type": null, "fg_color": {"type": "rgb", "rgb": "00000000", "indexed": null, "theme": null, "tint": 0.0, "auto": null}, "bg_color": {"type": "rgb", "rgb": "00000000", "indexed": null, "theme": null, "tint": 0.0, "auto": null}}, "alignment": {"horizontal": null, "vertical": null, "text_rotation": 0, "wrap_text": null, "shrink_to_fit": null, "indent": 0.0}, "border": {"left": {"style": null, "color": null}, "right": {"style": null, "color": null}, "top": {"style": null, "color": null}, "bottom": {"style": null, "color": null}, "diagonal": {"style": null, "color": null}, "diagonal_down": false, "diagonal_up": false, "outline": true, "vertical": null, "horizontal": null}, "protection": {"locked": true, "hidden": false}}
A115: Intro | B115: B17 | C115: 17 | D115: 2 | E115: Input | H115: {"type": "null", "value": null} | I115: General | J115: FALSE | K115: FALSE | L115: 11 | M115: Values must be of type <class 'str'> | N115: 00000000 | R115: FALSE | W115: {"number_format": "General", "font": {"name": "Calibri", "size": 11.0, "bold": false, "italic": false, "underline": null, "strike": null, "color": {"type": "theme", "rgb": "Values must be of type <class 'str'>", "indexed": null, "theme": 1, "tint": 0.0, "auto": null}, "vert_align": null}, "fill": {"fill_type": null, "fg_color": {"type": "rgb", "rgb": "00000000", "indexed": null, "theme": null, "tint": 0.0, "auto": null}, "bg_color": {"type": "rgb", "rgb": "00000000", "indexed": null, "theme": null, "tint": 0.0, "auto": null}}, "alignment": {"horizontal": null, "vertical": null, "text_rotation": 0, "wrap_text": null, "shrink_to_fit": null, "indent": 0.0}, "border": {"left": {"style": null, "color": null}, "right": {"style": null, "color": null}, "top": {"style": null, "color": null}, "bottom": {"style": null, "color": null}, "diagonal": {"style": null, "color": null}, "diagonal_down": false, "diagonal_up": false, "outline": true, "vertical": null, "horizontal": null}, "protection": {"locked": true, "hidden": false}}
A116: Intro | B116: C17 | C116: 17 | D116: 3 | E116: Input | H116: {"type": "null", "value": null} | I116: General | J116: FALSE | K116: FALSE | L116: 11 | M116: Values must be of type <class 'str'> | N116: 00000000 | R116: FALSE | W116: {"number_format": "General", "font": {"name": "Calibri", "size": 11.0, "bold": false, "italic": false, "underline": null, "strike": null, "color": {"type": "theme", "rgb": "Values must be of type <class 'str'>", "indexed": null, "theme": 1, "tint": 0.0, "auto": null}, "vert_align": null}, "fill": {"fill_type": null, "fg_color": {"type": "rgb", "rgb": "00000000", "indexed": null, "theme": null, "tint": 0.0, "auto": null}, "bg_color": {"type": "rgb", "rgb": "00000000", "indexed": null, "theme": null, "tint": 0.0, "auto": null}}, "alignment": {"horizontal": null, "vertical": null, "text_rotation": 0, "wrap_text": null, "shrink_to_fit": null, "indent": 0.0}, "border": {"left": {"style": null, "color": null}, "right": {"style": null, "color": null}, "top": {"style": null, "color": null}, "bottom": {"style": null, "color": null}, "diagonal": {"style": null, "color": null}, "diagonal_down": false, "diagonal_up": false, "outline": true, "vertical": null, "horizontal": null}, "protection": {"locked": true, "hidden": false}}
A117: Intro | B117: D17 | C117: 17 | D117: 4 | E117: Input | H117: {"type": "null", "value": null} | I117: General | J117: FALSE | K117: FALSE | L117: 11 | M117: Values must be of type <class 'str'> | N117: 00000000 | R117: FALSE | W117: {"number_format": "General", "font": {"name": "Calibri", "size": 11.0, "bold": false, "italic": false, "underline": null, "strike": null, "color": {"type": "theme", "rgb": "Values must be of type <class 'str'>", "indexed": null, "theme": 1, "tint": 0.0, "auto": null}, "vert_align": null}, "fill": {"fill_type": null, "fg_color": {"type": "rgb", "rgb": "00000000", "indexed": null, "theme": null, "tint": 0.0, "auto": null}, "bg_color": {"type": "rgb", "rgb": "00000000", "indexed": null, "theme": null, "tint": 0.0, "auto": null}}, "alignment": {"horizontal": null, "vertical": null, "text_rotation": 0, "wrap_text": null, "shrink_to_fit": null, "indent": 0.0}, "border": {"left": {"style": null, "color": null}, "right": {"style": null, "color": null}, "top": {"style": null, "color": null}, "bottom": {"style": null, "color": null}, "diagonal": {"style": null, "color": null}, "diagonal_down": false, "diagonal_up": false, "outline": true, "vertical": null, "horizontal": null}, "protection": {"locked": true, "hidden": false}}
A118: Intro | B118: E17 | C118: 17 | D118: 5 | E118: Input | H118: {"type": "null", "value": null} | I118: General | J118: FALSE | K118: FALSE | L118: 11 | M118: Values must be of type <class 'str'> | N118: 00000000 | O118: center | R118: FALSE | W118: {"number_format": "General", "font": {"name": "Calibri", "size": 11.0, "bold": false, "italic": false, "underline": null, "strike": null, "color": {"type": "theme", "rgb": "Values must be of type <class 'str'>", "indexed": null, "theme": 1, "tint": 0.0, "auto": null}, "vert_align": null}, "fill": {"fill_type": null, "fg_color": {"type": "rgb", "rgb": "00000000", "indexed": null, "theme": null, "tint": 0.0, "auto": null}, "bg_color": {"type": "rgb", "rgb": "00000000", "indexed": null, "theme": null, "tint": 0.0, "auto": null}}, "alignment": {"horizontal": "center", "vertical": null, "text_rotation": 0, "wrap_text": null, "shrink_to_fit": null, "indent": 0.0}, "border": {"left": {"style": null, "color": null}, "right": {"style": null, "color": null}, "top": {"style": null, "color": null}, "bottom": {"style": null, "color": null}, "diagonal": {"style": null, "color": null}, "diagonal_down": false, "diagonal_up": false, "outline": true, "vertical": null, "horizontal": null}, "protection": {"locked": true, "hidden": false}}
A119: Intro | B119: F17 | C119: 17 | D119: 6 | E119: Input | H119: {"type": "null", "value": null} | I119: General | J119: FALSE | K119: FALSE | L119: 11 | M119: Values must be of type <class 'str'> | N119: 00000000 | R119: FALSE | W119: {"number_format": "General", "font": {"name": "Calibri", "size": 11.0, "bold": false, "italic": false, "underline": null, "strike": null, "color": {"type": "theme", "rgb": "Values must be of type <class 'str'>", "indexed": null, "theme": 1, "tint": 0.0, "auto": null}, "vert_align": null}, "fill": {"fill_type": null, "fg_color": {"type": "rgb", "rgb": "00000000", "indexed": null, "theme": null, "tint": 0.0, "auto": null}, "bg_color": {"type": "rgb", "rgb": "00000000", "indexed": null, "theme": null, "tint": 0.0, "auto": null}}, "alignment": {"horizontal": null, "vertical": null, "text_rotation": 0, "wrap_text": null, "shrink_to_fit": null, "indent": 0.0}, "border": {"left": {"style": null, "color": null}, "right": {"style": null, "color": null}, "top": {"style": null, "color": null}, "bottom": {"style": null, "color": null}, "diagonal": {"style": null, "color": null}, "diagonal_down": false, "diagonal_up": false, "outline": true, "vertical": null, "horizontal": null}, "protection": {"locked": true, "hidden": false}}
A120: Intro | B120: G17 | C120: 17 | D120: 7 | E120: Input | H120: {"type": "null", "value": null} | I120: General | J120: FALSE | K120: FALSE | L120: 11 | M120: Values must be of type <class 'str'> | N120: 00000000 | R120: FALSE | W120: {"number_format": "General", "font": {"name": "Calibri", "size": 11.0, "bold": false, "italic": false, "underline": null, "strike": null, "color": {"type": "theme", "rgb": "Values must be of type <class 'str'>", "indexed": null, "theme": 1, "tint": 0.0, "auto": null}, "vert_align": null}, "fill": {"fill_type": null, "fg_color": {"type": "rgb", "rgb": "00000000", "indexed": null, "theme": null, "tint": 0.0, "auto": null}, "bg_color": {"type": "rgb", "rgb": "00000000", "indexed": null, "theme": null, "tint": 0.0, "auto": null}}, "alignment": {"horizontal": null, "vertical": null, "text_rotation": 0, "wrap_text": null, "shrink_to_fit": null, "indent": 0.0}, "border": {"left": {"style": null, "color": null}, "right": {"style": null, "color": null}, "top": {"style": null, "color": null}, "bottom": {"style": null, "color": null}, "diagonal": {"style": null, "color": null}, "diagonal_down": false, "diagonal_up": false, "outline": true, "vertical": null, "horizontal": null}, "protection": {"locked": true, "hidden": false}}
A121: Intro | B121: A18 | C121: 18 | D121: 1 | E121: Input | H121: {"type": "null", "value": null} | I121: General | J121: FALSE | K121: FALSE | L121: 11 | M121: Values must be of type <class 'str'> | N121: 00000000 | R121: FALSE | W121: {"number_format": "General", "font": {"name": "Calibri", "size": 11.0, "bold": false, "italic": false, "underline": null, "strike": null, "color": {"type": "theme", "rgb": "Values must be of type <class 'str'>", "indexed": null, "theme": 1, "tint": 0.0, "auto": null}, "vert_align": null}, "fill": {"fill_type": null, "fg_color": {"type": "rgb", "rgb": "00000000", "indexed": null, "theme": null, "tint": 0.0, "auto": null}, "bg_color": {"type": "rgb", "rgb": "00000000", "indexed": null, "theme": null, "tint": 0.0, "auto": null}}, "alignment": {"horizontal": null, "vertical": null, "text_rotation": 0, "wrap_text": null, "shrink_to_fit": null, "indent": 0.0}, "border": {"left": {"style": null, "color": null}, "right": {"style": null, "color": null}, "top": {"style": null, "color": null}, "bottom": {"style": null, "color": null}, "diagonal": {"style": null, "color": null}, "diagonal_down": false, "diagonal_up": false, "outline": true, "vertical": null, "horizontal": null}, "protection": {"locked": true, "hidden": false}}
A122: Intro | B122: B18 | C122: 18 | D122: 2 | E122: Input | H122: {"type": "null", "value": null} | I122: General | J122: FALSE | K122: FALSE | L122: 11 | M122: Values must be of type <class 'str'> | N122: 00000000 | R122: FALSE | W122: {"number_format": "General", "font": {"name": "Calibri", "size": 11.0, "bold": false, "italic": false, "underline": null, "strike": null, "color": {"type": "theme", "rgb": "Values must be of type <class 'str'>", "indexed": null, "theme": 1, "tint": 0.0, "auto": null}, "vert_align": null}, "fill": {"fill_type": null, "fg_color": {"type": "rgb", "rgb": "00000000", "indexed": null, "theme": null, "tint": 0.0, "auto": null}, "bg_color": {"type": "rgb", "rgb": "00000000", "indexed": null, "theme": null, "tint": 0.0, "auto": null}}, "alignment": {"horizontal": null, "vertical": null, "text_rotation": 0, "wrap_text": null, "shrink_to_fit": null, "indent": 0.0}, "border": {"left": {"style": null, "color": null}, "right": {"style": null, "color": null}, "top": {"style": null, "color": null}, "bottom": {"style": null, "color": null}, "diagonal": {"style": null, "color": null}, "diagonal_down": false, "diagonal_up": false, "outline": true, "vertical": null, "horizontal": null}, "protection": {"locked": true, "hidden": false}}
A123: Intro | B123: C18 | C123: 18 | D123: 3 | E123: Input | H123: {"type": "null", "value": null} | I123: General | J123: FALSE | K123: FALSE | L123: 11 | M123: Values must be of type <class 'str'> | N123: 00000000 | R123: FALSE | W123: {"number_format": "General", "font": {"name": "Calibri", "size": 11.0, "bold": false, "italic": false, "underline": null, "strike": null, "color": {"type": "theme", "rgb": "Values must be of type <class 'str'>", "indexed": null, "theme": 1, "tint": 0.0, "auto": null}, "vert_align": null}, "fill": {"fill_type": null, "fg_color": {"type": "rgb", "rgb": "00000000", "indexed": null, "theme": null, "tint": 0.0, "auto": null}, "bg_color": {"type": "rgb", "rgb": "00000000", "indexed": null, "theme": null, "tint": 0.0, "auto": null}}, "alignment": {"horizontal": null, "vertical": null, "text_rotation": 0, "wrap_text": null, "shrink_to_fit": null, "indent": 0.0}, "border": {"left": {"style": null, "color": null}, "right": {"style": null, "color": null}, "top": {"style": null, "color": null}, "bottom": {"style": null, "color": null}, "diagonal": {"style": null, "color": null}, "diagonal_down": false, "diagonal_up": false, "outline": true, "vertical": null, "horizontal": null}, "protection": {"locked": true, "hidden": false}}
A124: Intro | B124: D18 | C124: 18 | D124: 4 | E124: Input | H124: {"type": "null", "value": null} | I124: General | J124: FALSE | K124: FALSE | L124: 11 | M124: Values must be of type <class 'str'> | N124: 00000000 | R124: FALSE | W124: {"number_format": "General", "font": {"name": "Calibri", "size": 11.0, "bold": false, "italic": false, "underline": null, "strike": null, "color": {"type": "theme", "rgb": "Values must be of type <class 'str'>", "indexed": null, "theme": 1, "tint": 0.0, "auto": null}, "vert_align": null}, "fill": {"fill_type": null, "fg_color": {"type": "rgb", "rgb": "00000000", "indexed": null, "theme": null, "tint": 0.0, "auto": null}, "bg_color": {"type": "rgb", "rgb": "00000000", "indexed": null, "theme": null, "tint": 0.0, "auto": null}}, "alignment": {"horizontal": null, "vertical": null, "text_rotation": 0, "wrap_text": null, "shrink_to_fit": null, "indent": 0.0}, "border": {"left": {"style": null, "color": null}, "right": {"style": null, "color": null}, "top": {"style": null, "color": null}, "bottom": {"style": null, "color": null}, "diagonal": {"style": null, "color": null}, "diagonal_down": false, "diagonal_up": false, "outline": true, "vertical": null, "horizontal": null}, "protection": {"locked": true, "hidden": false}}
A125: Intro | B125: E18 | C125: 18 | D125: 5 | E125: Input | G125: IMS Proschool Pvt Ltd, | H125: {"type": "str", "value": "IMS Proschool Pvt Ltd,"} | I125: General | J125: FALSE | K125: FALSE | L125: 9 | M125: FF444444 | N125: 00000000 | O125: center | R125: TRUE | W125: {"number_format": "General", "font": {"name": "Tahoma", "size": 9.0, "bold": false, "italic": false, "underline": null, "strike": null, "color": {"type": "rgb", "rgb": "FF444444", "indexed": null, "theme": null, "tint": 0.0, "auto": null}, "vert_align": null}, "fill": {"fill_type": null, "fg_color": {"type": "rgb", "rgb": "00000000", "indexed": null, "theme": null, "tint": 0.0, "auto": null}, "bg_color": {"type": "rgb", "rgb": "00000000", "indexed": null, "theme": null, "tint": 0.0, "auto": null}}, "alignment": {"horizontal": "center", "vertical": null, "text_rotation": 0, "wrap_text": null, "shrink_to_fit": null, "indent": 0.0}, "border": {"left": {"style": null, "color": null}, "right": {"style": null, "color": null}, "top": {"style": null, "color": null}, "bottom": {"style": null, "color": null}, "diagonal": {"style": null, "color": null}, "diagonal_down": false, "diagonal_up": false, "outline": true, "vertical": null, "horizontal": null}, "protection": {"locked": true, "hidden": false}}
A126: Intro | B126: F18 | C126: 18 | D126: 6 | E126: Input | H126: {"type": "null", "value": null} | I126: General | J126: FALSE | K126: FALSE | L126: 11 | M126: Values must be of type <class 'str'> | N126: 00000000 | R126: FALSE | W126: {"number_format": "General", "font": {"name": "Calibri", "size": 11.0, "bold": false, "italic": false, "underline": null, "strike": null, "color": {"type": "theme", "rgb": "Values must be of type <class 'str'>", "indexed": null, "theme": 1, "tint": 0.0, "auto": null}, "vert_align": null}, "fill": {"fill_type": null, "fg_color": {"type": "rgb", "rgb": "00000000", "indexed": null, "theme": null, "tint": 0.0, "auto": null}, "bg_color": {"type": "rgb", "rgb": "00000000", "indexed": null, "theme": null, "tint": 0.0, "auto": null}}, "alignment": {"horizontal": null, "vertical": null, "text_rotation": 0, "wrap_text": null, "shrink_to_fit": null, "indent": 0.0}, "border": {"left": {"style": null, "color": null}, "right": {"style": null, "color": null}, "top": {"style": null, "color": null}, "bottom": {"style": null, "color": null}, "diagonal": {"style": null, "color": null}, "diagonal_down": false, "diagonal_up": false, "outline": true, "vertical": null, "horizontal": null}, "protection": {"locked": true, "hidden": false}}
A127: Intro | B127: G18 | C127: 18 | D127: 7 | E127: Input | H127: {"type": "null", "value": null} | I127: General | J127: FALSE | K127: FALSE | L127: 11 | M127: Values must be of type <class 'str'> | N127: 00000000 | R127: FALSE | W127: {"number_format": "General", "font": {"name": "Calibri", "size": 11.0, "bold": false, "italic": false, "underline": null, "strike": null, "color": {"type": "theme", "rgb": "Values must be of type <class 'str'>", "indexed": null, "theme": 1, "tint": 0.0, "auto": null}, "vert_align": null}, "fill": {"fill_type": null, "fg_color": {"type": "rgb", "rgb": "00000000", "indexed": null, "theme": null, "tint": 0.0, "auto": null}, "bg_color": {"type": "rgb", "rgb": "00000000", "indexed": null, "theme": null, "tint": 0.0, "auto": null}}, "alignment": {"horizontal": null, "vertical": null, "text_rotation": 0, "wrap_text": null, "shrink_to_fit": null, "indent": 0.0}, "border": {"left": {"style": null, "color": null}, "right": {"style": null, "color": null}, "top": {"style": null, "color": null}, "bottom": {"style": null, "color": null}, "diagonal": {"style": null, "color": null}, "diagonal_down": false, "diagonal_up": false, "outline": true, "vertical": null, "horizontal": null}, "protection": {"locked": true, "hidden": false}}
A128: Intro | B128: A19 | C128: 19 | D128: 1 | E128: Input | H128: {"type": "null", "value": null} | I128: General | J128: FALSE | K128: FALSE | L128: 11 | M128: Values must be of type <class 'str'> | N128: 00000000 | R128: FALSE | W128: {"number_format": "General", "font": {"name": "Calibri", "size": 11.0, "bold": false, "italic": false, "underline": null, "strike": null, "color": {"type": "theme", "rgb": "Values must be of type <class 'str'>", "indexed": null, "theme": 1, "tint": 0.0, "auto": null}, "vert_align": null}, "fill": {"fill_type": null, "fg_color": {"type": "rgb", "rgb": "00000000", "indexed": null, "theme": null, "tint": 0.0, "auto": null}, "bg_color": {"type": "rgb", "rgb": "00000000", "indexed": null, "theme": null, "tint": 0.0, "auto": null}}, "alignment": {"horizontal": null, "vertical": null, "text_rotation": 0, "wrap_text": null, "shrink_to_fit": null, "indent": 0.0}, "border": {"left": {"style": null, "color": null}, "right": {"style": null, "color": null}, "top": {"style": null, "color": null}, "bottom": {"style": null, "color": null}, "diagonal": {"style": null, "color": null}, "diagonal_down": false, "diagonal_up": false, "outline": true, "vertical": null, "horizontal": null}, "protection": {"locked": true, "hidden": false}}
A129: Intro | B129: B19 | C129: 19 | D129: 2 | E129: Input | H129: {"type": "null", "value": null} | I129: General | J129: FALSE | K129: FALSE | L129: 11 | M129: Values must be of type <class 'str'> | N129: 00000000 | R129: FALSE | W129: {"number_format": "General", "font": {"name": "Calibri", "size": 11.0, "bold": false, "italic": false, "underline": null, "strike": null, "color": {"type": "theme", "rgb": "Values must be of type <class 'str'>", "indexed": null, "theme": 1, "tint": 0.0, "auto": null}, "vert_align": null}, "fill": {"fill_type": null, "fg_color": {"type": "rgb", "rgb": "00000000", "indexed": null, "theme": null, "tint": 0.0, "auto": null}, "bg_color": {"type": "rgb", "rgb": "00000000", "indexed": null, "theme": null, "tint": 0.0, "auto": null}}, "alignment": {"horizontal": null, "vertical": null, "text_rotation": 0, "wrap_text": null, "shrink_to_fit": null, "indent": 0.0}, "border": {"left": {"style": null, "color": null}, "right": {"style": null, "color": null}, "top": {"style": null, "color": null}, "bottom": {"style": null, "color": null}, "diagonal": {"style": null, "color": null}, "diagonal_down": false, "diagonal_up": false, "outline": true, "vertical": null, "horizontal": null}, "protection": {"locked": true, "hidden": false}}
A130: Intro | B130: C19 | C130: 19 | D130: 3 | E130: Input | H130: {"type": "null", "value": null} | I130: General | J130: FALSE | K130: FALSE | L130: 11 | M130: Values must be of type <class 'str'> | N130: 00000000 | R130: FALSE | W130: {"number_format": "General", "font": {"name": "Calibri", "size": 11.0, "bold": false, "italic": false, "underline": null, "strike": null, "color": {"type": "theme", "rgb": "Values must be of type <class 'str'>", "indexed": null, "theme": 1, "tint": 0.0, "auto": null}, "vert_align": null}, "fill": {"fill_type": null, "fg_color": {"type": "rgb", "rgb": "00000000", "indexed": null, "theme": null, "tint": 0.0, "auto": null}, "bg_color": {"type": "rgb", "rgb": "00000000", "indexed": null, "theme": null, "tint": 0.0, "auto": null}}, "alignment": {"horizontal": null, "vertical": null, "text_rotation": 0, "wrap_text": null, "shrink_to_fit": null, "indent": 0.0}, "border": {"left": {"style": null, "color": null}, "right": {"style": null, "color": null}, "top": {"style": null, "color": null}, "bottom": {"style": null, "color": null}, "diagonal": {"style": null, "color": null}, "diagonal_down": false, "diagonal_up": false, "outline": true, "vertical": null, "horizontal": null}, "protection": {"locked": true, "hidden": false}}
A131: Intro | B131: D19 | C131: 19 | D131: 4 | E131: Input | H131: {"type": "null", "value": null} | I131: General | J131: FALSE | K131: FALSE | L131: 11 | M131: Values must be of type <class 'str'> | N131: 00000000 | R131: FALSE | W131: {"number_format": "General", "font": {"name": "Calibri", "size": 11.0, "bold": false, "italic": false, "underline": null, "strike": null, "color": {"type": "theme", "rgb": "Values must be of type <class 'str'>", "indexed": null, "theme": 1, "tint": 0.0, "auto": null}, "vert_align": null}, "fill": {"fill_type": null, "fg_color": {"type": "rgb", "rgb": "00000000", "indexed": null, "theme": null, "tint": 0.0, "auto": null}, "bg_color": {"type": "rgb", "rgb": "00000000", "indexed": null, "theme": null, "tint": 0.0, "auto": null}}, "alignment": {"horizontal": null, "vertical": null, "text_rotation": 0, "wrap_text": null, "shrink_to_fit": null, "indent": 0.0}, "border": {"left": {"style": null, "color": null}, "right": {"style": null, "color": null}, "top": {"style": null, "color": null}, "bottom": {"style": null, "color": null}, "diagonal": {"style": null, "color": null}, "diagonal_down": false, "diagonal_up": false, "outline": true, "vertical": null, "horizontal": null}, "protection": {"locked": true, "hidden": false}}
A132: Intro | B132: E19 | C132: 19 | D132: 5 | E132: Input | G132: Maharashtra High School Complex, | H132: {"type": "str", "value": "Maharashtra High School Complex,"} | I132: General | J132: FALSE | K132: FALSE | L132: 9 | M132: FF444444 | N132: 00000000 | O132: center | R132: TRUE | W132: {"number_format": "General", "font": {"name": "Tahoma", "size": 9.0, "bold": false, "italic": false, "underline": null, "strike": null, "color": {"type": "rgb", "rgb": "FF444444", "indexed": null, "theme": null, "tint": 0.0, "auto": null}, "vert_align": null}, "fill": {"fill_type": null, "fg_color": {"type": "rgb", "rgb": "00000000", "indexed": null, "theme": null, "tint": 0.0, "auto": null}, "bg_color": {"type": "rgb", "rgb": "00000000", "indexed": null, "theme": null, "tint": 0.0, "auto": null}}, "alignment": {"horizontal": "center", "vertical": null, "text_rotation": 0, "wrap_text": null, "shrink_to_fit": null, "indent": 0.0}, "border": {"left": {"style": null, "color": null}, "right": {"style": null, "color": null}, "top": {"style": null, "color": null}, "bottom": {"style": null, "color": null}, "diagonal": {"style": null, "color": null}, "diagonal_down": false, "diagonal_up": false, "outline": true, "vertical": null, "horizontal": null}, "protection": {"locked": true, "hidden": false}}
A133: Intro | B133: F19 | C133: 19 | D133: 6 | E133: Input | H133: {"type": "null", "value": null} | I133: General | J133: FALSE | K133: FALSE | L133: 11 | M133: Values must be of type <class 'str'> | N133: 00000000 | R133: FALSE | W133: {"number_format": "General", "font": {"name": "Calibri", "size": 11.0, "bold": false, "italic": false, "underline": null, "strike": null, "color": {"type": "theme", "rgb": "Values must be of type <class 'str'>", "indexed": null, "theme": 1, "tint": 0.0, "auto": null}, "vert_align": null}, "fill": {"fill_type": null, "fg_color": {"type": "rgb", "rgb": "00000000", "indexed": null, "theme": null, "tint": 0.0, "auto": null}, "bg_color": {"type": "rgb", "rgb": "00000000", "indexed": null, "theme": null, "tint": 0.0, "auto": null}}, "alignment": {"horizontal": null, "vertical": null, "text_rotation": 0, "wrap_text": null, "shrink_to_fit": null, "indent": 0.0}, "border": {"left": {"style": null, "color": null}, "right": {"style": null, "color": null}, "top": {"style": null, "color": null}, "bottom": {"style": null, "color": null}, "diagonal": {"style": null, "color": null}, "diagonal_down": false, "diagonal_up": false, "outline": true, "vertical": null, "horizontal": null}, "protection": {"locked": true, "hidden": false}}
A134: Intro | B134: G19 | C134: 19 | D134: 7 | E134: Input | H134: {"type": "null", "value": null} | I134: General | J134: FALSE | K134: FALSE | L134: 11 | M134: Values must be of type <class 'str'> | N134: 00000000 | R134: FALSE | W134: {"number_format": "General", "font": {"name": "Calibri", "size": 11.0, "bold": false, "italic": false, "underline": null, "strike": null, "color": {"type": "theme", "rgb": "Values must be of type <class 'str'>", "indexed": null, "theme": 1, "tint": 0.0, "auto": null}, "vert_align": null}, "fill": {"fill_type": null, "fg_color": {"type": "rgb", "rgb": "00000000", "indexed": null, "theme": null, "tint": 0.0, "auto": null}, "bg_color": {"type": "rgb", "rgb": "00000000", "indexed": null, "theme": null, "tint": 0.0, "auto": null}}, "alignment": {"horizontal": null, "vertical": null, "text_rotation": 0, "wrap_text": null, "shrink_to_fit": null, "indent": 0.0}, "border": {"left": {"style": null, "color": null}, "right": {"style": null, "color": null}, "top": {"style": null, "color": null}, "bottom": {"style": null, "color": null}, "diagonal": {"style": null, "color": null}, "diagonal_down": false, "diagonal_up": false, "outline": true, "vertical": null, "horizontal": null}, "protection": {"locked": true, "hidden": false}}
A135: Intro | B135: A20 | C135: 20 | D135: 1 | E135: Input | H135: {"type": "null", "value": null} | I135: General | J135: FALSE | K135: FALSE | L135: 11 | M135: Values must be of type <class 'str'> | N135: 00000000 | R135: FALSE | W135: {"number_format": "General", "font": {"name": "Calibri", "size": 11.0, "bold": false, "italic": false, "underline": null, "strike": null, "color": {"type": "theme", "rgb": "Values must be of type <class 'str'>", "indexed": null, "theme": 1, "tint": 0.0, "auto": null}, "vert_align": null}, "fill": {"fill_type": null, "fg_color": {"type": "rgb", "rgb": "00000000", "indexed": null, "theme": null, "tint": 0.0, "auto": null}, "bg_color": {"type": "rgb", "rgb": "00000000", "indexed": null, "theme": null, "tint": 0.0, "auto": null}}, "alignment": {"horizontal": null, "vertical": null, "text_rotation": 0, "wrap_text": null, "shrink_to_fit": null, "indent": 0.0}, "border": {"left": {"style": null, "color": null}, "right": {"style": null, "color": null}, "top": {"style": null, "color": null}, "bottom": {"style": null, "color": null}, "diagonal": {"style": null, "color": null}, "diagonal_down": false, "diagonal_up": false, "outline": true, "vertical": null, "horizontal": null}, "protection": {"locked": true, "hidden": false}}
...

Sheet Revenue Model
A1: Sheet | B1: Cell | C1: Row | D1: Column | E1: Type | F1: Formula | G1: Value | H1: ValueJSON | I1: NumberFormat | J1: FontBold | K1: FontItalic | L1: FontSize | M1: FontColor | N1: FillColor | O1: HorizontalAlignment | P1: VerticalAlignment | Q1: WrapText | R1: IncludeFlag | S1: GroupID | T1: GroupDirection | U1: GroupSize | V1: PatternFormula | W1: StyleJSON
A2: Revenue Model | B2: A1 | C2: 1 | D2: 1 | E2: Input | G2: ACC Ltd | H2: {"type": "str", "value": "ACC Ltd"} | I2: General | J2: TRUE | K2: FALSE | L2: 11 | M2: Values must be of type <class 'str'> | N2: Values must be of type <class 'str'> | P2: center | R2: TRUE | W2: {"number_format": "General", "font": {"name": "Calibri", "size": 11.0, "bold": true, "italic": false, "underline": null, "strike": null, "color": {"type": "theme", "rgb": "Values must be of type <class 'str'>", "indexed": null, "theme": 0, "tint": 0.0, "auto": null}, "vert_align": null}, "fill": {"fill_type": "solid", "fg_color": {"type": "theme", "rgb": "Values must be of type <class 'str'>", "indexed": null, "theme": 4, "tint": 0.0, "auto": null}, "bg_color": {"type": "indexed", "rgb": "Values must be of type <class 'str'>", "indexed": 64, "theme": null, "tint": 0.0, "auto": null}}, "alignment": {"horizontal": null, "vertical": "center", "text_rotation": 0, "wrap_text": null, "shrink_to_fit": null, "indent": 0.0}, "border": {"left": {"style": "thin", "color": {"type": "auto", "rgb": "Values must be of type <class 'str'>", "indexed": null, "theme": null, "tint": 0.0, "auto": true}}, "right": {"style": "thin", "color": {"type": "auto", "rgb": "Values must be of type <class 'str'>", "indexed": null, "theme": null, "tint": 0.0, "auto": true}}, "top": {"style": "thin", "color": {"type": "auto", "rgb": "Values must be of type <class 'str'>", "indexed": null, "theme": null, "tint": 0.0, "auto": true}}, "bottom": {"style": "thin", "color": {"type": "auto", "rgb": "Values must be of type <class 'str'>", "indexed": null, "theme": null, "tint": 0.0, "auto": true}}, "diagonal": {"style": null, "color": null}, "diagonal_down": false, "diagonal_up": false, "outline": true, "vertical": null, "horizontal": null}, "protection": {"locked": true, "hidden": false}}
A3: Revenue Model | B3: B1 | C3: 1 | D3: 2 | E3: Input | G3: 2015 | H3: {"type": "int", "value": 2015} | I3: General | J3: TRUE | K3: FALSE | L3: 11 | M3: Values must be of type <class 'str'> | N3: Values must be of type <class 'str'> | O3: center | P3: center | R3: TRUE | W3: {"number_format": "General", "font": {"name": "Calibri", "size": 11.0, "bold": true, "italic": false, "underline": null, "strike": null, "color": {"type": "theme", "rgb": "Values must be of type <class 'str'>", "indexed": null, "theme": 0, "tint": 0.0, "auto": null}, "vert_align": null}, "fill": {"fill_type": "solid", "fg_color": {"type": "theme", "rgb": "Values must be of type <class 'str'>", "indexed": null, "theme": 4, "tint": 0.0, "auto": null}, "bg_color": {"type": "indexed", "rgb": "Values must be of type <class 'str'>", "indexed": 64, "theme": null, "tint": 0.0, "auto": null}}, "alignment": {"horizontal": "center", "vertical": "center", "text_rotation": 0, "wrap_text": null, "shrink_to_fit": null, "indent": 0.0}, "border": {"left": {"style": "thin", "color": {"type": "auto", "rgb": "Values must be of type <class 'str'>", "indexed": null, "theme": null, "tint": 0.0, "auto": true}}, "right": {"style": "thin", "color": {"type": "auto", "rgb": "Values must be of type <class 'str'>", "indexed": null, "theme": null, "tint": 0.0, "auto": true}}, "top": {"style": "thin", "color": {"type": "auto", "rgb": "Values must be of type <class 'str'>", "indexed": null, "theme": null, "tint": 0.0, "auto": true}}, "bottom": {"style": "thin", "color": {"type": "auto", "rgb": "Values must be of type <class 'str'>", "indexed": null, "theme": null, "tint": 0.0, "auto": true}}, "diagonal": {"style": null, "color": null}, "diagonal_down": false, "diagonal_up": false, "outline": true, "vertical": null, "horizontal": null}, "protection": {"locked": true, "hidden": false}}
A4: Revenue Model | B4: C1 | C4: 1 | D4: 3 | E4: Input | G4: 2016 | H4: {"type": "int", "value": 2016} | I4: General | J4: TRUE | K4: FALSE | L4: 11 | M4: Values must be of type <class 'str'> | N4: Values must be of type <class 'str'> | O4: center | P4: center | R4: TRUE | W4: {"number_format": "General", "font": {"name": "Calibri", "size": 11.0, "bold": true, "italic": false, "underline": null, "strike": null, "color": {"type": "theme", "rgb": "Values must be of type <class 'str'>", "indexed": null, "theme": 0, "tint": 0.0, "auto": null}, "vert_align": null}, "fill": {"fill_type": "solid", "fg_color": {"type": "theme", "rgb": "Values must be of type <class 'str'>", "indexed": null, "theme": 4, "tint": 0.0, "auto": null}, "bg_color": {"type": "indexed", "rgb": "Values must be of type <class 'str'>", "indexed": 64, "theme": null, "tint": 0.0, "auto": null}}, "alignment": {"horizontal": "center", "vertical": "center", "text_rotation": 0, "wrap_text": null, "shrink_to_fit": null, "indent": 0.0}, "border": {"left": {"style": "thin", "color": {"type": "auto", "rgb": "Values must be of type <class 'str'>", "indexed": null, "theme": null, "tint": 0.0, "auto": true}}, "right": {"style": "thin", "color": {"type": "auto", "rgb": "Values must be of type <class 'str'>", "indexed": null, "theme": null, "tint": 0.0, "auto": true}}, "top": {"style": "thin", "color": {"type": "auto", "rgb": "Values must be of type <class 'str'>", "indexed": null, "theme": null, "tint": 0.0, "auto": true}}, "bottom": {"style": "thin", "color": {"type": "auto", "rgb": "Values must be of type <class 'str'>", "indexed": null, "theme": null, "tint": 0.0, "auto": true}}, "diagonal": {"style": null, "color": null}, "diagonal_down": false, "diagonal_up": false, "outline": true, "vertical": null, "horizontal": null}, "protection": {"locked": true, "hidden": false}}
A5: Revenue Model | B5: D1 | C5: 1 | D5: 4 | E5: Input | G5: 2017 | H5: {"type": "int", "value": 2017} | I5: General | J5: TRUE | K5: FALSE | L5: 11 | M5: Values must be of type <class 'str'> | N5: Values must be of type <class 'str'> | O5: center | P5: center | R5: TRUE | W5: {"number_format": "General", "font": {"name": "Calibri", "size": 11.0, "bold": true, "italic": false, "underline": null, "strike": null, "color": {"type": "theme", "rgb": "Values must be of type <class 'str'>", "indexed": null, "theme": 0, "tint": 0.0, "auto": null}, "vert_align": null}, "fill": {"fill_type": "solid", "fg_color": {"type": "theme", "rgb": "Values must be of type <class 'str'>", "indexed": null, "theme": 4, "tint": 0.0, "auto": null}, "bg_color": {"type": "indexed", "rgb": "Values must be of type <class 'str'>", "indexed": 64, "theme": null, "tint": 0.0, "auto": null}}, "alignment": {"horizontal": "center", "vertical": "center", "text_rotation": 0, "wrap_text": null, "shrink_to_fit": null, "indent": 0.0}, "border": {"left": {"style": "thin", "color": {"type": "auto", "rgb": "Values must be of type <class 'str'>", "indexed": null, "theme": null, "tint": 0.0, "auto": true}}, "right": {"style": "thin", "color": {"type": "auto", "rgb": "Values must be of type <class 'str'>", "indexed": null, "theme": null, "tint": 0.0, "auto": true}}, "top": {"style": "thin", "color": {"type": "auto", "rgb": "Values must be of type <class 'str'>", "indexed": null, "theme": null, "tint": 0.0, "auto": true}}, "bottom": {"style": "thin", "color": {"type": "auto", "rgb": "Values must be of type <class 'str'>", "indexed": null, "theme": null, "tint": 0.0, "auto": true}}, "diagonal": {"style": null, "color": null}, "diagonal_down": false, "diagonal_up": false, "outline": true, "vertical": null, "horizontal": null}, "protection": {"locked": true, "hidden": false}}
A6: Revenue Model | B6: E1 | C6: 1 | D6: 5 | E6: Input | G6: 2018 F | H6: {"type": "str", "value": "2018 F"} | I6: General | J6: TRUE | K6: FALSE | L6: 11 | M6: Values must be of type <class 'str'> | N6: Values must be of type <class 'str'> | O6: center | P6: center | R6: TRUE | W6: {"number_format": "General", "font": {"name": "Calibri", "size": 11.0, "bold": true, "italic": false, "underline": null, "strike": null, "color": {"type": "theme", "rgb": "Values must be of type <class 'str'>", "indexed": null, "theme": 0, "tint": 0.0, "auto": null}, "vert_align": null}, "fill": {"fill_type": "solid", "fg_color": {"type": "theme", "rgb": "Values must be of type <class 'str'>", "indexed": null, "theme": 4, "tint": 0.0, "auto": null}, "bg_color": {"type": "indexed", "rgb": "Values must be of type <class 'str'>", "indexed": 64, "theme": null, "tint": 0.0, "auto": null}}, "alignment": {"horizontal": "center", "vertical": "center", "text_rotation": 0, "wrap_text": null, "shrink_to_fit": null, "indent": 0.0}, "border": {"left": {"style": "thin", "color": {"type": "auto", "rgb": "Values must be of type <class 'str'>", "indexed": null, "theme": null, "tint": 0.0, "auto": true}}, "right": {"style": "thin", "color": {"type": "auto", "rgb": "Values must be of type <class 'str'>", "indexed": null, "theme": null, "tint": 0.0, "auto": true}}, "top": {"style": "thin", "color": {"type": "auto", "rgb": "Values must be of type <class 'str'>", "indexed": null, "theme": null, "tint": 0.0, "auto": true}}, "bottom": {"style": "thin", "color": {"type": "auto", "rgb": "Values must be of type <class 'str'>", "indexed": null, "theme": null, "tint": 0.0, "auto": true}}, "diagonal": {"style": null, "color": null}, "diagonal_down": false, "diagonal_up": false, "outline": true, "vertical": null, "horizontal": null}, "protection": {"locked": true, "hidden": false}}
A7: Revenue Model | B7: F1 | C7: 1 | D7: 6 | E7: Input | G7: 2019 F | H7: {"type": "str", "value": "2019 F"} | I7: General | J7: TRUE | K7: FALSE | L7: 11 | M7: Values must be of type <class 'str'> | N7: Values must be of type <class 'str'> | O7: center | P7: center | R7: TRUE | W7: {"number_format": "General", "font": {"name": "Calibri", "size": 11.0, "bold": true, "italic": false, "underline": null, "strike": null, "color": {"type": "theme", "rgb": "Values must be of type <class 'str'>", "indexed": null, "theme": 0, "tint": 0.0, "auto": null}, "vert_align": null}, "fill": {"fill_type": "solid", "fg_color": {"type": "theme", "rgb": "Values must be of type <class 'str'>", "indexed": null, "theme": 4, "tint": 0.0, "auto": null}, "bg_color": {"type": "indexed", "rgb": "Values must be of type <class 'str'>", "indexed": 64, "theme": null, "tint": 0.0, "auto": null}}, "alignment": {"horizontal": "center", "vertical": "center", "text_rotation": 0, "wrap_text": null, "shrink_to_fit": null, "indent": 0.0}, "border": {"left": {"style": "thin", "color": {"type": "auto", "rgb": "Values must be of type <class 'str'>", "indexed": null, "theme": null, "tint": 0.0, "auto": true}}, "right": {"style": "thin", "color": {"type": "auto", "rgb": "Values must be of type <class 'str'>", "indexed": null, "theme": null, "tint": 0.0, "auto": true}}, "top": {"style": "thin", "color": {"type": "auto", "rgb": "Values must be of type <class 'str'>", "indexed": null, "theme": null, "tint": 0.0, "auto": true}}, "bottom": {"style": "thin", "color": {"type": "auto", "rgb": "Values must be of type <class 'str'>", "indexed": null, "theme": null, "tint": 0.0, "auto": true}}, "diagonal": {"style": null, "color": null}, "diagonal_down": false, "diagonal_up": false, "outline": true, "vertical": null, "horizontal": null}, "protection": {"locked": true, "hidden": false}}
A8: Revenue Model | B8: G1 | C8: 1 | D8: 7 | E8: Input | G8: 2020 F | H8: {"type": "str", "value": "2020 F"} | I8: General | J8: TRUE | K8: FALSE | L8: 11 | M8: Values must be of type <class 'str'> | N8: Values must be of type <class 'str'> | O8: center | P8: center | R8: TRUE | W8: {"number_format": "General", "font": {"name": "Calibri", "size": 11.0, "bold": true, "italic": false, "underline": null, "strike": null, "color": {"type": "theme", "rgb": "Values must be of type <class 'str'>", "indexed": null, "theme": 0, "tint": 0.0, "auto": null}, "vert_align": null}, "fill": {"fill_type": "solid", "fg_color": {"type": "theme", "rgb": "Values must be of type <class 'str'>", "indexed": null, "theme": 4, "tint": 0.0, "auto": null}, "bg_color": {"type": "indexed", "rgb": "Values must be of type <class 'str'>", "indexed": 64, "theme": null, "tint": 0.0, "auto": null}}, "alignment": {"horizontal": "center", "vertical": "center", "text_rotation": 0, "wrap_text": null, "shrink_to_fit": null, "indent": 0.0}, "border": {"left": {"style": "thin", "color": {"type": "auto", "rgb": "Values must be of type <class 'str'>", "indexed": null, "theme": null, "tint": 0.0, "auto": true}}, "right": {"style": "thin", "color": {"type": "auto", "rgb": "Values must be of type <class 'str'>", "indexed": null, "theme": null, "tint": 0.0, "auto": true}}, "top": {"style": "thin", "color": {"type": "auto", "rgb": "Values must be of type <class 'str'>", "indexed": null, "theme": null, "tint": 0.0, "auto": true}}, "bottom": {"style": "thin", "color": {"type": "auto", "rgb": "Values must be of type <class 'str'>", "indexed": null, "theme": null, "tint": 0.0, "auto": true}}, "diagonal": {"style": null, "color": null}, "diagonal_down": false, "diagonal_up": false, "outline": true, "vertical": null, "horizontal": null}, "protection": {"locked": true, "hidden": false}}
A9: Revenue Model | B9: H1 | C9: 1 | D9: 8 | E9: Input | G9: 2021 F | H9: {"type": "str", "value": "2021 F"} | I9: General | J9: TRUE | K9: FALSE | L9: 11 | M9: Values must be of type <class 'str'> | N9: Values must be of type <class 'str'> | O9: center | P9: center | R9: TRUE | W9: {"number_format": "General", "font": {"name": "Calibri", "size": 11.0, "bold": true, "italic": false, "underline": null, "strike": null, "color": {"type": "theme", "rgb": "Values must be of type <class 'str'>", "indexed": null, "theme": 0, "tint": 0.0, "auto": null}, "vert_align": null}, "fill": {"fill_type": "solid", "fg_color": {"type": "theme", "rgb": "Values must be of type <class 'str'>", "indexed": null, "theme": 4, "tint": 0.0, "auto": null}, "bg_color": {"type": "indexed", "rgb": "Values must be of type <class 'str'>", "indexed": 64, "theme": null, "tint": 0.0, "auto": null}}, "alignment": {"horizontal": "center", "vertical": "center", "text_rotation": 0, "wrap_text": null, "shrink_to_fit": null, "indent": 0.0}, "border": {"left": {"style": "thin", "color": {"type": "auto", "rgb": "Values must be of type <class 'str'>", "indexed": null, "theme": null, "tint": 0.0, "auto": true}}, "right": {"style": "thin", "color": {"type": "auto", "rgb": "Values must be of type <class 'str'>", "indexed": null, "theme": null, "tint": 0.0, "auto": true}}, "top": {"style": "thin", "color": {"type": "auto", "rgb": "Values must be of type <class 'str'>", "indexed": null, "theme": null, "tint": 0.0, "auto": true}}, "bottom": {"style": "thin", "color": {"type": "auto", "rgb": "Values must be of type <class 'str'>", "indexed": null, "theme": null, "tint": 0.0, "auto": true}}, "diagonal": {"style": null, "color": null}, "diagonal_down": false, "diagonal_up": false, "outline": true, "vertical": null, "horizontal": null}, "protection": {"locked": true, "hidden": false}}
A10: Revenue Model | B10: I1 | C10: 1 | D10: 9 | E10: Input | G10: 2022 F | H10: {"type": "str", "value": "2022 F"} | I10: General | J10: TRUE | K10: FALSE | L10: 11 | M10: Values must be of type <class 'str'> | N10: Values must be of type <class 'str'> | O10: center | P10: center | R10: TRUE | W10: {"number_format": "General", "font": {"name": "Calibri", "size": 11.0, "bold": true, "italic": false, "underline": null, "strike": null, "color": {"type": "theme", "rgb": "Values must be of type <class 'str'>", "indexed": null, "theme": 0, "tint": 0.0, "auto": null}, "vert_align": null}, "fill": {"fill_type": "solid", "fg_color": {"type": "theme", "rgb": "Values must be of type <class 'str'>", "indexed": null, "theme": 4, "tint": 0.0, "auto": null}, "bg_color": {"type": "indexed", "rgb": "Values must be of type <class 'str'>", "indexed": 64, "theme": null, "tint": 0.0, "auto": null}}, "alignment": {"horizontal": "center", "vertical": "center", "text_rotation": 0, "wrap_text": null, "shrink_to_fit": null, "indent": 0.0}, "border": {"left": {"style": "thin", "color": {"type": "auto", "rgb": "Values must be of type <class 'str'>", "indexed": null, "theme": null, "tint": 0.0, "auto": true}}, "right": {"style": "thin", "color": {"type": "auto", "rgb": "Values must be of type <class 'str'>", "indexed": null, "theme": null, "tint": 0.0, "auto": true}}, "top": {"style": "thin", "color": {"type": "auto", "rgb": "Values must be of type <class 'str'>", "indexed": null, "theme": null, "tint": 0.0, "auto": true}}, "bottom": {"style": "thin", "color": {"type": "auto", "rgb": "Values must be of type <class 'str'>", "indexed": null, "theme": null, "tint": 0.0, "auto": true}}, "diagonal": {"style": null, "color": null}, "diagonal_down": false, "diagonal_up": false, "outline": true, "vertical": null, "horizontal": null}, "protection": {"locked": true, "hidden": false}}
A11: Revenue Model | B11: A2 | C11: 2 | D11: 1 | E11: Input | G11: Cement Sales - Value in cr | H11: {"type": "str", "value": "Cement Sales - Value in cr"} | I11: General | J11: FALSE | K11: FALSE | L11: 11 | M11: FF000000 | N11: 00000000 | R11: TRUE | W11: {"number_format": "General", "font": {"name": "Calibri", "size": 11.0, "bold": false, "italic": false, "underline": null, "strike": null, "color": {"type": "rgb", "rgb": "FF000000", "indexed": null, "theme": null, "tint": 0.0, "auto": null}, "vert_align": null}, "fill": {"fill_type": null, "fg_color": {"type": "rgb", "rgb": "00000000", "indexed": null, "theme": null, "tint": 0.0, "auto": null}, "bg_color": {"type": "rgb", "rgb": "00000000", "indexed": null, "theme": null, "tint": 0.0, "auto": null}}, "alignment": {"horizontal": null, "vertical": null, "text_rotation": 0, "wrap_text": null, "shrink_to_fit": null, "indent": 0.0}, "border": {"left": {"style": "thin", "color": {"type": "auto", "rgb": "Values must be of type <class 'str'>", "indexed": null, "theme": null, "tint": 0.0, "auto": true}}, "right": {"style": "thin", "color": {"type": "auto", "rgb": "Values must be of type <class 'str'>", "indexed": null, "theme": null, "tint": 0.0, "auto": true}}, "top": {"style": "thin", "color": {"type": "auto", "rgb": "Values must be of type <class 'str'>", "indexed": null, "theme": null, "tint": 0.0, "auto": true}}, "bottom": {"style": "thin", "color": {"type": "auto", "rgb": "Values must be of type <class 'str'>", "indexed": null, "theme": null, "tint": 0.0, "auto": true}}, "diagonal": {"style": null, "color": null}, "diagonal_down": false, "diagonal_up": false, "outline": true, "vertical": null, "horizontal": null}, "protection": {"locked": true, "hidden": false}}
A12: Revenue Model | B12: B2 | C12: 2 | D12: 2 | E12: Calculation | F12: ='DuPoint Analysis'!E9-1443 | G12: 11917 | H12: {"type": "int", "value": 11917} | I12: _-* #,##0_-;\-* #,##0_-;_-* "-"??_-;_-@_- | J12: FALSE | K12: FALSE | L12: 11 | M12: FF000000 | N12: 00000000 | R12: TRUE | V12: ='DuPoint Analysis'!R[7]C[3]-1443 | W12: {"number_format": "_-* #,##0_-;\\-* #,##0_-;_-* \"-\"??_-;_-@_-", "font": {"name": "Calibri", "size": 11.0, "bold": false, "italic": false, "underline": null, "strike": null, "color": {"type": "rgb", "rgb": "FF000000", "indexed": null, "theme": null, "tint": 0.0, "auto": null}, "vert_align": null}, "fill": {"fill_type": null, "fg_color": {"type": "rgb", "rgb": "00000000", "indexed": null, "theme": null, "tint": 0.0, "auto": null}, "bg_color": {"type": "rgb", "rgb": "00000000", "indexed": null, "theme": null, "tint": 0.0, "auto": null}}, "alignment": {"horizontal": null, "vertical": null, "text_rotation": 0, "wrap_text": null, "shrink_to_fit": null, "indent": 0.0}, "border": {"left": {"style": "thin", "color": {"type": "auto", "rgb": "Values must be of type <class 'str'>", "indexed": null, "theme": null, "tint": 0.0, "auto": true}}, "right": {"style": "thin", "color": {"type": "auto", "rgb": "Values must be of type <class 'str'>", "indexed": null, "theme": null, "tint": 0.0, "auto": true}}, "top": {"style": "thin", "color": {"type": "auto", "rgb": "Values must be of type <class 'str'>", "indexed": null, "theme": null, "tint": 0.0, "auto": true}}, "bottom": {"style": "thin", "color": {"type": "auto", "rgb": "Values must be of type <class 'str'>", "indexed": null, "theme": null, "tint": 0.0, "auto": true}}, "diagonal": {"style": null, "color": null}, "diagonal_down": false, "diagonal_up": false, "outline": true, "vertical": null, "horizontal": null}, "protection": {"locked": true, "hidden": false}}
A13: Revenue Model | B13: C2 | C13: 2 | D13: 3 | E13: Calculation | F13: ='DuPoint Analysis'!F9-1534 | G13: 11112.2 | H13: {"type": "float", "value": 11112.2} | I13: _-* #,##0_-;\-* #,##0_-;_-* "-"??_-;_-@_- | J13: FALSE | K13: FALSE | L13: 11 | M13: FF000000 | N13: 00000000 | R13: TRUE | V13: ='DuPoint Analysis'!R[7]C[3]-1534 | W13: {"number_format": "_-* #,##0_-;\\-* #,##0_-;_-* \"-\"??_-;_-@_-", "font": {"name": "Calibri", "size": 11.0, "bold": false, "italic": false, "underline": null, "strike": null, "color": {"type": "rgb", "rgb": "FF000000", "indexed": null, "theme": null, "tint": 0.0, "auto": null}, "vert_align": null}, "fill": {"fill_type": null, "fg_color": {"type": "rgb", "rgb": "00000000", "indexed": null, "theme": null, "tint": 0.0, "auto": null}, "bg_color": {"type": "rgb", "rgb": "00000000", "indexed": null, "theme": null, "tint": 0.0, "auto": null}}, "alignment": {"horizontal": null, "vertical": null, "text_rotation": 0, "wrap_text": null, "shrink_to_fit": null, "indent": 0.0}, "border": {"left": {"style": "thin", "color": {"type": "auto", "rgb": "Values must be of type <class 'str'>", "indexed": null, "theme": null, "tint": 0.0, "auto": true}}, "right": {"style": "thin", "color": {"type": "auto", "rgb": "Values must be of type <class 'str'>", "indexed": null, "theme": null, "tint": 0.0, "auto": true}}, "top": {"style": "thin", "color": {"type": "auto", "rgb": "Values must be of type <class 'str'>", "indexed": null, "theme": null, "tint": 0.0, "auto": true}}, "bottom": {"style": "thin", "color": {"type": "auto", "rgb": "Values must be of type <class 'str'>", "indexed": null, "theme": null, "tint": 0.0, "auto": true}}, "diagonal": {"style": null, "color": null}, "diagonal_down": false, "diagonal_up": false, "outline": true, "vertical": null, "horizontal": null}, "protection": {"locked": true, "hidden": false}}
A14: Revenue Model | B14: D2 | C14: 2 | D14: 4 | E14: Calculation | F14: ='DuPoint Analysis'!G9-916 | G14: 13413.58 | H14: {"type": "float", "value": 13413.58} | I14: _-* #,##0_-;\-* #,##0_-;_-* "-"??_-;_-@_- | J14: FALSE | K14: FALSE | L14: 11 | M14: FF000000 | N14: 00000000 | R14: TRUE | V14: ='DuPoint Analysis'!R[7]C[3]-916 | W14: {"number_format": "_-* #,##0_-;\\-* #,##0_-;_-* \"-\"??_-;_-@_-", "font": {"name": "Calibri", "size": 11.0, "bold": false, "italic": false, "underline": null, "strike": null, "color": {"type": "rgb", "rgb": "FF000000", "indexed": null, "theme": null, "tint": 0.0, "auto": null}, "vert_align": null}, "fill": {"fill_type": null, "fg_color": {"type": "rgb", "rgb": "00000000", "indexed": null, "theme": null, "tint": 0.0, "auto": null}, "bg_color": {"type": "rgb", "rgb": "00000000", "indexed": null, "theme": null, "tint": 0.0, "auto": null}}, "alignment": {"horizontal": null, "vertical": null, "text_rotation": 0, "wrap_text": null, "shrink_to_fit": null, "indent": 0.0}, "border": {"left": {"style": "thin", "color": {"type": "auto", "rgb": "Values must be of type <class 'str'>", "indexed": null, "theme": null, "tint": 0.0, "auto": true}}, "right": {"style": "thin", "color": {"type": "auto", "rgb": "Values must be of type <class 'str'>", "indexed": null, "theme": null, "tint": 0.0, "auto": true}}, "top": {"style": "thin", "color": {"type": "auto", "rgb": "Values must be of type <class 'str'>", "indexed": null, "theme": null, "tint": 0.0, "auto": true}}, "bottom": {"style": "thin", "color": {"type": "auto", "rgb": "Values must be of type <class 'str'>", "indexed": null, "theme": null, "tint": 0.0, "auto": true}}, "diagonal": {"style": null, "color": null}, "diagonal_down": false, "diagonal_up": false, "outline": true, "vertical": null, "horizontal": null}, "protection": {"locked": true, "hidden": false}}
A15: Revenue Model | B15: E2 | C15: 2 | D15: 5 | E15: Calculation | F15: =E4*E11 | G15: 14440.823 | H15: {"type": "float", "value": 14440.822518987343} | I15: _-* #,##0_-;\-* #,##0_-;_-* "-"??_-;_-@_- | J15: FALSE | K15: FALSE | L15: 11 | M15: FF000000 | N15: 00000000 | R15: TRUE | S15: G000001 | T15: Horizontal | U15: 5 | V15: =R[2]C[0]*R[9]C[0] | W15: {"number_format": "_-* #,##0_-;\\-* #,##0_-;_-* \"-\"??_-;_-@_-", "font": {"name": "Calibri", "size": 11.0, "bold": false, "italic": false, "underline": null, "strike": null, "color": {"type": "rgb", "rgb": "FF000000", "indexed": null, "theme": null, "tint": 0.0, "auto": null}, "vert_align": null}, "fill": {"fill_type": null, "fg_color": {"type": "rgb", "rgb": "00000000", "indexed": null, "theme": null, "tint": 0.0, "auto": null}, "bg_color": {"type": "rgb", "rgb": "00000000", "indexed": null, "theme": null, "tint": 0.0, "auto": null}}, "alignment": {"horizontal": null, "vertical": null, "text_rotation": 0, "wrap_text": null, "shrink_to_fit": null, "indent": 0.0}, "border": {"left": {"style": "thin", "color": {"type": "auto", "rgb": "Values must be of type <class 'str'>", "indexed": null, "theme": null, "tint": 0.0, "auto": true}}, "right": {"style": "thin", "color": {"type": "auto", "rgb": "Values must be of type <class 'str'>", "indexed": null, "theme": null, "tint": 0.0, "auto": true}}, "top": {"style": "thin", "color": {"type": "auto", "rgb": "Values must be of type <class 'str'>", "indexed": null, "theme": null, "tint": 0.0, "auto": true}}, "bottom": {"style": "thin", "color": {"type": "auto", "rgb": "Values must be of type <class 'str'>", "indexed": null, "theme": null, "tint": 0.0, "auto": true}}, "diagonal": {"style": null, "color": null}, "diagonal_down": false, "diagonal_up": false, "outline": true, "vertical": null, "horizontal": null}, "protection": {"locked": true, "hidden": false}}
A16: Revenue Model | B16: F2 | C16: 2 | D16: 6 | E16: Calculation | F16: =F4*F11 | G16: 15537.255 | H16: {"type": "float", "value": 15537.255339873422} | I16: _-* #,##0_-;\-* #,##0_-;_-* "-"??_-;_-@_- | J16: FALSE | K16: FALSE | L16: 11 | M16: FF000000 | N16: 00000000 | R16: TRUE | S16: G000001 | T16: Horizontal | U16: 5 | V16: =R[2]C[0]*R[9]C[0] | W16: {"number_format": "_-* #,##0_-;\\-* #,##0_-;_-* \"-\"??_-;_-@_-", "font": {"name": "Calibri", "size": 11.0, "bold": false, "italic": false, "underline": null, "strike": null, "color": {"type": "rgb", "rgb": "FF000000", "indexed": null, "theme": null, "tint": 0.0, "auto": null}, "vert_align": null}, "fill": {"fill_type": null, "fg_color": {"type": "rgb", "rgb": "00000000", "indexed": null, "theme": null, "tint": 0.0, "auto": null}, "bg_color": {"type": "rgb", "rgb": "00000000", "indexed": null, "theme": null, "tint": 0.0, "auto": null}}, "alignment": {"horizontal": null, "vertical": null, "text_rotation": 0, "wrap_text": null, "shrink_to_fit": null, "indent": 0.0}, "border": {"left": {"style": "thin", "color": {"type": "auto", "rgb": "Values must be of type <class 'str'>", "indexed": null, "theme": null, "tint": 0.0, "auto": true}}, "right": {"style": "thin", "color": {"type": "auto", "rgb": "Values must be of type <class 'str'>", "indexed": null, "theme": null, "tint": 0.0, "auto": true}}, "top": {"style": "thin", "color": {"type": "auto", "rgb": "Values must be of type <class 'str'>", "indexed": null, "theme": null, "tint": 0.0, "auto": true}}, "bottom": {"style": "thin", "color": {"type": "auto", "rgb": "Values must be of type <class 'str'>", "indexed": null, "theme": null, "tint": 0.0, "auto": true}}, "diagonal": {"style": null, "color": null}, "diagonal_down": false, "diagonal_up": false, "outline": true, "vertical": null, "horizontal": null}, "protection": {"locked": true, "hidden": false}}
A17: Revenue Model | B17: G2 | C17: 2 | D17: 7 | E17: Calculation | F17: =G4*G11 | G17: 16707.229 | H17: {"type": "float", "value": 16707.229386550636} | I17: _-* #,##0_-;\-* #,##0_-;_-* "-"??_-;_-@_- | J17: FALSE | K17: FALSE | L17: 11 | M17: FF000000 | N17: 00000000 | R17: TRUE | S17: G000001 | T17: Horizontal | U17: 5 | V17: =R[2]C[0]*R[9]C[0] | W17: {"number_format": "_-* #,##0_-;\\-* #,##0_-;_-* \"-\"??_-;_-@_-", "font": {"name": "Calibri", "size": 11.0, "bold": false, "italic": false, "underline": null, "strike": null, "color": {"type": "rgb", "rgb": "FF000000", "indexed": null, "theme": null, "tint": 0.0, "auto": null}, "vert_align": null}, "fill": {"fill_type": null, "fg_color": {"type": "rgb", "rgb": "00000000", "indexed": null, "theme": null, "tint": 0.0, "auto": null}, "bg_color": {"type": "rgb", "rgb": "00000000", "indexed": null, "theme": null, "tint": 0.0, "auto": null}}, "alignment": {"horizontal": null, "vertical": null, "text_rotation": 0, "wrap_text": null, "shrink_to_fit": null, "indent": 0.0}, "border": {"left": {"style": "thin", "color": {"type": "auto", "rgb": "Values must be of type <class 'str'>", "indexed": null, "theme": null, "tint": 0.0, "auto": true}}, "right": {"style": "thin", "color": {"type": "auto", "rgb": "Values must be of type <class 'str'>", "indexed": null, "theme": null, "tint": 0.0, "auto": true}}, "top": {"style": "thin", "color": {"type": "auto", "rgb": "Values must be of type <class 'str'>", "indexed": null, "theme": null, "tint": 0.0, "auto": true}}, "bottom": {"style": "thin", "color": {"type": "auto", "rgb": "Values must be of type <class 'str'>", "indexed": null, "theme": null, "tint": 0.0, "auto": true}}, "diagonal": {"style": null, "color": null}, "diagonal_down": false, "diagonal_up": false, "outline": true, "vertical": null, "horizontal": null}, "protection": {"locked": true, "hidden": false}}
A18: Revenue Model | B18: H2 | C18: 2 | D18: 8 | E18: Calculation | F18: =H4*H11 | G18: 17955.358 | H18: {"type": "float", "value": 17955.35769954589} | I18: _-* #,##0_-;\-* #,##0_-;_-* "-"??_-;_-@_- | J18: FALSE | K18: FALSE | L18: 11 | M18: FF000000 | N18: 00000000 | R18: TRUE | S18: G000001 | T18: Horizontal | U18: 5 | V18: =R[2]C[0]*R[9]C[0] | W18: {"number_format": "_-* #,##0_-;\\-* #,##0_-;_-* \"-\"??_-;_-@_-", "font": {"name": "Calibri", "size": 11.0, "bold": false, "italic": false, "underline": null, "strike": null, "color": {"type": "rgb", "rgb": "FF000000", "indexed": null, "theme": null, "tint": 0.0, "auto": null}, "vert_align": null}, "fill": {"fill_type": null, "fg_color": {"type": "rgb", "rgb": "00000000", "indexed": null, "theme": null, "tint": 0.0, "auto": null}, "bg_color": {"type": "rgb", "rgb": "00000000", "indexed": null, "theme": null, "tint": 0.0, "auto": null}}, "alignment": {"horizontal": null, "vertical": null, "text_rotation": 0, "wrap_text": null, "shrink_to_fit": null, "indent": 0.0}, "border": {"left": {"style": "thin", "color": {"type": "auto", "rgb": "Values must be of type <class 'str'>", "indexed": null, "theme": null, "tint": 0.0, "auto": true}}, "right": {"style": "thin", "color": {"type": "auto", "rgb": "Values must be of type <class 'str'>", "indexed": null, "theme": null, "tint": 0.0, "auto": true}}, "top": {"style": "thin", "color": {"type": "auto", "rgb": "Values must be of type <class 'str'>", "indexed": null, "theme": null, "tint": 0.0, "auto": true}}, "bottom": {"style": "thin", "color": {"type": "auto", "rgb": "Values must be of type <class 'str'>", "indexed": null, "theme": null, "tint": 0.0, "auto": true}}, "diagonal": {"style": null, "color": null}, "diagonal_down": false, "diagonal_up": false, "outline": true, "vertical": null, "horizontal": null}, "protection": {"locked": true, "hidden": false}}
A19: Revenue Model | B19: I2 | C19: 2 | D19: 9 | E19: Calculation | F19: =I4*I11 | G19: 19286.531 | H19: {"type": "float", "value": 19286.5307703743} | I19: _-* #,##0_-;\-* #,##0_-;_-* "-"??_-;_-@_- | J19: FALSE | K19: FALSE | L19: 11 | M19: FF000000 | N19: 00000000 | R19: TRUE | S19: G000001 | T19: Horizontal | U19: 5 | V19: =R[2]C[0]*R[9]C[0] | W19: {"number_format": "_-* #,##0_-;\\-* #,##0_-;_-* \"-\"??_-;_-@_-", "font": {"name": "Calibri", "size": 11.0, "bold": false, "italic": false, "underline": null, "strike": null, "color": {"type": "rgb", "rgb": "FF000000", "indexed": null, "theme": null, "tint": 0.0, "auto": null}, "vert_align": null}, "fill": {"fill_type": null, "fg_color": {"type": "rgb", "rgb": "00000000", "indexed": null, "theme": null, "tint": 0.0, "auto": null}, "bg_color": {"type": "rgb", "rgb": "00000000", "indexed": null, "theme": null, "tint": 0.0, "auto": null}}, "alignment": {"horizontal": null, "vertical": null, "text_rotation": 0, "wrap_text": null, "shrink_to_fit": null, "indent": 0.0}, "border": {"left": {"style": "thin", "color": {"type": "auto", "rgb": "Values must be of type <class 'str'>", "indexed": null, "theme": null, "tint": 0.0, "auto": true}}, "right": {"style": "thin", "color": {"type": "auto", "rgb": "Values must be of type <class 'str'>", "indexed": null, "theme": null, "tint": 0.0, "auto": true}}, "top": {"style": "thin", "color": {"type": "auto", "rgb": "Values must be of type <class 'str'>", "indexed": null, "theme": null, "tint": 0.0, "auto": true}}, "bottom": {"style": "thin", "color": {"type": "auto", "rgb": "Values must be of type <class 'str'>", "indexed": null, "theme": null, "tint": 0.0, "auto": true}}, "diagonal": {"style": null, "color": null}, "diagonal_down": false, "diagonal_up": false, "outline": true, "vertical": null, "horizontal": null}, "protection": {"locked": true, "hidden": false}}
A20: Revenue Model | B20: A3 | C20: 3 | D20: 1 | E20: Input | H20: {"type": "null", "value": null} | I20: General | J20: FALSE | K20: FALSE | L20: 11 | M20: FF000000 | N20: 00000000 | R20: FALSE | W20: {"number_format": "General", "font": {"name": "Calibri", "size": 11.0, "bold": false, "italic": false, "underline": null, "strike": null, "color": {"type": "rgb", "rgb": "FF000000", "indexed": null, "theme": null, "tint": 0.0, "auto": null}, "vert_align": null}, "fill": {"fill_type": null, "fg_color": {"type": "rgb", "rgb": "00000000", "indexed": null, "theme": null, "tint": 0.0, "auto": null}, "bg_color": {"type": "rgb", "rgb": "00000000", "indexed": null, "theme": null, "tint": 0.0, "auto": null}}, "alignment": {"horizontal": null, "vertical": null, "text_rotation": 0, "wrap_text": null, "shrink_to_fit": null, "indent": 0.0}, "border": {"left": {"style": "thin", "color": {"type": "auto", "rgb": "Values must be of type <class 'str'>", "indexed": null, "theme": null, "tint": 0.0, "auto": true}}, "right": {"style": "thin", "color": {"type": "auto", "rgb": "Values must be of type <class 'str'>", "indexed": null, "theme": null, "tint": 0.0, "auto": true}}, "top": {"style": "thin", "color": {"type": "auto", "rgb": "Values must be of type <class 'str'>", "indexed": null, "theme": null, "tint": 0.0, "auto": true}}, "bottom": {"style": "thin", "color": {"type": "auto", "rgb": "Values must be of type <class 'str'>", "indexed": null, "theme": null, "tint": 0.0, "auto": true}}, "diagonal": {"style": null, "color": null}, "diagonal_down": false, "diagonal_up": false, "outline": true, "vertical": null, "horizontal": null}, "protection": {"locked": true, "hidden": false}}
A21: Revenue Model | B21: B3 | C21: 3 | D21: 2 | E21: Input | H21: {"type": "null", "value": null} | I21: _-* #,##0_-;\-* #,##0_-;_-* "-"??_-;_-@_- | J21: FALSE | K21: FALSE | L21: 11 | M21: FF000000 | N21: 00000000 | R21: FALSE | W21: {"number_format": "_-* #,##0_-;\\-* #,##0_-;_-* \"-\"??_-;_-@_-", "font": {"name": "Calibri", "size": 11.0, "bold": false, "italic": false, "underline": null, "strike": null, "color": {"type": "rgb", "rgb": "FF000000", "indexed": null, "theme": null, "tint": 0.0, "auto": null}, "vert_align": null}, "fill": {"fill_type": null, "fg_color": {"type": "rgb", "rgb": "00000000", "indexed": null, "theme": null, "tint": 0.0, "auto": null}, "bg_color": {"type": "rgb", "rgb": "00000000", "indexed": null, "theme": null, "tint": 0.0, "auto": null}}, "alignment": {"horizontal": null, "vertical": null, "text_rotation": 0, "wrap_text": null, "shrink_to_fit": null, "indent": 0.0}, "border": {"left": {"style": "thin", "color": {"type": "auto", "rgb": "Values must be of type <class 'str'>", "indexed": null, "theme": null, "tint": 0.0, "auto": true}}, "right": {"style": "thin", "color": {"type": "auto", "rgb": "Values must be of type <class 'str'>", "indexed": null, "theme": null, "tint": 0.0, "auto": true}}, "top": {"style": "thin", "color": {"type": "auto", "rgb": "Values must be of type <class 'str'>", "indexed": null, "theme": null, "tint": 0.0, "auto": true}}, "bottom": {"style": "thin", "color": {"type": "auto", "rgb": "Values must be of type <class 'str'>", "indexed": null, "theme": null, "tint": 0.0, "auto": true}}, "diagonal": {"style": null, "color": null}, "diagonal_down": false, "diagonal_up": false, "outline": true, "vertical": null, "horizontal": null}, "protection": {"locked": true, "hidden": false}}
A22: Revenue Model | B22: C3 | C22: 3 | D22: 3 | E22: Input | H22: {"type": "null", "value": null} | I22: _-* #,##0_-;\-* #,##0_-;_-* "-"??_-;_-@_- | J22: FALSE | K22: FALSE | L22: 11 | M22: FF000000 | N22: 00000000 | R22: FALSE | W22: {"number_format": "_-* #,##0_-;\\-* #,##0_-;_-* \"-\"??_-;_-@_-", "font": {"name": "Calibri", "size": 11.0, "bold": false, "italic": false, "underline": null, "strike": null, "color": {"type": "rgb", "rgb": "FF000000", "indexed": null, "theme": null, "tint": 0.0, "auto": null}, "vert_align": null}, "fill": {"fill_type": null, "fg_color": {"type": "rgb", "rgb": "00000000", "indexed": null, "theme": null, "tint": 0.0, "auto": null}, "bg_color": {"type": "rgb", "rgb": "00000000", "indexed": null, "theme": null, "tint": 0.0, "auto": null}}, "alignment": {"horizontal": null, "vertical": null, "text_rotation": 0, "wrap_text": null, "shrink_to_fit": null, "indent": 0.0}, "border": {"left": {"style": "thin", "color": {"type": "auto", "rgb": "Values must be of type <class 'str'>", "indexed": null, "theme": null, "tint": 0.0, "auto": true}}, "right": {"style": "thin", "color": {"type": "auto", "rgb": "Values must be of type <class 'str'>", "indexed": null, "theme": null, "tint": 0.0, "auto": true}}, "top": {"style": "thin", "color": {"type": "auto", "rgb": "Values must be of type <class 'str'>", "indexed": null, "theme": null, "tint": 0.0, "auto": true}}, "bottom": {"style": "thin", "color": {"type": "auto", "rgb": "Values must be of type <class 'str'>", "indexed": null, "theme": null, "tint": 0.0, "auto": true}}, "diagonal": {"style": null, "color": null}, "diagonal_down": false, "diagonal_up": false, "outline": true, "vertical": null, "horizontal": null}, "protection": {"locked": true, "hidden": false}}
A23: Revenue Model | B23: D3 | C23: 3 | D23: 4 | E23: Input | H23: {"type": "null", "value": null} | I23: _-* #,##0_-;\-* #,##0_-;_-* "-"??_-;_-@_- | J23: FALSE | K23: FALSE | L23: 11 | M23: FF000000 | N23: 00000000 | R23: FALSE | W23: {"number_format": "_-* #,##0_-;\\-* #,##0_-;_-* \"-\"??_-;_-@_-", "font": {"name": "Calibri", "size": 11.0, "bold": false, "italic": false, "underline": null, "strike": null, "color": {"type": "rgb", "rgb": "FF000000", "indexed": null, "theme": null, "tint": 0.0, "auto": null}, "vert_align": null}, "fill": {"fill_type": null, "fg_color": {"type": "rgb", "rgb": "00000000", "indexed": null, "theme": null, "tint": 0.0, "auto": null}, "bg_color": {"type": "rgb", "rgb": "00000000", "indexed": null, "theme": null, "tint": 0.0, "auto": null}}, "alignment": {"horizontal": null, "vertical": null, "text_rotation": 0, "wrap_text": null, "shrink_to_fit": null, "indent": 0.0}, "border": {"left": {"style": "thin", "color": {"type": "auto", "rgb": "Values must be of type <class 'str'>", "indexed": null, "theme": null, "tint": 0.0, "auto": true}}, "right": {"style": "thin", "color": {"type": "auto", "rgb": "Values must be of type <class 'str'>", "indexed": null, "theme": null, "tint": 0.0, "auto": true}}, "top": {"style": "thin", "color": {"type": "auto", "rgb": "Values must be of type <class 'str'>", "indexed": null, "theme": null, "tint": 0.0, "auto": true}}, "bottom": {"style": "thin", "color": {"type": "auto", "rgb": "Values must be of type <class 'str'>", "indexed": null, "theme": null, "tint": 0.0, "auto": true}}, "diagonal": {"style": null, "color": null}, "diagonal_down": false, "diagonal_up": false, "outline": true, "vertical": null, "horizontal": null}, "protection": {"locked": true, "hidden": false}}
A24: Revenue Model | B24: E3 | C24: 3 | D24: 5 | E24: Input | H24: {"type": "null", "value": null} | I24: _-* #,##0_-;\-* #,##0_-;_-* "-"??_-;_-@_- | J24: FALSE | K24: FALSE | L24: 11 | M24: FF000000 | N24: 00000000 | R24: FALSE | W24: {"number_format": "_-* #,##0_-;\\-* #,##0_-;_-* \"-\"??_-;_-@_-", "font": {"name": "Calibri", "size": 11.0, "bold": false, "italic": false, "underline": null, "strike": null, "color": {"type": "rgb", "rgb": "FF000000", "indexed": null, "theme": null, "tint": 0.0, "auto": null}, "vert_align": null}, "fill": {"fill_type": null, "fg_color": {"type": "rgb", "rgb": "00000000", "indexed": null, "theme": null, "tint": 0.0, "auto": null}, "bg_color": {"type": "rgb", "rgb": "00000000", "indexed": null, "theme": null, "tint": 0.0, "auto": null}}, "alignment": {"horizontal": null, "vertical": null, "text_rotation": 0, "wrap_text": null, "shrink_to_fit": null, "indent": 0.0}, "border": {"left": {"style": "thin", "color": {"type": "auto", "rgb": "Values must be of type <class 'str'>", "indexed": null, "theme": null, "tint": 0.0, "auto": true}}, "right": {"style": "thin", "color": {"type": "auto", "rgb": "Values must be of type <class 'str'>", "indexed": null, "theme": null, "tint": 0.0, "auto": true}}, "top": {"style": "thin", "color": {"type": "auto", "rgb": "Values must be of type <class 'str'>", "indexed": null, "theme": null, "tint": 0.0, "auto": true}}, "bottom": {"style": "thin", "color": {"type": "auto", "rgb": "Values must be of type <class 'str'>", "indexed": null, "theme": null, "tint": 0.0, "auto": true}}, "diagonal": {"style": null, "color": null}, "diagonal_down": false, "diagonal_up": false, "outline": true, "vertical": null, "horizontal": null}, "protection": {"locked": true, "hidden": false}}
A25: Revenue Model | B25: F3 | C25: 3 | D25: 6 | E25: Input | H25: {"type": "null", "value": null} | I25: _-* #,##0_-;\-* #,##0_-;_-* "-"??_-;_-@_- | J25: FALSE | K25: FALSE | L25: 11 | M25: FF000000 | N25: 00000000 | R25: FALSE | W25: {"number_format": "_-* #,##0_-;\\-* #,##0_-;_-* \"-\"??_-;_-@_-", "font": {"name": "Calibri", "size": 11.0, "bold": false, "italic": false, "underline": null, "strike": null, "color": {"type": "rgb", "rgb": "FF000000", "indexed": null, "theme": null, "tint": 0.0, "auto": null}, "vert_align": null}, "fill": {"fill_type": null, "fg_color": {"type": "rgb", "rgb": "00000000", "indexed": null, "theme": null, "tint": 0.0, "auto": null}, "bg_color": {"type": "rgb", "rgb": "00000000", "indexed": null, "theme": null, "tint": 0.0, "auto": null}}, "alignment": {"horizontal": null, "vertical": null, "text_rotation": 0, "wrap_text": null, "shrink_to_fit": null, "indent": 0.0}, "border": {"left": {"style": "thin", "color": {"type": "auto", "rgb": "Values must be of type <class 'str'>", "indexed": null, "theme": null, "tint": 0.0, "auto": true}}, "right": {"style": "thin", "color": {"type": "auto", "rgb": "Values must be of type <class 'str'>", "indexed": null, "theme": null, "tint": 0.0, "auto": true}}, "top": {"style": "thin", "color": {"type": "auto", "rgb": "Values must be of type <class 'str'>", "indexed": null, "theme": null, "tint": 0.0, "auto": true}}, "bottom": {"style": "thin", "color": {"type": "auto", "rgb": "Values must be of type <class 'str'>", "indexed": null, "theme": null, "tint": 0.0, "auto": true}}, "diagonal": {"style": null, "color": null}, "diagonal_down": false, "diagonal_up": false, "outline": true, "vertical": null, "horizontal": null}, "protection": {"locked": true, "hidden": false}}
A26: Revenue Model | B26: G3 | C26: 3 | D26: 7 | E26: Input | H26: {"type": "null", "value": null} | I26: _-* #,##0_-;\-* #,##0_-;_-* "-"??_-;_-@_- | J26: FALSE | K26: FALSE | L26: 11 | M26: FF000000 | N26: 00000000 | R26: FALSE | W26: {"number_format": "_-* #,##0_-;\\-* #,##0_-;_-* \"-\"??_-;_-@_-", "font": {"name": "Calibri", "size": 11.0, "bold": false, "italic": false, "underline": null, "strike": null, "color": {"type": "rgb", "rgb": "FF000000", "indexed": null, "theme": null, "tint": 0.0, "auto": null}, "vert_align": null}, "fill": {"fill_type": null, "fg_color": {"type": "rgb", "rgb": "00000000", "indexed": null, "theme": null, "tint": 0.0, "auto": null}, "bg_color": {"type": "rgb", "rgb": "00000000", "indexed": null, "theme": null, "tint": 0.0, "auto": null}}, "alignment": {"horizontal": null, "vertical": null, "text_rotation": 0, "wrap_text": null, "shrink_to_fit": null, "indent": 0.0}, "border": {"left": {"style": "thin", "color": {"type": "auto", "rgb": "Values must be of type <class 'str'>", "indexed": null, "theme": null, "tint": 0.0, "auto": true}}, "right": {"style": "thin", "color": {"type": "auto", "rgb": "Values must be of type <class 'str'>", "indexed": null, "theme": null, "tint": 0.0, "auto": true}}, "top": {"style": "thin", "color": {"type": "auto", "rgb": "Values must be of type <class 'str'>", "indexed": null, "theme": null, "tint": 0.0, "auto": true}}, "bottom": {"style": "thin", "color": {"type": "auto", "rgb": "Values must be of type <class 'str'>", "indexed": null, "theme": null, "tint": 0.0, "auto": true}}, "diagonal": {"style": null, "color": null}, "diagonal_down": false, "diagonal_up": false, "outline": true, "vertical": null, "horizontal": null}, "protection": {"locked": true, "hidden": false}}
A27: Revenue Model | B27: H3 | C27: 3 | D27: 8 | E27: Input | H27: {"type": "null", "value": null} | I27: _-* #,##0_-;\-* #,##0_-;_-* "-"??_-;_-@_- | J27: FALSE | K27: FALSE | L27: 11 | M27: FF000000 | N27: 00000000 | R27: FALSE | W27: {"number_format": "_-* #,##0_-;\\-* #,##0_-;_-* \"-\"??_-;_-@_-", "font": {"name": "Calibri", "size": 11.0, "bold": false, "italic": false, "underline": null, "strike": null, "color": {"type": "rgb", "rgb": "FF000000", "indexed": null, "theme": null, "tint": 0.0, "auto": null}, "vert_align": null}, "fill": {"fill_type": null, "fg_color": {"type": "rgb", "rgb": "00000000", "indexed": null, "theme": null, "tint": 0.0, "auto": null}, "bg_color": {"type": "rgb", "rgb": "00000000", "indexed": null, "theme": null, "tint": 0.0, "auto": null}}, "alignment": {"horizontal": null, "vertical": null, "text_rotation": 0, "wrap_text": null, "shrink_to_fit": null, "indent": 0.0}, "border": {"left": {"style": "thin", "color": {"type": "auto", "rgb": "Values must be of type <class 'str'>", "indexed": null, "theme": null, "tint": 0.0, "auto": true}}, "right": {"style": "thin", "color": {"type": "auto", "rgb": "Values must be of type <class 'str'>", "indexed": null, "theme": null, "tint": 0.0, "auto": true}}, "top": {"style": "thin", "color": {"type": "auto", "rgb": "Values must be of type <class 'str'>", "indexed": null, "theme": null, "tint": 0.0, "auto": true}}, "bottom": {"style": "thin", "color": {"type": "auto", "rgb": "Values must be of type <class 'str'>", "indexed": null, "theme": null, "tint": 0.0, "auto": true}}, "diagonal": {"style": null, "color": null}, "diagonal_down": false, "diagonal_up": false, "outline": true, "vertical": null, "horizontal": null}, "protection": {"locked": true, "hidden": false}}
A28: Revenue Model | B28: I3 | C28: 3 | D28: 9 | E28: Input | H28: {"type": "null", "value": null} | I28: _-* #,##0_-;\-* #,##0_-;_-* "-"??_-;_-@_- | J28: FALSE | K28: FALSE | L28: 11 | M28: FF000000 | N28: 00000000 | R28: FALSE | W28: {"number_format": "_-* #,##0_-;\\-* #,##0_-;_-* \"-\"??_-;_-@_-", "font": {"name": "Calibri", "size": 11.0, "bold": false, "italic": false, "underline": null, "strike": null, "color": {"type": "rgb", "rgb": "FF000000", "indexed": null, "theme": null, "tint": 0.0, "auto": null}, "vert_align": null}, "fill": {"fill_type": null, "fg_color": {"type": "rgb", "rgb": "00000000", "indexed": null, "theme": null, "tint": 0.0, "auto": null}, "bg_color": {"type": "rgb", "rgb": "00000000", "indexed": null, "theme": null, "tint": 0.0, "auto": null}}, "alignment": {"horizontal": null, "vertical": null, "text_rotation": 0, "wrap_text": null, "shrink_to_fit": null, "indent": 0.0}, "border": {"left": {"style": "thin", "color": {"type": "auto", "rgb": "Values must be of type <class 'str'>", "indexed": null, "theme": null, "tint": 0.0, "auto": true}}, "right": {"style": "thin", "color": {"type": "auto", "rgb": "Values must be of type <class 'str'>", "indexed": null, "theme": null, "tint": 0.0, "auto": true}}, "top": {"style": "thin", "color": {"type": "auto", "rgb": "Values must be of type <class 'str'>", "indexed": null, "theme": null, "tint": 0.0, "auto": true}}, "bottom": {"style": "thin", "color": {"type": "auto", "rgb": "Values must be of type <class 'str'>", "indexed": null, "theme": null, "tint": 0.0, "auto": true}}, "diagonal": {"style": null, "color": null}, "diagonal_down": false, "diagonal_up": false, "outline": true, "vertical": null, "horizontal": null}, "protection": {"locked": true, "hidden": false}}
A29: Revenue Model | B29: A4 | C29: 4 | D29: 1 | E29: Input | G29: Cement Sales - Volume Million Tonnes | H29: {"type": "str", "value": "Cement Sales - Volume Million Tonnes"} | I29: General | J29: FALSE | K29: FALSE | L29: 11 | M29: FF000000 | N29: 00000000 | R29: TRUE | W29: {"number_format": "General", "font": {"name": "Calibri", "size": 11.0, "bold": false, "italic": false, "underline": null, "strike": null, "color": {"type": "rgb", "rgb": "FF000000", "indexed": null, "theme": null, "tint": 0.0, "auto": null}, "vert_align": null}, "fill": {"fill_type": null, "fg_color": {"type": "rgb", "rgb": "00000000", "indexed": null, "theme": null, "tint": 0.0, "auto": null}, "bg_color": {"type": "rgb", "rgb": "00000000", "indexed": null, "theme": null, "tint": 0.0, "auto": null}}, "alignment": {"horizontal": null, "vertical": null, "text_rotation": 0, "wrap_text": null, "shrink_to_fit": null, "indent": 0.0}, "border": {"left": {"style": "thin", "color": {"type": "auto", "rgb": "Values must be of type <class 'str'>", "indexed": null, "theme": null, "tint": 0.0, "auto": true}}, "right": {"style": "thin", "color": {"type": "auto", "rgb": "Values must be of type <class 'str'>", "indexed": null, "theme": null, "tint": 0.0, "auto": true}}, "top": {"style": "thin", "color": {"type": "auto", "rgb": "Values must be of type <class 'str'>", "indexed": null, "theme": null, "tint": 0.0, "auto": true}}, "bottom": {"style": "thin", "color": {"type": "auto", "rgb": "Values must be of type <class 'str'>", "indexed": null, "theme": null, "tint": 0.0, "auto": true}}, "diagonal": {"style": null, "color": null}, "diagonal_down": false, "diagonal_up": false, "outline": true, "vertical": null, "horizontal": null}, "protection": {"locked": true, "hidden": false}}
A30: Revenue Model | B30: B4 | C30: 4 | D30: 2 | E30: Input | G30: 23.62 | H30: {"type": "float", "value": 23.62} | I30: General | J30: FALSE | K30: FALSE | L30: 11 | M30: FF000000 | N30: 00000000 | R30: TRUE | W30: {"number_format": "General", "font": {"name": "Calibri", "size": 11.0, "bold": false, "italic": false, "underline": null, "strike": null, "color": {"type": "rgb", "rgb": "FF000000", "indexed": null, "theme": null, "tint": 0.0, "auto": null}, "vert_align": null}, "fill": {"fill_type": null, "fg_color": {"type": "rgb", "rgb": "00000000", "indexed": null, "theme": null, "tint": 0.0, "auto": null}, "bg_color": {"type": "rgb", "rgb": "00000000", "indexed": null, "theme": null, "tint": 0.0, "auto": null}}, "alignment": {"horizontal": null, "vertical": null, "text_rotation": 0, "wrap_text": null, "shrink_to_fit": null, "indent": 0.0}, "border": {"left": {"style": "thin", "color": {"type": "auto", "rgb": "Values must be of type <class 'str'>", "indexed": null, "theme": null, "tint": 0.0, "auto": true}}, "right": {"style": "thin", "color": {"type": "auto", "rgb": "Values must be of type <class 'str'>", "indexed": null, "theme": null, "tint": 0.0, "auto": true}}, "top": {"style": "thin", "color": {"type": "auto", "rgb": "Values must be of type <class 'str'>", "indexed": null, "theme": null, "tint": 0.0, "auto": true}}, "bottom": {"style": "thin", "color": {"type": "auto", "rgb": "Values must be of type <class 'str'>", "indexed": null, "theme": null, "tint": 0.0, "auto": true}}, "diagonal": {"style": null, "color": null}, "diagonal_down": false, "diagonal_up": false, "outline": true, "vertical": null, "horizontal": null}, "protection": {"locked": true, "hidden": false}}
A31: Revenue Model | B31: C4 | C31: 4 | D31: 3 | E31: Input | G31: 22.99 | H31: {"type": "float", "value": 22.99} | I31: General | J31: FALSE | K31: FALSE | L31: 11 | M31: FF000000 | N31: 00000000 | R31: TRUE | W31: {"number_format": "General", "font": {"name": "Calibri", "size": 11.0, "bold": false, "italic": false, "underline": null, "strike": null, "color": {"type": "rgb", "rgb": "FF000000", "indexed": null, "theme": null, "tint": 0.0, "auto": null}, "vert_align": null}, "fill": {"fill_type": null, "fg_color": {"type": "rgb", "rgb": "00000000", "indexed": null, "theme": null, "tint": 0.0, "auto": null}, "bg_color": {"type": "rgb", "rgb": "00000000", "indexed": null, "theme": null, "tint": 0.0, "auto": null}}, "alignment": {"horizontal": null, "vertical": null, "text_rotation": 0, "wrap_text": null, "shrink_to_fit": null, "indent": 0.0}, "border": {"left": {"style": "thin", "color": {"type": "auto", "rgb": "Values must be of type <class 'str'>", "indexed": null, "theme": null, "tint": 0.0, "auto": true}}, "right": {"style": "thin", "color": {"type": "auto", "rgb": "Values must be of type <class 'str'>", "indexed": null, "theme": null, "tint": 0.0, "auto": true}}, "top": {"style": "thin", "color": {"type": "auto", "rgb": "Values must be of type <class 'str'>", "indexed": null, "theme": null, "tint": 0.0, "auto": true}}, "bottom": {"style": "thin", "color": {"type": "auto", "rgb": "Values must be of type <class 'str'>", "indexed": null, "theme": null, "tint": 0.0, "auto": true}}, "diagonal": {"style": null, "color": null}, "diagonal_down": false, "diagonal_up": false, "outline": true, "vertical": null, "horizontal": null}, "protection": {"locked": true, "hidden": false}}
A32: Revenue Model | B32: D4 | C32: 4 | D32: 4 | E32: Input | G32: 26.21 | H32: {"type": "float", "value": 26.21} | I32: General | J32: FALSE | K32: FALSE | L32: 11 | M32: FF000000 | N32: 00000000 | R32: TRUE | W32: {"number_format": "General", "font": {"name": "Calibri", "size": 11.0, "bold": false, "italic": false, "underline": null, "strike": null, "color": {"type": "rgb", "rgb": "FF000000", "indexed": null, "theme": null, "tint": 0.0, "auto": null}, "vert_align": null}, "fill": {"fill_type": null, "fg_color": {"type": "rgb", "rgb": "00000000", "indexed": null, "theme": null, "tint": 0.0, "auto": null}, "bg_color": {"type": "rgb", "rgb": "00000000", "indexed": null, "theme": null, "tint": 0.0, "auto": null}}, "alignment": {"horizontal": null, "vertical": null, "text_rotation": 0, "wrap_text": null, "shrink_to_fit": null, "indent": 0.0}, "border": {"left": {"style": "thin", "color": {"type": "auto", "rgb": "Values must be of type <class 'str'>", "indexed": null, "theme": null, "tint": 0.0, "auto": true}}, "right": {"style": "thin", "color": {"type": "auto", "rgb": "Values must be of type <class 'str'>", "indexed": null, "theme": null, "tint": 0.0, "auto": true}}, "top": {"style": "thin", "color": {"type": "auto", "rgb": "Values must be of type <class 'str'>", "indexed": null, "theme": null, "tint": 0.0, "auto": true}}, "bottom": {"style": "thin", "color": {"type": "auto", "rgb": "Values must be of type <class 'str'>", "indexed": null, "theme": null, "tint": 0.0, "auto": true}}, "diagonal": {"style": null, "color": null}, "diagonal_down": false, "diagonal_up": false, "outline": true, "vertical": null, "horizontal": null}, "protection": {"locked": true, "hidden": false}}
A33: Revenue Model | B33: E4 | C33: 4 | D33: 5 | E33: Calculation | F33: =E5*E6 | G33: 26.873544 | H33: {"type": "float", "value": 26.87354430379747} | I33: 0.00 | J33: FALSE | K33: FALSE | L33: 11 | M33: FF000000 | N33: 00000000 | R33: TRUE | S33: G000002 | T33: Horizontal | U33: 5 | V33: =R[1]C[0]*R[2]C[0] | W33: {"number_format": "0.00", "font": {"name": "Calibri", "size": 11.0, "bold": false, "italic": false, "underline": null, "strike": null, "color": {"type": "rgb", "rgb": "FF000000", "indexed": null, "theme": null, "tint": 0.0, "auto": null}, "vert_align": null}, "fill": {"fill_type": null, "fg_color": {"type": "rgb", "rgb": "00000000", "indexed": null, "theme": null, "tint": 0.0, "auto": null}, "bg_color": {"type": "rgb", "rgb": "00000000", "indexed": null, "theme": null, "tint": 0.0, "auto": null}}, "alignment": {"horizontal": null, "vertical": null, "text_rotation": 0, "wrap_text": null, "shrink_to_fit": null, "indent": 0.0}, "border": {"left": {"style": "thin", "color": {"type": "auto", "rgb": "Values must be of type <class 'str'>", "indexed": null, "theme": null, "tint": 0.0, "auto": true}}, "right": {"style": "thin", "color": {"type": "auto", "rgb": "Values must be of type <class 'str'>", "indexed": null, "theme": null, "tint": 0.0, "auto": true}}, "top": {"style": "thin", "color": {"type": "auto", "rgb": "Values must be of type <class 'str'>", "indexed": null, "theme": null, "tint": 0.0, "auto": true}}, "bottom": {"style": "thin", "color": {"type": "auto", "rgb": "Values must be of type <class 'str'>", "indexed": null, "theme": null, "tint": 0.0, "auto": true}}, "diagonal": {"style": null, "color": null}, "diagonal_down": false, "diagonal_up": false, "outline": true, "vertical": null, "horizontal": null}, "protection": {"locked": true, "hidden": false}}
A34: Revenue Model | B34: F4 | C34: 4 | D34: 6 | E34: Calculation | F34: =F5*F6 | G34: 27.537089 | H34: {"type": "float", "value": 27.53708860759494} | I34: 0.00 | J34: FALSE | K34: FALSE | L34: 11 | M34: FF000000 | N34: 00000000 | R34: TRUE | S34: G000002 | T34: Horizontal | U34: 5 | V34: =R[1]C[0]*R[2]C[0] | W34: {"number_format": "0.00", "font": {"name": "Calibri", "size": 11.0, "bold": false, "italic": false, "underline": null, "strike": null, "color": {"type": "rgb", "rgb": "FF000000", "indexed": null, "theme": null, "tint": 0.0, "auto": null}, "vert_align": null}, "fill": {"fill_type": null, "fg_color": {"type": "rgb", "rgb": "00000000", "indexed": null, "theme": null, "tint": 0.0, "auto": null}, "bg_color": {"type": "rgb", "rgb": "00000000", "indexed": null, "theme": null, "tint": 0.0, "auto": null}}, "alignment": {"horizontal": null, "vertical": null, "text_rotation": 0, "wrap_text": null, "shrink_to_fit": null, "indent": 0.0}, "border": {"left": {"style": "thin", "color": {"type": "auto", "rgb": "Values must be of type <class 'str'>", "indexed": null, "theme": null, "tint": 0.0, "auto": true}}, "right": {"style": "thin", "color": {"type": "auto", "rgb": "Values must be of type <class 'str'>", "indexed": null, "theme": null, "tint": 0.0, "auto": true}}, "top": {"style": "thin", "color": {"type": "auto", "rgb": "Values must be of type <class 'str'>", "indexed": null, "theme": null, "tint": 0.0, "auto": true}}, "bottom": {"style": "thin", "color": {"type": "auto", "rgb": "Values must be of type <class 'str'>", "indexed": null, "theme": null, "tint": 0.0, "auto": true}}, "diagonal": {"style": null, "color": null}, "diagonal_down": false, "diagonal_up": false, "outline": true, "vertical": null, "horizontal": null}, "protection": {"locked": true, "hidden": false}}
A35: Revenue Model | B35: G4 | C35: 4 | D35: 7 | E35: Calculation | F35: =G5*G6 | G35: 28.200633 | H35: {"type": "float", "value": 28.200632911392407} | I35: 0.00 | J35: FALSE | K35: FALSE | L35: 11 | M35: FF000000 | N35: 00000000 | R35: TRUE | S35: G000002 | T35: Horizontal | U35: 5 | V35: =R[1]C[0]*R[2]C[0] | W35: {"number_format": "0.00", "font": {"name": "Calibri", "size": 11.0, "bold": false, "italic": false, "underline": null, "strike": null, "color": {"type": "rgb", "rgb": "FF000000", "indexed": null, "theme": null, "tint": 0.0, "auto": null}, "vert_align": null}, "fill": {"fill_type": null, "fg_color": {"type": "rgb", "rgb": "00000000", "indexed": null, "theme": null, "tint": 0.0, "auto": null}, "bg_color": {"type": "rgb", "rgb": "00000000", "indexed": null, "theme": null, "tint": 0.0, "auto": null}}, "alignment": {"horizontal": null, "vertical": null, "text_rotation": 0, "wrap_text": null, "shrink_to_fit": null, "indent": 0.0}, "border": {"left": {"style": "thin", "color": {"type": "auto", "rgb": "Values must be of type <class 'str'>", "indexed": null, "theme": null, "tint": 0.0, "auto": true}}, "right": {"style": "thin", "color": {"type": "auto", "rgb": "Values must be of type <class 'str'>", "indexed": null, "theme": null, "tint": 0.0, "auto": true}}, "top": {"style": "thin", "color": {"type": "auto", "rgb": "Values must be of type <class 'str'>", "indexed": null, "theme": null, "tint": 0.0, "auto": true}}, "bottom": {"style": "thin", "color": {"type": "auto", "rgb": "Values must be of type <class 'str'>", "indexed": null, "theme": null, "tint": 0.0, "auto": true}}, "diagonal": {"style": null, "color": null}, "diagonal_down": false, "diagonal_up": false, "outline": true, "vertical": null, "horizontal": null}, "protection": {"locked": true, "hidden": false}}
A36: Revenue Model | B36: H4 | C36: 4 | D36: 8 | E36: Calculation | F36: =H5*H6 | G36: 28.864177 | H36: {"type": "float", "value": 28.864177215189873} | I36: 0.00 | J36: FALSE | K36: FALSE | L36: 11 | M36: FF000000 | N36: 00000000 | R36: TRUE | S36: G000002 | T36: Horizontal | U36: 5 | V36: =R[1]C[0]*R[2]C[0] | W36: {"number_format": "0.00", "font": {"name": "Calibri", "size": 11.0, "bold": false, "italic": false, "underline": null, "strike": null, "color": {"type": "rgb", "rgb": "FF000000", "indexed": null, "theme": null, "tint": 0.0, "auto": null}, "vert_align": null}, "fill": {"fill_type": null, "fg_color": {"type": "rgb", "rgb": "00000000", "indexed": null, "theme": null, "tint": 0.0, "auto": null}, "bg_color": {"type": "rgb", "rgb": "00000000", "indexed": null, "theme": null, "tint": 0.0, "auto": null}}, "alignment": {"horizontal": null, "vertical": null, "text_rotation": 0, "wrap_text": null, "shrink_to_fit": null, "indent": 0.0}, "border": {"left": {"style": "thin", "color": {"type": "auto", "rgb": "Values must be of type <class 'str'>", "indexed": null, "theme": null, "tint": 0.0, "auto": true}}, "right": {"style": "thin", "color": {"type": "auto", "rgb": "Values must be of type <class 'str'>", "indexed": null, "theme": null, "tint": 0.0, "auto": true}}, "top": {"style": "thin", "color": {"type": "auto", "rgb": "Values must be of type <class 'str'>", "indexed": null, "theme": null, "tint": 0.0, "auto": true}}, "bottom": {"style": "thin", "color": {"type": "auto", "rgb": "Values must be of type <class 'str'>", "indexed": null, "theme": null, "tint": 0.0, "auto": true}}, "diagonal": {"style": null, "color": null}, "diagonal_down": false, "diagonal_up": false, "outline": true, "vertical": null, "horizontal": null}, "protection": {"locked": true, "hidden": false}}
A37: Revenue Model | B37: I4 | C37: 4 | D37: 9 | E37: Calculation | F37: =I5*I6 | G37: 29.527722 | H37: {"type": "float", "value": 29.527721518987345} | I37: 0.00 | J37: FALSE | K37: FALSE | L37: 11 | M37: FF000000 | N37: 00000000 | R37: TRUE | S37: G000002 | T37: Horizontal | U37: 5 | V37: =R[1]C[0]*R[2]C[0] | W37: {"number_format": "0.00", "font": {"name": "Calibri", "size": 11.0, "bold": false, "italic": false, "underline": null, "strike": null, "color": {"type": "rgb", "rgb": "FF000000", "indexed": null, "theme": null, "tint": 0.0, "auto": null}, "vert_align": null}, "fill": {"fill_type": null, "fg_color": {"type": "rgb", "rgb": "00000000", "indexed": null, "theme": null, "tint": 0.0, "auto": null}, "bg_color": {"type": "rgb", "rgb": "00000000", "indexed": null, "theme": null, "tint": 0.0, "auto": null}}, "alignment": {"horizontal": null, "vertical": null, "text_rotation": 0, "wrap_text": null, "shrink_to_fit": null, "indent": 0.0}, "border": {"left": {"style": "thin", "color": {"type": "auto", "rgb": "Values must be of type <class 'str'>", "indexed": null, "theme": null, "tint": 0.0, "auto": true}}, "right": {"style": "thin", "color": {"type": "auto", "rgb": "Values must be of type <class 'str'>", "indexed": null, "theme": null, "tint": 0.0, "auto": true}}, "top": {"style": "thin", "color": {"type": "auto", "rgb": "Values must be of type <class 'str'>", "indexed": null, "theme": null, "tint": 0.0, "auto": true}}, "bottom": {"style": "thin", "color": {"type": "auto", "rgb": "Values must be of type <class 'str'>", "indexed": null, "theme": null, "tint": 0.0, "auto": true}}, "diagonal": {"style": null, "color": null}, "diagonal_down": false, "diagonal_up": false, "outline": true, "vertical": null, "horizontal": null}, "protection": {"locked": true, "hidden": false}}
A38: Revenue Model | B38: A5 | C38: 5 | D38: 1 | E38: Input | G38: Cement Production Million Tonnes | H38: {"type": "str", "value": "Cement Production Million Tonnes"} | I38: General | J38: FALSE | K38: FALSE | L38: 11 | M38: FF000000 | N38: 00000000 | R38: TRUE | W38: {"number_format": "General", "font": {"name": "Calibri", "size": 11.0, "bold": false, "italic": false, "underline": null, "strike": null, "color": {"type": "rgb", "rgb": "FF000000", "indexed": null, "theme": null, "tint": 0.0, "auto": null}, "vert_align": null}, "fill": {"fill_type": null, "fg_color": {"type": "rgb", "rgb": "00000000", "indexed": null, "theme": null, "tint": 0.0, "auto": null}, "bg_color": {"type": "rgb", "rgb": "00000000", "indexed": null, "theme": null, "tint": 0.0, "auto": null}}, "alignment": {"horizontal": null, "vertical": null, "text_rotation": 0, "wrap_text": null, "shrink_to_fit": null, "indent": 0.0}, "border": {"left": {"style": "thin", "color": {"type": "auto", "rgb": "Values must be of type <class 'str'>", "indexed": null, "theme": null, "tint": 0.0, "auto": true}}, "right": {"style": "thin", "color": {"type": "auto", "rgb": "Values must be of type <class 'str'>", "indexed": null, "theme": null, "tint": 0.0, "auto": true}}, "top": {"style": "thin", "color": {"type": "auto", "rgb": "Values must be of type <class 'str'>", "indexed": null, "theme": null, "tint": 0.0, "auto": true}}, "bottom": {"style": "thin", "color": {"type": "auto", "rgb": "Values must be of type <class 'str'>", "indexed": null, "theme": null, "tint": 0.0, "auto": true}}, "diagonal": {"style": null, "color": null}, "diagonal_down": false, "diagonal_up": false, "outline": true, "vertical": null, "horizontal": null}, "protection": {"locked": true, "hidden": false}}
A39: Revenue Model | B39: B5 | C39: 5 | D39: 2 | E39: Input | G39: 23.84 | H39: {"type": "float", "value": 23.84} | I39: General | J39: FALSE | K39: FALSE | L39: 11 | M39: FF000000 | N39: 00000000 | R39: TRUE | W39: {"number_format": "General", "font": {"name": "Calibri", "size": 11.0, "bold": false, "italic": false, "underline": null, "strike": null, "color": {"type": "rgb", "rgb": "FF000000", "indexed": null, "theme": null, "tint": 0.0, "auto": null}, "vert_align": null}, "fill": {"fill_type": null, "fg_color": {"type": "rgb", "rgb": "00000000", "indexed": null, "theme": null, "tint": 0.0, "auto": null}, "bg_color": {"type": "rgb", "rgb": "00000000", "indexed": null, "theme": null, "tint": 0.0, "auto": null}}, "alignment": {"horizontal": null, "vertical": null, "text_rotation": 0, "wrap_text": null, "shrink_to_fit": null, "indent": 0.0}, "border": {"left": {"style": "thin", "color": {"type": "auto", "rgb": "Values must be of type <class 'str'>", "indexed": null, "theme": null, "tint": 0.0, "auto": true}}, "right": {"style": "thin", "color": {"type": "auto", "rgb": "Values must be of type <class 'str'>", "indexed": null, "theme": null, "tint": 0.0, "auto": true}}, "top": {"style": "thin", "color": {"type": "auto", "rgb": "Values must be of type <class 'str'>", "indexed": null, "theme": null, "tint": 0.0, "auto": true}}, "bottom": {"style": "thin", "color": {"type": "auto", "rgb": "Values must be of type <class 'str'>", "indexed": null, "theme": null, "tint": 0.0, "auto": true}}, "diagonal": {"style": null, "color": null}, "diagonal_down": false, "diagonal_up": false, "outline": true, "vertical": null, "horizontal": null}, "protection": {"locked": true, "hidden": false}}
A40: Revenue Model | B40: C5 | C40: 5 | D40: 3 | E40: Input | G40: 23.18 | H40: {"type": "float", "value": 23.18} | I40: General | J40: FALSE | K40: FALSE | L40: 11 | M40: FF000000 | N40: 00000000 | R40: TRUE | W40: {"number_format": "General", "font": {"name": "Calibri", "size": 11.0, "bold": false, "italic": false, "underline": null, "strike": null, "color": {"type": "rgb", "rgb": "FF000000", "indexed": null, "theme": null, "tint": 0.0, "auto": null}, "vert_align": null}, "fill": {"fill_type": null, "fg_color": {"type": "rgb", "rgb": "00000000", "indexed": null, "theme": null, "tint": 0.0, "auto": null}, "bg_color": {"type": "rgb", "rgb": "00000000", "indexed": null, "theme": null, "tint": 0.0, "auto": null}}, "alignment": {"horizontal": null, "vertical": null, "text_rotation": 0, "wrap_text": null, "shrink_to_fit": null, "indent": 0.0}, "border": {"left": {"style": "thin", "color": {"type": "auto", "rgb": "Values must be of type <class 'str'>", "indexed": null, "theme": null, "tint": 0.0, "auto": true}}, "right": {"style": "thin", "color": {"type": "auto", "rgb": "Values must be of type <class 'str'>", "indexed": null, "theme": null, "tint": 0.0, "auto": true}}, "top": {"style": "thin", "color": {"type": "auto", "rgb": "Values must be of type <class 'str'>", "indexed": null, "theme": null, "tint": 0.0, "auto": true}}, "bottom": {"style": "thin", "color": {"type": "auto", "rgb": "Values must be of type <class 'str'>", "indexed": null, "theme": null, "tint": 0.0, "auto": true}}, "diagonal": {"style": null, "color": null}, "diagonal_down": false, "diagonal_up": false, "outline": true, "vertical": null, "horizontal": null}, "protection": {"locked": true, "hidden": false}}
A41: Revenue Model | B41: D5 | C41: 5 | D41: 4 | E41: Input | G41: 26.56 | H41: {"type": "float", "value": 26.56} | I41: General | J41: FALSE | K41: FALSE | L41: 11 | M41: FF000000 | N41: 00000000 | R41: TRUE | W41: {"number_format": "General", "font": {"name": "Calibri", "size": 11.0, "bold": false, "italic": false, "underline": null, "strike": null, "color": {"type": "rgb", "rgb": "FF000000", "indexed": null, "theme": null, "tint": 0.0, "auto": null}, "vert_align": null}, "fill": {"fill_type": null, "fg_color": {"type": "rgb", "rgb": "00000000", "indexed": null, "theme": null, "tint": 0.0, "auto": null}, "bg_color": {"type": "rgb", "rgb": "00000000", "indexed": null, "theme": null, "tint": 0.0, "auto": null}}, "alignment": {"horizontal": null, "vertical": null, "text_rotation": 0, "wrap_text": null, "shrink_to_fit": null, "indent": 0.0}, "border": {"left": {"style": "thin", "color": {"type": "auto", "rgb": "Values must be of type <class 'str'>", "indexed": null, "theme": null, "tint": 0.0, "auto": true}}, "right": {"style": "thin", "color": {"type": "auto", "rgb": "Values must be of type <class 'str'>", "indexed": null, "theme": null, "tint": 0.0, "auto": true}}, "top": {"style": "thin", "color": {"type": "auto", "rgb": "Values must be of type <class 'str'>", "indexed": null, "theme": null, "tint": 0.0, "auto": true}}, "bottom": {"style": "thin", "color": {"type": "auto", "rgb": "Values must be of type <class 'str'>", "indexed": null, "theme": null, "tint": 0.0, "auto": true}}, "diagonal": {"style": null, "color": null}, "diagonal_down": false, "diagonal_up": false, "outline": true, "vertical": null, "horizontal": null}, "protection": {"locked": true, "hidden": false}}
A42: Revenue Model | B42: E5 | C42: 5 | D42: 5 | E42: Calculation | F42: =E9*E8 | G42: 27.232405 | H42: {"type": "float", "value": 27.232405063291136} | I42: 0.00 | J42: FALSE | K42: FALSE | L42: 11 | M42: FF000000 | N42: 00000000 | R42: TRUE | S42: G000003 | T42: Horizontal | U42: 5 | V42: =R[4]C[0]*R[3]C[0] | W42: {"number_format": "0.00", "font": {"name": "Calibri", "size": 11.0, "bold": false, "italic": false, "underline": null, "strike": null, "color": {"type": "rgb", "rgb": "FF000000", "indexed": null, "theme": null, "tint": 0.0, "auto": null}, "vert_align": null}, "fill": {"fill_type": null, "fg_color": {"type": "rgb", "rgb": "00000000", "indexed": null, "theme": null, "tint": 0.0, "auto": null}, "bg_color": {"type": "rgb", "rgb": "00000000", "indexed": null, "theme": null, "tint": 0.0, "auto": null}}, "alignment": {"horizontal": null, "vertical": null, "text_rotation": 0, "wrap_text": null, "shrink_to_fit": null, "indent": 0.0}, "border": {"left": {"style": "thin", "color": {"type": "auto", "rgb": "Values must be of type <class 'str'>", "indexed": null, "theme": null, "tint": 0.0, "auto": true}}, "right": {"style": "thin", "color": {"type": "auto", "rgb": "Values must be of type <class 'str'>", "indexed": null, "theme": null, "tint": 0.0, "auto": true}}, "top": {"style": "thin", "color": {"type": "auto", "rgb": "Values must be of type <class 'str'>", "indexed": null, "theme": null, "tint": 0.0, "auto": true}}, "bottom": {"style": "thin", "color": {"type": "auto", "rgb": "Values must be of type <class 'str'>", "indexed": null, "theme": null, "tint": 0.0, "auto": true}}, "diagonal": {"style": null, "color": null}, "diagonal_down": false, "diagonal_up": false, "outline": true, "vertical": null, "horizontal": null}, "protection": {"locked": true, "hidden": false}}
