Workbook
Name worksheet_title: 'PLANNED EXPENSES'!$O$2

Sheet START
B1: About this Template
B4: Use this business expense budget workbook to track planned and actual expenses and variances.
B5: Fill in company name and add logo.
B6: Enter details in tables in planned expenses worksheet and actual expenses worksheet.
B7: Tables are auto updated in expense variances worksheet and charts in expense analysis worksheet
B8: HOW TO USE THIS TEMPLATE
B9: Input data in the white cells on the PLANNED EXPENSES and ACTUAL EXPENSES worksheets, and the EXPENSE VARIANCES and EXPENSE ANALYSIS will be calculated for you. If you add a row on one sheet, the other sheets need to match.
B10: Note
B11: Additional instructions have been provided in column A in each worksheet. To learn more about tables, press SHIFT and then F10 within a table, select the TABLE option, and then select ALTERNATIVE TEXT.

Sheet PLANNED EXPENSES
B2: SBO Banking | O2: Detailed expense estimates
O3: Shaded cells are calculations
B5: PLANNED EXPENSES
B6: Employee costs | C6: Jan | D6: Feb | E6: Mar | F6: Apr | G6: May | H6: Jun | I6: Jul | J6: Aug | K6: Sep | L6: Oct | M6: Nov | N6: Dec | O6: YEAR
B7: Wages | C7: 85000 | D7: 85000 | E7: 85000 | F7: 87500 | G7: 87500 | H7: 87500 | I7: 87500 | J7: 92400 | K7: 92400 | L7: 92400 | M7: 92400 | N7: 92400 | O7: =SUM(C7:N7)
B8: Benefits | C8: =C7*0.27 | D8: =D7*0.27 | E8: =E7*0.27 | F8: =F7*0.27 | G8: =G7*0.27 | H8: =H7*0.27 | I8: =I7*0.27 | J8: =J7*0.27 | ... N8: =N7*0.27 | O8: =SUM(C8:N8)
B9: Subtotal | C9: =SUBTOTAL(109,EmployeePlan[Jan]) | D9: =SUBTOTAL(109,EmployeePlan[Feb]) | E9: =SUBTOTAL(109,EmployeePlan[Mar]) | F9: =SUBTOTAL(109,EmployeePlan[Apr]) | G9: =SUBTOTAL(109,EmployeePlan[May]) | H9: =SUBTOTAL(109,EmployeePlan[Jun]) | I9: =SUBTOTAL(109,EmployeePlan[Jul]) | J9: =SUBTOTAL(109,EmployeePlan[Aug]) | K9: =SUBTOTAL(109,EmployeePlan[Sep]) | L9: =SUBTOTAL(109,EmployeePlan[Oct]) | M9: =SUBTOTAL(109,EmployeePlan[Nov]) | N9: =SUBTOTAL(109,EmployeePlan[Dec]) | O9: =SUBTOTAL(109,EmployeePlan[YEAR])
B11: Office costs | C11: Jan | D11: Feb | E11: Mar | F11: Apr | G11: May | H11: Jun | I11: Jul | J11: Aug | K11: Sep | L11: Oct | M11: Nov | N11: Dec | O11: YEAR
B12: Office lease | C12: 9800 | D12: 9800 | E12: 9800 | F12: 9800 | G12: 9800 | H12: 9800 | I12: 9800 | J12: 9800 | K12: 9800 | L12: 9800 | M12: 9800 | N12: 9800 | O12: =SUM(C12:N12)
B13: Gas | C13: 300 | D13: 400 | E13: 400 | F13: 100 | G13: 100 | H13: 100 | I13: 100 | J13: 100 | K13: 100 | L13: 100 | M13: 400 | N13: 400 | O13: =SUM(C13:N13)
B14: Electric | C14: 300 | D14: 300 | E14: 300 | F14: 300 | G14: 300 | H14: 300 | I14: 300 | J14: 300 | K14: 300 | L14: 300 | M14: 300 | N14: 300 | O14: =SUM(C14:N14)
B15: Water | C15: 40 | D15: 40 | E15: 40 | F15: 40 | G15: 40 | H15: 40 | I15: 40 | J15: 40 | K15: 40 | L15: 40 | M15: 40 | N15: 40 | O15: =SUM(C15:N15)
B16: Telephone | C16: 250 | D16: 250 | E16: 250 | F16: 250 | G16: 250 | H16: 250 | I16: 250 | J16: 250 | K16: 250 | L16: 250 | M16: 250 | N16: 250 | O16: =SUM(C16:N16)
B17: Internet access | C17: 180 | D17: 180 | E17: 180 | F17: 180 | G17: 180 | H17: 180 | I17: 180 | J17: 180 | K17: 180 | L17: 180 | M17: 180 | N17: 180 | O17: =SUM(C17:N17)
B18: Office supplies | C18: 200 | D18: 200 | E18: 200 | F18: 200 | G18: 200 | H18: 200 | I18: 200 | J18: 200 | K18: 200 | L18: 200 | M18: 200 | N18: 200 | O18: =SUM(C18:N18)
B19: Security | C19: 600 | D19: 600 | E19: 600 | F19: 600 | G19: 600 | H19: 600 | I19: 600 | J19: 600 | K19: 600 | L19: 600 | M19: 600 | N19: 600 | O19: =SUM(C19:N19)
B20: Subtotal | C20: =SUBTOTAL(109,OfficePlan[Jan]) | D20: =SUBTOTAL(109,OfficePlan[Feb]) | E20: =SUBTOTAL(109,OfficePlan[Mar]) | F20: =SUBTOTAL(109,OfficePlan[Apr]) | G20: =SUBTOTAL(109,OfficePlan[May]) | H20: =SUBTOTAL(109,OfficePlan[Jun]) | I20: =SUBTOTAL(109,OfficePlan[Jul]) | J20: =SUBTOTAL(109,OfficePlan[Aug]) | K20: =SUBTOTAL(109,OfficePlan[Sep]) | L20: =SUBTOTAL(109,OfficePlan[Oct]) | M20: =SUBTOTAL(109,OfficePlan[Nov]) | N20: =SUBTOTAL(109,OfficePlan[Dec]) | O20: =SUBTOTAL(109,OfficePlan[YEAR])
B22: Marketing costs | C22: Jan | D22: Feb | E22: Mar | F22: Apr | G22: May | H22: Jun | I22: Jul | J22: Aug | K22: Sep | L22: Oct | M22: Nov | N22: Dec | O22: YEAR
B23: Web site hosting | C23: 500 | D23: 500 | E23: 500 | F23: 500 | G23: 500 | H23: 500 | I23: 500 | J23: 500 | K23: 500 | L23: 500 | M23: 500 | N23: 500 | O23: =SUM(C23:N23)
B24: Web site updates | C24: 200 | D24: 200 | E24: 200 | F24: 200 | G24: 200 | H24: 1000 | I24: 200 | J24: 200 | K24: 200 | L24: 200 | M24: 200 | N24: 1000 | O24: =SUM(C24:N24)
B25: Collateral preparation | C25: 5000 | D25: 0 | E25: 0 | F25: 5000 | G25: 0 | H25: 0 | I25: 5000 | J25: 0 | K25: 0 | L25: 5000 | M25: 0 | N25: 0 | O25: =SUM(C25:N25)
B26: Collateral printing | C26: 200 | D26: 200 | E26: 200 | F26: 200 | G26: 200 | H26: 200 | I26: 200 | J26: 200 | K26: 200 | L26: 200 | M26: 200 | N26: 200 | O26: =SUM(C26:N26)
B27: Marketing events | C27: 2000 | D27: 2000 | E27: 2000 | F27: 5000 | G27: 2000 | H27: 2000 | I27: 2000 | J27: 5000 | K27: 2000 | L27: 2000 | M27: 2000 | N27: 5000 | O27: =SUM(C27:N27)
B28: Miscellaneous expenses | C28: 200 | D28: 200 | E28: 200 | F28: 200 | G28: 200 | H28: 200 | I28: 200 | J28: 200 | K28: 200 | L28: 200 | M28: 200 | N28: 200 | O28: =SUM(C28:N28)
B29: Subtotal | C29: =SUBTOTAL(109,MarketingPlan[Jan]) | D29: =SUBTOTAL(109,MarketingPlan[Feb]) | E29: =SUBTOTAL(109,MarketingPlan[Mar]) | F29: =SUBTOTAL(109,MarketingPlan[Apr]) | G29: =SUBTOTAL(109,MarketingPlan[May]) | H29: =SUBTOTAL(109,MarketingPlan[Jun]) | I29: =SUBTOTAL(109,MarketingPlan[Jul]) | J29: =SUBTOTAL(109,MarketingPlan[Aug]) | K29: =SUBTOTAL(109,MarketingPlan[Sep]) | L29: =SUBTOTAL(109,MarketingPlan[Oct]) | M29: =SUBTOTAL(109,MarketingPlan[Nov]) | N29: =SUBTOTAL(109,MarketingPlan[Dec]) | O29: =SUBTOTAL(109,MarketingPlan[YEAR])
B31: Training/travel | C31: Jan | D31: Feb | E31: Mar | F31: Apr | G31: May | H31: Jun | I31: Jul | J31: Aug | K31: Sep | L31: Oct | M31: Nov | N31: Dec | O31: YEAR
B32: Training classes | C32: 2000 | D32: 2000 | E32: 2000 | F32: 2000 | G32: 2000 | H32: 2000 | I32: 2000 | J32: 2000 | K32: 2000 | L32: 2000 | M32: 2000 | N32: 2000 | O32: =SUM(C32:N32)
B33: Training-related travel costs | C33: 2000 | D33: 2000 | E33: 2000 | F33: 2000 | G33: 2000 | H33: 2000 | I33: 2000 | J33: 2000 | K33: 2000 | L33: 2000 | M33: 2000 | N33: 2000 | O33: =SUM(C33:N33)
B34: Subtotal | C34: =SUBTOTAL(109,TrainingAndTravelPlan[Jan]) | D34: =SUBTOTAL(109,TrainingAndTravelPlan[Feb]) | E34: =SUBTOTAL(109,TrainingAndTravelPlan[Mar]) | F34: =SUBTOTAL(109,TrainingAndTravelPlan[Apr]) | G34: =SUBTOTAL(109,TrainingAndTravelPlan[May]) | H34: =SUBTOTAL(109,TrainingAndTravelPlan[Jun]) | I34: =SUBTOTAL(109,TrainingAndTravelPlan[Jul]) | J34: =SUBTOTAL(109,TrainingAndTravelPlan[Aug]) | K34: =SUBTOTAL(109,TrainingAndTravelPlan[Sep]) | L34: =SUBTOTAL(109,TrainingAndTravelPlan[Oct]) | M34: =SUBTOTAL(109,TrainingAndTravelPlan[Nov]) | N34: =SUBTOTAL(109,TrainingAndTravelPlan[Dec]) | O34: =SUBTOTAL(109,TrainingAndTravelPlan[YEAR])
B36: Totals | C36: Jan | D36: Feb | E36: Mar | F36: Apr | G36: May | H36: Jun | I36: Jul | J36: Aug | K36: Sep | L36: Oct | M36: Nov | N36: Dec | O36: Year
B37: Monthly planned expenses | C37: =TrainingAndTravelPlan[[#Totals],[Jan]]+MarketingPlan[[#Totals],[Jan]]+OfficePlan[[#Totals],[Jan]]+EmployeePlan[[#Totals],[Jan]] | D37: =TrainingAndTravelPlan[[#Totals],[Feb]]+MarketingPlan[[#Totals],[Feb]]+OfficePlan[[#Totals],[Feb]]+EmployeePlan[[#Totals],[Feb]] | E37: =TrainingAndTravelPlan[[#Totals],[Mar]]+MarketingPlan[[#Totals],[Mar]]+OfficePlan[[#Totals],[Mar]]+EmployeePlan[[#Totals],[Mar]] | F37: =TrainingAndTravelPlan[[#Totals],[Apr]]+MarketingPlan[[#Totals],[Apr]]+OfficePlan[[#Totals],[Apr]]+EmployeePlan[[#Totals],[Apr]] | G37: =TrainingAndTravelPlan[[#Totals],[May]]+MarketingPlan[[#Totals],[May]]+OfficePlan[[#Totals],[May]]+EmployeePlan[[#Totals],[May]] | H37: =TrainingAndTravelPlan[[#Totals],[Jun]]+MarketingPlan[[#Totals],[Jun]]+OfficePlan[[#Totals],[Jun]]+EmployeePlan[[#Totals],[Jun]] | I37: =TrainingAndTravelPlan[[#Totals],[Jul]]+MarketingPlan[[#Totals],[Jul]]+OfficePlan[[#Totals],[Jul]]+EmployeePlan[[#Totals],[Jul]] | J37: =TrainingAndTravelPlan[[#Totals],[Aug]]+MarketingPlan[[#Totals],[Aug]]+OfficePlan[[#Totals],[Aug]]+EmployeePlan[[#Totals],[Aug]] | K37: =TrainingAndTravelPlan[[#Totals],[Sep]]+MarketingPlan[[#Totals],[Sep]]+OfficePlan[[#Totals],[Sep]]+EmployeePlan[[#Totals],[Sep]] | L37: =TrainingAndTravelPlan[[#Totals],[Oct]]+MarketingPlan[[#Totals],[Oct]]+OfficePlan[[#Totals],[Oct]]+EmployeePlan[[#Totals],[Oct]] | M37: =TrainingAndTravelPlan[[#Totals],[Nov]]+MarketingPlan[[#Totals],[Nov]]+OfficePlan[[#Totals],[Nov]]+EmployeePlan[[#Totals],[Nov]] | N37: =TrainingAndTravelPlan[[#Totals],[Dec]]+MarketingPlan[[#Totals],[Dec]]+OfficePlan[[#Totals],[Dec]]+EmployeePlan[[#Totals],[Dec]] | O37: =TrainingAndTravelPlan[[#Totals],[YEAR]]+MarketingPlan[[#Totals],[YEAR]]+OfficePlan[[#Totals],[YEAR]]+EmployeePlan[[#Totals],[YEAR]]
B38: TOTAL planned expenses | C38: =SUM($C$37:C37) | D38: =SUM($C$37:D37) | E38: =SUM($C$37:E37) | F38: =SUM($C$37:F37) | G38: =SUM($C$37:G37) | H38: =SUM($C$37:H37) | I38: =SUM($C$37:I37) | J38: =SUM($C$37:J37) | ... N38: =SUM($C$37:N37)

Sheet ACTUAL EXPENSES
B2: ='PLANNED EXPENSES'!B2:D3 | O2: =worksheet_title
O3: Shaded cells are calculations
B5: ACTUAL EXPENSES
B6: Employee costs | C6: Jan | D6: Feb | E6: Mar | F6: Apr | G6: May | H6: Jun | I6: Jul | J6: Aug | K6: Sep | L6: Oct | M6: Nov | N6: Dec | O6: YEAR
B7: Wages | C7: 85000 | D7: 85000 | E7: 85000 | F7: 88000 | G7: 88000 | H7: 88000 | O7: =SUM(C7:N7)
B8: Benefits | C8: =C7*0.27 | D8: =D7*0.27 | E8: =E7*0.27 | F8: =F7*0.27 | G8: =G7*0.27 | H8: =H7*0.27 | I8: =I7*0.27 | J8: =J7*0.27 | ... N8: =N7*0.27 | O8: =SUM(C8:N8)
B9: Subtotal | C9: =SUBTOTAL(109,EmployeeActual[Jan]) | D9: =SUBTOTAL(109,EmployeeActual[Feb]) | E9: =SUBTOTAL(109,EmployeeActual[Mar]) | F9: =SUBTOTAL(109,EmployeeActual[Apr]) | G9: =SUBTOTAL(109,EmployeeActual[May]) | H9: =SUBTOTAL(109,EmployeeActual[Jun]) | I9: =SUBTOTAL(109,EmployeeActual[Jul]) | J9: =SUBTOTAL(109,EmployeeActual[Aug]) | K9: =SUBTOTAL(109,EmployeeActual[Sep]) | L9: =SUBTOTAL(109,EmployeeActual[Oct]) | M9: =SUBTOTAL(109,EmployeeActual[Nov]) | N9: =SUBTOTAL(109,EmployeeActual[Dec]) | O9: =SUBTOTAL(109,EmployeeActual[YEAR])
B11: Office costs | C11: Jan | D11: Feb | E11: Mar | F11: Apr | G11: May | H11: Jun | I11: Jul | J11: Aug | K11: Sep | L11: Oct | M11: Nov | N11: Dec | O11: YEAR
B12: Office lease | C12: 9800 | D12: 9800 | E12: 9800 | F12: 9800 | G12: 9800 | H12: 9800 | O12: =SUM(C12:N12)
B13: Gas | C13: 4 | D13: 430 | E13: 385 | F13: 230 | G13: 87 | H13: 88 | O13: =SUM(C13:N13)
B14: Electric | C14: 288 | D14: 278 | E14: 268 | F14: 299 | G14: 306 | H14: 290 | O14: =SUM(C14:N14)
B15: Water | C15: 35 | D15: 33 | E15: 34 | F15: 36 | G15: 34 | H15: 36 | O15: =SUM(C15:N15)
B16: Telephone | C16: 224 | D16: 235 | E16: 265 | F16: 245 | G16: 245 | H16: 220 | O16: =SUM(C16:N16)
B17: Internet access | C17: 180 | D17: 180 | E17: 180 | F17: 180 | G17: 180 | H17: 180 | O17: =SUM(C17:N17)
B18: Office supplies | C18: 256 | D18: 142 | E18: 160 | F18: 221 | G18: 256 | H18: 240 | O18: =SUM(C18:N18)
B19: Security | C19: 600 | D19: 600 | E19: 600 | F19: 600 | G19: 600 | H19: 600 | O19: =SUM(C19:N19)
B20: Subtotal | C20: =SUBTOTAL(109,OfficeActual[Jan]) | D20: =SUBTOTAL(109,OfficeActual[Feb]) | E20: =SUBTOTAL(109,OfficeActual[Mar]) | F20: =SUBTOTAL(109,OfficeActual[Apr]) | G20: =SUBTOTAL(109,OfficeActual[May]) | H20: =SUBTOTAL(109,OfficeActual[Jun]) | I20: =SUBTOTAL(109,OfficeActual[Jul]) | J20: =SUBTOTAL(109,OfficeActual[Aug]) | K20: =SUBTOTAL(109,OfficeActual[Sep]) | L20: =SUBTOTAL(109,OfficeActual[Oct]) | M20: =SUBTOTAL(109,OfficeActual[Nov]) | N20: =SUBTOTAL(109,OfficeActual[Dec]) | O20: =SUBTOTAL(109,OfficeActual[YEAR])
B22: Marketing costs | C22: Jan | D22: Feb | E22: Mar | F22: Apr | G22: May | H22: Jun | I22: Jul | J22: Aug | K22: Sep | L22: Oct | M22: Nov | N22: Dec | O22: YEAR
B23: Web site hosting | C23: 500 | D23: 500 | E23: 500 | F23: 500 | G23: 500 | H23: 500 | O23: =SUM(C23:N23)
B24: Web site updates | C24: 200 | D24: 200 | E24: 200 | F24: 200 | G24: 200 | H24: 1500 | O24: =SUM(C24:N24)
B25: Collateral preparation | C25: 4800 | D25: 0 | E25: 0 | F25: 5500 | G25: 0 | H25: 0 | O25: =SUM(C25:N25)
B26: Collateral printing | C26: 100 | D26: 500 | E26: 100 | F26: 100 | G26: 600 | H26: 180 | O26: =SUM(C26:N26)
B27: Marketing events | C27: 1800 | D27: 2200 | E27: 2200 | F27: 4700 | G27: 1500 | H27: 2300 | O27: =SUM(C27:N27)
B28: Miscellaneous expenses | C28: 145 | D28: 156 | E28: 123 | F28: 223 | G28: 187 | H28: 245 | O28: =SUM(C28:N28)
B29: Subtotal | C29: =SUBTOTAL(109,MarketingActual[Jan]) | D29: =SUBTOTAL(109,MarketingActual[Feb]) | E29: =SUBTOTAL(109,MarketingActual[Mar]) | F29: =SUBTOTAL(109,MarketingActual[Apr]) | G29: =SUBTOTAL(109,MarketingActual[May]) | H29: =SUBTOTAL(109,MarketingActual[Jun]) | I29: =SUBTOTAL(109,MarketingActual[Jul]) | J29: =SUBTOTAL(109,MarketingActual[Aug]) | K29: =SUBTOTAL(109,MarketingActual[Sep]) | L29: =SUBTOTAL(109,MarketingActual[Oct]) | M29: =SUBTOTAL(109,MarketingActual[Nov]) | N29: =SUBTOTAL(109,MarketingActual[Dec]) | O29: =SUBTOTAL(109,MarketingActual[YEAR])
B31: Training/travel | C31: Jan | D31: Feb | E31: Mar | F31: Apr | G31: May | H31: Jun | I31: Jul | J31: Aug | K31: Sep | L31: Oct | M31: Nov | N31: Dec | O31: YEAR
B32: Training classes | C32: 1600 | D32: 2400 | E32: 1400 | F32: 1600 | G32: 1200 | H32: 2800 | O32: =SUM(C32:N32)
B33: Training-related travel costs | C33: 1200 | D33: 2200 | E33: 1400 | F33: 1200 | G33: 800 | H33: 3500 | O33: =SUM(C33:N33)
B34: Subtotal | C34: =SUBTOTAL(109,TrainingAndTravelActual[Jan]) | D34: =SUBTOTAL(109,TrainingAndTravelActual[Feb]) | E34: =SUBTOTAL(109,TrainingAndTravelActual[Mar]) | F34: =SUBTOTAL(109,TrainingAndTravelActual[Apr]) | G34: =SUBTOTAL(109,TrainingAndTravelActual[May]) | H34: =SUBTOTAL(109,TrainingAndTravelActual[Jun]) | I34: =SUBTOTAL(109,TrainingAndTravelActual[Jul]) | J34: =SUBTOTAL(109,TrainingAndTravelActual[Aug]) | K34: =SUBTOTAL(109,TrainingAndTravelActual[Sep]) | L34: =SUBTOTAL(109,TrainingAndTravelActual[Oct]) | M34: =SUBTOTAL(109,TrainingAndTravelActual[Nov]) | N34: =SUBTOTAL(109,TrainingAndTravelActual[Dec]) | O34: =SUBTOTAL(109,TrainingAndTravelActual[YEAR])
B36: Totals | C36: Jan | D36: Feb | E36: Mar | F36: Apr | G36: May | H36: Jun | I36: Jul | J36: Aug | K36: Sep | L36: Oct | M36: Nov | N36: Dec | O36: Year
B37: Monthly actual expenses | C37: =TrainingAndTravelActual[[#Totals],[Jan]]+MarketingActual[[#Totals],[Jan]]+OfficeActual[[#Totals],[Jan]]+EmployeeActual[[#Totals],[Jan]] | D37: =TrainingAndTravelActual[[#Totals],[Feb]]+MarketingActual[[#Totals],[Feb]]+OfficeActual[[#Totals],[Feb]]+EmployeeActual[[#Totals],[Feb]] | E37: =TrainingAndTravelActual[[#Totals],[Mar]]+MarketingActual[[#Totals],[Mar]]+OfficeActual[[#Totals],[Mar]]+EmployeeActual[[#Totals],[Mar]] | F37: =TrainingAndTravelActual[[#Totals],[Apr]]+MarketingActual[[#Totals],[Apr]]+OfficeActual[[#Totals],[Apr]]+EmployeeActual[[#Totals],[Apr]] | G37: =TrainingAndTravelActual[[#Totals],[May]]+MarketingActual[[#Totals],[May]]+OfficeActual[[#Totals],[May]]+EmployeeActual[[#Totals],[May]] | H37: =TrainingAndTravelActual[[#Totals],[Jun]]+MarketingActual[[#Totals],[Jun]]+OfficeActual[[#Totals],[Jun]]+EmployeeActual[[#Totals],[Jun]] | I37: =TrainingAndTravelActual[[#Totals],[Jul]]+MarketingActual[[#Totals],[Jul]]+OfficeActual[[#Totals],[Jul]]+EmployeeActual[[#Totals],[Jul]] | J37: =TrainingAndTravelActual[[#Totals],[Aug]]+MarketingActual[[#Totals],[Aug]]+OfficeActual[[#Totals],[Aug]]+EmployeeActual[[#Totals],[Aug]] | K37: =TrainingAndTravelActual[[#Totals],[Sep]]+MarketingActual[[#Totals],[Sep]]+OfficeActual[[#Totals],[Sep]]+EmployeeActual[[#Totals],[Sep]] | L37: =TrainingAndTravelActual[[#Totals],[Oct]]+MarketingActual[[#Totals],[Oct]]+OfficeActual[[#Totals],[Oct]]+EmployeeActual[[#Totals],[Oct]] | M37: =TrainingAndTravelActual[[#Totals],[Nov]]+MarketingActual[[#Totals],[Nov]]+OfficeActual[[#Totals],[Nov]]+EmployeeActual[[#Totals],[Nov]] | N37: =TrainingAndTravelActual[[#Totals],[Dec]]+MarketingActual[[#Totals],[Dec]]+OfficeActual[[#Totals],[Dec]]+EmployeeActual[[#Totals],[Dec]] | O37: =TrainingAndTravelActual[[#Totals],[YEAR]]+MarketingActual[[#Totals],[YEAR]]+OfficeActual[[#Totals],[YEAR]]+EmployeeActual[[#Totals],[YEAR]]
B38: TOTAL actual expenses | C38: =SUM($C$37:C37) | D38: =SUM($C$37:D37) | E38: =SUM($C$37:E37) | F38: =SUM($C$37:F37) | G38: =SUM($C$37:G37) | H38: =SUM($C$37:H37) | I38: =SUM($C$37:I37) | J38: =SUM($C$37:J37) | ... N38: =SUM($C$37:N37)

Sheet EXPENSE VARIANCES
B2: ='PLANNED EXPENSES'!B2:D3 | O2: =worksheet_title
O3: Shaded cells are calculations
B5: EXPENSE VARIANCES
B6: Employee costs | C6: Jan | D6: Feb | E6: Mar | F6: Apr | G6: May | H6: Jun | I6: Jul | J6: Aug | K6: Sep | L6: Oct | M6: Nov | N6: Dec | O6: YEAR
B7: Wages | C7: =INDEX(EmployeePlan[],MATCH(INDEX(EmployeeVariances[],ROW()-ROW(EmployeeVariances[[#Headers],[Jan]]),1),INDEX(EmployeePlan[],,1),0),MATCH(EmployeeVariances[[#Headers],[Jan]],EmployeePlan[#Headers],0))-INDEX(EmployeeActual[],MATCH(INDEX(EmployeeVariances[],ROW()-ROW(EmployeeVariances[[#Headers],[Jan]]),1),INDEX(EmployeePlan[],,1),0),MATCH(EmployeeVariances[[#Headers],[Jan]],EmployeeActual[#Headers],0)) | D7: =INDEX(EmployeePlan[],MATCH(INDEX(EmployeeVariances[],ROW()-ROW(EmployeeVariances[[#Headers],[Feb]]),1),INDEX(EmployeePlan[],,1),0),MATCH(EmployeeVariances[[#Headers],[Feb]],EmployeePlan[#Headers],0))-INDEX(EmployeeActual[],MATCH(INDEX(EmployeeVariances[],ROW()-ROW(EmployeeVariances[[#Headers],[Feb]]),1),INDEX(EmployeePlan[],,1),0),MATCH(EmployeeVariances[[#Headers],[Feb]],EmployeeActual[#Headers],0)) | E7: =INDEX(EmployeePlan[],MATCH(INDEX(EmployeeVariances[],ROW()-ROW(EmployeeVariances[[#Headers],[Mar]]),1),INDEX(EmployeePlan[],,1),0),MATCH(EmployeeVariances[[#Headers],[Mar]],EmployeePlan[#Headers],0))-INDEX(EmployeeActual[],MATCH(INDEX(EmployeeVariances[],ROW()-ROW(EmployeeVariances[[#Headers],[Mar]]),1),INDEX(EmployeePlan[],,1),0),MATCH(EmployeeVariances[[#Headers],[Mar]],EmployeeActual[#Headers],0)) | F7: =INDEX(EmployeePlan[],MATCH(INDEX(EmployeeVariances[],ROW()-ROW(EmployeeVariances[[#Headers],[Apr]]),1),INDEX(EmployeePlan[],,1),0),MATCH(EmployeeVariances[[#Headers],[Apr]],EmployeePlan[#Headers],0))-INDEX(EmployeeActual[],MATCH(INDEX(EmployeeVariances[],ROW()-ROW(EmployeeVariances[[#Headers],[Apr]]),1),INDEX(EmployeePlan[],,1),0),MATCH(EmployeeVariances[[#Headers],[Apr]],EmployeeActual[#Headers],0)) | G7: =INDEX(EmployeePlan[],MATCH(INDEX(EmployeeVariances[],ROW()-ROW(EmployeeVariances[[#Headers],[May]]),1),INDEX(EmployeePlan[],,1),0),MATCH(EmployeeVariances[[#Headers],[May]],EmployeePlan[#Headers],0))-INDEX(EmployeeActual[],MATCH(INDEX(EmployeeVariances[],ROW()-ROW(EmployeeVariances[[#Headers],[May]]),1),INDEX(EmployeePlan[],,1),0),MATCH(EmployeeVariances[[#Headers],[May]],EmployeeActual[#Headers],0)) | H7: =INDEX(EmployeePlan[],MATCH(INDEX(EmployeeVariances[],ROW()-ROW(EmployeeVariances[[#Headers],[Jun]]),1),INDEX(EmployeePlan[],,1),0),MATCH(EmployeeVariances[[#Headers],[Jun]],EmployeePlan[#Headers],0))-INDEX(EmployeeActual[],MATCH(INDEX(EmployeeVariances[],ROW()-ROW(EmployeeVariances[[#Headers],[Jun]]),1),INDEX(EmployeePlan[],,1),0),MATCH(EmployeeVariances[[#Headers],[Jun]],EmployeeActual[#Headers],0)) | I7: =INDEX(EmployeePlan[],MATCH(INDEX(EmployeeVariances[],ROW()-ROW(EmployeeVariances[[#Headers],[Jul]]),1),INDEX(EmployeePlan[],,1),0),MATCH(EmployeeVariances[[#Headers],[Jul]],EmployeePlan[#Headers],0))-INDEX(EmployeeActual[],MATCH(INDEX(EmployeeVariances[],ROW()-ROW(EmployeeVariances[[#Headers],[Jul]]),1),INDEX(EmployeePlan[],,1),0),MATCH(EmployeeVariances[[#Headers],[Jul]],EmployeeActual[#Headers],0)) | J7: =INDEX(EmployeePlan[],MATCH(INDEX(EmployeeVariances[],ROW()-ROW(EmployeeVariances[[#Headers],[Aug]]),1),INDEX(EmployeePlan[],,1),0),MATCH(EmployeeVariances[[#Headers],[Aug]],EmployeePlan[#Headers],0))-INDEX(EmployeeActual[],MATCH(INDEX(EmployeeVariances[],ROW()-ROW(EmployeeVariances[[#Headers],[Aug]]),1),INDEX(EmployeePlan[],,1),0),MATCH(EmployeeVariances[[#Headers],[Aug]],EmployeeActual[#Headers],0)) | K7: =INDEX(EmployeePlan[],MATCH(INDEX(EmployeeVariances[],ROW()-ROW(EmployeeVariances[[#Headers],[Sep]]),1),INDEX(EmployeePlan[],,1),0),MATCH(EmployeeVariances[[#Headers],[Sep]],EmployeePlan[#Headers],0))-INDEX(EmployeeActual[],MATCH(INDEX(EmployeeVariances[],ROW()-ROW(EmployeeVariances[[#Headers],[Sep]]),1),INDEX(EmployeePlan[],,1),0),MATCH(EmployeeVariances[[#Headers],[Sep]],EmployeeActual[#Headers],0)) | L7: =INDEX(EmployeePlan[],MATCH(INDEX(EmployeeVariances[],ROW()-ROW(EmployeeVariances[[#Headers],[Oct]]),1),INDEX(EmployeePlan[],,1),0),MATCH(EmployeeVariances[[#Headers],[Oct]],EmployeePlan[#Headers],0))-INDEX(EmployeeActual[],MATCH(INDEX(EmployeeVariances[],ROW()-ROW(EmployeeVariances[[#Headers],[Oct]]),1),INDEX(EmployeePlan[],,1),0),MATCH(EmployeeVariances[[#Headers],[Oct]],EmployeeActual[#Headers],0)) | M7: =INDEX(EmployeePlan[],MATCH(INDEX(EmployeeVariances[],ROW()-ROW(EmployeeVariances[[#Headers],[Nov]]),1),INDEX(EmployeePlan[],,1),0),MATCH(EmployeeVariances[[#Headers],[Nov]],EmployeePlan[#Headers],0))-INDEX(EmployeeActual[],MATCH(INDEX(EmployeeVariances[],ROW()-ROW(EmployeeVariances[[#Headers],[Nov]]),1),INDEX(EmployeePlan[],,1),0),MATCH(EmployeeVariances[[#Headers],[Nov]],EmployeeActual[#Headers],0)) | N7: =INDEX(EmployeePlan[],MATCH(INDEX(EmployeeVariances[],ROW()-ROW(EmployeeVariances[[#Headers],[Dec]]),1),INDEX(EmployeePlan[],,1),0),MATCH(EmployeeVariances[[#Headers],[Dec]],EmployeePlan[#Headers],0))-INDEX(EmployeeActual[],MATCH(INDEX(EmployeeVariances[],ROW()-ROW(EmployeeVariances[[#Headers],[Dec]]),1),INDEX(EmployeePlan[],,1),0),MATCH(EmployeeVariances[[#Headers],[Dec]],EmployeeActual[#Headers],0)) | O7: =SUM(EmployeeVariances[[#This Row],[Jan]:[Dec]])
B8: Benefits | C8: =INDEX(EmployeePlan[],MATCH(INDEX(EmployeeVariances[],ROW()-ROW(EmployeeVariances[[#Headers],[Jan]]),1),INDEX(EmployeePlan[],,1),0),MATCH(EmployeeVariances[[#Headers],[Jan]],EmployeePlan[#Headers],0))-INDEX(EmployeeActual[],MATCH(INDEX(EmployeeVariances[],ROW()-ROW(EmployeeVariances[[#Headers],[Jan]]),1),INDEX(EmployeePlan[],,1),0),MATCH(EmployeeVariances[[#Headers],[Jan]],EmployeeActual[#Headers],0)) | D8: =INDEX(EmployeePlan[],MATCH(INDEX(EmployeeVariances[],ROW()-ROW(EmployeeVariances[[#Headers],[Feb]]),1),INDEX(EmployeePlan[],,1),0),MATCH(EmployeeVariances[[#Headers],[Feb]],EmployeePlan[#Headers],0))-INDEX(EmployeeActual[],MATCH(INDEX(EmployeeVariances[],ROW()-ROW(EmployeeVariances[[#Headers],[Feb]]),1),INDEX(EmployeePlan[],,1),0),MATCH(EmployeeVariances[[#Headers],[Feb]],EmployeeActual[#Headers],0)) | E8: =INDEX(EmployeePlan[],MATCH(INDEX(EmployeeVariances[],ROW()-ROW(EmployeeVariances[[#Headers],[Mar]]),1),INDEX(EmployeePlan[],,1),0),MATCH(EmployeeVariances[[#Headers],[Mar]],EmployeePlan[#Headers],0))-INDEX(EmployeeActual[],MATCH(INDEX(EmployeeVariances[],ROW()-ROW(EmployeeVariances[[#Headers],[Mar]]),1),INDEX(EmployeePlan[],,1),0),MATCH(EmployeeVariances[[#Headers],[Mar]],EmployeeActual[#Headers],0)) | F8: =INDEX(EmployeePlan[],MATCH(INDEX(EmployeeVariances[],ROW()-ROW(EmployeeVariances[[#Headers],[Apr]]),1),INDEX(EmployeePlan[],,1),0),MATCH(EmployeeVariances[[#Headers],[Apr]],EmployeePlan[#Headers],0))-INDEX(EmployeeActual[],MATCH(INDEX(EmployeeVariances[],ROW()-ROW(EmployeeVariances[[#Headers],[Apr]]),1),INDEX(EmployeePlan[],,1),0),MATCH(EmployeeVariances[[#Headers],[Apr]],EmployeeActual[#Headers],0)) | G8: =INDEX(EmployeePlan[],MATCH(INDEX(EmployeeVariances[],ROW()-ROW(EmployeeVariances[[#Headers],[May]]),1),INDEX(EmployeePlan[],,1),0),MATCH(EmployeeVariances[[#Headers],[May]],EmployeePlan[#Headers],0))-INDEX(EmployeeActual[],MATCH(INDEX(EmployeeVariances[],ROW()-ROW(EmployeeVariances[[#Headers],[May]]),1),INDEX(EmployeePlan[],,1),0),MATCH(EmployeeVariances[[#Headers],[May]],EmployeeActual[#Headers],0)) | H8: =INDEX(EmployeePlan[],MATCH(INDEX(EmployeeVariances[],ROW()-ROW(EmployeeVariances[[#Headers],[Jun]]),1),INDEX(EmployeePlan[],,1),0),MATCH(EmployeeVariances[[#Headers],[Jun]],EmployeePlan[#Headers],0))-INDEX(EmployeeActual[],MATCH(INDEX(EmployeeVariances[],ROW()-ROW(EmployeeVariances[[#Headers],[Jun]]),1),INDEX(EmployeePlan[],,1),0),MATCH(EmployeeVariances[[#Headers],[Jun]],EmployeeActual[#Headers],0)) | I8: =INDEX(EmployeePlan[],MATCH(INDEX(EmployeeVariances[],ROW()-ROW(EmployeeVariances[[#Headers],[Jul]]),1),INDEX(EmployeePlan[],,1),0),MATCH(EmployeeVariances[[#Headers],[Jul]],EmployeePlan[#Headers],0))-INDEX(EmployeeActual[],MATCH(INDEX(EmployeeVariances[],ROW()-ROW(EmployeeVariances[[#Headers],[Jul]]),1),INDEX(EmployeePlan[],,1),0),MATCH(EmployeeVariances[[#Headers],[Jul]],EmployeeActual[#Headers],0)) | J8: =INDEX(EmployeePlan[],MATCH(INDEX(EmployeeVariances[],ROW()-ROW(EmployeeVariances[[#Headers],[Aug]]),1),INDEX(EmployeePlan[],,1),0),MATCH(EmployeeVariances[[#Headers],[Aug]],EmployeePlan[#Headers],0))-INDEX(EmployeeActual[],MATCH(INDEX(EmployeeVariances[],ROW()-ROW(EmployeeVariances[[#Headers],[Aug]]),1),INDEX(EmployeePlan[],,1),0),MATCH(EmployeeVariances[[#Headers],[Aug]],EmployeeActual[#Headers],0)) | K8: =INDEX(EmployeePlan[],MATCH(INDEX(EmployeeVariances[],ROW()-ROW(EmployeeVariances[[#Headers],[Sep]]),1),INDEX(EmployeePlan[],,1),0),MATCH(EmployeeVariances[[#Headers],[Sep]],EmployeePlan[#Headers],0))-INDEX(EmployeeActual[],MATCH(INDEX(EmployeeVariances[],ROW()-ROW(EmployeeVariances[[#Headers],[Sep]]),1),INDEX(EmployeePlan[],,1),0),MATCH(EmployeeVariances[[#Headers],[Sep]],EmployeeActual[#Headers],0)) | L8: =INDEX(EmployeePlan[],MATCH(INDEX(EmployeeVariances[],ROW()-ROW(EmployeeVariances[[#Headers],[Oct]]),1),INDEX(EmployeePlan[],,1),0),MATCH(EmployeeVariances[[#Headers],[Oct]],EmployeePlan[#Headers],0))-INDEX(EmployeeActual[],MATCH(INDEX(EmployeeVariances[],ROW()-ROW(EmployeeVariances[[#Headers],[Oct]]),1),INDEX(EmployeePlan[],,1),0),MATCH(EmployeeVariances[[#Headers],[Oct]],EmployeeActual[#Headers],0)) | M8: =INDEX(EmployeePlan[],MATCH(INDEX(EmployeeVariances[],ROW()-ROW(EmployeeVariances[[#Headers],[Nov]]),1),INDEX(EmployeePlan[],,1),0),MATCH(EmployeeVariances[[#Headers],[Nov]],EmployeePlan[#Headers],0))-INDEX(EmployeeActual[],MATCH(INDEX(EmployeeVariances[],ROW()-ROW(EmployeeVariances[[#Headers],[Nov]]),1),INDEX(EmployeePlan[],,1),0),MATCH(EmployeeVariances[[#Headers],[Nov]],EmployeeActual[#Headers],0)) | N8: =INDEX(EmployeePlan[],MATCH(INDEX(EmployeeVariances[],ROW()-ROW(EmployeeVariances[[#Headers],[Dec]]),1),INDEX(EmployeePlan[],,1),0),MATCH(EmployeeVariances[[#Headers],[Dec]],EmployeePlan[#Headers],0))-INDEX(EmployeeActual[],MATCH(INDEX(EmployeeVariances[],ROW()-ROW(EmployeeVariances[[#Headers],[Dec]]),1),INDEX(EmployeePlan[],,1),0),MATCH(EmployeeVariances[[#Headers],[Dec]],EmployeeActual[#Headers],0)) | O8: =SUM(EmployeeVariances[[#This Row],[Jan]:[Dec]])
B9: Subtotal | C9: =SUBTOTAL(109,EmployeeVariances[Jan]) | D9: =SUBTOTAL(109,EmployeeVariances[Feb]) | E9: =SUBTOTAL(109,EmployeeVariances[Mar]) | F9: =SUBTOTAL(109,EmployeeVariances[Apr]) | G9: =SUBTOTAL(109,EmployeeVariances[May]) | H9: =SUBTOTAL(109,EmployeeVariances[Jun]) | I9: =SUBTOTAL(109,EmployeeVariances[Jul]) | J9: =SUBTOTAL(109,EmployeeVariances[Aug]) | K9: =SUBTOTAL(109,EmployeeVariances[Sep]) | L9: =SUBTOTAL(109,EmployeeVariances[Oct]) | M9: =SUBTOTAL(109,EmployeeVariances[Nov]) | N9: =SUBTOTAL(109,EmployeeVariances[Dec]) | O9: =SUBTOTAL(109,EmployeeVariances[YEAR])
B11: Office costs | C11: Jan | D11: Feb | E11: Mar | F11: Apr | G11: May | H11: Jun | I11: Jul | J11: Aug | K11: Sep | L11: Oct | M11: Nov | N11: Dec | O11: YEAR
B12: Office lease | C12: =INDEX(OfficePlan[],MATCH(INDEX(OfficeVariances[],ROW()-ROW(OfficeVariances[[#Headers],[Jan]]),1),INDEX(OfficePlan[],,1),0),MATCH(OfficeVariances[[#Headers],[Jan]],OfficePlan[#Headers],0))-INDEX(OfficeActual[],MATCH(INDEX(OfficeVariances[],ROW()-ROW(OfficeVariances[[#Headers],[Jan]]),1),INDEX(OfficePlan[],,1),0),MATCH(OfficeVariances[[#Headers],[Jan]],OfficeActual[#Headers],0)) | D12: =INDEX(OfficePlan[],MATCH(INDEX(OfficeVariances[],ROW()-ROW(OfficeVariances[[#Headers],[Feb]]),1),INDEX(OfficePlan[],,1),0),MATCH(OfficeVariances[[#Headers],[Feb]],OfficePlan[#Headers],0))-INDEX(OfficeActual[],MATCH(INDEX(OfficeVariances[],ROW()-ROW(OfficeVariances[[#Headers],[Feb]]),1),INDEX(OfficePlan[],,1),0),MATCH(OfficeVariances[[#Headers],[Feb]],OfficeActual[#Headers],0)) | E12: =INDEX(OfficePlan[],MATCH(INDEX(OfficeVariances[],ROW()-ROW(OfficeVariances[[#Headers],[Mar]]),1),INDEX(OfficePlan[],,1),0),MATCH(OfficeVariances[[#Headers],[Mar]],OfficePlan[#Headers],0))-INDEX(OfficeActual[],MATCH(INDEX(OfficeVariances[],ROW()-ROW(OfficeVariances[[#Headers],[Mar]]),1),INDEX(OfficePlan[],,1),0),MATCH(OfficeVariances[[#Headers],[Mar]],OfficeActual[#Headers],0)) | F12: =INDEX(OfficePlan[],MATCH(INDEX(OfficeVariances[],ROW()-ROW(OfficeVariances[[#Headers],[Apr]]),1),INDEX(OfficePlan[],,1),0),MATCH(OfficeVariances[[#Headers],[Apr]],OfficePlan[#Headers],0))-INDEX(OfficeActual[],MATCH(INDEX(OfficeVariances[],ROW()-ROW(OfficeVariances[[#Headers],[Apr]]),1),INDEX(OfficePlan[],,1),0),MATCH(OfficeVariances[[#Headers],[Apr]],OfficeActual[#Headers],0)) | G12: =INDEX(OfficePlan[],MATCH(INDEX(OfficeVariances[],ROW()-ROW(OfficeVariances[[#Headers],[May]]),1),INDEX(OfficePlan[],,1),0),MATCH(OfficeVariances[[#Headers],[May]],OfficePlan[#Headers],0))-INDEX(OfficeActual[],MATCH(INDEX(OfficeVariances[],ROW()-ROW(OfficeVariances[[#Headers],[May]]),1),INDEX(OfficePlan[],,1),0),MATCH(OfficeVariances[[#Headers],[May]],OfficeActual[#Headers],0)) | H12: =INDEX(OfficePlan[],MATCH(INDEX(OfficeVariances[],ROW()-ROW(OfficeVariances[[#Headers],[Jun]]),1),INDEX(OfficePlan[],,1),0),MATCH(OfficeVariances[[#Headers],[Jun]],OfficePlan[#Headers],0))-INDEX(OfficeActual[],MATCH(INDEX(OfficeVariances[],ROW()-ROW(OfficeVariances[[#Headers],[Jun]]),1),INDEX(OfficePlan[],,1),0),MATCH(OfficeVariances[[#Headers],[Jun]],OfficeActual[#Headers],0)) | I12: =INDEX(OfficePlan[],MATCH(INDEX(OfficeVariances[],ROW()-ROW(OfficeVariances[[#Headers],[Jul]]),1),INDEX(OfficePlan[],,1),0),MATCH(OfficeVariances[[#Headers],[Jul]],OfficePlan[#Headers],0))-INDEX(OfficeActual[],MATCH(INDEX(OfficeVariances[],ROW()-ROW(OfficeVariances[[#Headers],[Jul]]),1),INDEX(OfficePlan[],,1),0),MATCH(OfficeVariances[[#Headers],[Jul]],OfficeActual[#Headers],0)) | J12: =INDEX(OfficePlan[],MATCH(INDEX(OfficeVariances[],ROW()-ROW(OfficeVariances[[#Headers],[Aug]]),1),INDEX(OfficePlan[],,1),0),MATCH(OfficeVariances[[#Headers],[Aug]],OfficePlan[#Headers],0))-INDEX(OfficeActual[],MATCH(INDEX(OfficeVariances[],ROW()-ROW(OfficeVariances[[#Headers],[Aug]]),1),INDEX(OfficePlan[],,1),0),MATCH(OfficeVariances[[#Headers],[Aug]],OfficeActual[#Headers],0)) | K12: =INDEX(OfficePlan[],MATCH(INDEX(OfficeVariances[],ROW()-ROW(OfficeVariances[[#Headers],[Sep]]),1),INDEX(OfficePlan[],,1),0),MATCH(OfficeVariances[[#Headers],[Sep]],OfficePlan[#Headers],0))-INDEX(OfficeActual[],MATCH(INDEX(OfficeVariances[],ROW()-ROW(OfficeVariances[[#Headers],[Sep]]),1),INDEX(OfficePlan[],,1),0),MATCH(OfficeVariances[[#Headers],[Sep]],OfficeActual[#Headers],0)) | L12: =INDEX(OfficePlan[],MATCH(INDEX(OfficeVariances[],ROW()-ROW(OfficeVariances[[#Headers],[Oct]]),1),INDEX(OfficePlan[],,1),0),MATCH(OfficeVariances[[#Headers],[Oct]],OfficePlan[#Headers],0))-INDEX(OfficeActual[],MATCH(INDEX(OfficeVariances[],ROW()-ROW(OfficeVariances[[#Headers],[Oct]]),1),INDEX(OfficePlan[],,1),0),MATCH(OfficeVariances[[#Headers],[Oct]],OfficeActual[#Headers],0)) | M12: =INDEX(OfficePlan[],MATCH(INDEX(OfficeVariances[],ROW()-ROW(OfficeVariances[[#Headers],[Nov]]),1),INDEX(OfficePlan[],,1),0),MATCH(OfficeVariances[[#Headers],[Nov]],OfficePlan[#Headers],0))-INDEX(OfficeActual[],MATCH(INDEX(OfficeVariances[],ROW()-ROW(OfficeVariances[[#Headers],[Nov]]),1),INDEX(OfficePlan[],,1),0),MATCH(OfficeVariances[[#Headers],[Nov]],OfficeActual[#Headers],0)) | N12: =INDEX(OfficePlan[],MATCH(INDEX(OfficeVariances[],ROW()-ROW(OfficeVariances[[#Headers],[Dec]]),1),INDEX(OfficePlan[],,1),0),MATCH(OfficeVariances[[#Headers],[Dec]],OfficePlan[#Headers],0))-INDEX(OfficeActual[],MATCH(INDEX(OfficeVariances[],ROW()-ROW(OfficeVariances[[#Headers],[Dec]]),1),INDEX(OfficePlan[],,1),0),MATCH(OfficeVariances[[#Headers],[Dec]],OfficeActual[#Headers],0)) | O12: =SUM(OfficeVariances[[#This Row],[Jan]:[Dec]])
B13: Gas | C13: =INDEX(OfficePlan[],MATCH(INDEX(OfficeVariances[],ROW()-ROW(OfficeVariances[[#Headers],[Jan]]),1),INDEX(OfficePlan[],,1),0),MATCH(OfficeVariances[[#Headers],[Jan]],OfficePlan[#Headers],0))-INDEX(OfficeActual[],MATCH(INDEX(OfficeVariances[],ROW()-ROW(OfficeVariances[[#Headers],[Jan]]),1),INDEX(OfficePlan[],,1),0),MATCH(OfficeVariances[[#Headers],[Jan]],OfficeActual[#Headers],0)) | D13: =INDEX(OfficePlan[],MATCH(INDEX(OfficeVariances[],ROW()-ROW(OfficeVariances[[#Headers],[Feb]]),1),INDEX(OfficePlan[],,1),0),MATCH(OfficeVariances[[#Headers],[Feb]],OfficePlan[#Headers],0))-INDEX(OfficeActual[],MATCH(INDEX(OfficeVariances[],ROW()-ROW(OfficeVariances[[#Headers],[Feb]]),1),INDEX(OfficePlan[],,1),0),MATCH(OfficeVariances[[#Headers],[Feb]],OfficeActual[#Headers],0)) | E13: =INDEX(OfficePlan[],MATCH(INDEX(OfficeVariances[],ROW()-ROW(OfficeVariances[[#Headers],[Mar]]),1),INDEX(OfficePlan[],,1),0),MATCH(OfficeVariances[[#Headers],[Mar]],OfficePlan[#Headers],0))-INDEX(OfficeActual[],MATCH(INDEX(OfficeVariances[],ROW()-ROW(OfficeVariances[[#Headers],[Mar]]),1),INDEX(OfficePlan[],,1),0),MATCH(OfficeVariances[[#Headers],[Mar]],OfficeActual[#Headers],0)) | F13: =INDEX(OfficePlan[],MATCH(INDEX(OfficeVariances[],ROW()-ROW(OfficeVariances[[#Headers],[Apr]]),1),INDEX(OfficePlan[],,1),0),MATCH(OfficeVariances[[#Headers],[Apr]],OfficePlan[#Headers],0))-INDEX(OfficeActual[],MATCH(INDEX(OfficeVariances[],ROW()-ROW(OfficeVariances[[#Headers],[Apr]]),1),INDEX(OfficePlan[],,1),0),MATCH(OfficeVariances[[#Headers],[Apr]],OfficeActual[#Headers],0)) | G13: =INDEX(OfficePlan[],MATCH(INDEX(OfficeVariances[],ROW()-ROW(OfficeVariances[[#Headers],[May]]),1),INDEX(OfficePlan[],,1),0),MATCH(OfficeVariances[[#Headers],[May]],OfficePlan[#Headers],0))-INDEX(OfficeActual[],MATCH(INDEX(OfficeVariances[],ROW()-ROW(OfficeVariances[[#Headers],[May]]),1),INDEX(OfficePlan[],,1),0),MATCH(OfficeVariances[[#Headers],[May]],OfficeActual[#Headers],0)) | H13: =INDEX(OfficePlan[],MATCH(INDEX(OfficeVariances[],ROW()-ROW(OfficeVariances[[#Headers],[Jun]]),1),INDEX(OfficePlan[],,1),0),MATCH(OfficeVariances[[#Headers],[Jun]],OfficePlan[#Headers],0))-INDEX(OfficeActual[],MATCH(INDEX(OfficeVariances[],ROW()-ROW(OfficeVariances[[#Headers],[Jun]]),1),INDEX(OfficePlan[],,1),0),MATCH(OfficeVariances[[#Headers],[Jun]],OfficeActual[#Headers],0)) | I13: =INDEX(OfficePlan[],MATCH(INDEX(OfficeVariances[],ROW()-ROW(OfficeVariances[[#Headers],[Jul]]),1),INDEX(OfficePlan[],,1),0),MATCH(OfficeVariances[[#Headers],[Jul]],OfficePlan[#Headers],0))-INDEX(OfficeActual[],MATCH(INDEX(OfficeVariances[],ROW()-ROW(OfficeVariances[[#Headers],[Jul]]),1),INDEX(OfficePlan[],,1),0),MATCH(OfficeVariances[[#Headers],[Jul]],OfficeActual[#Headers],0)) | J13: =INDEX(OfficePlan[],MATCH(INDEX(OfficeVariances[],ROW()-ROW(OfficeVariances[[#Headers],[Aug]]),1),INDEX(OfficePlan[],,1),0),MATCH(OfficeVariances[[#Headers],[Aug]],OfficePlan[#Headers],0))-INDEX(OfficeActual[],MATCH(INDEX(OfficeVariances[],ROW()-ROW(OfficeVariances[[#Headers],[Aug]]),1),INDEX(OfficePlan[],,1),0),MATCH(OfficeVariances[[#Headers],[Aug]],OfficeActual[#Headers],0)) | K13: =INDEX(OfficePlan[],MATCH(INDEX(OfficeVariances[],ROW()-ROW(OfficeVariances[[#Headers],[Sep]]),1),INDEX(OfficePlan[],,1),0),MATCH(OfficeVariances[[#Headers],[Sep]],OfficePlan[#Headers],0))-INDEX(OfficeActual[],MATCH(INDEX(OfficeVariances[],ROW()-ROW(OfficeVariances[[#Headers],[Sep]]),1),INDEX(OfficePlan[],,1),0),MATCH(OfficeVariances[[#Headers],[Sep]],OfficeActual[#Headers],0)) | L13: =INDEX(OfficePlan[],MATCH(INDEX(OfficeVariances[],ROW()-ROW(OfficeVariances[[#Headers],[Oct]]),1),INDEX(OfficePlan[],,1),0),MATCH(OfficeVariances[[#Headers],[Oct]],OfficePlan[#Headers],0))-INDEX(OfficeActual[],MATCH(INDEX(OfficeVariances[],ROW()-ROW(OfficeVariances[[#Headers],[Oct]]),1),INDEX(OfficePlan[],,1),0),MATCH(OfficeVariances[[#Headers],[Oct]],OfficeActual[#Headers],0)) | M13: =INDEX(OfficePlan[],MATCH(INDEX(OfficeVariances[],ROW()-ROW(OfficeVariances[[#Headers],[Nov]]),1),INDEX(OfficePlan[],,1),0),MATCH(OfficeVariances[[#Headers],[Nov]],OfficePlan[#Headers],0))-INDEX(OfficeActual[],MATCH(INDEX(OfficeVariances[],ROW()-ROW(OfficeVariances[[#Headers],[Nov]]),1),INDEX(OfficePlan[],,1),0),MATCH(OfficeVariances[[#Headers],[Nov]],OfficeActual[#Headers],0)) | N13: =INDEX(OfficePlan[],MATCH(INDEX(OfficeVariances[],ROW()-ROW(OfficeVariances[[#Headers],[Dec]]),1),INDEX(OfficePlan[],,1),0),MATCH(OfficeVariances[[#Headers],[Dec]],OfficePlan[#Headers],0))-INDEX(OfficeActual[],MATCH(INDEX(OfficeVariances[],ROW()-ROW(OfficeVariances[[#Headers],[Dec]]),1),INDEX(OfficePlan[],,1),0),MATCH(OfficeVariances[[#Headers],[Dec]],OfficeActual[#Headers],0)) | O13: =SUM(OfficeVariances[[#This Row],[Jan]:[Dec]])
B14: Electric | C14: =INDEX(OfficePlan[],MATCH(INDEX(OfficeVariances[],ROW()-ROW(OfficeVariances[[#Headers],[Jan]]),1),INDEX(OfficePlan[],,1),0),MATCH(OfficeVariances[[#Headers],[Jan]],OfficePlan[#Headers],0))-INDEX(OfficeActual[],MATCH(INDEX(OfficeVariances[],ROW()-ROW(OfficeVariances[[#Headers],[Jan]]),1),INDEX(OfficePlan[],,1),0),MATCH(OfficeVariances[[#Headers],[Jan]],OfficeActual[#Headers],0)) | D14: =INDEX(OfficePlan[],MATCH(INDEX(OfficeVariances[],ROW()-ROW(OfficeVariances[[#Headers],[Feb]]),1),INDEX(OfficePlan[],,1),0),MATCH(OfficeVariances[[#Headers],[Feb]],OfficePlan[#Headers],0))-INDEX(OfficeActual[],MATCH(INDEX(OfficeVariances[],ROW()-ROW(OfficeVariances[[#Headers],[Feb]]),1),INDEX(OfficePlan[],,1),0),MATCH(OfficeVariances[[#Headers],[Feb]],OfficeActual[#Headers],0)) | E14: =INDEX(OfficePlan[],MATCH(INDEX(OfficeVariances[],ROW()-ROW(OfficeVariances[[#Headers],[Mar]]),1),INDEX(OfficePlan[],,1),0),MATCH(OfficeVariances[[#Headers],[Mar]],OfficePlan[#Headers],0))-INDEX(OfficeActual[],MATCH(INDEX(OfficeVariances[],ROW()-ROW(OfficeVariances[[#Headers],[Mar]]),1),INDEX(OfficePlan[],,1),0),MATCH(OfficeVariances[[#Headers],[Mar]],OfficeActual[#Headers],0)) | F14: =INDEX(OfficePlan[],MATCH(INDEX(OfficeVariances[],ROW()-ROW(OfficeVariances[[#Headers],[Apr]]),1),INDEX(OfficePlan[],,1),0),MATCH(OfficeVariances[[#Headers],[Apr]],OfficePlan[#Headers],0))-INDEX(OfficeActual[],MATCH(INDEX(OfficeVariances[],ROW()-ROW(OfficeVariances[[#Headers],[Apr]]),1),INDEX(OfficePlan[],,1),0),MATCH(OfficeVariances[[#Headers],[Apr]],OfficeActual[#Headers],0)) | G14: =INDEX(OfficePlan[],MATCH(INDEX(OfficeVariances[],ROW()-ROW(OfficeVariances[[#Headers],[May]]),1),INDEX(OfficePlan[],,1),0),MATCH(OfficeVariances[[#Headers],[May]],OfficePlan[#Headers],0))-INDEX(OfficeActual[],MATCH(INDEX(OfficeVariances[],ROW()-ROW(OfficeVariances[[#Headers],[May]]),1),INDEX(OfficePlan[],,1),0),MATCH(OfficeVariances[[#Headers],[May]],OfficeActual[#Headers],0)) | H14: =INDEX(OfficePlan[],MATCH(INDEX(OfficeVariances[],ROW()-ROW(OfficeVariances[[#Headers],[Jun]]),1),INDEX(OfficePlan[],,1),0),MATCH(OfficeVariances[[#Headers],[Jun]],OfficePlan[#Headers],0))-INDEX(OfficeActual[],MATCH(INDEX(OfficeVariances[],ROW()-ROW(OfficeVariances[[#Headers],[Jun]]),1),INDEX(OfficePlan[],,1),0),MATCH(OfficeVariances[[#Headers],[Jun]],OfficeActual[#Headers],0)) | I14: =INDEX(OfficePlan[],MATCH(INDEX(OfficeVariances[],ROW()-ROW(OfficeVariances[[#Headers],[Jul]]),1),INDEX(OfficePlan[],,1),0),MATCH(OfficeVariances[[#Headers],[Jul]],OfficePlan[#Headers],0))-INDEX(OfficeActual[],MATCH(INDEX(OfficeVariances[],ROW()-ROW(OfficeVariances[[#Headers],[Jul]]),1),INDEX(OfficePlan[],,1),0),MATCH(OfficeVariances[[#Headers],[Jul]],OfficeActual[#Headers],0)) | J14: =INDEX(OfficePlan[],MATCH(INDEX(OfficeVariances[],ROW()-ROW(OfficeVariances[[#Headers],[Aug]]),1),INDEX(OfficePlan[],,1),0),MATCH(OfficeVariances[[#Headers],[Aug]],OfficePlan[#Headers],0))-INDEX(OfficeActual[],MATCH(INDEX(OfficeVariances[],ROW()-ROW(OfficeVariances[[#Headers],[Aug]]),1),INDEX(OfficePlan[],,1),0),MATCH(OfficeVariances[[#Headers],[Aug]],OfficeActual[#Headers],0)) | K14: =INDEX(OfficePlan[],MATCH(INDEX(OfficeVariances[],ROW()-ROW(OfficeVariances[[#Headers],[Sep]]),1),INDEX(OfficePlan[],,1),0),MATCH(OfficeVariances[[#Headers],[Sep]],OfficePlan[#Headers],0))-INDEX(OfficeActual[],MATCH(INDEX(OfficeVariances[],ROW()-ROW(OfficeVariances[[#Headers],[Sep]]),1),INDEX(OfficePlan[],,1),0),MATCH(OfficeVariances[[#Headers],[Sep]],OfficeActual[#Headers],0)) | L14: =INDEX(OfficePlan[],MATCH(INDEX(OfficeVariances[],ROW()-ROW(OfficeVariances[[#Headers],[Oct]]),1),INDEX(OfficePlan[],,1),0),MATCH(OfficeVariances[[#Headers],[Oct]],OfficePlan[#Headers],0))-INDEX(OfficeActual[],MATCH(INDEX(OfficeVariances[],ROW()-ROW(OfficeVariances[[#Headers],[Oct]]),1),INDEX(OfficePlan[],,1),0),MATCH(OfficeVariances[[#Headers],[Oct]],OfficeActual[#Headers],0)) | M14: =INDEX(OfficePlan[],MATCH(INDEX(OfficeVariances[],ROW()-ROW(OfficeVariances[[#Headers],[Nov]]),1),INDEX(OfficePlan[],,1),0),MATCH(OfficeVariances[[#Headers],[Nov]],OfficePlan[#Headers],0))-INDEX(OfficeActual[],MATCH(INDEX(OfficeVariances[],ROW()-ROW(OfficeVariances[[#Headers],[Nov]]),1),INDEX(OfficePlan[],,1),0),MATCH(OfficeVariances[[#Headers],[Nov]],OfficeActual[#Headers],0)) | N14: =INDEX(OfficePlan[],MATCH(INDEX(OfficeVariances[],ROW()-ROW(OfficeVariances[[#Headers],[Dec]]),1),INDEX(OfficePlan[],,1),0),MATCH(OfficeVariances[[#Headers],[Dec]],OfficePlan[#Headers],0))-INDEX(OfficeActual[],MATCH(INDEX(OfficeVariances[],ROW()-ROW(OfficeVariances[[#Headers],[Dec]]),1),INDEX(OfficePlan[],,1),0),MATCH(OfficeVariances[[#Headers],[Dec]],OfficeActual[#Headers],0)) | O14: =SUM(OfficeVariances[[#This Row],[Jan]:[Dec]])
B15: Water | C15: =INDEX(OfficePlan[],MATCH(INDEX(OfficeVariances[],ROW()-ROW(OfficeVariances[[#Headers],[Jan]]),1),INDEX(OfficePlan[],,1),0),MATCH(OfficeVariances[[#Headers],[Jan]],OfficePlan[#Headers],0))-INDEX(OfficeActual[],MATCH(INDEX(OfficeVariances[],ROW()-ROW(OfficeVariances[[#Headers],[Jan]]),1),INDEX(OfficePlan[],,1),0),MATCH(OfficeVariances[[#Headers],[Jan]],OfficeActual[#Headers],0)) | D15: =INDEX(OfficePlan[],MATCH(INDEX(OfficeVariances[],ROW()-ROW(OfficeVariances[[#Headers],[Feb]]),1),INDEX(OfficePlan[],,1),0),MATCH(OfficeVariances[[#Headers],[Feb]],OfficePlan[#Headers],0))-INDEX(OfficeActual[],MATCH(INDEX(OfficeVariances[],ROW()-ROW(OfficeVariances[[#Headers],[Feb]]),1),INDEX(OfficePlan[],,1),0),MATCH(OfficeVariances[[#Headers],[Feb]],OfficeActual[#Headers],0)) | E15: =INDEX(OfficePlan[],MATCH(INDEX(OfficeVariances[],ROW()-ROW(OfficeVariances[[#Headers],[Mar]]),1),INDEX(OfficePlan[],,1),0),MATCH(OfficeVariances[[#Headers],[Mar]],OfficePlan[#Headers],0))-INDEX(OfficeActual[],MATCH(INDEX(OfficeVariances[],ROW()-ROW(OfficeVariances[[#Headers],[Mar]]),1),INDEX(OfficePlan[],,1),0),MATCH(OfficeVariances[[#Headers],[Mar]],OfficeActual[#Headers],0)) | F15: =INDEX(OfficePlan[],MATCH(INDEX(OfficeVariances[],ROW()-ROW(OfficeVariances[[#Headers],[Apr]]),1),INDEX(OfficePlan[],,1),0),MATCH(OfficeVariances[[#Headers],[Apr]],OfficePlan[#Headers],0))-INDEX(OfficeActual[],MATCH(INDEX(OfficeVariances[],ROW()-ROW(OfficeVariances[[#Headers],[Apr]]),1),INDEX(OfficePlan[],,1),0),MATCH(OfficeVariances[[#Headers],[Apr]],OfficeActual[#Headers],0)) | G15: =INDEX(OfficePlan[],MATCH(INDEX(OfficeVariances[],ROW()-ROW(OfficeVariances[[#Headers],[May]]),1),INDEX(OfficePlan[],,1),0),MATCH(OfficeVariances[[#Headers],[May]],OfficePlan[#Headers],0))-INDEX(OfficeActual[],MATCH(INDEX(OfficeVariances[],ROW()-ROW(OfficeVariances[[#Headers],[May]]),1),INDEX(OfficePlan[],,1),0),MATCH(OfficeVariances[[#Headers],[May]],OfficeActual[#Headers],0)) | H15: =INDEX(OfficePlan[],MATCH(INDEX(OfficeVariances[],ROW()-ROW(OfficeVariances[[#Headers],[Jun]]),1),INDEX(OfficePlan[],,1),0),MATCH(OfficeVariances[[#Headers],[Jun]],OfficePlan[#Headers],0))-INDEX(OfficeActual[],MATCH(INDEX(OfficeVariances[],ROW()-ROW(OfficeVariances[[#Headers],[Jun]]),1),INDEX(OfficePlan[],,1),0),MATCH(OfficeVariances[[#Headers],[Jun]],OfficeActual[#Headers],0)) | I15: =INDEX(OfficePlan[],MATCH(INDEX(OfficeVariances[],ROW()-ROW(OfficeVariances[[#Headers],[Jul]]),1),INDEX(OfficePlan[],,1),0),MATCH(OfficeVariances[[#Headers],[Jul]],OfficePlan[#Headers],0))-INDEX(OfficeActual[],MATCH(INDEX(OfficeVariances[],ROW()-ROW(OfficeVariances[[#Headers],[Jul]]),1),INDEX(OfficePlan[],,1),0),MATCH(OfficeVariances[[#Headers],[Jul]],OfficeActual[#Headers],0)) | J15: =INDEX(OfficePlan[],MATCH(INDEX(OfficeVariances[],ROW()-ROW(OfficeVariances[[#Headers],[Aug]]),1),INDEX(OfficePlan[],,1),0),MATCH(OfficeVariances[[#Headers],[Aug]],OfficePlan[#Headers],0))-INDEX(OfficeActual[],MATCH(INDEX(OfficeVariances[],ROW()-ROW(OfficeVariances[[#Headers],[Aug]]),1),INDEX(OfficePlan[],,1),0),MATCH(OfficeVariances[[#Headers],[Aug]],OfficeActual[#Headers],0)) | K15: =INDEX(OfficePlan[],MATCH(INDEX(OfficeVariances[],ROW()-ROW(OfficeVariances[[#Headers],[Sep]]),1),INDEX(OfficePlan[],,1),0),MATCH(OfficeVariances[[#Headers],[Sep]],OfficePlan[#Headers],0))-INDEX(OfficeActual[],MATCH(INDEX(OfficeVariances[],ROW()-ROW(OfficeVariances[[#Headers],[Sep]]),1),INDEX(OfficePlan[],,1),0),MATCH(OfficeVariances[[#Headers],[Sep]],OfficeActual[#Headers],0)) | L15: =INDEX(OfficePlan[],MATCH(INDEX(OfficeVariances[],ROW()-ROW(OfficeVariances[[#Headers],[Oct]]),1),INDEX(OfficePlan[],,1),0),MATCH(OfficeVariances[[#Headers],[Oct]],OfficePlan[#Headers],0))-INDEX(OfficeActual[],MATCH(INDEX(OfficeVariances[],ROW()-ROW(OfficeVariances[[#Headers],[Oct]]),1),INDEX(OfficePlan[],,1),0),MATCH(OfficeVariances[[#Headers],[Oct]],OfficeActual[#Headers],0)) | M15: =INDEX(OfficePlan[],MATCH(INDEX(OfficeVariances[],ROW()-ROW(OfficeVariances[[#Headers],[Nov]]),1),INDEX(OfficePlan[],,1),0),MATCH(OfficeVariances[[#Headers],[Nov]],OfficePlan[#Headers],0))-INDEX(OfficeActual[],MATCH(INDEX(OfficeVariances[],ROW()-ROW(OfficeVariances[[#Headers],[Nov]]),1),INDEX(OfficePlan[],,1),0),MATCH(OfficeVariances[[#Headers],[Nov]],OfficeActual[#Headers],0)) | N15: =INDEX(OfficePlan[],MATCH(INDEX(OfficeVariances[],ROW()-ROW(OfficeVariances[[#Headers],[Dec]]),1),INDEX(OfficePlan[],,1),0),MATCH(OfficeVariances[[#Headers],[Dec]],OfficePlan[#Headers],0))-INDEX(OfficeActual[],MATCH(INDEX(OfficeVariances[],ROW()-ROW(OfficeVariances[[#Headers],[Dec]]),1),INDEX(OfficePlan[],,1),0),MATCH(OfficeVariances[[#Headers],[Dec]],OfficeActual[#Headers],0)) | O15: =SUM(OfficeVariances[[#This Row],[Jan]:[Dec]])
B16: Telephone | C16: =INDEX(OfficePlan[],MATCH(INDEX(OfficeVariances[],ROW()-ROW(OfficeVariances[[#Headers],[Jan]]),1),INDEX(OfficePlan[],,1),0),MATCH(OfficeVariances[[#Headers],[Jan]],OfficePlan[#Headers],0))-INDEX(OfficeActual[],MATCH(INDEX(OfficeVariances[],ROW()-ROW(OfficeVariances[[#Headers],[Jan]]),1),INDEX(OfficePlan[],,1),0),MATCH(OfficeVariances[[#Headers],[Jan]],OfficeActual[#Headers],0)) | D16: =INDEX(OfficePlan[],MATCH(INDEX(OfficeVariances[],ROW()-ROW(OfficeVariances[[#Headers],[Feb]]),1),INDEX(OfficePlan[],,1),0),MATCH(OfficeVariances[[#Headers],[Feb]],OfficePlan[#Headers],0))-INDEX(OfficeActual[],MATCH(INDEX(OfficeVariances[],ROW()-ROW(OfficeVariances[[#Headers],[Feb]]),1),INDEX(OfficePlan[],,1),0),MATCH(OfficeVariances[[#Headers],[Feb]],OfficeActual[#Headers],0)) | E16: =INDEX(OfficePlan[],MATCH(INDEX(OfficeVariances[],ROW()-ROW(OfficeVariances[[#Headers],[Mar]]),1),INDEX(OfficePlan[],,1),0),MATCH(OfficeVariances[[#Headers],[Mar]],OfficePlan[#Headers],0))-INDEX(OfficeActual[],MATCH(INDEX(OfficeVariances[],ROW()-ROW(OfficeVariances[[#Headers],[Mar]]),1),INDEX(OfficePlan[],,1),0),MATCH(OfficeVariances[[#Headers],[Mar]],OfficeActual[#Headers],0)) | F16: =INDEX(OfficePlan[],MATCH(INDEX(OfficeVariances[],ROW()-ROW(OfficeVariances[[#Headers],[Apr]]),1),INDEX(OfficePlan[],,1),0),MATCH(OfficeVariances[[#Headers],[Apr]],OfficePlan[#Headers],0))-INDEX(OfficeActual[],MATCH(INDEX(OfficeVariances[],ROW()-ROW(OfficeVariances[[#Headers],[Apr]]),1),INDEX(OfficePlan[],,1),0),MATCH(OfficeVariances[[#Headers],[Apr]],OfficeActual[#Headers],0)) | G16: =INDEX(OfficePlan[],MATCH(INDEX(OfficeVariances[],ROW()-ROW(OfficeVariances[[#Headers],[May]]),1),INDEX(OfficePlan[],,1),0),MATCH(OfficeVariances[[#Headers],[May]],OfficePlan[#Headers],0))-INDEX(OfficeActual[],MATCH(INDEX(OfficeVariances[],ROW()-ROW(OfficeVariances[[#Headers],[May]]),1),INDEX(OfficePlan[],,1),0),MATCH(OfficeVariances[[#Headers],[May]],OfficeActual[#Headers],0)) | H16: =INDEX(OfficePlan[],MATCH(INDEX(OfficeVariances[],ROW()-ROW(OfficeVariances[[#Headers],[Jun]]),1),INDEX(OfficePlan[],,1),0),MATCH(OfficeVariances[[#Headers],[Jun]],OfficePlan[#Headers],0))-INDEX(OfficeActual[],MATCH(INDEX(OfficeVariances[],ROW()-ROW(OfficeVariances[[#Headers],[Jun]]),1),INDEX(OfficePlan[],,1),0),MATCH(OfficeVariances[[#Headers],[Jun]],OfficeActual[#Headers],0)) | I16: =INDEX(OfficePlan[],MATCH(INDEX(OfficeVariances[],ROW()-ROW(OfficeVariances[[#Headers],[Jul]]),1),INDEX(OfficePlan[],,1),0),MATCH(OfficeVariances[[#Headers],[Jul]],OfficePlan[#Headers],0))-INDEX(OfficeActual[],MATCH(INDEX(OfficeVariances[],ROW()-ROW(OfficeVariances[[#Headers],[Jul]]),1),INDEX(OfficePlan[],,1),0),MATCH(OfficeVariances[[#Headers],[Jul]],OfficeActual[#Headers],0)) | J16: =INDEX(OfficePlan[],MATCH(INDEX(OfficeVariances[],ROW()-ROW(OfficeVariances[[#Headers],[Aug]]),1),INDEX(OfficePlan[],,1),0),MATCH(OfficeVariances[[#Headers],[Aug]],OfficePlan[#Headers],0))-INDEX(OfficeActual[],MATCH(INDEX(OfficeVariances[],ROW()-ROW(OfficeVariances[[#Headers],[Aug]]),1),INDEX(OfficePlan[],,1),0),MATCH(OfficeVariances[[#Headers],[Aug]],OfficeActual[#Headers],0)) | K16: =INDEX(OfficePlan[],MATCH(INDEX(OfficeVariances[],ROW()-ROW(OfficeVariances[[#Headers],[Sep]]),1),INDEX(OfficePlan[],,1),0),MATCH(OfficeVariances[[#Headers],[Sep]],OfficePlan[#Headers],0))-INDEX(OfficeActual[],MATCH(INDEX(OfficeVariances[],ROW()-ROW(OfficeVariances[[#Headers],[Sep]]),1),INDEX(OfficePlan[],,1),0),MATCH(OfficeVariances[[#Headers],[Sep]],OfficeActual[#Headers],0)) | L16: =INDEX(OfficePlan[],MATCH(INDEX(OfficeVariances[],ROW()-ROW(OfficeVariances[[#Headers],[Oct]]),1),INDEX(OfficePlan[],,1),0),MATCH(OfficeVariances[[#Headers],[Oct]],OfficePlan[#Headers],0))-INDEX(OfficeActual[],MATCH(INDEX(OfficeVariances[],ROW()-ROW(OfficeVariances[[#Headers],[Oct]]),1),INDEX(OfficePlan[],,1),0),MATCH(OfficeVariances[[#Headers],[Oct]],OfficeActual[#Headers],0)) | M16: =INDEX(OfficePlan[],MATCH(INDEX(OfficeVariances[],ROW()-ROW(OfficeVariances[[#Headers],[Nov]]),1),INDEX(OfficePlan[],,1),0),MATCH(OfficeVariances[[#Headers],[Nov]],OfficePlan[#Headers],0))-INDEX(OfficeActual[],MATCH(INDEX(OfficeVariances[],ROW()-ROW(OfficeVariances[[#Headers],[Nov]]),1),INDEX(OfficePlan[],,1),0),MATCH(OfficeVariances[[#Headers],[Nov]],OfficeActual[#Headers],0)) | N16: =INDEX(OfficePlan[],MATCH(INDEX(OfficeVariances[],ROW()-ROW(OfficeVariances[[#Headers],[Dec]]),1),INDEX(OfficePlan[],,1),0),MATCH(OfficeVariances[[#Headers],[Dec]],OfficePlan[#Headers],0))-INDEX(OfficeActual[],MATCH(INDEX(OfficeVariances[],ROW()-ROW(OfficeVariances[[#Headers],[Dec]]),1),INDEX(OfficePlan[],,1),0),MATCH(OfficeVariances[[#Headers],[Dec]],OfficeActual[#Headers],0)) | O16: =SUM(OfficeVariances[[#This Row],[Jan]:[Dec]])
B17: Internet access | C17: =INDEX(OfficePlan[],MATCH(INDEX(OfficeVariances[],ROW()-ROW(OfficeVariances[[#Headers],[Jan]]),1),INDEX(OfficePlan[],,1),0),MATCH(OfficeVariances[[#Headers],[Jan]],OfficePlan[#Headers],0))-INDEX(OfficeActual[],MATCH(INDEX(OfficeVariances[],ROW()-ROW(OfficeVariances[[#Headers],[Jan]]),1),INDEX(OfficePlan[],,1),0),MATCH(OfficeVariances[[#Headers],[Jan]],OfficeActual[#Headers],0)) | D17: =INDEX(OfficePlan[],MATCH(INDEX(OfficeVariances[],ROW()-ROW(OfficeVariances[[#Headers],[Feb]]),1),INDEX(OfficePlan[],,1),0),MATCH(OfficeVariances[[#Headers],[Feb]],OfficePlan[#Headers],0))-INDEX(OfficeActual[],MATCH(INDEX(OfficeVariances[],ROW()-ROW(OfficeVariances[[#Headers],[Feb]]),1),INDEX(OfficePlan[],,1),0),MATCH(OfficeVariances[[#Headers],[Feb]],OfficeActual[#Headers],0)) | E17: =INDEX(OfficePlan[],MATCH(INDEX(OfficeVariances[],ROW()-ROW(OfficeVariances[[#Headers],[Mar]]),1),INDEX(OfficePlan[],,1),0),MATCH(OfficeVariances[[#Headers],[Mar]],OfficePlan[#Headers],0))-INDEX(OfficeActual[],MATCH(INDEX(OfficeVariances[],ROW()-ROW(OfficeVariances[[#Headers],[Mar]]),1),INDEX(OfficePlan[],,1),0),MATCH(OfficeVariances[[#Headers],[Mar]],OfficeActual[#Headers],0)) | F17: =INDEX(OfficePlan[],MATCH(INDEX(OfficeVariances[],ROW()-ROW(OfficeVariances[[#Headers],[Apr]]),1),INDEX(OfficePlan[],,1),0),MATCH(OfficeVariances[[#Headers],[Apr]],OfficePlan[#Headers],0))-INDEX(OfficeActual[],MATCH(INDEX(OfficeVariances[],ROW()-ROW(OfficeVariances[[#Headers],[Apr]]),1),INDEX(OfficePlan[],,1),0),MATCH(OfficeVariances[[#Headers],[Apr]],OfficeActual[#Headers],0)) | G17: =INDEX(OfficePlan[],MATCH(INDEX(OfficeVariances[],ROW()-ROW(OfficeVariances[[#Headers],[May]]),1),INDEX(OfficePlan[],,1),0),MATCH(OfficeVariances[[#Headers],[May]],OfficePlan[#Headers],0))-INDEX(OfficeActual[],MATCH(INDEX(OfficeVariances[],ROW()-ROW(OfficeVariances[[#Headers],[May]]),1),INDEX(OfficePlan[],,1),0),MATCH(OfficeVariances[[#Headers],[May]],OfficeActual[#Headers],0)) | H17: =INDEX(OfficePlan[],MATCH(INDEX(OfficeVariances[],ROW()-ROW(OfficeVariances[[#Headers],[Jun]]),1),INDEX(OfficePlan[],,1),0),MATCH(OfficeVariances[[#Headers],[Jun]],OfficePlan[#Headers],0))-INDEX(OfficeActual[],MATCH(INDEX(OfficeVariances[],ROW()-ROW(OfficeVariances[[#Headers],[Jun]]),1),INDEX(OfficePlan[],,1),0),MATCH(OfficeVariances[[#Headers],[Jun]],OfficeActual[#Headers],0)) | I17: =INDEX(OfficePlan[],MATCH(INDEX(OfficeVariances[],ROW()-ROW(OfficeVariances[[#Headers],[Jul]]),1),INDEX(OfficePlan[],,1),0),MATCH(OfficeVariances[[#Headers],[Jul]],OfficePlan[#Headers],0))-INDEX(OfficeActual[],MATCH(INDEX(OfficeVariances[],ROW()-ROW(OfficeVariances[[#Headers],[Jul]]),1),INDEX(OfficePlan[],,1),0),MATCH(OfficeVariances[[#Headers],[Jul]],OfficeActual[#Headers],0)) | J17: =INDEX(OfficePlan[],MATCH(INDEX(OfficeVariances[],ROW()-ROW(OfficeVariances[[#Headers],[Aug]]),1),INDEX(OfficePlan[],,1),0),MATCH(OfficeVariances[[#Headers],[Aug]],OfficePlan[#Headers],0))-INDEX(OfficeActual[],MATCH(INDEX(OfficeVariances[],ROW()-ROW(OfficeVariances[[#Headers],[Aug]]),1),INDEX(OfficePlan[],,1),0),MATCH(OfficeVariances[[#Headers],[Aug]],OfficeActual[#Headers],0)) | K17: =INDEX(OfficePlan[],MATCH(INDEX(OfficeVariances[],ROW()-ROW(OfficeVariances[[#Headers],[Sep]]),1),INDEX(OfficePlan[],,1),0),MATCH(OfficeVariances[[#Headers],[Sep]],OfficePlan[#Headers],0))-INDEX(OfficeActual[],MATCH(INDEX(OfficeVariances[],ROW()-ROW(OfficeVariances[[#Headers],[Sep]]),1),INDEX(OfficePlan[],,1),0),MATCH(OfficeVariances[[#Headers],[Sep]],OfficeActual[#Headers],0)) | L17: =INDEX(OfficePlan[],MATCH(INDEX(OfficeVariances[],ROW()-ROW(OfficeVariances[[#Headers],[Oct]]),1),INDEX(OfficePlan[],,1),0),MATCH(OfficeVariances[[#Headers],[Oct]],OfficePlan[#Headers],0))-INDEX(OfficeActual[],MATCH(INDEX(OfficeVariances[],ROW()-ROW(OfficeVariances[[#Headers],[Oct]]),1),INDEX(OfficePlan[],,1),0),MATCH(OfficeVariances[[#Headers],[Oct]],OfficeActual[#Headers],0)) | M17: =INDEX(OfficePlan[],MATCH(INDEX(OfficeVariances[],ROW()-ROW(OfficeVariances[[#Headers],[Nov]]),1),INDEX(OfficePlan[],,1),0),MATCH(OfficeVariances[[#Headers],[Nov]],OfficePlan[#Headers],0))-INDEX(OfficeActual[],MATCH(INDEX(OfficeVariances[],ROW()-ROW(OfficeVariances[[#Headers],[Nov]]),1),INDEX(OfficePlan[],,1),0),MATCH(OfficeVariances[[#Headers],[Nov]],OfficeActual[#Headers],0)) | N17: =INDEX(OfficePlan[],MATCH(INDEX(OfficeVariances[],ROW()-ROW(OfficeVariances[[#Headers],[Dec]]),1),INDEX(OfficePlan[],,1),0),MATCH(OfficeVariances[[#Headers],[Dec]],OfficePlan[#Headers],0))-INDEX(OfficeActual[],MATCH(INDEX(OfficeVariances[],ROW()-ROW(OfficeVariances[[#Headers],[Dec]]),1),INDEX(OfficePlan[],,1),0),MATCH(OfficeVariances[[#Headers],[Dec]],OfficeActual[#Headers],0)) | O17: =SUM(OfficeVariances[[#This Row],[Jan]:[Dec]])
B18: Office supplies | C18: =INDEX(OfficePlan[],MATCH(INDEX(OfficeVariances[],ROW()-ROW(OfficeVariances[[#Headers],[Jan]]),1),INDEX(OfficePlan[],,1),0),MATCH(OfficeVariances[[#Headers],[Jan]],OfficePlan[#Headers],0))-INDEX(OfficeActual[],MATCH(INDEX(OfficeVariances[],ROW()-ROW(OfficeVariances[[#Headers],[Jan]]),1),INDEX(OfficePlan[],,1),0),MATCH(OfficeVariances[[#Headers],[Jan]],OfficeActual[#Headers],0)) | D18: =INDEX(OfficePlan[],MATCH(INDEX(OfficeVariances[],ROW()-ROW(OfficeVariances[[#Headers],[Feb]]),1),INDEX(OfficePlan[],,1),0),MATCH(OfficeVariances[[#Headers],[Feb]],OfficePlan[#Headers],0))-INDEX(OfficeActual[],MATCH(INDEX(OfficeVariances[],ROW()-ROW(OfficeVariances[[#Headers],[Feb]]),1),INDEX(OfficePlan[],,1),0),MATCH(OfficeVariances[[#Headers],[Feb]],OfficeActual[#Headers],0)) | E18: =INDEX(OfficePlan[],MATCH(INDEX(OfficeVariances[],ROW()-ROW(OfficeVariances[[#Headers],[Mar]]),1),INDEX(OfficePlan[],,1),0),MATCH(OfficeVariances[[#Headers],[Mar]],OfficePlan[#Headers],0))-INDEX(OfficeActual[],MATCH(INDEX(OfficeVariances[],ROW()-ROW(OfficeVariances[[#Headers],[Mar]]),1),INDEX(OfficePlan[],,1),0),MATCH(OfficeVariances[[#Headers],[Mar]],OfficeActual[#Headers],0)) | F18: =INDEX(OfficePlan[],MATCH(INDEX(OfficeVariances[],ROW()-ROW(OfficeVariances[[#Headers],[Apr]]),1),INDEX(OfficePlan[],,1),0),MATCH(OfficeVariances[[#Headers],[Apr]],OfficePlan[#Headers],0))-INDEX(OfficeActual[],MATCH(INDEX(OfficeVariances[],ROW()-ROW(OfficeVariances[[#Headers],[Apr]]),1),INDEX(OfficePlan[],,1),0),MATCH(OfficeVariances[[#Headers],[Apr]],OfficeActual[#Headers],0)) | G18: =INDEX(OfficePlan[],MATCH(INDEX(OfficeVariances[],ROW()-ROW(OfficeVariances[[#Headers],[May]]),1),INDEX(OfficePlan[],,1),0),MATCH(OfficeVariances[[#Headers],[May]],OfficePlan[#Headers],0))-INDEX(OfficeActual[],MATCH(INDEX(OfficeVariances[],ROW()-ROW(OfficeVariances[[#Headers],[May]]),1),INDEX(OfficePlan[],,1),0),MATCH(OfficeVariances[[#Headers],[May]],OfficeActual[#Headers],0)) | H18: =INDEX(OfficePlan[],MATCH(INDEX(OfficeVariances[],ROW()-ROW(OfficeVariances[[#Headers],[Jun]]),1),INDEX(OfficePlan[],,1),0),MATCH(OfficeVariances[[#Headers],[Jun]],OfficePlan[#Headers],0))-INDEX(OfficeActual[],MATCH(INDEX(OfficeVariances[],ROW()-ROW(OfficeVariances[[#Headers],[Jun]]),1),INDEX(OfficePlan[],,1),0),MATCH(OfficeVariances[[#Headers],[Jun]],OfficeActual[#Headers],0)) | I18: =INDEX(OfficePlan[],MATCH(INDEX(OfficeVariances[],ROW()-ROW(OfficeVariances[[#Headers],[Jul]]),1),INDEX(OfficePlan[],,1),0),MATCH(OfficeVariances[[#Headers],[Jul]],OfficePlan[#Headers],0))-INDEX(OfficeActual[],MATCH(INDEX(OfficeVariances[],ROW()-ROW(OfficeVariances[[#Headers],[Jul]]),1),INDEX(OfficePlan[],,1),0),MATCH(OfficeVariances[[#Headers],[Jul]],OfficeActual[#Headers],0)) | J18: =INDEX(OfficePlan[],MATCH(INDEX(OfficeVariances[],ROW()-ROW(OfficeVariances[[#Headers],[Aug]]),1),INDEX(OfficePlan[],,1),0),MATCH(OfficeVariances[[#Headers],[Aug]],OfficePlan[#Headers],0))-INDEX(OfficeActual[],MATCH(INDEX(OfficeVariances[],ROW()-ROW(OfficeVariances[[#Headers],[Aug]]),1),INDEX(OfficePlan[],,1),0),MATCH(OfficeVariances[[#Headers],[Aug]],OfficeActual[#Headers],0)) | K18: =INDEX(OfficePlan[],MATCH(INDEX(OfficeVariances[],ROW()-ROW(OfficeVariances[[#Headers],[Sep]]),1),INDEX(OfficePlan[],,1),0),MATCH(OfficeVariances[[#Headers],[Sep]],OfficePlan[#Headers],0))-INDEX(OfficeActual[],MATCH(INDEX(OfficeVariances[],ROW()-ROW(OfficeVariances[[#Headers],[Sep]]),1),INDEX(OfficePlan[],,1),0),MATCH(OfficeVariances[[#Headers],[Sep]],OfficeActual[#Headers],0)) | L18: =INDEX(OfficePlan[],MATCH(INDEX(OfficeVariances[],ROW()-ROW(OfficeVariances[[#Headers],[Oct]]),1),INDEX(OfficePlan[],,1),0),MATCH(OfficeVariances[[#Headers],[Oct]],OfficePlan[#Headers],0))-INDEX(OfficeActual[],MATCH(INDEX(OfficeVariances[],ROW()-ROW(OfficeVariances[[#Headers],[Oct]]),1),INDEX(OfficePlan[],,1),0),MATCH(OfficeVariances[[#Headers],[Oct]],OfficeActual[#Headers],0)) | M18: =INDEX(OfficePlan[],MATCH(INDEX(OfficeVariances[],ROW()-ROW(OfficeVariances[[#Headers],[Nov]]),1),INDEX(OfficePlan[],,1),0),MATCH(OfficeVariances[[#Headers],[Nov]],OfficePlan[#Headers],0))-INDEX(OfficeActual[],MATCH(INDEX(OfficeVariances[],ROW()-ROW(OfficeVariances[[#Headers],[Nov]]),1),INDEX(OfficePlan[],,1),0),MATCH(OfficeVariances[[#Headers],[Nov]],OfficeActual[#Headers],0)) | N18: =INDEX(OfficePlan[],MATCH(INDEX(OfficeVariances[],ROW()-ROW(OfficeVariances[[#Headers],[Dec]]),1),INDEX(OfficePlan[],,1),0),MATCH(OfficeVariances[[#Headers],[Dec]],OfficePlan[#Headers],0))-INDEX(OfficeActual[],MATCH(INDEX(OfficeVariances[],ROW()-ROW(OfficeVariances[[#Headers],[Dec]]),1),INDEX(OfficePlan[],,1),0),MATCH(OfficeVariances[[#Headers],[Dec]],OfficeActual[#Headers],0)) | O18: =SUM(OfficeVariances[[#This Row],[Jan]:[Dec]])
B19: Security | C19: =INDEX(OfficePlan[],MATCH(INDEX(OfficeVariances[],ROW()-ROW(OfficeVariances[[#Headers],[Jan]]),1),INDEX(OfficePlan[],,1),0),MATCH(OfficeVariances[[#Headers],[Jan]],OfficePlan[#Headers],0))-INDEX(OfficeActual[],MATCH(INDEX(OfficeVariances[],ROW()-ROW(OfficeVariances[[#Headers],[Jan]]),1),INDEX(OfficePlan[],,1),0),MATCH(OfficeVariances[[#Headers],[Jan]],OfficeActual[#Headers],0)) | D19: =INDEX(OfficePlan[],MATCH(INDEX(OfficeVariances[],ROW()-ROW(OfficeVariances[[#Headers],[Feb]]),1),INDEX(OfficePlan[],,1),0),MATCH(OfficeVariances[[#Headers],[Feb]],OfficePlan[#Headers],0))-INDEX(OfficeActual[],MATCH(INDEX(OfficeVariances[],ROW()-ROW(OfficeVariances[[#Headers],[Feb]]),1),INDEX(OfficePlan[],,1),0),MATCH(OfficeVariances[[#Headers],[Feb]],OfficeActual[#Headers],0)) | E19: =INDEX(OfficePlan[],MATCH(INDEX(OfficeVariances[],ROW()-ROW(OfficeVariances[[#Headers],[Mar]]),1),INDEX(OfficePlan[],,1),0),MATCH(OfficeVariances[[#Headers],[Mar]],OfficePlan[#Headers],0))-INDEX(OfficeActual[],MATCH(INDEX(OfficeVariances[],ROW()-ROW(OfficeVariances[[#Headers],[Mar]]),1),INDEX(OfficePlan[],,1),0),MATCH(OfficeVariances[[#Headers],[Mar]],OfficeActual[#Headers],0)) | F19: =INDEX(OfficePlan[],MATCH(INDEX(OfficeVariances[],ROW()-ROW(OfficeVariances[[#Headers],[Apr]]),1),INDEX(OfficePlan[],,1),0),MATCH(OfficeVariances[[#Headers],[Apr]],OfficePlan[#Headers],0))-INDEX(OfficeActual[],MATCH(INDEX(OfficeVariances[],ROW()-ROW(OfficeVariances[[#Headers],[Apr]]),1),INDEX(OfficePlan[],,1),0),MATCH(OfficeVariances[[#Headers],[Apr]],OfficeActual[#Headers],0)) | G19: =INDEX(OfficePlan[],MATCH(INDEX(OfficeVariances[],ROW()-ROW(OfficeVariances[[#Headers],[May]]),1),INDEX(OfficePlan[],,1),0),MATCH(OfficeVariances[[#Headers],[May]],OfficePlan[#Headers],0))-INDEX(OfficeActual[],MATCH(INDEX(OfficeVariances[],ROW()-ROW(OfficeVariances[[#Headers],[May]]),1),INDEX(OfficePlan[],,1),0),MATCH(OfficeVariances[[#Headers],[May]],OfficeActual[#Headers],0)) | H19: =INDEX(OfficePlan[],MATCH(INDEX(OfficeVariances[],ROW()-ROW(OfficeVariances[[#Headers],[Jun]]),1),INDEX(OfficePlan[],,1),0),MATCH(OfficeVariances[[#Headers],[Jun]],OfficePlan[#Headers],0))-INDEX(OfficeActual[],MATCH(INDEX(OfficeVariances[],ROW()-ROW(OfficeVariances[[#Headers],[Jun]]),1),INDEX(OfficePlan[],,1),0),MATCH(OfficeVariances[[#Headers],[Jun]],OfficeActual[#Headers],0)) | I19: =INDEX(OfficePlan[],MATCH(INDEX(OfficeVariances[],ROW()-ROW(OfficeVariances[[#Headers],[Jul]]),1),INDEX(OfficePlan[],,1),0),MATCH(OfficeVariances[[#Headers],[Jul]],OfficePlan[#Headers],0))-INDEX(OfficeActual[],MATCH(INDEX(OfficeVariances[],ROW()-ROW(OfficeVariances[[#Headers],[Jul]]),1),INDEX(OfficePlan[],,1),0),MATCH(OfficeVariances[[#Headers],[Jul]],OfficeActual[#Headers],0)) | J19: =INDEX(OfficePlan[],MATCH(INDEX(OfficeVariances[],ROW()-ROW(OfficeVariances[[#Headers],[Aug]]),1),INDEX(OfficePlan[],,1),0),MATCH(OfficeVariances[[#Headers],[Aug]],OfficePlan[#Headers],0))-INDEX(OfficeActual[],MATCH(INDEX(OfficeVariances[],ROW()-ROW(OfficeVariances[[#Headers],[Aug]]),1),INDEX(OfficePlan[],,1),0),MATCH(OfficeVariances[[#Headers],[Aug]],OfficeActual[#Headers],0)) | K19: =INDEX(OfficePlan[],MATCH(INDEX(OfficeVariances[],ROW()-ROW(OfficeVariances[[#Headers],[Sep]]),1),INDEX(OfficePlan[],,1),0),MATCH(OfficeVariances[[#Headers],[Sep]],OfficePlan[#Headers],0))-INDEX(OfficeActual[],MATCH(INDEX(OfficeVariances[],ROW()-ROW(OfficeVariances[[#Headers],[Sep]]),1),INDEX(OfficePlan[],,1),0),MATCH(OfficeVariances[[#Headers],[Sep]],OfficeActual[#Headers],0)) | L19: =INDEX(OfficePlan[],MATCH(INDEX(OfficeVariances[],ROW()-ROW(OfficeVariances[[#Headers],[Oct]]),1),INDEX(OfficePlan[],,1),0),MATCH(OfficeVariances[[#Headers],[Oct]],OfficePlan[#Headers],0))-INDEX(OfficeActual[],MATCH(INDEX(OfficeVariances[],ROW()-ROW(OfficeVariances[[#Headers],[Oct]]),1),INDEX(OfficePlan[],,1),0),MATCH(OfficeVariances[[#Headers],[Oct]],OfficeActual[#Headers],0)) | M19: =INDEX(OfficePlan[],MATCH(INDEX(OfficeVariances[],ROW()-ROW(OfficeVariances[[#Headers],[Nov]]),1),INDEX(OfficePlan[],,1),0),MATCH(OfficeVariances[[#Headers],[Nov]],OfficePlan[#Headers],0))-INDEX(OfficeActual[],MATCH(INDEX(OfficeVariances[],ROW()-ROW(OfficeVariances[[#Headers],[Nov]]),1),INDEX(OfficePlan[],,1),0),MATCH(OfficeVariances[[#Headers],[Nov]],OfficeActual[#Headers],0)) | N19: =INDEX(OfficePlan[],MATCH(INDEX(OfficeVariances[],ROW()-ROW(OfficeVariances[[#Headers],[Dec]]),1),INDEX(OfficePlan[],,1),0),MATCH(OfficeVariances[[#Headers],[Dec]],OfficePlan[#Headers],0))-INDEX(OfficeActual[],MATCH(INDEX(OfficeVariances[],ROW()-ROW(OfficeVariances[[#Headers],[Dec]]),1),INDEX(OfficePlan[],,1),0),MATCH(OfficeVariances[[#Headers],[Dec]],OfficeActual[#Headers],0)) | O19: =SUM(OfficeVariances[[#This Row],[Jan]:[Dec]])
B20: Subtotal | C20: =SUBTOTAL(109,OfficeVariances[Jan]) | D20: =SUBTOTAL(109,OfficeVariances[Feb]) | E20: =SUBTOTAL(109,OfficeVariances[Mar]) | F20: =SUBTOTAL(109,OfficeVariances[Apr]) | G20: =SUBTOTAL(109,OfficeVariances[May]) | H20: =SUBTOTAL(109,OfficeVariances[Jun]) | I20: =SUBTOTAL(109,OfficeVariances[Jul]) | J20: =SUBTOTAL(109,OfficeVariances[Aug]) | K20: =SUBTOTAL(109,OfficeVariances[Sep]) | L20: =SUBTOTAL(109,OfficeVariances[Oct]) | M20: =SUBTOTAL(109,OfficeVariances[Nov]) | N20: =SUBTOTAL(109,OfficeVariances[Dec]) | O20: =SUBTOTAL(109,OfficeVariances[YEAR])
B22: Marketing costs | C22: Jan | D22: Feb | E22: Mar | F22: Apr | G22: May | H22: Jun | I22: Jul | J22: Aug | K22: Sep | L22: Oct | M22: Nov | N22: Dec | O22: YEAR
B23: Web site hosting | C23: =INDEX(MarketingPlan[],MATCH(INDEX(MarketingVariances[],ROW()-ROW(MarketingVariances[[#Headers],[Jan]]),1),INDEX(MarketingPlan[],,1),0),MATCH(MarketingVariances[[#Headers],[Jan]],MarketingPlan[#Headers],0))-INDEX(MarketingActual[],MATCH(INDEX(MarketingVariances[],ROW()-ROW(MarketingVariances[[#Headers],[Jan]]),1),INDEX(MarketingPlan[],,1),0),MATCH(MarketingVariances[[#Headers],[Jan]],MarketingActual[#Headers],0)) | D23: =INDEX(MarketingPlan[],MATCH(INDEX(MarketingVariances[],ROW()-ROW(MarketingVariances[[#Headers],[Feb]]),1),INDEX(MarketingPlan[],,1),0),MATCH(MarketingVariances[[#Headers],[Feb]],MarketingPlan[#Headers],0))-INDEX(MarketingActual[],MATCH(INDEX(MarketingVariances[],ROW()-ROW(MarketingVariances[[#Headers],[Feb]]),1),INDEX(MarketingPlan[],,1),0),MATCH(MarketingVariances[[#Headers],[Feb]],MarketingActual[#Headers],0)) | E23: =INDEX(MarketingPlan[],MATCH(INDEX(MarketingVariances[],ROW()-ROW(MarketingVariances[[#Headers],[Mar]]),1),INDEX(MarketingPlan[],,1),0),MATCH(MarketingVariances[[#Headers],[Mar]],MarketingPlan[#Headers],0))-INDEX(MarketingActual[],MATCH(INDEX(MarketingVariances[],ROW()-ROW(MarketingVariances[[#Headers],[Mar]]),1),INDEX(MarketingPlan[],,1),0),MATCH(MarketingVariances[[#Headers],[Mar]],MarketingActual[#Headers],0)) | F23: =INDEX(MarketingPlan[],MATCH(INDEX(MarketingVariances[],ROW()-ROW(MarketingVariances[[#Headers],[Apr]]),1),INDEX(MarketingPlan[],,1),0),MATCH(MarketingVariances[[#Headers],[Apr]],MarketingPlan[#Headers],0))-INDEX(MarketingActual[],MATCH(INDEX(MarketingVariances[],ROW()-ROW(MarketingVariances[[#Headers],[Apr]]),1),INDEX(MarketingPlan[],,1),0),MATCH(MarketingVariances[[#Headers],[Apr]],MarketingActual[#Headers],0)) | G23: =INDEX(MarketingPlan[],MATCH(INDEX(MarketingVariances[],ROW()-ROW(MarketingVariances[[#Headers],[May]]),1),INDEX(MarketingPlan[],,1),0),MATCH(MarketingVariances[[#Headers],[May]],MarketingPlan[#Headers],0))-INDEX(MarketingActual[],MATCH(INDEX(MarketingVariances[],ROW()-ROW(MarketingVariances[[#Headers],[May]]),1),INDEX(MarketingPlan[],,1),0),MATCH(MarketingVariances[[#Headers],[May]],MarketingActual[#Headers],0)) | H23: =INDEX(MarketingPlan[],MATCH(INDEX(MarketingVariances[],ROW()-ROW(MarketingVariances[[#Headers],[Jun]]),1),INDEX(MarketingPlan[],,1),0),MATCH(MarketingVariances[[#Headers],[Jun]],MarketingPlan[#Headers],0))-INDEX(MarketingActual[],MATCH(INDEX(MarketingVariances[],ROW()-ROW(MarketingVariances[[#Headers],[Jun]]),1),INDEX(MarketingPlan[],,1),0),MATCH(MarketingVariances[[#Headers],[Jun]],MarketingActual[#Headers],0)) | I23: =INDEX(MarketingPlan[],MATCH(INDEX(MarketingVariances[],ROW()-ROW(MarketingVariances[[#Headers],[Jul]]),1),INDEX(MarketingPlan[],,1),0),MATCH(MarketingVariances[[#Headers],[Jul]],MarketingPlan[#Headers],0))-INDEX(MarketingActual[],MATCH(INDEX(MarketingVariances[],ROW()-ROW(MarketingVariances[[#Headers],[Jul]]),1),INDEX(MarketingPlan[],,1),0),MATCH(MarketingVariances[[#Headers],[Jul]],MarketingActual[#Headers],0)) | J23: =INDEX(MarketingPlan[],MATCH(INDEX(MarketingVariances[],ROW()-ROW(MarketingVariances[[#Headers],[Aug]]),1),INDEX(MarketingPlan[],,1),0),MATCH(MarketingVariances[[#Headers],[Aug]],MarketingPlan[#Headers],0))-INDEX(MarketingActual[],MATCH(INDEX(MarketingVariances[],ROW()-ROW(MarketingVariances[[#Headers],[Aug]]),1),INDEX(MarketingPlan[],,1),0),MATCH(MarketingVariances[[#Headers],[Aug]],MarketingActual[#Headers],0)) | K23: =INDEX(MarketingPlan[],MATCH(INDEX(MarketingVariances[],ROW()-ROW(MarketingVariances[[#Headers],[Sep]]),1),INDEX(MarketingPlan[],,1),0),MATCH(MarketingVariances[[#Headers],[Sep]],MarketingPlan[#Headers],0))-INDEX(MarketingActual[],MATCH(INDEX(MarketingVariances[],ROW()-ROW(MarketingVariances[[#Headers],[Sep]]),1),INDEX(MarketingPlan[],,1),0),MATCH(MarketingVariances[[#Headers],[Sep]],MarketingActual[#Headers],0)) | L23: =INDEX(MarketingPlan[],MATCH(INDEX(MarketingVariances[],ROW()-ROW(MarketingVariances[[#Headers],[Oct]]),1),INDEX(MarketingPlan[],,1),0),MATCH(MarketingVariances[[#Headers],[Oct]],MarketingPlan[#Headers],0))-INDEX(MarketingActual[],MATCH(INDEX(MarketingVariances[],ROW()-ROW(MarketingVariances[[#Headers],[Oct]]),1),INDEX(MarketingPlan[],,1),0),MATCH(MarketingVariances[[#Headers],[Oct]],MarketingActual[#Headers],0)) | M23: =INDEX(MarketingPlan[],MATCH(INDEX(MarketingVariances[],ROW()-ROW(MarketingVariances[[#Headers],[Nov]]),1),INDEX(MarketingPlan[],,1),0),MATCH(MarketingVariances[[#Headers],[Nov]],MarketingPlan[#Headers],0))-INDEX(MarketingActual[],MATCH(INDEX(MarketingVariances[],ROW()-ROW(MarketingVariances[[#Headers],[Nov]]),1),INDEX(MarketingPlan[],,1),0),MATCH(MarketingVariances[[#Headers],[Nov]],MarketingActual[#Headers],0)) | N23: =INDEX(MarketingPlan[],MATCH(INDEX(MarketingVariances[],ROW()-ROW(MarketingVariances[[#Headers],[Dec]]),1),INDEX(MarketingPlan[],,1),0),MATCH(MarketingVariances[[#Headers],[Dec]],MarketingPlan[#Headers],0))-INDEX(MarketingActual[],MATCH(INDEX(MarketingVariances[],ROW()-ROW(MarketingVariances[[#Headers],[Dec]]),1),INDEX(MarketingPlan[],,1),0),MATCH(MarketingVariances[[#Headers],[Dec]],MarketingActual[#Headers],0)) | O23: =SUM(MarketingVariances[[#This Row],[Jan]:[Dec]])
B24: Web site updates | C24: =INDEX(MarketingPlan[],MATCH(INDEX(MarketingVariances[],ROW()-ROW(MarketingVariances[[#Headers],[Jan]]),1),INDEX(MarketingPlan[],,1),0),MATCH(MarketingVariances[[#Headers],[Jan]],MarketingPlan[#Headers],0))-INDEX(MarketingActual[],MATCH(INDEX(MarketingVariances[],ROW()-ROW(MarketingVariances[[#Headers],[Jan]]),1),INDEX(MarketingPlan[],,1),0),MATCH(MarketingVariances[[#Headers],[Jan]],MarketingActual[#Headers],0)) | D24: =INDEX(MarketingPlan[],MATCH(INDEX(MarketingVariances[],ROW()-ROW(MarketingVariances[[#Headers],[Feb]]),1),INDEX(MarketingPlan[],,1),0),MATCH(MarketingVariances[[#Headers],[Feb]],MarketingPlan[#Headers],0))-INDEX(MarketingActual[],MATCH(INDEX(MarketingVariances[],ROW()-ROW(MarketingVariances[[#Headers],[Feb]]),1),INDEX(MarketingPlan[],,1),0),MATCH(MarketingVariances[[#Headers],[Feb]],MarketingActual[#Headers],0)) | E24: =INDEX(MarketingPlan[],MATCH(INDEX(MarketingVariances[],ROW()-ROW(MarketingVariances[[#Headers],[Mar]]),1),INDEX(MarketingPlan[],,1),0),MATCH(MarketingVariances[[#Headers],[Mar]],MarketingPlan[#Headers],0))-INDEX(MarketingActual[],MATCH(INDEX(MarketingVariances[],ROW()-ROW(MarketingVariances[[#Headers],[Mar]]),1),INDEX(MarketingPlan[],,1),0),MATCH(MarketingVariances[[#Headers],[Mar]],MarketingActual[#Headers],0)) | F24: =INDEX(MarketingPlan[],MATCH(INDEX(MarketingVariances[],ROW()-ROW(MarketingVariances[[#Headers],[Apr]]),1),INDEX(MarketingPlan[],,1),0),MATCH(MarketingVariances[[#Headers],[Apr]],MarketingPlan[#Headers],0))-INDEX(MarketingActual[],MATCH(INDEX(MarketingVariances[],ROW()-ROW(MarketingVariances[[#Headers],[Apr]]),1),INDEX(MarketingPlan[],,1),0),MATCH(MarketingVariances[[#Headers],[Apr]],MarketingActual[#Headers],0)) | G24: =INDEX(MarketingPlan[],MATCH(INDEX(MarketingVariances[],ROW()-ROW(MarketingVariances[[#Headers],[May]]),1),INDEX(MarketingPlan[],,1),0),MATCH(MarketingVariances[[#Headers],[May]],MarketingPlan[#Headers],0))-INDEX(MarketingActual[],MATCH(INDEX(MarketingVariances[],ROW()-ROW(MarketingVariances[[#Headers],[May]]),1),INDEX(MarketingPlan[],,1),0),MATCH(MarketingVariances[[#Headers],[May]],MarketingActual[#Headers],0)) | H24: =INDEX(MarketingPlan[],MATCH(INDEX(MarketingVariances[],ROW()-ROW(MarketingVariances[[#Headers],[Jun]]),1),INDEX(MarketingPlan[],,1),0),MATCH(MarketingVariances[[#Headers],[Jun]],MarketingPlan[#Headers],0))-INDEX(MarketingActual[],MATCH(INDEX(MarketingVariances[],ROW()-ROW(MarketingVariances[[#Headers],[Jun]]),1),INDEX(MarketingPlan[],,1),0),MATCH(MarketingVariances[[#Headers],[Jun]],MarketingActual[#Headers],0)) | I24: =INDEX(MarketingPlan[],MATCH(INDEX(MarketingVariances[],ROW()-ROW(MarketingVariances[[#Headers],[Jul]]),1),INDEX(MarketingPlan[],,1),0),MATCH(MarketingVariances[[#Headers],[Jul]],MarketingPlan[#Headers],0))-INDEX(MarketingActual[],MATCH(INDEX(MarketingVariances[],ROW()-ROW(MarketingVariances[[#Headers],[Jul]]),1),INDEX(MarketingPlan[],,1),0),MATCH(MarketingVariances[[#Headers],[Jul]],MarketingActual[#Headers],0)) | J24: =INDEX(MarketingPlan[],MATCH(INDEX(MarketingVariances[],ROW()-ROW(MarketingVariances[[#Headers],[Aug]]),1),INDEX(MarketingPlan[],,1),0),MATCH(MarketingVariances[[#Headers],[Aug]],MarketingPlan[#Headers],0))-INDEX(MarketingActual[],MATCH(INDEX(MarketingVariances[],ROW()-ROW(MarketingVariances[[#Headers],[Aug]]),1),INDEX(MarketingPlan[],,1),0),MATCH(MarketingVariances[[#Headers],[Aug]],MarketingActual[#Headers],0)) | K24: =INDEX(MarketingPlan[],MATCH(INDEX(MarketingVariances[],ROW()-ROW(MarketingVariances[[#Headers],[Sep]]),1),INDEX(MarketingPlan[],,1),0),MATCH(MarketingVariances[[#Headers],[Sep]],MarketingPlan[#Headers],0))-INDEX(MarketingActual[],MATCH(INDEX(MarketingVariances[],ROW()-ROW(MarketingVariances[[#Headers],[Sep]]),1),INDEX(MarketingPlan[],,1),0),MATCH(MarketingVariances[[#Headers],[Sep]],MarketingActual[#Headers],0)) | L24: =INDEX(MarketingPlan[],MATCH(INDEX(MarketingVariances[],ROW()-ROW(MarketingVariances[[#Headers],[Oct]]),1),INDEX(MarketingPlan[],,1),0),MATCH(MarketingVariances[[#Headers],[Oct]],MarketingPlan[#Headers],0))-INDEX(MarketingActual[],MATCH(INDEX(MarketingVariances[],ROW()-ROW(MarketingVariances[[#Headers],[Oct]]),1),INDEX(MarketingPlan[],,1),0),MATCH(MarketingVariances[[#Headers],[Oct]],MarketingActual[#Headers],0)) | M24: =INDEX(MarketingPlan[],MATCH(INDEX(MarketingVariances[],ROW()-ROW(MarketingVariances[[#Headers],[Nov]]),1),INDEX(MarketingPlan[],,1),0),MATCH(MarketingVariances[[#Headers],[Nov]],MarketingPlan[#Headers],0))-INDEX(MarketingActual[],MATCH(INDEX(MarketingVariances[],ROW()-ROW(MarketingVariances[[#Headers],[Nov]]),1),INDEX(MarketingPlan[],,1),0),MATCH(MarketingVariances[[#Headers],[Nov]],MarketingActual[#Headers],0)) | N24: =INDEX(MarketingPlan[],MATCH(INDEX(MarketingVariances[],ROW()-ROW(MarketingVariances[[#Headers],[Dec]]),1),INDEX(MarketingPlan[],,1),0),MATCH(MarketingVariances[[#Headers],[Dec]],MarketingPlan[#Headers],0))-INDEX(MarketingActual[],MATCH(INDEX(MarketingVariances[],ROW()-ROW(MarketingVariances[[#Headers],[Dec]]),1),INDEX(MarketingPlan[],,1),0),MATCH(MarketingVariances[[#Headers],[Dec]],MarketingActual[#Headers],0)) | O24: =SUM(MarketingVariances[[#This Row],[Jan]:[Dec]])
B25: Collateral preparation | C25: =INDEX(MarketingPlan[],MATCH(INDEX(MarketingVariances[],ROW()-ROW(MarketingVariances[[#Headers],[Jan]]),1),INDEX(MarketingPlan[],,1),0),MATCH(MarketingVariances[[#Headers],[Jan]],MarketingPlan[#Headers],0))-INDEX(MarketingActual[],MATCH(INDEX(MarketingVariances[],ROW()-ROW(MarketingVariances[[#Headers],[Jan]]),1),INDEX(MarketingPlan[],,1),0),MATCH(MarketingVariances[[#Headers],[Jan]],MarketingActual[#Headers],0)) | D25: =INDEX(MarketingPlan[],MATCH(INDEX(MarketingVariances[],ROW()-ROW(MarketingVariances[[#Headers],[Feb]]),1),INDEX(MarketingPlan[],,1),0),MATCH(MarketingVariances[[#Headers],[Feb]],MarketingPlan[#Headers],0))-INDEX(MarketingActual[],MATCH(INDEX(MarketingVariances[],ROW()-ROW(MarketingVariances[[#Headers],[Feb]]),1),INDEX(MarketingPlan[],,1),0),MATCH(MarketingVariances[[#Headers],[Feb]],MarketingActual[#Headers],0)) | E25: =INDEX(MarketingPlan[],MATCH(INDEX(MarketingVariances[],ROW()-ROW(MarketingVariances[[#Headers],[Mar]]),1),INDEX(MarketingPlan[],,1),0),MATCH(MarketingVariances[[#Headers],[Mar]],MarketingPlan[#Headers],0))-INDEX(MarketingActual[],MATCH(INDEX(MarketingVariances[],ROW()-ROW(MarketingVariances[[#Headers],[Mar]]),1),INDEX(MarketingPlan[],,1),0),MATCH(MarketingVariances[[#Headers],[Mar]],MarketingActual[#Headers],0)) | F25: =INDEX(MarketingPlan[],MATCH(INDEX(MarketingVariances[],ROW()-ROW(MarketingVariances[[#Headers],[Apr]]),1),INDEX(MarketingPlan[],,1),0),MATCH(MarketingVariances[[#Headers],[Apr]],MarketingPlan[#Headers],0))-INDEX(MarketingActual[],MATCH(INDEX(MarketingVariances[],ROW()-ROW(MarketingVariances[[#Headers],[Apr]]),1),INDEX(MarketingPlan[],,1),0),MATCH(MarketingVariances[[#Headers],[Apr]],MarketingActual[#Headers],0)) | G25: =INDEX(MarketingPlan[],MATCH(INDEX(MarketingVariances[],ROW()-ROW(MarketingVariances[[#Headers],[May]]),1),INDEX(MarketingPlan[],,1),0),MATCH(MarketingVariances[[#Headers],[May]],MarketingPlan[#Headers],0))-INDEX(MarketingActual[],MATCH(INDEX(MarketingVariances[],ROW()-ROW(MarketingVariances[[#Headers],[May]]),1),INDEX(MarketingPlan[],,1),0),MATCH(MarketingVariances[[#Headers],[May]],MarketingActual[#Headers],0)) | H25: =INDEX(MarketingPlan[],MATCH(INDEX(MarketingVariances[],ROW()-ROW(MarketingVariances[[#Headers],[Jun]]),1),INDEX(MarketingPlan[],,1),0),MATCH(MarketingVariances[[#Headers],[Jun]],MarketingPlan[#Headers],0))-INDEX(MarketingActual[],MATCH(INDEX(MarketingVariances[],ROW()-ROW(MarketingVariances[[#Headers],[Jun]]),1),INDEX(MarketingPlan[],,1),0),MATCH(MarketingVariances[[#Headers],[Jun]],MarketingActual[#Headers],0)) | I25: =INDEX(MarketingPlan[],MATCH(INDEX(MarketingVariances[],ROW()-ROW(MarketingVariances[[#Headers],[Jul]]),1),INDEX(MarketingPlan[],,1),0),MATCH(MarketingVariances[[#Headers],[Jul]],MarketingPlan[#Headers],0))-INDEX(MarketingActual[],MATCH(INDEX(MarketingVariances[],ROW()-ROW(MarketingVariances[[#Headers],[Jul]]),1),INDEX(MarketingPlan[],,1),0),MATCH(MarketingVariances[[#Headers],[Jul]],MarketingActual[#Headers],0)) | J25: =INDEX(MarketingPlan[],MATCH(INDEX(MarketingVariances[],ROW()-ROW(MarketingVariances[[#Headers],[Aug]]),1),INDEX(MarketingPlan[],,1),0),MATCH(MarketingVariances[[#Headers],[Aug]],MarketingPlan[#Headers],0))-INDEX(MarketingActual[],MATCH(INDEX(MarketingVariances[],ROW()-ROW(MarketingVariances[[#Headers],[Aug]]),1),INDEX(MarketingPlan[],,1),0),MATCH(MarketingVariances[[#Headers],[Aug]],MarketingActual[#Headers],0)) | K25: =INDEX(MarketingPlan[],MATCH(INDEX(MarketingVariances[],ROW()-ROW(MarketingVariances[[#Headers],[Sep]]),1),INDEX(MarketingPlan[],,1),0),MATCH(MarketingVariances[[#Headers],[Sep]],MarketingPlan[#Headers],0))-INDEX(MarketingActual[],MATCH(INDEX(MarketingVariances[],ROW()-ROW(MarketingVariances[[#Headers],[Sep]]),1),INDEX(MarketingPlan[],,1),0),MATCH(MarketingVariances[[#Headers],[Sep]],MarketingActual[#Headers],0)) | L25: =INDEX(MarketingPlan[],MATCH(INDEX(MarketingVariances[],ROW()-ROW(MarketingVariances[[#Headers],[Oct]]),1),INDEX(MarketingPlan[],,1),0),MATCH(MarketingVariances[[#Headers],[Oct]],MarketingPlan[#Headers],0))-INDEX(MarketingActual[],MATCH(INDEX(MarketingVariances[],ROW()-ROW(MarketingVariances[[#Headers],[Oct]]),1),INDEX(MarketingPlan[],,1),0),MATCH(MarketingVariances[[#Headers],[Oct]],MarketingActual[#Headers],0)) | M25: =INDEX(MarketingPlan[],MATCH(INDEX(MarketingVariances[],ROW()-ROW(MarketingVariances[[#Headers],[Nov]]),1),INDEX(MarketingPlan[],,1),0),MATCH(MarketingVariances[[#Headers],[Nov]],MarketingPlan[#Headers],0))-INDEX(MarketingActual[],MATCH(INDEX(MarketingVariances[],ROW()-ROW(MarketingVariances[[#Headers],[Nov]]),1),INDEX(MarketingPlan[],,1),0),MATCH(MarketingVariances[[#Headers],[Nov]],MarketingActual[#Headers],0)) | N25: =INDEX(MarketingPlan[],MATCH(INDEX(MarketingVariances[],ROW()-ROW(MarketingVariances[[#Headers],[Dec]]),1),INDEX(MarketingPlan[],,1),0),MATCH(MarketingVariances[[#Headers],[Dec]],MarketingPlan[#Headers],0))-INDEX(MarketingActual[],MATCH(INDEX(MarketingVariances[],ROW()-ROW(MarketingVariances[[#Headers],[Dec]]),1),INDEX(MarketingPlan[],,1),0),MATCH(MarketingVariances[[#Headers],[Dec]],MarketingActual[#Headers],0)) | O25: =SUM(MarketingVariances[[#This Row],[Jan]:[Dec]])
B26: Collateral printing | C26: =INDEX(MarketingPlan[],MATCH(INDEX(MarketingVariances[],ROW()-ROW(MarketingVariances[[#Headers],[Jan]]),1),INDEX(MarketingPlan[],,1),0),MATCH(MarketingVariances[[#Headers],[Jan]],MarketingPlan[#Headers],0))-INDEX(MarketingActual[],MATCH(INDEX(MarketingVariances[],ROW()-ROW(MarketingVariances[[#Headers],[Jan]]),1),INDEX(MarketingPlan[],,1),0),MATCH(MarketingVariances[[#Headers],[Jan]],MarketingActual[#Headers],0)) | D26: =INDEX(MarketingPlan[],MATCH(INDEX(MarketingVariances[],ROW()-ROW(MarketingVariances[[#Headers],[Feb]]),1),INDEX(MarketingPlan[],,1),0),MATCH(MarketingVariances[[#Headers],[Feb]],MarketingPlan[#Headers],0))-INDEX(MarketingActual[],MATCH(INDEX(MarketingVariances[],ROW()-ROW(MarketingVariances[[#Headers],[Feb]]),1),INDEX(MarketingPlan[],,1),0),MATCH(MarketingVariances[[#Headers],[Feb]],MarketingActual[#Headers],0)) | E26: =INDEX(MarketingPlan[],MATCH(INDEX(MarketingVariances[],ROW()-ROW(MarketingVariances[[#Headers],[Mar]]),1),INDEX(MarketingPlan[],,1),0),MATCH(MarketingVariances[[#Headers],[Mar]],MarketingPlan[#Headers],0))-INDEX(MarketingActual[],MATCH(INDEX(MarketingVariances[],ROW()-ROW(MarketingVariances[[#Headers],[Mar]]),1),INDEX(MarketingPlan[],,1),0),MATCH(MarketingVariances[[#Headers],[Mar]],MarketingActual[#Headers],0)) | F26: =INDEX(MarketingPlan[],MATCH(INDEX(MarketingVariances[],ROW()-ROW(MarketingVariances[[#Headers],[Apr]]),1),INDEX(MarketingPlan[],,1),0),MATCH(MarketingVariances[[#Headers],[Apr]],MarketingPlan[#Headers],0))-INDEX(MarketingActual[],MATCH(INDEX(MarketingVariances[],ROW()-ROW(MarketingVariances[[#Headers],[Apr]]),1),INDEX(MarketingPlan[],,1),0),MATCH(MarketingVariances[[#Headers],[Apr]],MarketingActual[#Headers],0)) | G26: =INDEX(MarketingPlan[],MATCH(INDEX(MarketingVariances[],ROW()-ROW(MarketingVariances[[#Headers],[May]]),1),INDEX(MarketingPlan[],,1),0),MATCH(MarketingVariances[[#Headers],[May]],MarketingPlan[#Headers],0))-INDEX(MarketingActual[],MATCH(INDEX(MarketingVariances[],ROW()-ROW(MarketingVariances[[#Headers],[May]]),1),INDEX(MarketingPlan[],,1),0),MATCH(MarketingVariances[[#Headers],[May]],MarketingActual[#Headers],0)) | H26: =INDEX(MarketingPlan[],MATCH(INDEX(MarketingVariances[],ROW()-ROW(MarketingVariances[[#Headers],[Jun]]),1),INDEX(MarketingPlan[],,1),0),MATCH(MarketingVariances[[#Headers],[Jun]],MarketingPlan[#Headers],0))-INDEX(MarketingActual[],MATCH(INDEX(MarketingVariances[],ROW()-ROW(MarketingVariances[[#Headers],[Jun]]),1),INDEX(MarketingPlan[],,1),0),MATCH(MarketingVariances[[#Headers],[Jun]],MarketingActual[#Headers],0)) | I26: =INDEX(MarketingPlan[],MATCH(INDEX(MarketingVariances[],ROW()-ROW(MarketingVariances[[#Headers],[Jul]]),1),INDEX(MarketingPlan[],,1),0),MATCH(MarketingVariances[[#Headers],[Jul]],MarketingPlan[#Headers],0))-INDEX(MarketingActual[],MATCH(INDEX(MarketingVariances[],ROW()-ROW(MarketingVariances[[#Headers],[Jul]]),1),INDEX(MarketingPlan[],,1),0),MATCH(MarketingVariances[[#Headers],[Jul]],MarketingActual[#Headers],0)) | J26: =INDEX(MarketingPlan[],MATCH(INDEX(MarketingVariances[],ROW()-ROW(MarketingVariances[[#Headers],[Aug]]),1),INDEX(MarketingPlan[],,1),0),MATCH(MarketingVariances[[#Headers],[Aug]],MarketingPlan[#Headers],0))-INDEX(MarketingActual[],MATCH(INDEX(MarketingVariances[],ROW()-ROW(MarketingVariances[[#Headers],[Aug]]),1),INDEX(MarketingPlan[],,1),0),MATCH(MarketingVariances[[#Headers],[Aug]],MarketingActual[#Headers],0)) | K26: =INDEX(MarketingPlan[],MATCH(INDEX(MarketingVariances[],ROW()-ROW(MarketingVariances[[#Headers],[Sep]]),1),INDEX(MarketingPlan[],,1),0),MATCH(MarketingVariances[[#Headers],[Sep]],MarketingPlan[#Headers],0))-INDEX(MarketingActual[],MATCH(INDEX(MarketingVariances[],ROW()-ROW(MarketingVariances[[#Headers],[Sep]]),1),INDEX(MarketingPlan[],,1),0),MATCH(MarketingVariances[[#Headers],[Sep]],MarketingActual[#Headers],0)) | L26: =INDEX(MarketingPlan[],MATCH(INDEX(MarketingVariances[],ROW()-ROW(MarketingVariances[[#Headers],[Oct]]),1),INDEX(MarketingPlan[],,1),0),MATCH(MarketingVariances[[#Headers],[Oct]],MarketingPlan[#Headers],0))-INDEX(MarketingActual[],MATCH(INDEX(MarketingVariances[],ROW()-ROW(MarketingVariances[[#Headers],[Oct]]),1),INDEX(MarketingPlan[],,1),0),MATCH(MarketingVariances[[#Headers],[Oct]],MarketingActual[#Headers],0)) | M26: =INDEX(MarketingPlan[],MATCH(INDEX(MarketingVariances[],ROW()-ROW(MarketingVariances[[#Headers],[Nov]]),1),INDEX(MarketingPlan[],,1),0),MATCH(MarketingVariances[[#Headers],[Nov]],MarketingPlan[#Headers],0))-INDEX(MarketingActual[],MATCH(INDEX(MarketingVariances[],ROW()-ROW(MarketingVariances[[#Headers],[Nov]]),1),INDEX(MarketingPlan[],,1),0),MATCH(MarketingVariances[[#Headers],[Nov]],MarketingActual[#Headers],0)) | N26: =INDEX(MarketingPlan[],MATCH(INDEX(MarketingVariances[],ROW()-ROW(MarketingVariances[[#Headers],[Dec]]),1),INDEX(MarketingPlan[],,1),0),MATCH(MarketingVariances[[#Headers],[Dec]],MarketingPlan[#Headers],0))-INDEX(MarketingActual[],MATCH(INDEX(MarketingVariances[],ROW()-ROW(MarketingVariances[[#Headers],[Dec]]),1),INDEX(MarketingPlan[],,1),0),MATCH(MarketingVariances[[#Headers],[Dec]],MarketingActual[#Headers],0)) | O26: =SUM(MarketingVariances[[#This Row],[Jan]:[Dec]])
B27: Marketing events | C27: =INDEX(MarketingPlan[],MATCH(INDEX(MarketingVariances[],ROW()-ROW(MarketingVariances[[#Headers],[Jan]]),1),INDEX(MarketingPlan[],,1),0),MATCH(MarketingVariances[[#Headers],[Jan]],MarketingPlan[#Headers],0))-INDEX(MarketingActual[],MATCH(INDEX(MarketingVariances[],ROW()-ROW(MarketingVariances[[#Headers],[Jan]]),1),INDEX(MarketingPlan[],,1),0),MATCH(MarketingVariances[[#Headers],[Jan]],MarketingActual[#Headers],0)) | D27: =INDEX(MarketingPlan[],MATCH(INDEX(MarketingVariances[],ROW()-ROW(MarketingVariances[[#Headers],[Feb]]),1),INDEX(MarketingPlan[],,1),0),MATCH(MarketingVariances[[#Headers],[Feb]],MarketingPlan[#Headers],0))-INDEX(MarketingActual[],MATCH(INDEX(MarketingVariances[],ROW()-ROW(MarketingVariances[[#Headers],[Feb]]),1),INDEX(MarketingPlan[],,1),0),MATCH(MarketingVariances[[#Headers],[Feb]],MarketingActual[#Headers],0)) | E27: =INDEX(MarketingPlan[],MATCH(INDEX(MarketingVariances[],ROW()-ROW(MarketingVariances[[#Headers],[Mar]]),1),INDEX(MarketingPlan[],,1),0),MATCH(MarketingVariances[[#Headers],[Mar]],MarketingPlan[#Headers],0))-INDEX(MarketingActual[],MATCH(INDEX(MarketingVariances[],ROW()-ROW(MarketingVariances[[#Headers],[Mar]]),1),INDEX(MarketingPlan[],,1),0),MATCH(MarketingVariances[[#Headers],[Mar]],MarketingActual[#Headers],0)) | F27: =INDEX(MarketingPlan[],MATCH(INDEX(MarketingVariances[],ROW()-ROW(MarketingVariances[[#Headers],[Apr]]),1),INDEX(MarketingPlan[],,1),0),MATCH(MarketingVariances[[#Headers],[Apr]],MarketingPlan[#Headers],0))-INDEX(MarketingActual[],MATCH(INDEX(MarketingVariances[],ROW()-ROW(MarketingVariances[[#Headers],[Apr]]),1),INDEX(MarketingPlan[],,1),0),MATCH(MarketingVariances[[#Headers],[Apr]],MarketingActual[#Headers],0)) | G27: =INDEX(MarketingPlan[],MATCH(INDEX(MarketingVariances[],ROW()-ROW(MarketingVariances[[#Headers],[May]]),1),INDEX(MarketingPlan[],,1),0),MATCH(MarketingVariances[[#Headers],[May]],MarketingPlan[#Headers],0))-INDEX(MarketingActual[],MATCH(INDEX(MarketingVariances[],ROW()-ROW(MarketingVariances[[#Headers],[May]]),1),INDEX(MarketingPlan[],,1),0),MATCH(MarketingVariances[[#Headers],[May]],MarketingActual[#Headers],0)) | H27: =INDEX(MarketingPlan[],MATCH(INDEX(MarketingVariances[],ROW()-ROW(MarketingVariances[[#Headers],[Jun]]),1),INDEX(MarketingPlan[],,1),0),MATCH(MarketingVariances[[#Headers],[Jun]],MarketingPlan[#Headers],0))-INDEX(MarketingActual[],MATCH(INDEX(MarketingVariances[],ROW()-ROW(MarketingVariances[[#Headers],[Jun]]),1),INDEX(MarketingPlan[],,1),0),MATCH(MarketingVariances[[#Headers],[Jun]],MarketingActual[#Headers],0)) | I27: =INDEX(MarketingPlan[],MATCH(INDEX(MarketingVariances[],ROW()-ROW(MarketingVariances[[#Headers],[Jul]]),1),INDEX(MarketingPlan[],,1),0),MATCH(MarketingVariances[[#Headers],[Jul]],MarketingPlan[#Headers],0))-INDEX(MarketingActual[],MATCH(INDEX(MarketingVariances[],ROW()-ROW(MarketingVariances[[#Headers],[Jul]]),1),INDEX(MarketingPlan[],,1),0),MATCH(MarketingVariances[[#Headers],[Jul]],MarketingActual[#Headers],0)) | J27: =INDEX(MarketingPlan[],MATCH(INDEX(MarketingVariances[],ROW()-ROW(MarketingVariances[[#Headers],[Aug]]),1),INDEX(MarketingPlan[],,1),0),MATCH(MarketingVariances[[#Headers],[Aug]],MarketingPlan[#Headers],0))-INDEX(MarketingActual[],MATCH(INDEX(MarketingVariances[],ROW()-ROW(MarketingVariances[[#Headers],[Aug]]),1),INDEX(MarketingPlan[],,1),0),MATCH(MarketingVariances[[#Headers],[Aug]],MarketingActual[#Headers],0)) | K27: =INDEX(MarketingPlan[],MATCH(INDEX(MarketingVariances[],ROW()-ROW(MarketingVariances[[#Headers],[Sep]]),1),INDEX(MarketingPlan[],,1),0),MATCH(MarketingVariances[[#Headers],[Sep]],MarketingPlan[#Headers],0))-INDEX(MarketingActual[],MATCH(INDEX(MarketingVariances[],ROW()-ROW(MarketingVariances[[#Headers],[Sep]]),1),INDEX(MarketingPlan[],,1),0),MATCH(MarketingVariances[[#Headers],[Sep]],MarketingActual[#Headers],0)) | L27: =INDEX(MarketingPlan[],MATCH(INDEX(MarketingVariances[],ROW()-ROW(MarketingVariances[[#Headers],[Oct]]),1),INDEX(MarketingPlan[],,1),0),MATCH(MarketingVariances[[#Headers],[Oct]],MarketingPlan[#Headers],0))-INDEX(MarketingActual[],MATCH(INDEX(MarketingVariances[],ROW()-ROW(MarketingVariances[[#Headers],[Oct]]),1),INDEX(MarketingPlan[],,1),0),MATCH(MarketingVariances[[#Headers],[Oct]],MarketingActual[#Headers],0)) | M27: =INDEX(MarketingPlan[],MATCH(INDEX(MarketingVariances[],ROW()-ROW(MarketingVariances[[#Headers],[Nov]]),1),INDEX(MarketingPlan[],,1),0),MATCH(MarketingVariances[[#Headers],[Nov]],MarketingPlan[#Headers],0))-INDEX(MarketingActual[],MATCH(INDEX(MarketingVariances[],ROW()-ROW(MarketingVariances[[#Headers],[Nov]]),1),INDEX(MarketingPlan[],,1),0),MATCH(MarketingVariances[[#Headers],[Nov]],MarketingActual[#Headers],0)) | N27: =INDEX(MarketingPlan[],MATCH(INDEX(MarketingVariances[],ROW()-ROW(MarketingVariances[[#Headers],[Dec]]),1),INDEX(MarketingPlan[],,1),0),MATCH(MarketingVariances[[#Headers],[Dec]],MarketingPlan[#Headers],0))-INDEX(MarketingActual[],MATCH(INDEX(MarketingVariances[],ROW()-ROW(MarketingVariances[[#Headers],[Dec]]),1),INDEX(MarketingPlan[],,1),0),MATCH(MarketingVariances[[#Headers],[Dec]],MarketingActual[#Headers],0)) | O27: =SUM(MarketingVariances[[#This Row],[Jan]:[Dec]])
B28: Miscellaneous expenses | C28: =INDEX(MarketingPlan[],MATCH(INDEX(MarketingVariances[],ROW()-ROW(MarketingVariances[[#Headers],[Jan]]),1),INDEX(MarketingPlan[],,1),0),MATCH(MarketingVariances[[#Headers],[Jan]],MarketingPlan[#Headers],0))-INDEX(MarketingActual[],MATCH(INDEX(MarketingVariances[],ROW()-ROW(MarketingVariances[[#Headers],[Jan]]),1),INDEX(MarketingPlan[],,1),0),MATCH(MarketingVariances[[#Headers],[Jan]],MarketingActual[#Headers],0)) | D28: =INDEX(MarketingPlan[],MATCH(INDEX(MarketingVariances[],ROW()-ROW(MarketingVariances[[#Headers],[Feb]]),1),INDEX(MarketingPlan[],,1),0),MATCH(MarketingVariances[[#Headers],[Feb]],MarketingPlan[#Headers],0))-INDEX(MarketingActual[],MATCH(INDEX(MarketingVariances[],ROW()-ROW(MarketingVariances[[#Headers],[Feb]]),1),INDEX(MarketingPlan[],,1),0),MATCH(MarketingVariances[[#Headers],[Feb]],MarketingActual[#Headers],0)) | E28: =INDEX(MarketingPlan[],MATCH(INDEX(MarketingVariances[],ROW()-ROW(MarketingVariances[[#Headers],[Mar]]),1),INDEX(MarketingPlan[],,1),0),MATCH(MarketingVariances[[#Headers],[Mar]],MarketingPlan[#Headers],0))-INDEX(MarketingActual[],MATCH(INDEX(MarketingVariances[],ROW()-ROW(MarketingVariances[[#Headers],[Mar]]),1),INDEX(MarketingPlan[],,1),0),MATCH(MarketingVariances[[#Headers],[Mar]],MarketingActual[#Headers],0)) | F28: =INDEX(MarketingPlan[],MATCH(INDEX(MarketingVariances[],ROW()-ROW(MarketingVariances[[#Headers],[Apr]]),1),INDEX(MarketingPlan[],,1),0),MATCH(MarketingVariances[[#Headers],[Apr]],MarketingPlan[#Headers],0))-INDEX(MarketingActual[],MATCH(INDEX(MarketingVariances[],ROW()-ROW(MarketingVariances[[#Headers],[Apr]]),1),INDEX(MarketingPlan[],,1),0),MATCH(MarketingVariances[[#Headers],[Apr]],MarketingActual[#Headers],0)) | G28: =INDEX(MarketingPlan[],MATCH(INDEX(MarketingVariances[],ROW()-ROW(MarketingVariances[[#Headers],[May]]),1),INDEX(MarketingPlan[],,1),0),MATCH(MarketingVariances[[#Headers],[May]],MarketingPlan[#Headers],0))-INDEX(MarketingActual[],MATCH(INDEX(MarketingVariances[],ROW()-ROW(MarketingVariances[[#Headers],[May]]),1),INDEX(MarketingPlan[],,1),0),MATCH(MarketingVariances[[#Headers],[May]],MarketingActual[#Headers],0)) | H28: =INDEX(MarketingPlan[],MATCH(INDEX(MarketingVariances[],ROW()-ROW(MarketingVariances[[#Headers],[Jun]]),1),INDEX(MarketingPlan[],,1),0),MATCH(MarketingVariances[[#Headers],[Jun]],MarketingPlan[#Headers],0))-INDEX(MarketingActual[],MATCH(INDEX(MarketingVariances[],ROW()-ROW(MarketingVariances[[#Headers],[Jun]]),1),INDEX(MarketingPlan[],,1),0),MATCH(MarketingVariances[[#Headers],[Jun]],MarketingActual[#Headers],0)) | I28: =INDEX(MarketingPlan[],MATCH(INDEX(MarketingVariances[],ROW()-ROW(MarketingVariances[[#Headers],[Jul]]),1),INDEX(MarketingPlan[],,1),0),MATCH(MarketingVariances[[#Headers],[Jul]],MarketingPlan[#Headers],0))-INDEX(MarketingActual[],MATCH(INDEX(MarketingVariances[],ROW()-ROW(MarketingVariances[[#Headers],[Jul]]),1),INDEX(MarketingPlan[],,1),0),MATCH(MarketingVariances[[#Headers],[Jul]],MarketingActual[#Headers],0)) | J28: =INDEX(MarketingPlan[],MATCH(INDEX(MarketingVariances[],ROW()-ROW(MarketingVariances[[#Headers],[Aug]]),1),INDEX(MarketingPlan[],,1),0),MATCH(MarketingVariances[[#Headers],[Aug]],MarketingPlan[#Headers],0))-INDEX(MarketingActual[],MATCH(INDEX(MarketingVariances[],ROW()-ROW(MarketingVariances[[#Headers],[Aug]]),1),INDEX(MarketingPlan[],,1),0),MATCH(MarketingVariances[[#Headers],[Aug]],MarketingActual[#Headers],0)) | K28: =INDEX(MarketingPlan[],MATCH(INDEX(MarketingVariances[],ROW()-ROW(MarketingVariances[[#Headers],[Sep]]),1),INDEX(MarketingPlan[],,1),0),MATCH(MarketingVariances[[#Headers],[Sep]],MarketingPlan[#Headers],0))-INDEX(MarketingActual[],MATCH(INDEX(MarketingVariances[],ROW()-ROW(MarketingVariances[[#Headers],[Sep]]),1),INDEX(MarketingPlan[],,1),0),MATCH(MarketingVariances[[#Headers],[Sep]],MarketingActual[#Headers],0)) | L28: =INDEX(MarketingPlan[],MATCH(INDEX(MarketingVariances[],ROW()-ROW(MarketingVariances[[#Headers],[Oct]]),1),INDEX(MarketingPlan[],,1),0),MATCH(MarketingVariances[[#Headers],[Oct]],MarketingPlan[#Headers],0))-INDEX(MarketingActual[],MATCH(INDEX(MarketingVariances[],ROW()-ROW(MarketingVariances[[#Headers],[Oct]]),1),INDEX(MarketingPlan[],,1),0),MATCH(MarketingVariances[[#Headers],[Oct]],MarketingActual[#Headers],0)) | M28: =INDEX(MarketingPlan[],MATCH(INDEX(MarketingVariances[],ROW()-ROW(MarketingVariances[[#Headers],[Nov]]),1),INDEX(MarketingPlan[],,1),0),MATCH(MarketingVariances[[#Headers],[Nov]],MarketingPlan[#Headers],0))-INDEX(MarketingActual[],MATCH(INDEX(MarketingVariances[],ROW()-ROW(MarketingVariances[[#Headers],[Nov]]),1),INDEX(MarketingPlan[],,1),0),MATCH(MarketingVariances[[#Headers],[Nov]],MarketingActual[#Headers],0)) | N28: =INDEX(MarketingPlan[],MATCH(INDEX(MarketingVariances[],ROW()-ROW(MarketingVariances[[#Headers],[Dec]]),1),INDEX(MarketingPlan[],,1),0),MATCH(MarketingVariances[[#Headers],[Dec]],MarketingPlan[#Headers],0))-INDEX(MarketingActual[],MATCH(INDEX(MarketingVariances[],ROW()-ROW(MarketingVariances[[#Headers],[Dec]]),1),INDEX(MarketingPlan[],,1),0),MATCH(MarketingVariances[[#Headers],[Dec]],MarketingActual[#Headers],0)) | O28: =SUM(MarketingVariances[[#This Row],[Jan]:[Dec]])
B29: Subtotal | C29: =SUBTOTAL(109,MarketingVariances[Jan]) | D29: =SUBTOTAL(109,MarketingVariances[Feb]) | E29: =SUBTOTAL(109,MarketingVariances[Mar]) | F29: =SUBTOTAL(109,MarketingVariances[Apr]) | G29: =SUBTOTAL(109,MarketingVariances[May]) | H29: =SUBTOTAL(109,MarketingVariances[Jun]) | I29: =SUBTOTAL(109,MarketingVariances[Jul]) | J29: =SUBTOTAL(109,MarketingVariances[Aug]) | K29: =SUBTOTAL(109,MarketingVariances[Sep]) | L29: =SUBTOTAL(109,MarketingVariances[Oct]) | M29: =SUBTOTAL(109,MarketingVariances[Nov]) | N29: =SUBTOTAL(109,MarketingVariances[Dec]) | O29: =SUBTOTAL(109,MarketingVariances[YEAR])
B31: Training/travel | C31: Jan | D31: Feb | E31: Mar | F31: Apr | G31: May | H31: Jun | I31: Jul | J31: Aug | K31: Sep | L31: Oct | M31: Nov | N31: Dec | O31: YEAR
B32: Training classes | C32: =INDEX(TrainingAndTravelPlan[],MATCH(INDEX(TrainingAndTravelVariances[],ROW()-ROW(TrainingAndTravelVariances[[#Headers],[Jan]]),1),INDEX(TrainingAndTravelPlan[],,1),0),MATCH(TrainingAndTravelVariances[[#Headers],[Jan]],TrainingAndTravelPlan[#Headers],0))-INDEX(TrainingAndTravelActual[],MATCH(INDEX(TrainingAndTravelVariances[],ROW()-ROW(TrainingAndTravelVariances[[#Headers],[Jan]]),1),INDEX(TrainingAndTravelPlan[],,1),0),MATCH(TrainingAndTravelVariances[[#Headers],[Jan]],TrainingAndTravelActual[#Headers],0)) | D32: =INDEX(TrainingAndTravelPlan[],MATCH(INDEX(TrainingAndTravelVariances[],ROW()-ROW(TrainingAndTravelVariances[[#Headers],[Feb]]),1),INDEX(TrainingAndTravelPlan[],,1),0),MATCH(TrainingAndTravelVariances[[#Headers],[Feb]],TrainingAndTravelPlan[#Headers],0))-INDEX(TrainingAndTravelActual[],MATCH(INDEX(TrainingAndTravelVariances[],ROW()-ROW(TrainingAndTravelVariances[[#Headers],[Feb]]),1),INDEX(TrainingAndTravelPlan[],,1),0),MATCH(TrainingAndTravelVariances[[#Headers],[Feb]],TrainingAndTravelActual[#Headers],0)) | E32: =INDEX(TrainingAndTravelPlan[],MATCH(INDEX(TrainingAndTravelVariances[],ROW()-ROW(TrainingAndTravelVariances[[#Headers],[Mar]]),1),INDEX(TrainingAndTravelPlan[],,1),0),MATCH(TrainingAndTravelVariances[[#Headers],[Mar]],TrainingAndTravelPlan[#Headers],0))-INDEX(TrainingAndTravelActual[],MATCH(INDEX(TrainingAndTravelVariances[],ROW()-ROW(TrainingAndTravelVariances[[#Headers],[Mar]]),1),INDEX(TrainingAndTravelPlan[],,1),0),MATCH(TrainingAndTravelVariances[[#Headers],[Mar]],TrainingAndTravelActual[#Headers],0)) | F32: =INDEX(TrainingAndTravelPlan[],MATCH(INDEX(TrainingAndTravelVariances[],ROW()-ROW(TrainingAndTravelVariances[[#Headers],[Apr]]),1),INDEX(TrainingAndTravelPlan[],,1),0),MATCH(TrainingAndTravelVariances[[#Headers],[Apr]],TrainingAndTravelPlan[#Headers],0))-INDEX(TrainingAndTravelActual[],MATCH(INDEX(TrainingAndTravelVariances[],ROW()-ROW(TrainingAndTravelVariances[[#Headers],[Apr]]),1),INDEX(TrainingAndTravelPlan[],,1),0),MATCH(TrainingAndTravelVariances[[#Headers],[Apr]],TrainingAndTravelActual[#Headers],0)) | G32: =INDEX(TrainingAndTravelPlan[],MATCH(INDEX(TrainingAndTravelVariances[],ROW()-ROW(TrainingAndTravelVariances[[#Headers],[May]]),1),INDEX(TrainingAndTravelPlan[],,1),0),MATCH(TrainingAndTravelVariances[[#Headers],[May]],TrainingAndTravelPlan[#Headers],0))-INDEX(TrainingAndTravelActual[],MATCH(INDEX(TrainingAndTravelVariances[],ROW()-ROW(TrainingAndTravelVariances[[#Headers],[May]]),1),INDEX(TrainingAndTravelPlan[],,1),0),MATCH(TrainingAndTravelVariances[[#Headers],[May]],TrainingAndTravelActual[#Headers],0)) | H32: =INDEX(TrainingAndTravelPlan[],MATCH(INDEX(TrainingAndTravelVariances[],ROW()-ROW(TrainingAndTravelVariances[[#Headers],[Jun]]),1),INDEX(TrainingAndTravelPlan[],,1),0),MATCH(TrainingAndTravelVariances[[#Headers],[Jun]],TrainingAndTravelPlan[#Headers],0))-INDEX(TrainingAndTravelActual[],MATCH(INDEX(TrainingAndTravelVariances[],ROW()-ROW(TrainingAndTravelVariances[[#Headers],[Jun]]),1),INDEX(TrainingAndTravelPlan[],,1),0),MATCH(TrainingAndTravelVariances[[#Headers],[Jun]],TrainingAndTravelActual[#Headers],0)) | I32: =INDEX(TrainingAndTravelPlan[],MATCH(INDEX(TrainingAndTravelVariances[],ROW()-ROW(TrainingAndTravelVariances[[#Headers],[Jul]]),1),INDEX(TrainingAndTravelPlan[],,1),0),MATCH(TrainingAndTravelVariances[[#Headers],[Jul]],TrainingAndTravelPlan[#Headers],0))-INDEX(TrainingAndTravelActual[],MATCH(INDEX(TrainingAndTravelVariances[],ROW()-ROW(TrainingAndTravelVariances[[#Headers],[Jul]]),1),INDEX(TrainingAndTravelPlan[],,1),0),MATCH(TrainingAndTravelVariances[[#Headers],[Jul]],TrainingAndTravelActual[#Headers],0)) | J32: =INDEX(TrainingAndTravelPlan[],MATCH(INDEX(TrainingAndTravelVariances[],ROW()-ROW(TrainingAndTravelVariances[[#Headers],[Aug]]),1),INDEX(TrainingAndTravelPlan[],,1),0),MATCH(TrainingAndTravelVariances[[#Headers],[Aug]],TrainingAndTravelPlan[#Headers],0))-INDEX(TrainingAndTravelActual[],MATCH(INDEX(TrainingAndTravelVariances[],ROW()-ROW(TrainingAndTravelVariances[[#Headers],[Aug]]),1),INDEX(TrainingAndTravelPlan[],,1),0),MATCH(TrainingAndTravelVariances[[#Headers],[Aug]],TrainingAndTravelActual[#Headers],0)) | K32: =INDEX(TrainingAndTravelPlan[],MATCH(INDEX(TrainingAndTravelVariances[],ROW()-ROW(TrainingAndTravelVariances[[#Headers],[Sep]]),1),INDEX(TrainingAndTravelPlan[],,1),0),MATCH(TrainingAndTravelVariances[[#Headers],[Sep]],TrainingAndTravelPlan[#Headers],0))-INDEX(TrainingAndTravelActual[],MATCH(INDEX(TrainingAndTravelVariances[],ROW()-ROW(TrainingAndTravelVariances[[#Headers],[Sep]]),1),INDEX(TrainingAndTravelPlan[],,1),0),MATCH(TrainingAndTravelVariances[[#Headers],[Sep]],TrainingAndTravelActual[#Headers],0)) | L32: =INDEX(TrainingAndTravelPlan[],MATCH(INDEX(TrainingAndTravelVariances[],ROW()-ROW(TrainingAndTravelVariances[[#Headers],[Oct]]),1),INDEX(TrainingAndTravelPlan[],,1),0),MATCH(TrainingAndTravelVariances[[#Headers],[Oct]],TrainingAndTravelPlan[#Headers],0))-INDEX(TrainingAndTravelActual[],MATCH(INDEX(TrainingAndTravelVariances[],ROW()-ROW(TrainingAndTravelVariances[[#Headers],[Oct]]),1),INDEX(TrainingAndTravelPlan[],,1),0),MATCH(TrainingAndTravelVariances[[#Headers],[Oct]],TrainingAndTravelActual[#Headers],0)) | M32: =INDEX(TrainingAndTravelPlan[],MATCH(INDEX(TrainingAndTravelVariances[],ROW()-ROW(TrainingAndTravelVariances[[#Headers],[Nov]]),1),INDEX(TrainingAndTravelPlan[],,1),0),MATCH(TrainingAndTravelVariances[[#Headers],[Nov]],TrainingAndTravelPlan[#Headers],0))-INDEX(TrainingAndTravelActual[],MATCH(INDEX(TrainingAndTravelVariances[],ROW()-ROW(TrainingAndTravelVariances[[#Headers],[Nov]]),1),INDEX(TrainingAndTravelPlan[],,1),0),MATCH(TrainingAndTravelVariances[[#Headers],[Nov]],TrainingAndTravelActual[#Headers],0)) | N32: =INDEX(TrainingAndTravelPlan[],MATCH(INDEX(TrainingAndTravelVariances[],ROW()-ROW(TrainingAndTravelVariances[[#Headers],[Dec]]),1),INDEX(TrainingAndTravelPlan[],,1),0),MATCH(TrainingAndTravelVariances[[#Headers],[Dec]],TrainingAndTravelPlan[#Headers],0))-INDEX(TrainingAndTravelActual[],MATCH(INDEX(TrainingAndTravelVariances[],ROW()-ROW(TrainingAndTravelVariances[[#Headers],[Dec]]),1),INDEX(TrainingAndTravelPlan[],,1),0),MATCH(TrainingAndTravelVariances[[#Headers],[Dec]],TrainingAndTravelActual[#Headers],0)) | O32: =SUM(TrainingAndTravelVariances[[#This Row],[Jan]:[Dec]])
B33: Training-related travel costs | C33: =INDEX(TrainingAndTravelPlan[],MATCH(INDEX(TrainingAndTravelVariances[],ROW()-ROW(TrainingAndTravelVariances[[#Headers],[Jan]]),1),INDEX(TrainingAndTravelPlan[],,1),0),MATCH(TrainingAndTravelVariances[[#Headers],[Jan]],TrainingAndTravelPlan[#Headers],0))-INDEX(TrainingAndTravelActual[],MATCH(INDEX(TrainingAndTravelVariances[],ROW()-ROW(TrainingAndTravelVariances[[#Headers],[Jan]]),1),INDEX(TrainingAndTravelPlan[],,1),0),MATCH(TrainingAndTravelVariances[[#Headers],[Jan]],TrainingAndTravelActual[#Headers],0)) | D33: =INDEX(TrainingAndTravelPlan[],MATCH(INDEX(TrainingAndTravelVariances[],ROW()-ROW(TrainingAndTravelVariances[[#Headers],[Feb]]),1),INDEX(TrainingAndTravelPlan[],,1),0),MATCH(TrainingAndTravelVariances[[#Headers],[Feb]],TrainingAndTravelPlan[#Headers],0))-INDEX(TrainingAndTravelActual[],MATCH(INDEX(TrainingAndTravelVariances[],ROW()-ROW(TrainingAndTravelVariances[[#Headers],[Feb]]),1),INDEX(TrainingAndTravelPlan[],,1),0),MATCH(TrainingAndTravelVariances[[#Headers],[Feb]],TrainingAndTravelActual[#Headers],0)) | E33: =INDEX(TrainingAndTravelPlan[],MATCH(INDEX(TrainingAndTravelVariances[],ROW()-ROW(TrainingAndTravelVariances[[#Headers],[Mar]]),1),INDEX(TrainingAndTravelPlan[],,1),0),MATCH(TrainingAndTravelVariances[[#Headers],[Mar]],TrainingAndTravelPlan[#Headers],0))-INDEX(TrainingAndTravelActual[],MATCH(INDEX(TrainingAndTravelVariances[],ROW()-ROW(TrainingAndTravelVariances[[#Headers],[Mar]]),1),INDEX(TrainingAndTravelPlan[],,1),0),MATCH(TrainingAndTravelVariances[[#Headers],[Mar]],TrainingAndTravelActual[#Headers],0)) | F33: =INDEX(TrainingAndTravelPlan[],MATCH(INDEX(TrainingAndTravelVariances[],ROW()-ROW(TrainingAndTravelVariances[[#Headers],[Apr]]),1),INDEX(TrainingAndTravelPlan[],,1),0),MATCH(TrainingAndTravelVariances[[#Headers],[Apr]],TrainingAndTravelPlan[#Headers],0))-INDEX(TrainingAndTravelActual[],MATCH(INDEX(TrainingAndTravelVariances[],ROW()-ROW(TrainingAndTravelVariances[[#Headers],[Apr]]),1),INDEX(TrainingAndTravelPlan[],,1),0),MATCH(TrainingAndTravelVariances[[#Headers],[Apr]],TrainingAndTravelActual[#Headers],0)) | G33: =INDEX(TrainingAndTravelPlan[],MATCH(INDEX(TrainingAndTravelVariances[],ROW()-ROW(TrainingAndTravelVariances[[#Headers],[May]]),1),INDEX(TrainingAndTravelPlan[],,1),0),MATCH(TrainingAndTravelVariances[[#Headers],[May]],TrainingAndTravelPlan[#Headers],0))-INDEX(TrainingAndTravelActual[],MATCH(INDEX(TrainingAndTravelVariances[],ROW()-ROW(TrainingAndTravelVariances[[#Headers],[May]]),1),INDEX(TrainingAndTravelPlan[],,1),0),MATCH(TrainingAndTravelVariances[[#Headers],[May]],TrainingAndTravelActual[#Headers],0)) | H33: =INDEX(TrainingAndTravelPlan[],MATCH(INDEX(TrainingAndTravelVariances[],ROW()-ROW(TrainingAndTravelVariances[[#Headers],[Jun]]),1),INDEX(TrainingAndTravelPlan[],,1),0),MATCH(TrainingAndTravelVariances[[#Headers],[Jun]],TrainingAndTravelPlan[#Headers],0))-INDEX(TrainingAndTravelActual[],MATCH(INDEX(TrainingAndTravelVariances[],ROW()-ROW(TrainingAndTravelVariances[[#Headers],[Jun]]),1),INDEX(TrainingAndTravelPlan[],,1),0),MATCH(TrainingAndTravelVariances[[#Headers],[Jun]],TrainingAndTravelActual[#Headers],0)) | I33: =INDEX(TrainingAndTravelPlan[],MATCH(INDEX(TrainingAndTravelVariances[],ROW()-ROW(TrainingAndTravelVariances[[#Headers],[Jul]]),1),INDEX(TrainingAndTravelPlan[],,1),0),MATCH(TrainingAndTravelVariances[[#Headers],[Jul]],TrainingAndTravelPlan[#Headers],0))-INDEX(TrainingAndTravelActual[],MATCH(INDEX(TrainingAndTravelVariances[],ROW()-ROW(TrainingAndTravelVariances[[#Headers],[Jul]]),1),INDEX(TrainingAndTravelPlan[],,1),0),MATCH(TrainingAndTravelVariances[[#Headers],[Jul]],TrainingAndTravelActual[#Headers],0)) | J33: =INDEX(TrainingAndTravelPlan[],MATCH(INDEX(TrainingAndTravelVariances[],ROW()-ROW(TrainingAndTravelVariances[[#Headers],[Aug]]),1),INDEX(TrainingAndTravelPlan[],,1),0),MATCH(TrainingAndTravelVariances[[#Headers],[Aug]],TrainingAndTravelPlan[#Headers],0))-INDEX(TrainingAndTravelActual[],MATCH(INDEX(TrainingAndTravelVariances[],ROW()-ROW(TrainingAndTravelVariances[[#Headers],[Aug]]),1),INDEX(TrainingAndTravelPlan[],,1),0),MATCH(TrainingAndTravelVariances[[#Headers],[Aug]],TrainingAndTravelActual[#Headers],0)) | K33: =INDEX(TrainingAndTravelPlan[],MATCH(INDEX(TrainingAndTravelVariances[],ROW()-ROW(TrainingAndTravelVariances[[#Headers],[Sep]]),1),INDEX(TrainingAndTravelPlan[],,1),0),MATCH(TrainingAndTravelVariances[[#Headers],[Sep]],TrainingAndTravelPlan[#Headers],0))-INDEX(TrainingAndTravelActual[],MATCH(INDEX(TrainingAndTravelVariances[],ROW()-ROW(TrainingAndTravelVariances[[#Headers],[Sep]]),1),INDEX(TrainingAndTravelPlan[],,1),0),MATCH(TrainingAndTravelVariances[[#Headers],[Sep]],TrainingAndTravelActual[#Headers],0)) | L33: =INDEX(TrainingAndTravelPlan[],MATCH(INDEX(TrainingAndTravelVariances[],ROW()-ROW(TrainingAndTravelVariances[[#Headers],[Oct]]),1),INDEX(TrainingAndTravelPlan[],,1),0),MATCH(TrainingAndTravelVariances[[#Headers],[Oct]],TrainingAndTravelPlan[#Headers],0))-INDEX(TrainingAndTravelActual[],MATCH(INDEX(TrainingAndTravelVariances[],ROW()-ROW(TrainingAndTravelVariances[[#Headers],[Oct]]),1),INDEX(TrainingAndTravelPlan[],,1),0),MATCH(TrainingAndTravelVariances[[#Headers],[Oct]],TrainingAndTravelActual[#Headers],0)) | M33: =INDEX(TrainingAndTravelPlan[],MATCH(INDEX(TrainingAndTravelVariances[],ROW()-ROW(TrainingAndTravelVariances[[#Headers],[Nov]]),1),INDEX(TrainingAndTravelPlan[],,1),0),MATCH(TrainingAndTravelVariances[[#Headers],[Nov]],TrainingAndTravelPlan[#Headers],0))-INDEX(TrainingAndTravelActual[],MATCH(INDEX(TrainingAndTravelVariances[],ROW()-ROW(TrainingAndTravelVariances[[#Headers],[Nov]]),1),INDEX(TrainingAndTravelPlan[],,1),0),MATCH(TrainingAndTravelVariances[[#Headers],[Nov]],TrainingAndTravelActual[#Headers],0)) | N33: =INDEX(TrainingAndTravelPlan[],MATCH(INDEX(TrainingAndTravelVariances[],ROW()-ROW(TrainingAndTravelVariances[[#Headers],[Dec]]),1),INDEX(TrainingAndTravelPlan[],,1),0),MATCH(TrainingAndTravelVariances[[#Headers],[Dec]],TrainingAndTravelPlan[#Headers],0))-INDEX(TrainingAndTravelActual[],MATCH(INDEX(TrainingAndTravelVariances[],ROW()-ROW(TrainingAndTravelVariances[[#Headers],[Dec]]),1),INDEX(TrainingAndTravelPlan[],,1),0),MATCH(TrainingAndTravelVariances[[#Headers],[Dec]],TrainingAndTravelActual[#Headers],0)) | O33: =SUM(TrainingAndTravelVariances[[#This Row],[Jan]:[Dec]])
B34: Subtotal | C34: =SUBTOTAL(109,TrainingAndTravelVariances[Jan]) | D34: =SUBTOTAL(109,TrainingAndTravelVariances[Feb]) | E34: =SUBTOTAL(109,TrainingAndTravelVariances[Mar]) | F34: =SUBTOTAL(109,TrainingAndTravelVariances[Apr]) | G34: =SUBTOTAL(109,TrainingAndTravelVariances[May]) | H34: =SUBTOTAL(109,TrainingAndTravelVariances[Jun]) | I34: =SUBTOTAL(109,TrainingAndTravelVariances[Jul]) | J34: =SUBTOTAL(109,TrainingAndTravelVariances[Aug]) | K34: =SUBTOTAL(109,TrainingAndTravelVariances[Sep]) | L34: =SUBTOTAL(109,TrainingAndTravelVariances[Oct]) | M34: =SUBTOTAL(109,TrainingAndTravelVariances[Nov]) | N34: =SUBTOTAL(109,TrainingAndTravelVariances[Dec]) | O34: =SUBTOTAL(109,TrainingAndTravelVariances[YEAR])
B36: Totals | C36: Jan | D36: Feb | E36: Mar | F36: Apr | G36: May | H36: Jun | I36: Jul | J36: Aug | K36: Sep | L36: Oct | M36: Nov | N36: Dec | O36: Year
B37: Monthly variances | C37: =TrainingAndTravelVariances[[#Totals],[Jan]]+MarketingVariances[[#Totals],[Jan]]+OfficeVariances[[#Totals],[Jan]]+EmployeeVariances[[#Totals],[Jan]] | D37: =TrainingAndTravelVariances[[#Totals],[Feb]]+MarketingVariances[[#Totals],[Feb]]+OfficeVariances[[#Totals],[Feb]]+EmployeeVariances[[#Totals],[Feb]] | E37: =TrainingAndTravelVariances[[#Totals],[Mar]]+MarketingVariances[[#Totals],[Mar]]+OfficeVariances[[#Totals],[Mar]]+EmployeeVariances[[#Totals],[Mar]] | F37: =TrainingAndTravelVariances[[#Totals],[Apr]]+MarketingVariances[[#Totals],[Apr]]+OfficeVariances[[#Totals],[Apr]]+EmployeeVariances[[#Totals],[Apr]] | G37: =TrainingAndTravelVariances[[#Totals],[May]]+MarketingVariances[[#Totals],[May]]+OfficeVariances[[#Totals],[May]]+EmployeeVariances[[#Totals],[May]] | H37: =TrainingAndTravelVariances[[#Totals],[Jun]]+MarketingVariances[[#Totals],[Jun]]+OfficeVariances[[#Totals],[Jun]]+EmployeeVariances[[#Totals],[Jun]] | I37: =TrainingAndTravelVariances[[#Totals],[Jul]]+MarketingVariances[[#Totals],[Jul]]+OfficeVariances[[#Totals],[Jul]]+EmployeeVariances[[#Totals],[Jul]] | J37: =TrainingAndTravelVariances[[#Totals],[Aug]]+MarketingVariances[[#Totals],[Aug]]+OfficeVariances[[#Totals],[Aug]]+EmployeeVariances[[#Totals],[Aug]] | K37: =TrainingAndTravelVariances[[#Totals],[Sep]]+MarketingVariances[[#Totals],[Sep]]+OfficeVariances[[#Totals],[Sep]]+EmployeeVariances[[#Totals],[Sep]] | L37: =TrainingAndTravelVariances[[#Totals],[Oct]]+MarketingVariances[[#Totals],[Oct]]+OfficeVariances[[#Totals],[Oct]]+EmployeeVariances[[#Totals],[Oct]] | M37: =TrainingAndTravelVariances[[#Totals],[Nov]]+MarketingVariances[[#Totals],[Nov]]+OfficeVariances[[#Totals],[Nov]]+EmployeeVariances[[#Totals],[Nov]] | N37: =TrainingAndTravelVariances[[#Totals],[Dec]]+MarketingVariances[[#Totals],[Dec]]+OfficeVariances[[#Totals],[Dec]]+EmployeeVariances[[#Totals],[Dec]] | O37: =TrainingAndTravelVariances[[#Totals],[YEAR]]+MarketingVariances[[#Totals],[YEAR]]+OfficeVariances[[#Totals],[YEAR]]+EmployeeVariances[[#Totals],[YEAR]]
B38: TOTAL variances | C38: =SUM($C$37:C37) | D38: =SUM($C$37:D37) | E38: =SUM($C$37:E37) | F38: =SUM($C$37:F37) | G38: =SUM($C$37:G37) | H38: =SUM($C$37:H37) | I38: =SUM($C$37:I37) | J38: =SUM($C$37:J37) | ... N38: =SUM($C$37:N37)

Sheet EXPENSE ANALYSIS
B2: ='PLANNED EXPENSES'!B2:D3
F3: Detailed expense estimates
B5: Expense category | C5: Planned expenses | D5: Actual expenses | E5: Expense variances | F5: Variance percentage
B6: Employee costs | C6: =EmployeePlan[[#Totals],[YEAR]] | D6: =EmployeeActual[[#Totals],[YEAR]] | E6: =C6-D6 | F6: =E6/C6
B7: ='PLANNED EXPENSES'!B11 | C7: =OfficePlan[[#Totals],[YEAR]] | D7: =OfficeActual[[#Totals],[YEAR]] | E7: =C7-D7 | F7: =E7/C7
B8: ='PLANNED EXPENSES'!B22 | C8: =MarketingPlan[[#Totals],[YEAR]] | D8: =MarketingActual[[#Totals],[YEAR]] | E8: =C8-D8 | F8: =E8/C8
B9: ='PLANNED EXPENSES'!B31 | C9: =TrainingAndTravelPlan[[#Totals],[YEAR]] | D9: =TrainingAndTravelActual[[#Totals],[YEAR]] | E9: =C9-D9 | F9: =E9/C9
B10: ='PLANNED EXPENSES'!B36 | C10: ='PLANNED EXPENSES'!O37 | D10: ='ACTUAL EXPENSES'!O37 | E10: =C10-D10 | F10: =E10/C10
